Workbook
Name copy: #REF!
Name copy1: #REF!
Name Go_To_Sheet: #REF!
Name loai_1: #REF!
Name loai_1_name: #REF!

Sheet File Sheets Summary
A1: STT | B1: Nội dung tài liệu | C1: Sheet
A2: 1 | B2: Trang bìa tài liệu | C2: Cover
A3: 2 | B3: Danh sách và mô tả tất cả các sheet trong file | C3: File Sheets Summary
A4: 3 | B4: Tổng hợp tiến độ thiết kế toàn bộ Data Vault | C4: Summary Tracking
A5: 4 | B5: Tracking tiến độ mapping và phát triển Data Vault | C5: Tracking Mapping&Dev Vault
A6: 5 | B6: Danh sách các bảng dữ liệu nguồn được đưa lên Silver | C6: Source Table
A7: 6 | B7: Tổng hợp danh sách các bảng Raw Vault | C7: Summary Raw Vault
A8: 7 | B8: Tổng hợp danh sách các bảng Business Vault | C8: Summary Business Vault
A9: 8 | B9: Nguyên tắc và quy tắc thiết kế mô hình dữ liệu Data Vault | C9: Rules
A10: 9 | B10: Thống kê chi tiết trạng thái Mapping | C10: Mapping Statistics
A11: 10 | B11: Mapping chi tiết từ T24 sang Data Vault (hiện tại) | C11: T24 Vault Mapping
A12: 11 | B12: Mapping chi tiết từ WAY4 sang Data Vault | C12: WAY4 Vault Mapping
A13: 12 | B13: Mapping chi tiết từ OMNI sang Data Vault | C13: OMNI Vault Mapping
... A20: 19 | B20: Thống kê chi tiết trạng thái Mapping (bản bổ sung) | C20: Mapping Statistics
B22: Bổ sung thêm sheet khảo sát chi tiết các bảng lỗi từ source | C22: Hỏi Linh, thêm các sheet làm việc với T24 để làm rõ cacsc bảng bị lỗi dữ liệu từ nguồn
B23: Bổ sung thêm sheet v_stg_ | C23: hashdiff | D23: HA làm
C24: filter
C25: Note

Sheet Summary Raw Vault_old
A6: Source | B6: Group | C6: Table Name | D6: Description
A7: T24, Way4, Omni, BPM | B7: REFERENCE | C7: reference | D7: Bảng tổng hợp tất cả các bảng danh mục chứa thông tin mô tả và phân loại từ các nguồn T24, Way4, Omni, BPM
A8: T24 | B8: COLLATERAL | C8: hub_collateral | D8: Bảng định danh mã tài sản đảm bảo (TSĐB)
A9: T24 | B9: COLLATERAL | C9: sat_collateral_information | D9: Thông tin chung tài sản đảm bảo (Loại, mô tả, mã, trạng thái tài sản,...)
A10: T24 | B10: COLLATERAL | C10: sat_collateral_valuation | D10: Thông tin định giá tài sản đảm bảo (Loại tiền, giá trị danh nghĩa, đảm bảo, ghi sổ,...)
A11: T24 | B11: COLLATERAL | C11: sat_collateral_insurance | D11: Thông tin hợp đồng bảo hiểm của TSĐB (Tài sản phải mua bảo hiểm, số hợp đồng bảo hiểm, sản phẩm bảo hiểm,...)
A12: T24 | B12: COLLATERAL | C12: sat_collateral_vehicle | D12: Thông tin tài sản đảm bảo là phương tiện
A13: T24 | B13: COLLATERAL | C13: sat_collateral_instrument | D13: Thông tin tài sản đảm bảo là chứng khoán
A14: T24 | B14: COLLATERAL | C14: sat_collateral_real_estate | D14: Thông tin tài sản đảm bảo là bất động sản
A15: T24 | B15: COLLATERAL | C15: sat_collateral_other | D15: Thông tin khác về TSĐB (Địa điểm lưu kho, Số tài khoản tham chiếu, Số hợp đồng thế chấp TSĐB)
A16: T24 | B16: COLLATERAL | C16: link_collateral_branch | D16: Liên kết tài sản đảm bảo với chi nhánh
A17: T24 | B17: COLLATERAL | C17: link_collateral_man_branch | D17: Liên kết tài sản đảm bảo với chi nhánh quản lý tài sản
... A522: BPM | B522: TSBD | C522: link_tsbd_giaodich_chinh_khach_hang | D522: Liên kết giữa khách hàng và giao dịch tài sản bảo đảm

Sheet Source Table
A1: Source | B1: Table Name in Source | C1: Description | D1: Phase | E1: Reference | F1: Note
A2: T24 | B2: t24_customer | C2: Bảng master thông tin khách hàng | D2: Phase 1
A3: T24 | B3: t24_account | C3: Bảng master thông tin tài khoản (bao gồm tài khoản CASA, tài khoản deposits, tài khoản nội bộ của OCB,...) | D3: Phase 1
A4: T24 | B4: t24_account_closed | C4: Bảng tài khoản đã đóng (các tài khoản khách hàng đã đóng) | D4: Phase 1
A5: T24 | B5: t24_account_credit_int | C5: Bảng lãi suất trên số dư nợ cho từng tài khoản | D5: Phase 1
A6: T24 | B6: t24_account_debit_int | C6: Bảng lãi suất trên số dư có cho từng tài khoản | D6: Phase 1
A7: T24 | B7: t24_accr_acct_cr | C7: Bảng khai báo lãi suất trên số dư có cho từng tài khoản | D7: Phase 2
A8: T24 | B8: t24_accr_acct_dr | C8: Bảng khai báo lãi suất trên số dư nợ cho từng tài khoản | D8: Phase 2
A9: T24 | B9: t24_acct_activity | C9: Bảng lưu biến động số dư tài khoản trong 1 tháng - ghi nhận các giao dịch phát sinh làm thay đổi số dư nợ, số dư có của tài khoản khách hàng | D9: Phase 2
A10: T24 | B10: t24_acct_gen_condition | C10: Bảng khai báo nhóm sản phẩm tài khoản | D10: Phase 2 | E10: Y
A11: T24 | B11: t24_acct_group_condition | C11: Bảng khai báo nhóm số dư tối thiểu tài khoản | D11: Phase 2 | E11: Y
A12: T24 | B12: t24_ac_locked_events | C12: Bảng tài khoản bị phong tỏa | D12: Phase 1
A13: T24 | B13: t24_apportion_acct_categ | C13: Bảng dùng để xử lý VAT và thu nhập (bảng local riêng) | D13: Phase 2
A14: T24 | B14: t24_auto_name | C14: Bảng danh mục nhãn hiệu xe (liên quan đến hợp đồng LD) | D14: Phase 2 | E14: Y
A15: T24 | B15: t24_az_account | C15: Bảng thông tin hợp đồng tiền gửi có kì hạn/Số tài khoản tiết kiệm (Tất cả những IDs trong AZ_ACCOUNT đều nằm trong bảng ACCOUNT) | D15: Phase 1
A16: T24 | B16: t24_az_product_parameter | C16: Bảng danh mục phân loại sản phẩm của hợp đồng tiền gửi có kì hạn/Số tài khoản tiết kiệm | D16: Phase 1 | E16: Y
A17: T24 | B17: t24_bank_assure_inp | C17: Bảng lưu thông tin bảo hiểm khoản vay (không còn sử dụng) | D17: Phase 2
A18: T24 | B18: t24_bc_sort_code | C18: Bảng danh sách ngân hàng tham gia CITAD/VCB/BIDV | D18: Phase 1 | E18: Y
A19: T24 | B19: t24_basic_interest | C19: Bảng danh sách key lãi suất | D19: Phase 1 | E19: Y
A20: T24 | B20: t24_bosc_comp_reg | C20: Bảng danh mục công ty chứng khoán liên quan đến hợp đồng LD | D20: Phase 2 | E20: Y
A21: T24 | B21: t24_categ_entry | C21: Bảng bút toán thu nhập/chi phí | D21: Phase 1
A22: T24 | B22: t24_category | C22: Bảng danh sách phân loại category | D22: Phase 1 | E22: Y
A23: T24 | B23: t24_collateral | C23: Bảng master thông tin TSĐB | D23: Phase 1
A24: T24 | B24: t24_collateral_code | C24: Bảng danh sách mã TSĐB cụ thể | D24: Phase 1 | E24: Y
A25: T24 | B25: t24_collateral_right | C25: Bảng liên kết quyền TSĐB | D25: Phase 1
A26: T24 | B26: t24_collateral_type | C26: Bảng danh mục loại TSĐB | D26: Phase 1 | E26: Y
A27: T24 | B27: t24_crb | C27: Bảng CRB | D27: Phase 1
A28: T24 | B28: t24_ocbh_coll_bpm_store | C28: Bảng tạm đối soát trạng thái TSBĐ giữa hệ thống BPM và hệ thống T24 | D28: Phase 2
A29: T24 | B29: t24_ocbh_coll_rev_agent | C29: Bảng thông tin đơn vị định giá TSĐB (OCB customed) | D29: Phase 1
A30: T24 | B30: t24_company | C30: Bảng danh mục chi nhánh | D30: Phase 1
A31: T24 | B31: t24_comp_level_group | C31: Bảng lưu phân cấp Mã chi nhánh | D31: Phase 2
A32: T24 | B32: t24_consolidate_prft_loss | C32: Bảng chi phí/lợi nhuận toàn hàng | D32: Phase 1
A33: T24 | B33: t24_country | C33: Bảng danh mục quốc gia | D33: Phase 1 | E33: Y
A34: T24 | B34: t24_currency | C34: Bảng thông tin về các loại đồng tiền, tỉ giá | D34: Phase 1
A35: T24 | B35: t24_cus_pkg | C35: Bảng thông tin các gói ưu đãi cho khách hàng | D35: Phase 1
A36: T24 | B36: t24_dealer_desk | C36: Bảng danh mục dealer | D36: Phase 1 | E36: Y
A37: T24 | B37: t24_de_bic | C37: Bảng danh mục ngân hàng tham gia Swift | D37: Phase 1 | E37: Y
A38: T24 | B38: t24_denom_exchange | C38: Bảng lưu tỷ giá cho đồng có mệnh giá nhỏ | D38: Phase 2 | E38: Y
A39: T24 | B39: t24_department | C39: Bảng danh mục phòng ban | D39: Phase 1 | E39: Y
A40: T24 | B40: t24_dept_acct_officer | C40: Bảng thông tin nhân viên bán hàng | D40: Phase 1
A41: T24 | B41: t24_diary | C41: Bảng khai báo sự kiện giao dịch liên quan đến chứng khoán | D41: Phase 2
A42: T24 | B42: t24_drawings | C42: Bảng bộ chứng từ thanh toán L/C | D42: Phase 1
A43: T24 | B43: t24_eb_contract_balances | C43: Bảng thông tin số dư theo hợp đồng (không sử dụng) | D43: Phase 2 | F43: Nghiệp vụ không sử dụng bảng này để làm báo cáo
A44: T24 | B44: t24_entitlement | C44: Bảng lưu trữ số tiền được chia theo danh mục nắm giữ (được phái sinh từ bảng t24_diary) | D44: Phase 2
A45: T24 | B45: t24_funds_transfer | C45: Bảng thông tin giao dịch chuyển tiền | D45: Phase 1
A46: T24 | B46: t24_ft_txn_type_condition | C46: Bảng danh mục loại giao dịch | D46: Phase 1 | E46: Y
A47: T24 | B47: t24_forex | C47: Bảng thông tin giao dịch forex | D47: Phase 1
A48: T24 | B48: t24_group_capitalisation | C48: Bảng tham số ngày kép lãi của nhóm SP tài khoản | D48: Phase 2 | E48: Y
A49: T24 | B49: t24_holiday | C49: Bảng danh mục ngày nghỉ lễ | D49: Phase 1
A50: T24 | B50: t24_industry | C50: Bảng danh mục ngành kinh tế | D50: Phase 1 | E50: Y
A51: T24 | B51: t24_insurance_int | C51: Bảng khai báo bảo hiểm khoản vay (không còn sử dụng) | D51: Phase 2 | F51: Bảng này không còn được sử dụng (chỉ chứa những hợp đồng LD tồn tại năm 2012, 2013)
A52: T24 | B52: t24_int_chg_type | C52: Bảng danh mục loại lãi suất FTP | D52: Phase 2 | E52: Y
A53: T24 | B53: t24_job_title | C53: Bảng danh mục nghề nghiệp/Chức danh của khách hàng | D53: Phase 2 | E53: Y
A54: T24 | B54: t24_letter_of_credit | C54: Bảng thông tin L/C | D54: Phase 1
A55: T24 | B55: t24_lc_enrichment | C55: Bảng lưu trữ phần diễn giải đầy đủ cho các mã code, ký tự viết tắt dùng riêng trong nghiệp vụ L/C | D55: Phase 2 | E55: Y
A56: T24 | B56: t24_lc_types | C56: Bảng danh mục loại L/C | D56: Phase 1 | E56: Y
A57: T24 | B57: t24_ld_aprv_info | C57: Bảng thông tin người và cấp phê duyệt hợp đồng tín dụng/khoản vay | D57: Phase 1
A58: T24 | B58: t24_ld_aprv_user | C58: Bảng thông tin user thẩm quyền duyệt LD | D58: Phase 1 | E58: Y
A59: T24 | B59: t24_ld_extra_info | C59: Bảng thông tin bổ sung cho LD | D59: Phase 1
A60: T24 | B60: t24_ld_ins_type_comp | C60: Bảng danh mục công ty bảo hiểm LD | D60: Phase 1 | E60: Y
A61: T24 | B61: t24_ld_partner | C61: Bảng danh mục đối tác LD | D61: Phase 1 | E61: Y
A62: T24 | B62: t24_ld_promotion | C62: Bảng danh mục gói khuyến mãi LD | D62: Phase 1 | E62: Y
A63: T24 | B63: t24_ld_schedule_define | C63: Bảng lịch trình trả nợ LD | D63: Phase 1
A64: T24 | B64: t24_li_comp_level_right | C64: Bảng khai báo hạn mức được phê duyệt của từng đơn vị | D64: Phase 2
A65: T24 | B65: t24_limit | C65: Bảng thông tin hạn mức tín dụng | D65: Phase 1
A66: T24 | B66: t24_limit_level_auth | C66: Bảng hạn mức phê duyệt trên T24 (theo chức danh user) | D66: Phase 2 | E66: Y
A67: T24 | B67: t24_limit_reference | C67: Bảng tham chiếu hạn mức tín dụng | D67: Phase 1 | E67: Y
A68: T24 | B68: t24_lmm_account_balances | C68: Bảng dự tính dự thu cho LD | D68: Phase 1
A69: T24 | B69: t24_ln_cust_revs_dtls | C69: Bảng thoái thu của hợp đồng vay | D69: Phase 1
A70: T24 | B70: t24_loan_method | C70: Bảng danh mục phương thức cho vay | D70: Phase 1 | E70: Y
A71: T24 | B71: t24_loan_purpose | C71: Bảng danh mục mục đích vay | D71: Phase 1 | E71: Y
A72: T24 | B72: t24_loan_subproduct | C72: Bảng danh mục sản phẩm vay | D72: Phase 1 | E72: Y
A73: T24 | B73: t24_md_deal | C73: Bảng thông tin hợp đồng bảo lãnh | D73: Phase 1
A74: T24 | B74: t24_ocbh_ac_restrict | C74: Bảng đăng kí tài khoản hạn chế của tài khoản thấu chi và đăng kí thu hộ | D74: Phase 2
A75: T24 | B75: t24_ocbh_classification | C75: Bảng danh mục phân khúc khách hàng (OCB customed) | D75: Phase 1 | E75: Y
A76: T24 | B76: t24_ocbh_coll_basel | C76: Bảng TSĐB theo chuẩn basel (OCB customed) | D76: Phase 1
A77: T24 | B77: t24_ocbh_cu_add_inf_corp_vn | C77: Bảng thông tin khách hàng doanh nghiệp Việt Nam (bổ sung thông tin của lãnh đạo công ty) (OCB customed) | D77: Phase 2
A78: T24 | B78: t24_ocbh_cus_ext_info | C78: Bảng bổ sung thông tin khách hàng (OCB customed) | D78: Phase 1
A79: T24 | B79: t24_ocbh_cus_group | C79: Bảng danh mục khối quản lý (OCB customed) | D79: Phase 1 | E79: Y
A80: T24 | B80: t24_ocbh_cus_indiv_bl | C80: Không có data trên UAT và Prod | D80: Phase 1
A81: T24 | B81: t24_ocbh_deposit_prgm | C81: Bảng danh mục chính sách ưu đãi tiết kiệm (OCB customed) | D81: Phase 1 | E81: Y
A82: T24 | B82: t24_ocbh_ft_outward_purpose | C82: Bảng danh mục mục đích chuyển tiền nước ngoài (OCB customed) | D82: Phase 1 | E82: Y
A83: T24 | B83: t24_ocbh_fx_buyfcy_purpose | C83: Bảng danh mục mua bán ngoại tệ | D83: Phase 1 | E83: Y
A84: T24 | B84: t24_ocbh_industry_tt15 | C84: Bảng danh mục mã ngành nghề theo TT15 (OCB customed) | D84: Phase 2 | E84: Y
A85: T24 | B85: t24_ocbh_ld_basel | C85: Bảng LD theo chuẩn basel (OCB customed) | D85: Phase 1
A86: T24 | B86: t24_ocbh_ld_prod_main | C86: Bảng sản phẩm cho vay theo TT02 (OCB customed) | D86: Phase 1 | E86: Y
A87: T24 | B87: t24_ocbh_loan_pro_bundle | C87: Bảng danh mục mã loại sản phẩm vay (OCB customed) | D87: Phase 1 | E87: Y
A88: T24 | B88: t24_ocbh_md_purpose | C88: Bảng danh mục gói sản phẩm vay (OCB customed) | D88: Phase 1 | E88: Y
A89: T24 | B89: t24_ocbh_prod_package_partner | C89: Bảng danh mục mã gói TKTM (OCB customed) | D89: Phase 1
A90: T24 | B90: t24_ocbh_product_package | C90: Bảng thông tin đối tác hưởng gói ưu đãi (OCB customed) | D90: Phase 1 | E90: Y
A91: T24 | B91: t24_ocbh_scm_extra_info | C91: Bảng tham chiếu của Security master, dùng để tính FTP (quản lý vốn) (OCB customed) | D91: Phase 2
A92: T24 | B92: t24_ocbt_sub_industry | C92: Bảng danh mục ngành kinh tế chi tiết (OCB customed) | D92: Phase 1
A93: T24 | B93: t24_pc_re_stat_line_bal | C93: Bảng cân đối số dư toàn hàng có điều chỉnh | D93: Phase 1
A94: T24 | B94: t24_periodic_interest | C94: Bảng danh mục khóa lãi suất thả nổi định kì | D94: Phase 2
A95: T24 | B95: t24_posting_restrict | C95: Bảng danh mục mã hạn chế thanh toán | D95: Phase 1 | E95: Y
A96: T24 | B96: t24_prod_package_cb | C96: Bảng danh mục quản lý các gói tài khoản | D96: Phase 2 | E96: Y
A97: T24 | B97: t24_province | C97: Bảng danh mục tỉnh thành | D97: Phase 1 | E97: Y
A98: T24 | B98: t24_re_consol_spec_entry | C98: Bảng bút toán liên quan đến hợp đồng | D98: Phase 1
A99: T24 | B99: t24_repo | C99: Bảng thông tin hợp đồng repo | D99: Phase 1
A100: T24 | B100: t24_re_stat_line_bal | C100: Bảng cân đối số dư toàn hàng | D100: Phase 1
...

Sheet Summary Business Vault
A1: Summary Business Vault
A2: Source | B2: Group | C2: Table Name | D2: Description | E2: Các bảng raw vault sử dụng cho BV | F2: Note
A3: Raw Vault | B3: Point in time | C3: pit_loan | D3: Bảng Point-in-Time tổng hợp các điểm thời gian hiệu lực của các Satellite thuộc hợp đồng tín dụng | E3: hub_loan sat_loans_information sat_loans_classification sat_loans_rate sat_loans_terms
A4: Raw Vault | B4: Point in time | C4: pit_account | D4: Bảng Point-in-Time tổng hợp các điểm thời gian hiệu lực của các Satellite thuộc tài khoản | E4: hub_account sat_deposits_rate sat_deposits_information sat_deposits_terms sat_account_balance sat_account_information sat_account_classification
A5: Raw Vault | B5: Point in time | C5: pit_customer | D5: Bảng Point-in-Time tổng hợp các điểm thời gian hiệu lực của các Satellite thuộc khách hàng | E5: hub_customer sat_customer_information sat_customer_extra_information sat_customer_contract sat_customer_classification sat_customer_kyc sat_customer_financial_statement sat_cust_package
A6: Raw Vault | B6: Point in time | C6: pit_acnt_contract | D6: Bảng Point-in-Time tổng hợp các điểm thời gian hiệu lực của các Satellite thuộc hợp đồng tài khoản (WAY4) | E6: hub_acnt_contract sat_acnt_contract_cs_status_log sat_acnt_contract_information sat_acnt_contract_type sat_acnt_contract_add_data sat_acnt_contract_other
A7: Raw Vault | B7: Bridge | C7: bridge_loan | D7: Bảng Bridge kết hợp các Hashkey liên quan đến hợp đồng tín dụng (khoản vay trong hạn, quá hạn, tài khoản thấu chi). Nguồn gốc của bridge loan lấy từ CRB , chỉ lọc gl like 2% và loại bỏ những tieu khoan = TOTAL, ROUNDING.ADJUSTMENT | E7: hub_loans link_crb_loans hub_loans_payment_due link_crb_loans_payment_due hub_account link_crb_account hub_crb link_crb_branch link_crb_customer link_loans_dept_acct_officer_NVQL link_loans_salesid
A8: Raw Vault | B8: Bridge | C8: bridge_account | D8: Bảng Bridge kết hợp các Hashkey liên quan đến tài khoản (khách hàng, chi nhánh, nhân viên) | E8: link_crb_account hub_crb link_crb_loans link_crb_branch link_crb_customer link_account_dept_acct_officer hub_account hub_loans hub_branch hub_customer hub_acct_officer
A9: Raw Vault | B9: Bridge | C9: bridge_card | D9: Bảng Bridge kết hợp các Hashkey liên quan đến thẻ (hợp đồng tài khoản, khách hàng, cấp liability, cấp account, cấp card). Nguồn gốc của bridge loan lấy từ CRB , chỉ lọc gl like 4% và loại bỏ những tieu khoan = TOTAL, ROUNDING.ADJUSTMENT | E9: link_account_contract_card effsat_link_account_contract_card link_acnt_contract_client link_client_customer link_acnt_contract_branch link_acnt_contract_product hub_acnt_contract hub_client hub_customer hub_branch hub_product
A10: Raw Vault | B10: Bridge | C10: bridge_ft | D10: Bảng Bridge kết hợp các Hashkey liên quan đến giao dịch chuyển tiền trên t24 (account debit, credit, customer,v.v) | E10: hub_funds_transfer link_funds_transfer_debit_account link_funds_transfer_credit_account link_account_customer link_funds_transfer_branch link_funds_transfer_clearing_citad hub_account hub_customer hub_clearing_citad
A11: Raw Vault | B11: Bridge | C11: bridge_doc | D11: Bảng Bridge kết hợp các Hashkey liên quan đến giao dịch của way4 (hợp đồng tài khoản nguồn/đích, m_transaction) | E11: link_doc_fin_auth hub_document link_doc_m_transaction link_doc_target_acnt_contract link_acnt_contract_client link_client_customer hub_m_transaction hub_acnt_contract hub_client hub_customer
A12: Raw Vault | B12: asOfDate | C12: calendar | D12: Bảng lịch tạo ra các ngày snapshot dùng để join với bảng PIT và Bridge (Bảng Calendar xác định danh sách ngày làm việc trong năm, ngày làm việc cuối tháng, ngày làm việc đầu tháng, ngày làm việc tiếp theo, ngày làm việc trước đó, ngày làm việc đầu năm, ngày làm việc cuối năm, được dùng làm trục thời gian chuẩn trong các câu truy vấn) | E12: ref_holiday

Sheet Mapping Stat.
A1: Source | B1: Table Name in Source | C1: Phase | D1: Số trường | E1: Số trường đã mapping phase 1 + 2 | F1: Còn lại | G1: Mô tả | H1: Note
A2: WAY4 | B2: account_type | C2: Phase 1 | D2: 17 | G2: Reference table
A3: WAY4 | B3: acnt_contract | C3: Phase 1 | D3: 101 | E3: 101 | F3: =D3-E3 -> 0
A4: WAY4 | B4: appl_product | C4: Phase 1 | D4: 50 | E4: 50 | F4: =D4-E4 -> 0
A5: WAY4 | B5: billing_log | C5: Phase 1 | D5: 17 | E5: 17 | F5: =D5-E5 -> 0
A6: WAY4 | B6: client | C6: Phase 1 | D6: 67 | E6: 65 | F6: =D6-E6 -> 2 | G6: 2 trường không sử dụng: ENABLE_AFFILIATION, AFFILIATION_TYPE Một số trường quan trọng thì đã thống nhất lấy từ bảng client_address: TITLE, SALUTATION_SUFFIX, BIRTH_NAM, COUNTRY, ADDRESS_ZIP, ADDRESS_LINE_1, ADDRESS_LINE_2, ADDRESS_LINE_3, ADDRESS_LINE_4, PHONE, PHONE_H, PHONE_M, FAX, FAX_H, E_MAIL, URL, STATE, CITY
A7: WAY4 | B7: contr_status | C7: Phase 1 | D7: 16 | G7: Reference table
A8: WAY4 | B8: country | C8: Phase 1 | D8: 20 | G8: Reference table
A9: WAY4 | B9: cs_status_log | C9: Phase 1 | D9: 23 | E9: 23 | F9: =D9-E9 -> 0
A10: WAY4 | B10: cs_status_type | C10: Phase 1 | D10: 21 | G10: Reference table
A11: WAY4 | B11: cs_status_value | C11: Phase 1 | D11: 18 | G11: Reference table
A12: WAY4 | B12: currency | C12: Phase 1 | D12: 11 | G12: Reference table
A13: WAY4 | B13: device_rec | C13: Phase 1 | D13: 39 | E13: 39 | F13: =D13-E13 -> 0
A14: WAY4 | B14: doc | C14: Phase 1 | D14: 89 | E14: 89 | F14: =D14-E14 -> 0
A15: WAY4 | B15: entry | C15: Phase 1 | D15: 33 | E15: 33 | F15: =D15-E15 -> 0
A16: WAY4 | B16: m_transaction | C16: Phase 1 | D16: 34 | E16: 34 | F16: =D16-E16 -> 0
A17: WAY4 | B17: mess_channel | C17: Phase 1 | D17: 11 | G17: Reference table
A18: WAY4 | B18: sic | C18: Phase 1 | D18: 12 | G18: Reference table
A19: WAY4 | B19: templ_approved | C19: Phase 1 | D19: 58 | E19: 57 | F19: =D19-E19 -> 1 | G19: 1 trường không sử dụng, ko có data ACCOUNT_NUMERATION
A20: WAY4 | B20: trans_type | C20: Phase 1 | D20: 27 | G20: Reference table
A21: WAY4 | B21: balance | C21: Phase 1 | D21: 39 | E21: 39 | F21: =D21-E21 -> 0
A22: WAY4 | B22: acq_dev_cycle | C22: Phase 1 | D22: 14 | E22: 14 | F22: =D22-E22 -> 0
A23: WAY4 | B23: billing | C23: Phase 1 | D23: 42 | E23: 42 | F23: =D23-E23 -> 0
A24: WAY4 | B24: payment | C24: Phase 1 | D24: 20 | E24: 20 | F24: =D24-E24 -> 0
A25: WAY4 | B25: acc_templ | C25: Phase 2 | D25: 67 | E25: 67 | F25: =D25-E25 -> 0
A26: WAY4 | B26: account | C26: Phase 2 | D26: 40 | F26: =D26-E26 -> 40
A27: WAY4 | B27: add_data | C27: Phase 2 | D27: 10 | G27: Reference table
A28: WAY4 | B28: bank_unit | C28: Phase 2 | D28: 13 | G28: Reference table
A29: WAY4 | B29: bin_table | C29: Phase 2 | D29: 34 | G29: Reference table
A30: WAY4 | B30: branch | C30: Phase 2 | D30: 14 | F30: =D30-E30 -> 14
A31: WAY4 | B31: card_info | C31: Phase 2 | D31: 45 | F31: =D31-E31 -> 45
A32: WAY4 | B32: client_address | C32: Phase 2 | D32: 41 | F32: =D32-E32 -> 41
A33: WAY4 | B33: event_type | C33: Phase 2 | D33: 25 | G33: Reference table
A34: WAY4 | B34: evnt_action | C34: Phase 2 | D34: 7 | G34: Reference table
A35: WAY4 | B35: gl_trace | C35: Phase 2 | D35: 24 | F35: =D35-E35 -> 24
A36: WAY4 | B36: invoice_log | C36: Phase 2 | D36: 35 | F36: =D36-E36 -> 35
A37: WAY4 | B37: item | C37: Phase 2 | D37: 27 | F37: =D37-E37 -> 27
A38: WAY4 | B38: resp_code | C38: Phase 2 | D38: 10 | G38: Reference table
A39: WAY4 | B39: td_auth_sch | C39: Phase 2 | D39: 22 | E39: 22 | F39: =D39-E39 -> 0
A40: WAY4 | B40: td_auth_type | C40: Phase 2 | D40: 12 | G40: Reference table
A41: WAY4 | B41: trans_cond | C41: Phase 2 | D41: 14 | G41: Reference table
A42: WAY4 | B42: usage_action | C42: Phase 2 | D42: 36 | G42: Reference table
A43: OMNI | B43: onboarding_report | C43: Phase 1 | D43: 10 | E43: 10 | F43: =D43-E43 -> 0
A44: OMNI | B44: en_user | C44: Phase 1 | D44: 14 | E44: 14 | F44: =D44-E44 -> 0
A45: OMNI | B45: payment_order | C45: Phase 1 | D45: 52 | E45: 52 | F45: =D45-E45 -> 0 | G45: bảng cũ là pmt_order -> payment_order
A46: OMNI | B46: oversea_ft_request | C46: Phase 1 | D46: 49 | E46: 49 | F46: =D46-E46 -> 0
A47: OMNI | B47: service_provider | C47: Phase 1 | D47: 42 | G47: Reference table
A48: OMNI | B48: services | C48: Phase 1 | D48: 17 | G48: Reference table
A49: OMNI | B49: auto_debit | C49: Phase 1 | D49: 35 | E49: 35 | F49: =D49-E49 -> 0
A50: OMNI | B50: omni_service | C50: Phase 1 | D50: 35 | E50: 35 | F50: =D50-E50 -> 0
A51: OMNI | B51: audit_message | C51: Phase 1 | D51: 25 | E51: 25 | F51: =D51-E51 -> 0
A52: OMNI | B52: transfer_bill_history | C52: Phase 2 | D52: 37 | E52: 24 | F52: =D52-E52 -> 13
A53: OMNI | B53: message | C53: Phase 2 | D53: 19 | E53: 0 | F53: =D53-E53 -> 19
A54: OMNI | B54: user_notification | C54: Phase 2 | D54: 20 | E54: 8 | F54: =D54-E54 -> 12
A55: OMNI | B55: customer_data_sharing_consent | C55: Phase 2 | D55: 13 | E55: 8 | F55: =D55-E55 -> 5
A56: OMNI | B56: clevertap_tracking | C56: Phase 2 | D56: 7 | E56: 0 | F56: =D56-E56 -> 7
A57: OMNI | B57: device | C57: Phase 2 | D57: 11 | E57: 10 | F57: =D57-E57 -> 1
A58: OMNI | B58: device_detail | C58: Phase 2 | D58: 6 | E58: 5 | F58: =D58-E58 -> 1
A59: OMNI | B59: voucher | C59: Phase 2 | D59: 13 | E59: 8 | F59: =D59-E59 -> 5
A60: OMNI | B60: voucher_campaign | C60: Phase 2 | D60: 20 | E60: 14 | F60: =D60-E60 -> 6
... A63: OMNI | B63: party | C63: Phase 2 | D63: 35 | E63: 11 | F63: =D63-E63 -> 24
A64: OMNI | B64: package | C64: Phase 2 | D64: 12 | G64: Reference table
A65: OMNI | B65: service_type | C65: Phase 2 | D65: 8 | G65: Reference table
A66: OMNI | B66: fee_discount | C66: Phase 2 | D66: 15 | G66: Reference table
A67: OMNI | B67: od_registration | C67: Phase 2 | D67: 37 | E67: 25 | F67: =D67-E67 -> 12
A68: OMNI | B68: od_linked_deposit | C68: Phase 2 | D68: 11 | E68: 2 | F68: =D68-E68 -> 9
A69: OMNI | B69: salesman | C69: Phase 2
A70: OMNI | B70: customers | C70: Phase 2 | D70: 3 | E70: 3 | F70: =D70-E70 -> 0
A71: OMNI | B71: payment_history | C71: Phase 2 | D71: 26 | E71: 10 | F71: =D71-E71 -> 16
A72: BPM | B72: auth_to_chuc_don_vi | C72: Phase 1 | D72: 18 | E72: 18 | F72: =D72-E72 -> 0
A73: BPM | B73: auth_nhan_vien | C73: Phase 1 | D73: 14 | E73: 14 | F73: =D73-E73 -> 0
A74: BPM | B74: c_danh_muc | C74: Phase 1 | D74: 6 | E74: 6 | F74: =D74-E74 -> 0 | G74: Reference table
A75: BPM | B75: xl_ksgn_chung | C75: Phase 1 | D75: 93 | E75: 89 | F75: =D75-E75 -> 4 | G75: cbtmtttm_id, id_the_chinh, nhom_cbxl_gdtdv, tg_nhan_hs, user_cbkd thêm từ DBX: cap_pd_chung_id
A76: BPM | B76: sk10_san_pham | C76: Phase 1 | D76: 11 | E76: 11 | F76: 0 | G76: Reference table
A77: BPM | B77: qlns_nguoi_lao_dong_info | C77: Phase 1 | D77: 76 | E77: 76 | F77: 0
A78: BPM | B78: pdtd_tsbd_link | C78: Phase 1 | D78: 2 | E78: 2 | F78: 0
A79: BPM | B79: xl_ct_han_muc | C79: Phase 1 | D79: 13 | E79: 13 | F79: 0
A80: BPM | B80: auth_nhom | C80: Phase 1 | D80: 18 | E80: 19 | F80: 0 | G80: Reference table: thêm ma_nhom_ten từ DBX
A81: BPM | B81: giao_dich_sla | C81: Phase 1 | D81: 46 | E81: 46 | F81: 0
A82: BPM | B82: tsbd_giaodich_chitiet | C82: Phase 1 | D82: 37 | E82: 37 | F82: 0
A83: BPM | B83: giao_dich_link | C83: Phase 1 | D83: 14 | E83: 14 | F83: 0
A84: BPM | B84: tdtc_nghiep_vu_xl_gdtd | C84: Phase 1 | D84: 9 | E84: 9 | F84: 0
A85: BPM | B85: tdcn_xl_gdtd | C85: Phase 1 | D85: 13 | E85: 13 | F85: 0
A86: BPM | B86: tht_nhom_chinh_sach_the | C86: Phase 1 | D86: 14 | E86: 14 | F86: 0
A87: BPM | B87: pdtd_nhom_giao_dich | C87: Phase 1 | D87: 89 | E87: 90 | F87: 0 | G87: Thêm trường datadate
A88: BPM | B88: khach_hang | C88: Phase 1 | D88: 17 | E88: 17 | F88: 0
A89: BPM | B89: pdtd_san_pham | C89: Phase 1 | D89: 17 | E89: 19 | F89: 0 | G89: Thêm từ DBX: datadate, gd_chinh_id, rowid
A90: BPM | B90: giao_dich | C90: Phase 1 | D90: 17 | E90: 18 | F90: 0 | G90: Thêm từ DBX: datadate
A91: BPM | B91: tdcn_thong_tin_chung | C91: Phase 1 | D91: 42 | E91: 43 | F91: 0 | G91: Thêm từ DBX: datadate
A92: BPM | B92: tdcn_tai_san_bao_dam | C92: Phase 1 | D92: 11 | E92: 12 | F92: 0 | G92: Thêm từ DBX: datadate
A93: BPM | B93: danh_muc | C93: Phase 1 | D93: 11 | E93: 11 | F93: 0 | G93: Reference table
A94: BPM | B94: tsbd_giaodich_chinh | C94: Phase 1 | D94: 82 | E94: 83 | F94: 0 | G94: Thêm từ DBX: datadate
A95: BPM | B95: tsbd_tai_san | C95: Phase 1 | D95: 45 | E95: 46 | F95: 0 | G95: Thêm từ DBX: datadate
A96: BPM | B96: xl_pdtd_link | C96: Phase 1 | D96: 9 | E96: 10 | F96: 0 | G96: Thêm từ DBX: datadate
A97: BPM | B97: giao_dich_tsbd | C97: Phase 1 | D97: 17 | E97: 19 | F97: 0 | G97: Thêm từ DBX: datadate, rowid
A98: BPM | B98: tdtc_thong_tin_chung | C98: Phase 1 | D98: 16 | E98: 16 | F98: 0
A99: BPM | B99: tdtc_thong_tin_to_trinh | C99: Phase 1 | D99: 53 | E99: 53 | F99: 0
A100: BPM | B100: xl_ksgn_ct | C100: Phase 1 | D100: 12 | E100: 12 | F100: 0
A101: BPM | B101: xl_ct_lich_su | C101: Phase 1 | D101: 25 | E101: 25 | F101: 0
A102: BPM | B102: tsbd_giaodich_lich_su_V2 | C102: Phase 1 | D102: 28 | E102: 28 | F102: 0
...

Sheet Mapping Statistics
A1: Note: Những bảng được liệt kê là những bảng thuộc Phase 1, đã được OCB cung cấp dữ liệu trong file Metadata và có ở Vault Mapping. Những bảng còn lại không được liệt kê dưới đây thuộc bảng Reference
A2: Source | B2: Bảng | C2: Số lượng trường đã mapping | D2: Số lượng trường trong metadata | E2: Số trường còn lại (lưu ý: không tính những trường data_date vì đó là những trường load dữ liệu vào nguồn) | F2: Tên trường không đưa vào Raw vault | G2: Mô tả ở Metadata file | H2: Note
A3: T24 | B3: T24_CUSTOMER | C3: 97 | D3: 99 | E3: 2 | F3: SP_RATING | G3: STANDARD&POOR Loại xếp hạng | H3: trường nãy sẽ được đưa vào sau khi bổ sung thêm các trường xếp hạng theo basel lên bronze
F4: FITCH_RATING | G4: FITCH Loại xếp hạng | H4: trường nãy sẽ được đưa vào sau khi bổ sung thêm các trường xếp hạng theo basel lên bronze
A5: T24 | B5: T24_OCBH_CUS_EXT_INFO | C5: 15 | D5: 15 | E5: 0 | F5: N/A | G5: N/A
A6: T24 | B6: T24_DEPT_ACCT_OFFICER | C6: 34 | D6: 34 | E6: 0 | F6: N/A | G6: N/A
A7: T24 | B7: T24_CUS_PKG | C7: 13 | D7: 13 | E7: 0 | F7: N/A | G7: N/A
A8: T24 | B8: T24_OCBH_PROD_PACKAGE_PARTNER | C8: 16 | D8: 16 | E8: 0 | F8: N/A | G8: N/A
A9: T24 | B9: T24_USER | C9: 42 | D9: 43 | E9: 1 | F9: IP_ID | G9: Không có field này trong nguồn | H9: không thể bổ sung do không có ở nguồn
A10: T24 | B10: T24_COLLATERAL | C10: 91 | D10: 91 | E10: 0 | F10: N/A | G10: N/A
A11: T24 | B11: T24_COLLATERAL_RIGHT | C11: 12 | D11: 12 | E11: 0 | F11: N/A | G11: N/A
A12: T24 | B12: T24_OCBH_COLL_BASEL | C12: 25 | D12: 25 | E12: 0 | F12: N/A | G12: N/A
A13: T24 | B13: T24_ACCOUNT | C13: 53 | D13: 53 | E13: 0 | F13: N/A | G13: N/A
A14: T24 | B14: T24_ACCOUNT_DEBIT_INT | C14: 10 | D14: 12 | E14: 2 | F14: EFF_DT | G14: Không có field này trong nguồn | H14: không thể bổ sung do không có ở nguồn
F15: IS_MAX_EFF_DT | G15: Không có field này trong nguồn | H15: không thể bổ sung do không có ở nguồn
A16: T24 | B16: T24_ACCOUNT_CREDIT_INT | C16: 8 | D16: 8 | E16: 0 | F16: N/A | G16: N/A
A17: T24 | B17: T24_AC_LOCKED_EVENTS | C17: 11 | D17: 11 | E17: 0 | F17: N/A | G17: N/A
A18: T24 | B18: T24_OCBH_SUB_VIRTUAL_ACCOUNT | C18: 10 | D18: 10 | E18: 0 | F18: N/A | G18: N/A
A19: T24 | B19: T24_CRB | C19: 24 | D19: 24 | E19: 0 | F19: N/A | G19: N/A
A20: T24 | B20: T24_LOANS_AND_DEPOSITS | C20: 104 | D20: 104 | E20: 0 | F20: N/A | G20: N/A
A21: T24 | B21: T24_LD_SCHEDULE_DEFINE | C21: 10 | D21: 10 | E21: 0 | F21: N/A | G21: N/A
A22: T24 | B22: T24_PAYMENT_DUE | C22: 56 | D22: 56 | E22: 0 | F22: N/A | G22: N/A
A23: T24 | B23: T24_LD_APRV_INFO | C23: 10 | D23: 10 | E23: 0 | F23: N/A | G23: N/A
A24: T24 | B24: T24_LMM_ACCOUNT_BALANCES | C24: 23 | D24: 25 | E24: 2 | F24: AR_ID | G24: Không có field này trong nguồn | H24: không thể bổ sung do không có ở nguồn
F25: CRT_TM | G25: Không có field này trong nguồn | H25: không thể bổ sung do không có ở nguồn
A26: T24 | B26: T24_LN_CUST_REVS_DTLS | C26: 15 | D26: 15 | E26: 0 | F26: N/A | G26: N/A
A27: T24 | B27: T24_OCBH_LD_BASEL | C27: 15 | D27: 15 | E27: 0 | F27: N/A | G27: N/A
A28: T24 | B28: T24_LD_EXTRA_INFO | C28: 31 | D28: 31 | E28: 0 | F28: N/A | G28: N/A
A29: T24 | B29: T24_LIMIT | C29: 35 | D29: 37 | E29: 2 | F29: T_RATE | G29: Không có field này trong nguồn | H29: không thể bổ sung do không có ở nguồn
F30: AR_ID | G30: Không có field này trong nguồn | H30: không thể bổ sung do không có ở nguồn
A31: T24 | B31: T24_AZ_ACCOUNT | C31: 54 | D31: 56 | E31: 2 | F31: T_TERM_RATE | G31: Không có field này trong nguồn | H31: không thể bổ sung do không có ở nguồn
F32: T_ONLINE_ACTUAL_BAL | G32: Không có field này trong nguồn | H32: không thể bổ sung do không có ở nguồn
A33: T24 | B33: T24_CATEG_ENTRY | C33: 26 | D33: 26 | E33: 0 | F33: N/A | G33: N/A
A34: T24 | B34: T24_RE_STAT_LINE_BAL | C34: 17 | D34: 17 | E34: 0 | F34: N/A | G34: N/A
A35: T24 | B35: T24_PC_RE_STAT_LINE_BAL | C35: 18 | D35: 18 | E35: 0 | F35: N/A | G35: N/A
A36: T24 | B36: T24_CONSOLIDATE_PRFT_LOSS | C36: 6 | D36: 6 | E36: 0 | F36: N/A | G36: N/A
A37: T24 | B37: T24_LINE_MVMT_TOANHANG | C37: 15 | D37: 15 | E37: 0 | F37: N/A | G37: N/A
A38: T24 | B38: T24_RE_CONSOL_SPEC_ENTRY | C38: 30 | D38: 30 | E38: 0 | F38: N/A | G38: N/A
A39: T24 | B39: T24_STMT_ENTRY | C39: 35 | D39: 35 | E39: 0 | F39: N/A | G39: N/A
A40: T24 | B40: T24_CURRENCY | C40: 14 | D40: 14 | E40: 0 | F40: N/A | G40: N/A
A41: T24 | B41: T24_GDI | C41: 15 | D41: 15 | E41: 0 | F41: N/A | G41: N/A
A42: T24 | B42: T24_GCI | C42: 15 | D42: 15 | E42: 0 | F42: N/A | G42: N/A
A43: T24 | B43: T24_FOREX | C43: 64 | D43: 65 | E43: 1 | F43: AR_ID | G43: Không có field này trong nguồn | H43: không thể bổ sung do không có ở nguồn
A44: T24 | B44: T24_MONEY_MARKET | C44: 76 | D44: 76 | E44: 0 | F44: N/A | G44: N/A
A45: T24 | B45: T24_REPO | C45: 51 | D45: 51 | E45: 0 | F45: N/A | G45: N/A
A46: T24 | B46: T24_SECURITY_MASTER | C46: 60 | D46: 60 | E46: 0 | F46: N/A | G46: N/A
A47: T24 | B47: T24_SEC_TRADE | C47: 62 | D47: 62 | E47: 0 | F47: N/A | G47: N/A
A48: T24 | B48: T24_SC_TRADING_POSITION | C48: 27 | D48: 27 | E48: 0 | F48: N/A | G48: N/A
A49: T24 | B49: T24_LETTER_OF_CREDIT | C49: 59 | D49: 68 | E49: 9 | F49: LIMITLK_AR_ID | G49: Không có field này trong nguồn | H49: không thể bổ sung do không có ở nguồn
F50: LDREFLK_AR_ID | G50: Không có field này trong nguồn | H50: không thể bổ sung do không có ở nguồn
F51: CRPRVACCLK_AR_ID | G51: Không có field này trong nguồn | H51: không thể bổ sung do không có ở nguồn
F52: AR_ID | G52: Không có field này trong nguồn | H52: không thể bổ sung do không có ở nguồn
F53: T_RISK_COUNTRY | G53: Không có field này trong nguồn | H53: không thể bổ sung do không có ở nguồn
F54: T_OCB_BANK_ID | G54: Không có field này trong nguồn | H54: không thể bổ sung do không có ở nguồn
F55: T_OCB_SMARTLINK | G55: Không có field này trong nguồn | H55: không thể bổ sung do không có ở nguồn
F56: T_OCB_LD_HTLS | G56: Không có field này trong nguồn | H56: không thể bổ sung do không có ở nguồn
F57: T_OCB_TERM_HTLS | G57: Không có field này trong nguồn | H57: không thể bổ sung do không có ở nguồn
A58: T24 | B58: T24_DRAWINGS | C58: 23 | D58: 24 | E58: 1 | F58: AR_ID | G58: Không có field này trong nguồn | H58: không thể bổ sung do không có ở nguồn
A59: T24 | B59: T24_MD_DEAL | C59: 94 | D59: 98 | E59: 4 | F59: AR_ID | G59: Không có field này trong nguồn | H59: không thể bổ sung do không có ở nguồn
F60: LIMITLK_AR_ID | G60: Không có field này trong nguồn | H60: không thể bổ sung do không có ở nguồn
F61: T_CHARGE_DATE_MULTI_VAL | G61: Không có field này trong nguồn | H61: không thể bổ sung do không có ở nguồn
F62: T_CHARGE_AMT_MULTI_VAL | G62: Không có field này trong nguồn | H62: không thể bổ sung do không có ở nguồn
A63: T24 | B63: T24_FUNDS_TRANSFER | C63: 96 | D63: 99 | E63: 3 | F63: DEBIT_AR_ID | G63: Không có field này trong nguồn | H63: không thể bổ sung do không có ở nguồn
F64: CREDIT_AR_ID | G64: Không có field này trong nguồn | H64: không thể bổ sung do không có ở nguồn
F65: TXN_ID | G65: Không có field này trong nguồn | H65: không thể bổ sung do không có ở nguồn
A66: T24 | B66: T24_TELLER | C66: 48 | D66: 50 | E66: 2 | F66: ACCT2_AR_ID | G66: Không có field này trong nguồn | H66: không thể bổ sung do không có ở nguồn
F67: TXN_ID | G67: Không có field này trong nguồn | H67: không thể bổ sung do không có ở nguồn
A68: T24 | B68: T24_VMBL_INT_CLR_CITAD | C68: 37 | D68: 37 | E68: 0 | F68: N/A | G68: N/A
A69: WAY4 | B69: ACNT_CONTRACT | C69: 101 | D69: 101 | E69: =C69-D69 -> 0 | F69: N/A | G69: N/A
A70: WAY4 | B70: APPL_PRODUCT | C70: 50 | D70: 50 | E70: =C70-D70 -> 0 | F70: N/A | G70: N/A
A71: WAY4 | B71: BILLING_LOG | C71: 17 | D71: 17 | E71: =C71-D71 -> 0 | F71: N/A | G71: N/A
A72: WAY4 | B72: CLIENT | C72: 67 | D72: 67 | E72: =D72-C72 -> 0 | F72: N/A | G72: N/A | H72: Một số trường quan trọng đã thống nhất lấy từ bảng client_address: TITLE, SALUTATION_SUFFIX, BIRTH_NAM, COUNTRY, ADDRESS_ZIP, ADDRESS_LINE_1, ADDRESS_LINE_2, ADDRESS_LINE_3, ADDRESS_LINE_4, PHONE, PHONE_H, PHONE_M, FAX, FAX_H, E_MAIL, URL, STATE, CITY
A73: WAY4 | B73: CS_STATUS_LOG | C73: 23 | D73: 23 | E73: =C73-D73 -> 0 | F73: N/A | G73: N/A
A74: WAY4 | B74: DEVICE_REC | C74: 39 | D74: 39 | E74: =C74-D74 -> 0 | F74: N/A | G74: N/A
A75: WAY4 | B75: DOC | C75: 89 | D75: 89 | E75: =C75-D75 -> 0 | F75: N/A | G75: N/A
A76: WAY4 | B76: ENTRY | C76: 33 | D76: 33 | E76: =C76-D76 -> 0 | F76: N/A | G76: N/A
A77: WAY4 | B77: M_TRANSACTION | C77: 34 | D77: 34 | E77: =C77-D77 -> 0 | F77: N/A | G77: N/A
A78: WAY4 | B78: TEMPL_APPROVED | C78: 58 | D78: 58 | E78: =D78-C78 -> 0 | F78: N/A | G78: N/A
A79: WAY4 | B79: BALANCE | C79: 39 | D79: 39 | E79: =C79-D79 -> 0 | F79: N/A | G79: N/A
A80: WAY4 | B80: ACQ_DEV_CYCLE | C80: 14 | D80: 14 | E80: =C80-D80 -> 0 | F80: N/A | G80: N/A
A81: WAY4 | B81: BILLING | C81: 42 | D81: 42 | E81: =C81-D81 -> 0 | F81: N/A | G81: N/A
A82: WAY4 | B82: PAYMENT | C82: 20 | D82: 20 | E82: =C82-D82 -> 0 | F82: N/A | G82: N/A
A83: OMNI | B83: EN_USER | C83: 14 | D83: 14 | E83: =C83-D83 -> 0 | F83: N/A | G83: N/A
A84: OMNI | B84: ONBOARDING_REPORT | C84: 10 | D84: 10 | E84: =C84-D84 -> 0 | F84: N/A | G84: N/A
A85: OMNI | B85: PAYMENT_ORDER.PMT_ORDER | C85: 52 | D85: 52 | E85: =C85-D85 -> 0 | F85: N/A | G85: N/A
A86: OMNI | B86: OVERSEA_FT_REQUEST | C86: 49 | D86: 49 | E86: =C86-D86 -> 0 | F86: N/A | G86: N/A
A87: OMNI | B87: AUTO_DEBIT | C87: 31 | D87: 35 | E87: =D87-C87 -> 4 | F87: ENTRUST_PAYMENT | G87: Không có field này trong nguồn
F88: ENTRUST_BANK_REF | G88: Không có field này trong nguồn
F89: ENTRUST_SERVICE_NAME | G89: Không có field này trong nguồn
F90: BILL_CODE_TYPE | G90: Không có field này trong nguồn
A91: OMNI | B91: OMNI_SERVICE | C91: 35 | D91: 35 | E91: =C91-D91 -> 0 | F91: N/A | G91: N/A
A92: OMNI | B92: AUDIT_MESSAGE | C92: 25 | D92: 25 | E92: =C92-D92 -> 0 | F92: N/A | G92: N/A
A93: BPM | B93: AUTH_TO_CHUC_DON_VI | C93: 18 | D93: 18 | E93: 0 | F93: N/A | G93: N/A
A94: BPM | B94: AUTH_NHAN_VIEN | C94: 14 | D94: 14 | E94: 0 | F94: N/A | G94: N/A
A95: BPM | B95: XL_KSGN_CHUNG | C95: 93 | D95: 89 | E95: 0 | F95: N/A | G95: N/A
A96: BPM | B96: QLNS_NGUOI_LAO_DONG_INFO | C96: 76 | D96: 76 | E96: 0 | F96: NA | G96: NA
A97: BPM | B97: PDTD_TSBD_LINK | C97: 2 | D97: 2 | E97: 0 | F97: N/A | G97: N/A
A98: BPM | B98: TSBD_TAI_SAN | C98: 46 | D98: 46 | E98: 0 | F98: N/A | G98: N/A
A99: BPM | B99: XL_CT_HAN_MUC | C99: 13 | D99: 13 | E99: 0 | F99: N/A | G99: N/A
A100: BPM | B100: GIAO_DICH_SLA | C100: 46 | D100: 46 | E100: 0 | F100: N/A | G100: N/A
...

Sheet Cover
B6: Chuyển giao tài liệu
B7: SP2. Tài liệu phân tích nguồn dữ liệu và thiết kế luồng dữ liệu
B9: Dự án: | C9: TRIỂN KHAI HỆ THỐNG VÙNG DỮ LIỆU SILVER TRÊN NỀN TẢNG DATABRICKS
B10: Thông tin liên hệ:
B11: Cuong Huy Nguyen
B12: Director
B13: Raffles VN Co. Ltd.
B14: Level 5, Sentinel Place, 41A Ly Thai To, Hoan Kiem Dt., Hanoi, Vietnam
B15: Tel: +84 4 39388826
B16: Cell: +65 9879 1959 / + 84 912153459
B17: Email: cuongnguyen@raffles.com.vn
B19: Long Quang Nguyen
B20: Manager
B21: Raffles VN Co. Ltd.
B22: Level 5, Sentinel Place, 41A Ly Thai To, Hoan Kiem Dt., Hanoi, Vietnam
... B29: Thực hiện bởi Raffles VN Co. Ltd

Sheet Rules
A1: Nhóm nguyên tắc | B1: Nội dung | C1: Mô tả / Quy định áp dụng | D1: Ví dụ / Thông tin chi tiết
A2: Nguyên tắc chung | B2: Định hướng thiết kế | C2: Áp dụng mô hình Data Vault 2.0 để tích hợp dữ liệu đa nguồn, lưu lịch sử đầy đủ, đảm bảo khả năng mở rộng và truy vết dữ liệu.
B3: Phạm vi dữ liệu | C3: Chỉ đưa vào Data Vault các nguồn dữ liệu phục vụ cho SOR, BCN, Basel và Feature Store. | D3: T24: 15 Groups (Entity, Loan, Security, Account, Accounting, Transaction, Trade Finance, Money Market, Collateral, Forex, Deposit, Currency, Limit, Calendar, Deposit) WAY4: 8 Groups (Contract, Accounting, Transaction, Entity, Device, Card, Product, Issuing) OMNI: 15 Groups (Omni_Service, Payment_Order, Cc_Registration, Od_Registration, Voucher, Transfer Bill, Party, Account_Information, Notification, Device, User_Omni, Data_Sharing_Consent, Onboarding_Report, Clevertap_Tracking, Customer) BPM: 5 Groups (Entity, Giải ngân, Giao dịch, Phê duyệt, TSBD) Appsflyer: 5 Groups (Installs, Reinstalls, In_App_Events, Uninstall, Appsflyer) CRM&CallCenter: 4 Groups (Contact, User, Callcenter, Campaign) Clevertap: 2 Groups (Campaign, Event)
A4: Nguyên tắc thiết kế | B4: Business Object | C4: Business Object được xác định theo tên bảng nguồn (Source Table). Chỉ chuẩn hoá và đặt lại tên khi tên nguồn không phản ánh rõ đối tượng nghiệp vụ.
B5: Business Key | C5: Sử dụng khóa nghiệp vụ (Business Key) làm cơ sở định danh, không phụ thuộc khóa kỹ thuật nguồn. | D5: T24_ACCOUNT.ID, T24_COLLATERAL.ID Đặc biệt: T24_CRB có BK = T24_CRB.TIEUKHOAN + T24_CRB.GL (composite key)
B6: Content | C6: Phân loại nhóm thông tin hoặc ngữ cảnh dữ liệu. | D6: information, classification, amount, status_log, type, status,...
B7: Cấu trúc tên bảng | C7: Hub: hub_<Business Object> Sat: sat_<Business Object>_<Content> Link: link_<Business Object Main>_<Business Object Other> Sts: sts_hub_<Business Object> Effsat: effsat_link_<Business Object Main>_<Business Object Other> | D7: hub_billing_log sat_billing_log_information link_billing_log_account_contract sts_hub_billing_log effsat_link_billing_log_account_contract
B8: Hashkey | C8: Mỗi Hub/Link có cột <entity>_hashkey [PK] tạo ra từ hàm hash từ Business Key. Bảng Sat tham chiếu hashkey của Hub tương ứng làm FK. | D8: hub_account.account_hashkey = hash(T24_ACCOUNT.ID) link_card_client.lnk_card_client_hashkey = hash(card_id || client_id)
B9: Cấu trúc tên cột | C9: Tên cột từ cột tương ứng của Business Object.
B10: Data Type | C10: Kiểu dữ liệu từ cột tương ứng của Business Object (được thống nhất từ metadata). | D10: string, number, date
B11: Cú pháp mapping | C11: <Source Table>.<Column> | D11: T24_ACCOUNT.T_ACCOUNT_TITLE_1
B12: Bộ lọc bản ghi nguồn | C12: Chỉ lấy bản ghi đang hoạt động. Áp dụng điều kiện lọc phù hợp với từng hệ thống nguồn.
B13: Các trường nghiệp vụ bắt buộc | C13: • source_event_date: Ngày sự kiện nguồn phát sinh bản ghi, dùng làm thành phần xác định phiên bản dữ liệu. • hashdiff: Giá trị hash tổng hợp của toàn bộ cột nội dung (payload), dùng để phát hiện thay đổi. • record_source: Tên hệ thống nguồn phát sinh dữ liệu. | D13: sat_loans_information: source_event_date = ngày ETL chạy (ví dụ: 2025-01-01) hashdiff = MD5(t_loan_amount || t_maturity || t_interest_rate || ...) record_source = 'T24'
B14: Quy tắc đặt tên bảng cho Business Vault (BV) | C14: Các bảng Business Vault đặt tên theo loại bảng và business object liên quan: • Point-in-Time (PIT): pit_<Business Object> • Bridge: bridge_<Business Object chính> • AsOfDate: calendar (bảng lịch dùng chung) Tên bảng BV không thêm tiền tố nguồn (không dùng hub_/sat_/link_). Business Object trong BV lấy từ Hub trung tâm mà PIT hoặc Bridge tham chiếu. | D14: pit_loan → PIT cho hub_loans pit_account → PIT cho hub_account pit_customer → PIT cho hub_customer bridge_loan → Bridge tổng hợp từ hub_crb, hub_loans, hub_account, hub_customer, hub_branch bridge_card → Bridge tổng hợp cho nghiệp vụ thẻ calendar → Bảng lịch (asOfDate)
B15: Quy tắc xác định khóa nghiệp vụ (Business Key - BK) theo từng loại bảng Raw Vault | C15: Business Key (BK) là khóa nghiệp vụ từ hệ thống nguồn, dùng để định danh duy nhất một thực thể. Hashkey được tạo bằng hàm hash (SHA256) từ BK, không thay thế BK. • Hub: BK là khóa tự nhiên của bảng nguồn (thường là trường ID). Composite BK khi một thực thể cần nhiều trường để định danh duy nhất. • Link: BK là tập hợp BK của các Hub tham gia liên kết. Hashkey của Link được tính từ tổ hợp BK này. • Sat: Không có BK riêng. Loại bảng này thừa kế BK từ Hub liên kết qua hashkey (FK). • Effsat: Không có BK riêng. Loại bảng này thừa kế BK từ Link liên kết qua hashkey (FK). • Sts: BK giống Hub tương ứng, dùng để ghi nhận trạng thái xóa / tái xuất hiện của một thực thể Hub. | D15: Hub có BK: hub_client.business_key = ows_client.id hub_acnt_contract.business_key = ows_acnt_contract.id Hub có composite BK: hub_crb.business_key = T24_CRB.TIEUKHOAN + T24_CRB.GL Link BK (tổ hợp BK các Hub): link_client_customer.link_client_customer_hashkey = hash(ows_client.id || ows_client.client_number) link_device_acnt_contract.link_device_acnt_contract_hashkey = hash(ows_device_rec.id || ows_device_rec.acnt_contract__oid) Sat - kế thừa BK từ Hub: sat_client_classification.client_hashkey = hash(ows_client.id) → BK = hub_client.business_key Sts - kế thừa BK từ Hub: sts_hub_client.client_hashkey = hash(ows_client.id) → BK = hub_client.business_key

Sheet T24 Vault Mapping_Phase1
A1: Source_system | B1: Group | C1: Table Name | D1: Column Name | E1: Description | F1: Data Type | G1: Mapping | H1: Key | I1: Phase
A2: T24 | B2: ACCOUNT | C2: hub_virtual_account | D2: virtual_account_hashkey | E2: Hub Virtual Account | F2: string | G2: T24_OCBH_SUB_VIRTUAL_ACCOUNT.ID | H2: [PK] | I2: Phase 1
A3: T24 | B3: ACCOUNT | C3: hub_virtual_account | D3: business_key | E3: Business Key | F3: string | G3: T24_OCBH_SUB_VIRTUAL_ACCOUNT.ID | I3: Phase 1
A4: T24 | B4: ACCOUNT | C4: sts_hub_virtual_account | D4: account_hashkey | E4: Hub Hash Key tài khoản | F4: string | G4: hub_virtual_account.virtual_account_hashkey | H4: [PK] | I4: Phase 1
A5: T24 | B5: ACCOUNT | C5: sts_hub_virtual_account | D5: source_event_date | E5: Ngày sự kiện nguồn | F5: date | G5: N/A | I5: Phase 1
A6: T24 | B6: ACCOUNT | C6: sts_hub_virtual_account | D6: cdc_status | E6: Trạng thái CDC - Change Data Capture (D = Deleted, I = Insert/ Reinsert) • D (Deleted): ID đã tồn tại trong Hub nhưng bị mất dấu (xóa vật lý) ở bảng nguồn trong ngày tương ứng source_event_date • I (Inserted/Reinserted): ID từng bị xóa trong quá khứ, nay xuất hiện trở lại ở bảng nguồn trong ngày tương ứng source_event_date | F6: string | G6: N/A | I6: Phase 1
A7: T24 | B7: ACCOUNT | C7: hub_account_locked_events | D7: ac_locked_events_hashkey | E7: Hub Hash Key Account Locked | F7: string | G7: T24_AC_LOCKED_EVENTS.ID | H7: [PK] | I7: Phase 1
A8: T24 | B8: ACCOUNT | C8: hub_account_locked_events | D8: business_key | E8: Business Key | F8: string | G8: T24_AC_LOCKED_EVENTS.ID | I8: Phase 1
A9: T24 | B9: ACCOUNT | C9: sts_hub_account_locked_events | D9: ac_locked_events_hashkey | E9: Hub Hash Key Account Locked | F9: string | G9: hub_account_locked_events.ac_locked_events_hashkey | H9: [PK] | I9: Phase 1
A10: T24 | B10: ACCOUNT | C10: sts_hub_account_locked_events | D10: source_event_date | E10: Ngày sự kiện nguồn | F10: date | G10: N/A | I10: Phase 1
A11: T24 | B11: ACCOUNT | C11: sts_hub_account_locked_events | D11: cdc_status | E11: Trạng thái CDC - Change Data Capture (D = Deleted, I = Insert/ Reinsert) • D (Deleted): ID đã tồn tại trong Hub nhưng bị mất dấu (xóa vật lý) ở bảng nguồn trong ngày tương ứng source_event_date • I (Inserted/Reinserted): ID từng bị xóa trong quá khứ, nay xuất hiện trở lại ở bảng nguồn trong ngày tương ứng source_event_date | F11: string | G11: N/A | I11: Phase 1
A12: T24 | B12: ACCOUNT | C12: hub_account | D12: account_hashkey | E12: Hub Hash Key tài khoản | F12: string | G12: T24_ACCOUNT.ID | H12: [PK] | I12: Phase 1
A13: T24 | B13: ACCOUNT | C13: hub_account | D13: business_key | E13: Business Key: Mã tài khoản | F13: string | G13: T24_ACCOUNT.ID | I13: Phase 1
A14: T24 | B14: ACCOUNT | C14: sts_hub_account | D14: account_hashkey | E14: Hub Hash Key tài khoản | F14: string | G14: hub_account.account_hashkey | H14: [PK] | I14: Phase 1
A15: T24 | B15: ACCOUNT | C15: sts_hub_account | D15: source_event_date | E15: Ngày sự kiện nguồn | F15: date | G15: N/A | I15: Phase 1
A16: T24 | B16: ACCOUNT | C16: sts_hub_account | D16: cdc_status | E16: Trạng thái CDC - Change Data Capture (D = Deleted, I = Insert/ Reinsert) • D (Deleted): ID đã tồn tại trong Hub nhưng bị mất dấu (xóa vật lý) ở bảng nguồn trong ngày tương ứng source_event_date • I (Inserted/Reinserted): ID từng bị xóa trong quá khứ, nay xuất hiện trở lại ở bảng nguồn trong ngày tương ứng source_event_date | F16: string | G16: N/A | I16: Phase 1
A17: T24 | B17: ACCOUNT | C17: sat_virtual_account | D17: virtual_account_hashkey | E17: Hub Virtual Account | F17: string | G17: T24_OCBH_SUB_VIRTUAL_ACCOUNT.ID | H17: [PK] | I17: Phase 1
A18: T24 | B18: ACCOUNT | C18: sat_virtual_account | D18: t_va_id | E18: Prefix của ID TK định danh | F18: string | G18: T24_OCBH_SUB_VIRTUAL_ACCOUNT.T_VA_ID | I18: Phase 1
A19: T24 | B19: ACCOUNT | C19: sat_virtual_account | D19: t_sub_id | E19: Surfix của ID TK định danh | F19: string | G19: T24_OCBH_SUB_VIRTUAL_ACCOUNT.T_SUB_ID | I19: Phase 1
A20: T24 | B20: ACCOUNT | C20: sat_virtual_account | D20: t_sub_va_name | E20: Tên TK định danh | F20: string | G20: T24_OCBH_SUB_VIRTUAL_ACCOUNT.T_SUB_VA_NAME | I20: Phase 1
A21: T24 | B21: ACCOUNT | C21: sat_virtual_account | D21: t_credit_acct_spa | E21: TK ghi có của TK định danh | F21: string | G21: T24_OCBH_SUB_VIRTUAL_ACCOUNT.T_CREDIT_ACCT_SPA | I21: Phase 1
A22: T24 | B22: ACCOUNT | C22: sat_virtual_account | D22: t_sva_record_status | E22: Tình trạng bản ghi ( Duyệt/chờ duyệt) | F22: string | G22: T24_OCBH_SUB_VIRTUAL_ACCOUNT.T_SVA_RECORD_STATUS | I22: Phase 1
A23: T24 | B23: ACCOUNT | C23: sat_virtual_account | D23: t_sva_status | E23: Tình trạng ( Active/Inative_ | F23: string | G23: T24_OCBH_SUB_VIRTUAL_ACCOUNT.T_SVA_STATUS | I23: Phase 1
A24: T24 | B24: ACCOUNT | C24: sat_virtual_account | D24: t_date_time_input | E24: Ngày nhập | F24: string | G24: T24_OCBH_SUB_VIRTUAL_ACCOUNT.T_DATE_TIME_INPUT | I24: Phase 1
A25: T24 | B25: ACCOUNT | C25: sat_virtual_account | D25: t_date_time_approval | E25: Ngày duyệt | F25: string | G25: T24_OCBH_SUB_VIRTUAL_ACCOUNT.T_DATE_TIME_APPROVAL | I25: Phase 1
A26: T24 | B26: ACCOUNT | C26: sat_account_system | D26: account_hashkey | E26: Hub Hash Key tài khoản | F26: string | G26: T24_ACCOUNT.ID | H26: [PK] | I26: Phase 1
A27: T24 | B27: ACCOUNT | C27: sat_account_system | D27: t_inputter | E27: Người nhập | F27: string | G27: T24_ACCOUNT.T_INPUTTER | I27: Phase 1
A28: T24 | B28: ACCOUNT | C28: sat_account_system | D28: t_authoriser | E28: Người duyệt | F28: string | G28: T24_ACCOUNT.T_AUTHORISER | I28: Phase 1
A29: T24 | B29: ACCOUNT | C29: sat_account_system | D29: t_date_time | E29: Ngày giờ cập nhật thông tin TK | F29: string | G29: T24_ACCOUNT.T_DATE_TIME | I29: Phase 1
A30: T24 | B30: ACCOUNT | C30: sat_account_system | D30: t_date_last_update | E30: Ngày phát sinh giao dịch sau cùng | F30: string | G30: T24_ACCOUNT.T_DATE_LAST_UPDATE | I30: Phase 1
A31: T24 | B31: ACCOUNT | C31: sat_account_system | D31: t_package_date | E31: Mã gói ưu đãi KHDN (Smart) | F31: string | G31: T24_ACCOUNT.T_PACKAGE_DATE | I31: Phase 1
A32: T24 | B32: ACCOUNT | C32: sat_account_system | D32: t_curr_no | E32: Số lần thay đổi | F32: string | G32: T24_ACCOUNT.T_CURR_NO | I32: Phase 1
A33: T24 | B33: ACCOUNT | C33: sat_account_system | D33: t_ocb_reason_rest | E33: Lý do hạn chế TK | F33: string | G33: T24_ACCOUNT.T_OCB_REASON_REST | I33: Phase 1
A34: T24 | B34: ACCOUNT | C34: sat_account_other | D34: account_hashkey | E34: Hub Hash Key tài khoản | F34: string | G34: T24_ACCOUNT.ID | H34: [PK] | I34: Phase 1
A35: T24 | B35: ACCOUNT | C35: sat_account_other | D35: t_open_cleared_bal | E35: Không dùng | F35: decimal(23,4) | G35: T24_ACCOUNT.T_OPEN_CLEARED_BAL | I35: Phase 1
A36: T24 | B36: ACCOUNT | C36: sat_account_other | D36: t_online_cleared_bal | E36: Không dùng | F36: decimal(23,4) | G36: T24_ACCOUNT.T_ONLINE_CLEARED_BAL | I36: Phase 1
A37: T24 | B37: ACCOUNT | C37: sat_account_other | D37: t_int_balance | E37: Không dùng | F37: decimal(15,4) | G37: T24_ACCOUNT.T_INT_BALANCE | I37: Phase 1
A38: T24 | B38: ACCOUNT | C38: sat_account_other | D38: t_ref_officer | E38: Không dùng | F38: string | G38: T24_ACCOUNT.T_REF_OFFICER | I38: Phase 1
A39: T24 | B39: ACCOUNT | C39: sat_account_other | D39: t_master_account | E39: Không dùng | F39: string | G39: T24_ACCOUNT.T_MASTER_ACCOUNT | I39: Phase 1
A40: T24 | B40: ACCOUNT | C40: sat_account_other | D40: t_int_liqu_acct | E40: Không dùng | F40: string | G40: T24_ACCOUNT.T_INT_LIQU_ACCT | I40: Phase 1
A41: T24 | B41: ACCOUNT | C41: sat_account_other | D41: t_accr_dr_amount | E41: Không dùng | F41: string | G41: T24_ACCOUNT.T_ACCR_DR_AMOUNT | I41: Phase 1
A42: T24 | B42: ACCOUNT | C42: sat_account_other | D42: t_dpi_fin_date | E42: Không dùng (ptud 744 ) | F42: string | G42: T24_ACCOUNT.T_DPI_FIN_DATE | I42: Phase 1
A43: T24 | B43: ACCOUNT | C43: sat_account_other | D43: t_tran_last_cr_cust | E43: Không dùng | F43: string | G43: T24_ACCOUNT.T_TRAN_LAST_CR_CUST | I43: Phase 1
A44: T24 | B44: ACCOUNT | C44: sat_account_other | D44: t_tran_last_dr_cust | E44: Không dùng | F44: string | G44: T24_ACCOUNT.T_TRAN_LAST_DR_CUST | I44: Phase 1
A45: T24 | B45: ACCOUNT | C45: sat_account_locked_events | D45: ac_locked_events_hashkey | E45: Hub Hash Key Account Locked | F45: string | G45: T24_AC_LOCKED_EVENTS.ID | H45: [PK] | I45: Phase 1
A46: T24 | B46: ACCOUNT | C46: sat_account_locked_events | D46: t_account_number | E46: Số tài khoản | F46: string | G46: T24_AC_LOCKED_EVENTS.T_ACCOUNT_NUMBER | I46: Phase 1
A47: T24 | B47: ACCOUNT | C47: sat_account_locked_events | D47: t_description | E47: Diễn giải | F47: string | G47: T24_AC_LOCKED_EVENTS.T_DESCRIPTION | I47: Phase 1
A48: T24 | B48: ACCOUNT | C48: sat_account_locked_events | D48: t_from_date | E48: Từ ngày | F48: string | G48: T24_AC_LOCKED_EVENTS.T_FROM_DATE | I48: Phase 1
A49: T24 | B49: ACCOUNT | C49: sat_account_locked_events | D49: t_to_date | E49: Đến ngày | F49: string | G49: T24_AC_LOCKED_EVENTS.T_TO_DATE | I49: Phase 1
A50: T24 | B50: ACCOUNT | C50: sat_account_locked_events | D50: t_locked_amount | E50: Số tiền phong tỏa | F50: decimal(38, 10) | G50: T24_AC_LOCKED_EVENTS.T_LOCKED_AMOUNT | I50: Phase 1
A51: T24 | B51: ACCOUNT | C51: sat_account_locked_events | D51: t_inputter | E51: Người nhập | F51: string | G51: T24_AC_LOCKED_EVENTS.T_INPUTTER | I51: Phase 1
A52: T24 | B52: ACCOUNT | C52: sat_account_locked_events | D52: t_authoriser | E52: Người duyệt | F52: string | G52: T24_AC_LOCKED_EVENTS.T_AUTHORISER | I52: Phase 1
A53: T24 | B53: ACCOUNT | C53: sat_account_locked_events | D53: t_date_time | E53: Ngày giờ thực hiện | F53: string | G53: T24_AC_LOCKED_EVENTS.T_DATE_TIME | I53: Phase 1
A54: T24 | B54: ACCOUNT | C54: sat_account_locked_events | D54: t_block_reason | E54: Lý do phong tỏa | F54: string | G54: T24_AC_LOCKED_EVENTS.T_BLOCK_REASON | I54: Phase 1
A55: T24 | B55: ACCOUNT | C55: sat_account_information | D55: account_hashkey | E55: Hub Hash Key tài khoản | F55: string | G55: T24_ACCOUNT.ID | H55: [PK] | I55: Phase 1
A56: T24 | B56: ACCOUNT | C56: sat_account_information | D56: t_account_title_1 | E56: Tên tài khoản 1 | F56: string | G56: T24_ACCOUNT.T_ACCOUNT_TITLE_1 | I56: Phase 1
A57: T24 | B57: ACCOUNT | C57: sat_account_information | D57: t_account_title_2 | E57: Tên tài khoản 2 | F57: string | G57: T24_ACCOUNT.T_ACCOUNT_TITLE_2 | I57: Phase 1
A58: T24 | B58: ACCOUNT | C58: sat_account_information | D58: t_short_title | E58: Tên tài khoản rút ngắn | F58: string | G58: T24_ACCOUNT.T_SHORT_TITLE | I58: Phase 1
A59: T24 | B59: ACCOUNT | C59: sat_account_information | D59: t_opening_date | E59: Ngày mở TK | F59: string | G59: T24_ACCOUNT.T_OPENING_DATE | I59: Phase 1
A60: T24 | B60: ACCOUNT | C60: sat_account_information | D60: t_create_date | E60: Ngày tạo | F60: string | G60: T24_ACCOUNT.T_CREATE_DATE | I60: Phase 1
A61: T24 | B61: ACCOUNT | C61: sat_account_information | D61: t_mature_date | E61: Ngày đáo hạn | F61: string | G61: T24_ACCOUNT.T_MATURE_DATE | I61: Phase 1
A62: T24 | B62: ACCOUNT | C62: sat_account_information | D62: t_value_date | E62: Ngày giá trị | F62: string | G62: T24_ACCOUNT.T_VALUE_DATE | I62: Phase 1
A63: T24 | B63: ACCOUNT | C63: sat_account_information | D63: t_acct_close_date | E63: Ngày đóng tài khoản | F63: string | G63: T24_ACCOUNT_CLOSED.T_ACCT_CLOSE_DATE | I63: Phase 1
A64: T24 | B64: ACCOUNT | C64: sat_account_information | D64: t_term_xau | E64: Kỳ hạn | F64: string | G64: T24_ACCOUNT.T_TERM_XAU | I64: Phase 1
A65: T24 | B65: ACCOUNT | C65: sat_account_information | D65: t_posting_restrict | E65: Thuộc tính hạn chế tài khoản | F65: string | G65: T24_ACCOUNT.T_POSTING_RESTRICT | I65: Phase 1
A66: T24 | B66: ACCOUNT | C66: sat_account_information | D66: t_record_status | E66: Tình trạng bản ghi | F66: string | G66: T24_ACCOUNT.T_RECORD_STATUS | I66: Phase 1
A67: T24 | B67: ACCOUNT | C67: sat_account_information | D67: t_alt_acct_id | E67: Số TK cũ | F67: string | G67: T24_ACCOUNT.T_ALT_ACCT_ID | I67: Phase 1
... A72: T24 | B72: ACCOUNT | C72: sat_account_information | D72: t_ocb_beauty_sts | E72: Kênh mở TK ngắn | F72: string | G72: T24_ACCOUNT.T_OCB_BEAUTY_STS | I72: Phase 1
A73: T24 | B73: ACCOUNT | C73: sat_account_debit_int | D73: account_hashkey | E73: Hub Hash Key tài khoản | F73: string | G73: T24_ACCOUNT_DEBIT_INT.ID -- cắt chuỗi trước dấu '-' (lấy phần đầu) | H73: [PK] | I73: Phase 1
A74: T24 | B74: ACCOUNT | C74: sat_account_debit_int | D74: ma_key | E74: Ngày áp dụng lãi suất | F74: string | G74: T24_ACCOUNT_DEBIT_INT.ID -- cắt chuỗi sau dấu '-' (lấy phần sau) | H74: [PK] | I74: Phase 1
A75: T24 | B75: ACCOUNT | C75: sat_account_debit_int | D75: t_charge_key | E75: Mã code phí | F75: string | G75: T24_ACCOUNT_DEBIT_INT.T_CHARGE_KEY | I75: Phase 1
A76: T24 | B76: ACCOUNT | C76: sat_account_debit_int | D76: t_interest_day_basis | E76: Cơ sở tính lãi | F76: string | G76: T24_ACCOUNT_DEBIT_INT.T_INTEREST_DAY_BASIS | I76: Phase 1
A77: T24 | B77: ACCOUNT | C77: sat_account_debit_int | D77: t_dr_balance_type | E77: Cách tính số dư ghi nợ | F77: string | G77: T24_ACCOUNT_DEBIT_INT.T_DR_BALANCE_TYPE | I77: Phase 1
A78: T24 | B78: ACCOUNT | C78: sat_account_debit_int | D78: t_dr_calcul_type | E78: Phương pháp tính lãi ghi nợ | F78: string | G78: T24_ACCOUNT_DEBIT_INT.T_DR_CALCUL_TYPE | I78: Phase 1
A79: T24 | B79: ACCOUNT | C79: sat_account_debit_int | D79: t_dr_int_rate | E79: Lãi suất ghi nợ | F79: decimal(38, 10) | G79: T24_ACCOUNT_DEBIT_INT.T_DR_INT_RATE | I79: Phase 1
A80: T24 | B80: ACCOUNT | C80: sat_account_debit_int | D80: t_dr_margin_rate | E80: Giá trị biên độ để điều chỉnh lãi suất | F80: decimal(38, 10) | G80: T24_ACCOUNT_DEBIT_INT.T_DR_MARGIN_RATE | I80: Phase 1
A81: T24 | B81: ACCOUNT | C81: sat_account_debit_int | D81: t_dr_basic_rate | E81: Mức Lãi suất cơ bản ghi nợ | F81: decimal(38, 10) | G81: T24_ACCOUNT_DEBIT_INT.T_DR_BASIC_RATE | I81: Phase 1
A82: T24 | B82: ACCOUNT | C82: sat_account_debit_int | D82: t_dr_margin_oper | E82: Phương pháp điều chỉnh lãi suất bằng biên độ | F82: string | G82: T24_ACCOUNT_DEBIT_INT.T_DR_MARGIN_OPER | I82: Phase 1
A83: T24 | B83: ACCOUNT | C83: sts_hub_account_debit_int | D83: account_hashkey | E83: Hub Hash Key tài khoản | F83: string | G83: hub_account.account_hashkey | H83: [PK] | I83: Phase 1
A84: T24 | B84: ACCOUNT | C84: sts_hub_account_debit_int | D84: source_event_date | E84: Ngày sự kiện nguồn | F84: date | G84: N/A | I84: Phase 1
A85: T24 | B85: ACCOUNT | C85: sts_hub_account_debit_int | D85: cdc_status | E85: Trạng thái CDC - Change Data Capture (D = Deleted, I = Insert/ Reinsert) • D (Deleted): ID đã tồn tại trong Hub nhưng bị mất dấu (xóa vật lý) ở bảng nguồn trong ngày tương ứng source_event_date • I (Inserted/Reinserted): ID từng bị xóa trong quá khứ, nay xuất hiện trở lại ở bảng nguồn trong ngày tương ứng source_event_date | F85: string | G85: N/A | I85: Phase 1
A86: T24 | B86: ACCOUNT | C86: sat_account_credit_int | D86: account_hashkey | E86: Hub Hash Key tài khoản | F86: string | G86: T24_ACCOUNT_CREDIT_INT.ID -- cắt chuỗi trước dấu '-' (lấy phần đầu) | H86: [PK] | I86: Phase 1
A87: T24 | B87: ACCOUNT | C87: sat_account_credit_int | D87: ma_key | E87: Ngày áp dụng lãi suất | F87: string | G87: T24_ACCOUNT_CREDIT_INT.ID -- cắt chuỗi sau dấu '-' (lấy phần sau) | H87: [PK] | I87: Phase 1
A88: T24 | B88: ACCOUNT | C88: sat_account_credit_int | D88: t_interest_day_basis | E88: Cơ sở tính lãi | F88: string | G88: T24_ACCOUNT_CREDIT_INT.T_INTEREST_DAY_BASIS | I88: Phase 1
A89: T24 | B89: ACCOUNT | C89: sat_account_credit_int | D89: t_cr_balance_type | E89: Loại số dư tính lãi ghi có | F89: string | G89: T24_ACCOUNT_CREDIT_INT.T_CR_BALANCE_TYPE | I89: Phase 1
A90: T24 | B90: ACCOUNT | C90: sat_account_credit_int | D90: t_cr_calcul_type | E90: Phương pháp tính lãi ghi có | F90: string | G90: T24_ACCOUNT_CREDIT_INT.T_CR_CALCUL_TYPE | I90: Phase 1
A91: T24 | B91: ACCOUNT | C91: sat_account_credit_int | D91: t_cr_int_rate | E91: Lãi suất ghi có | F91: string | G91: T24_ACCOUNT_CREDIT_INT.T_CR_INT_RATE | I91: Phase 1
A92: T24 | B92: ACCOUNT | C92: sat_account_credit_int | D92: t_cr_margin_rate | E92: Margin lãi suất | F92: string | G92: T24_ACCOUNT_CREDIT_INT.T_CR_MARGIN_RATE | I92: Phase 1
A93: T24 | B93: ACCOUNT | C93: sat_account_credit_int | D93: t_cr_minimum_bal | E93: Số dư tối thiểu tính lãi ghi có | F93: decimal(38, 10) | G93: T24_ACCOUNT_CREDIT_INT.T_CR_MINIMUM_BAL | I93: Phase 1
A94: T24 | B94: ACCOUNT | C94: sat_account_credit_int | D94: t_cr_limit_amt | E94: Số tiền tối đa tính lãi ghi có | F94: string | G94: T24_ACCOUNT_CREDIT_INT.T_CR_LIMIT_AMT | I94: Phase 1
A95: T24 | B95: ACCOUNT | C95: sts_hub_account_credit_int | D95: account_hashkey | E95: Hub Hash Key tài khoản | F95: string | G95: hub_account.account_hashkey | H95: [PK] | I95: Phase 1
A96: T24 | B96: ACCOUNT | C96: sts_hub_account_credit_int | D96: source_event_date | E96: Ngày sự kiện nguồn | F96: date | G96: N/A | I96: Phase 1
A97: T24 | B97: ACCOUNT | C97: sts_hub_account_credit_int | D97: cdc_status | E97: Trạng thái CDC - Change Data Capture (D = Deleted, I = Insert/ Reinsert) • D (Deleted): ID đã tồn tại trong Hub nhưng bị mất dấu (xóa vật lý) ở bảng nguồn trong ngày tương ứng source_event_date • I (Inserted/Reinserted): ID từng bị xóa trong quá khứ, nay xuất hiện trở lại ở bảng nguồn trong ngày tương ứng source_event_date | F97: string | G97: N/A | I97: Phase 1
A98: T24 | B98: ACCOUNT | C98: sat_account_classification | D98: account_hashkey | E98: Hub Hash Key tài khoản | F98: string | G98: T24_ACCOUNT.ID | H98: [PK] | I98: Phase 1
A99: T24 | B99: ACCOUNT | C99: sat_account_classification | D99: t_category | E99: Mã phân loại category | F99: int | G99: T24_ACCOUNT.T_CATEGORY | I99: Phase 1
A100: T24 | B100: ACCOUNT | C100: sat_account_classification | D100: t_sub_product | E100: Mã sản phẩm thấu chi TK | F100: string | G100: T24_ACCOUNT.T_SUB_PRODUCT | I100: Phase 1
A101: T24 | B101: ACCOUNT | C101: sat_account_classification | D101: t_pl_cate | E101: Mã PL category liên quan đến thu nhập chi phí | F101: string | G101: T24_ACCOUNT.T_PL_CATE | I101: Phase 1
A102: T24 | B102: ACCOUNT | C102: sat_account_classification | D102: t_cust_group | E102: Mã khối | F102: string | G102: T24_ACCOUNT.T_CUST_GROUP | I102: Phase 1
A103: T24 | B103: ACCOUNT | C103: sat_account_classification | D103: t_condition_group | E103: Mã nhóm điều kiện lãi suất | F103: int | G103: T24_ACCOUNT.T_CONDITION_GROUP | I103: Phase 1
A104: T24 | B104: ACCOUNT | C104: sat_account_classification | D104: t_limit_ref | E104: Mã hạn mức | F104: string | G104: T24_ACCOUNT.T_LIMIT_REF | I104: Phase 1
...

Sheet sts hub
C1: lọc
A2: 1 | B2: sts_hub_account
A3: 2 | B3: sts_hub_account_credit_int | C3: sts cho sat
A4: 3 | B4: sts_hub_account_debit_int | C4: sts cho sat
A5: 4 | B5: sts_hub_account_locked_events
A6: 5 | B6: sts_hub_acct_officer
A7: 6 | B7: sts_hub_branch
A8: 7 | B8: sts_hub_clearing_citad
A9: 8 | B9: sts_hub_collateral
A10: 9 | B10: sts_hub_collateral_basel | C10: sts cho sat
A11: 10 | B11: sts_hub_collateral_right
A12: 11 | B12: sts_hub_consolidate_profit_n_loss
A13: 12 | B13: sts_hub_crb
A14: 13 | B14: sts_hub_customer
A15: 14 | B15: sts_hub_deposits
A16: 15 | B16: sts_hub_drawings
A17: 16 | B17: sts_hub_forex
A18: 17 | B18: sts_hub_gci
A19: 18 | B19: sts_hub_gdi
A20: 19 | B20: sts_hub_letter_of_credit
A21: 20 | B21: sts_hub_limit
A22: 21 | B22: sts_hub_loans
A23: 22 | B23: sts_hub_loans_ld_aprv_info | C23: sts cho sat
A24: 23 | B24: sts_hub_loans_ld_basel | C24: sts cho sat
A25: 24 | B25: sts_hub_loans_ld_extra_info | C25: sts cho sat
A26: 25 | B26: sts_hub_loans_ld_schedule_define | C26: sts cho sat
A27: 26 | B27: sts_hub_loans_lmm_account_balances | C27: sts cho sat
A28: 27 | B28: sts_hub_loans_ln_cust_revs | C28: sts cho sat
A29: 28 | B29: sts_hub_loans_payment_due
A30: 29 | B30: sts_hub_md_deal
A31: 30 | B31: sts_hub_money_market
A32: 31 | B32: sts_hub_money_market_lmm_account_balances
A33: 32 | B33: sts_hub_product_package_partner
A34: 33 | B34: sts_hub_repo
A35: 34 | B35: sts_hub_sc_trading_position
A36: 35 | B36: sts_hub_sec_trade
A37: 36 | B37: sts_hub_security
A38: 37 | B38: sts_hub_user
A39: 38 | B39: sts_hub_virtual_account

Sheet T24 Vault Mapping_old
A1: Source_system | B1: Group | C1: Table Name | D1: Column Name | E1: Description | F1: Data Type | G1: Mapping | H1: Key
A2: T24 | B2: ACCOUNT | C2: hub_virtual_account | D2: virtual_account_hashkey | E2: Hub Virtual Account | F2: string | G2: T24_OCBH_SUB_VIRTUAL_ACCOUNT.ID | H2: [PK]
A3: T24 | B3: ACCOUNT | C3: hub_virtual_account | D3: business_key | E3: Business Key | F3: string | G3: T24_OCBH_SUB_VIRTUAL_ACCOUNT.ID
A4: T24 | B4: ACCOUNT | C4: hub_account_locked_events | D4: ac_locked_events_hashkey | E4: Hub Hash Key Account Locked | F4: string | G4: T24_AC_LOCKED_EVENTS.ID | H4: [PK]
A5: T24 | B5: ACCOUNT | C5: hub_account_locked_events | D5: business_key | E5: Business Key | F5: string | G5: T24_AC_LOCKED_EVENTS.ID
A6: T24 | B6: ACCOUNT | C6: hub_account | D6: account_hashkey | E6: Hub Hash Key tài khoản | F6: string | G6: T24_ACCOUNT.ID | H6: [PK]
A7: T24 | B7: ACCOUNT | C7: hub_account | D7: business_key | E7: Business Key: Mã tài khoản | F7: string | G7: T24_ACCOUNT.ID
A8: T24 | B8: ACCOUNT | C8: sat_virtual_account | D8: virtual_account_hashkey | E8: Hub Virtual Account | F8: string | G8: T24_OCBH_SUB_VIRTUAL_ACCOUNT.ID | H8: [PK]
A9: T24 | B9: ACCOUNT | C9: sat_virtual_account | D9: t_va_id | E9: Prefix của ID TK định danh | F9: string | G9: T24_OCBH_SUB_VIRTUAL_ACCOUNT.T_VA_ID
A10: T24 | B10: ACCOUNT | C10: sat_virtual_account | D10: t_sub_id | E10: Surfix của ID TK định danh | F10: string | G10: T24_OCBH_SUB_VIRTUAL_ACCOUNT.T_SUB_ID
A11: T24 | B11: ACCOUNT | C11: sat_virtual_account | D11: t_sub_va_name | E11: Tên TK định danh | F11: string | G11: T24_OCBH_SUB_VIRTUAL_ACCOUNT.T_SUB_VA_NAME
A12: T24 | B12: ACCOUNT | C12: sat_virtual_account | D12: t_credit_acct_spa | E12: TK ghi có của TK định danh | F12: string | G12: T24_OCBH_SUB_VIRTUAL_ACCOUNT.T_CREDIT_ACCT_SPA
A13: T24 | B13: ACCOUNT | C13: sat_virtual_account | D13: t_sva_record_status | E13: Tình trạng bản ghi ( Duyệt/chờ duyệt) | F13: string | G13: T24_OCBH_SUB_VIRTUAL_ACCOUNT.T_SVA_RECORD_STATUS
A14: T24 | B14: ACCOUNT | C14: sat_virtual_account | D14: t_sva_status | E14: Tình trạng ( Active/Inative_ | F14: string | G14: T24_OCBH_SUB_VIRTUAL_ACCOUNT.T_SVA_STATUS
A15: T24 | B15: ACCOUNT | C15: sat_virtual_account | D15: t_date_time_input | E15: Ngày nhập | F15: string | G15: T24_OCBH_SUB_VIRTUAL_ACCOUNT.T_DATE_TIME_INPUT
A16: T24 | B16: ACCOUNT | C16: sat_virtual_account | D16: t_date_time_approval | E16: Ngày duyệt | F16: string | G16: T24_OCBH_SUB_VIRTUAL_ACCOUNT.T_DATE_TIME_APPROVAL
A17: T24 | B17: ACCOUNT | C17: sat_account_system | D17: account_hashkey | E17: Hub Hash Key tài khoản | F17: string | G17: T24_ACCOUNT.ID | H17: [PK]
A18: T24 | B18: ACCOUNT | C18: sat_account_system | D18: t_inputter | E18: Người nhập | F18: string | G18: T24_ACCOUNT.T_INPUTTER
A19: T24 | B19: ACCOUNT | C19: sat_account_system | D19: t_authoriser | E19: Người duyệt | F19: string | G19: T24_ACCOUNT.T_AUTHORISER
A20: T24 | B20: ACCOUNT | C20: sat_account_system | D20: t_date_time | E20: Ngày giờ cập nhật thông tin TK | F20: string | G20: T24_ACCOUNT.T_DATE_TIME
A21: T24 | B21: ACCOUNT | C21: sat_account_system | D21: t_date_last_update | E21: Ngày phát sinh giao dịch sau cùng | F21: string | G21: T24_ACCOUNT.T_DATE_LAST_UPDATE
A22: T24 | B22: ACCOUNT | C22: sat_account_system | D22: t_package_date | E22: Mã gói ưu đãi KHDN (Smart) | F22: string | G22: T24_ACCOUNT.T_PACKAGE_DATE
A23: T24 | B23: ACCOUNT | C23: sat_account_system | D23: t_curr_no | E23: Số lần thay đổi | F23: string | G23: T24_ACCOUNT.T_CURR_NO
A24: T24 | B24: ACCOUNT | C24: sat_account_system | D24: t_ocb_reason_rest | E24: Lý do hạn chế TK | F24: string | G24: T24_ACCOUNT.T_OCB_REASON_REST
A25: T24 | B25: ACCOUNT | C25: sat_account_other | D25: account_hashkey | E25: Hub Hash Key tài khoản | F25: string | G25: T24_ACCOUNT.ID | H25: [PK]
A26: T24 | B26: ACCOUNT | C26: sat_account_other | D26: t_open_cleared_bal | E26: Không dùng | F26: decimal(23,4) | G26: T24_ACCOUNT.T_OPEN_CLEARED_BAL
A27: T24 | B27: ACCOUNT | C27: sat_account_other | D27: t_online_cleared_bal | E27: Không dùng | F27: decimal(23,4) | G27: T24_ACCOUNT.T_ONLINE_CLEARED_BAL
A28: T24 | B28: ACCOUNT | C28: sat_account_other | D28: t_int_balance | E28: Không dùng | F28: decimal(15,4) | G28: T24_ACCOUNT.T_INT_BALANCE
A29: T24 | B29: ACCOUNT | C29: sat_account_other | D29: t_ref_officer | E29: Không dùng | F29: string | G29: T24_ACCOUNT.T_REF_OFFICER
A30: T24 | B30: ACCOUNT | C30: sat_account_other | D30: t_master_account | E30: Không dùng | F30: string | G30: T24_ACCOUNT.T_MASTER_ACCOUNT
A31: T24 | B31: ACCOUNT | C31: sat_account_other | D31: t_int_liqu_acct | E31: Không dùng | F31: string | G31: T24_ACCOUNT.T_INT_LIQU_ACCT
A32: T24 | B32: ACCOUNT | C32: sat_account_other | D32: t_accr_dr_amount | E32: Không dùng | F32: string | G32: T24_ACCOUNT.T_ACCR_DR_AMOUNT
A33: T24 | B33: ACCOUNT | C33: sat_account_other | D33: t_dpi_fin_date | E33: Không dùng (ptud 744 ) | F33: string | G33: T24_ACCOUNT.T_DPI_FIN_DATE
A34: T24 | B34: ACCOUNT | C34: sat_account_other | D34: t_tran_last_cr_cust | E34: Không dùng | F34: string | G34: T24_ACCOUNT.T_TRAN_LAST_CR_CUST
A35: T24 | B35: ACCOUNT | C35: sat_account_other | D35: t_tran_last_dr_cust | E35: Không dùng | F35: string | G35: T24_ACCOUNT.T_TRAN_LAST_DR_CUST
A36: T24 | B36: ACCOUNT | C36: sat_account_locked_events | D36: ac_locked_events_hashkey | E36: Hub Hash Key Account Locked | F36: string | G36: T24_AC_LOCKED_EVENTS.ID | H36: [PK]
A37: T24 | B37: ACCOUNT | C37: sat_account_locked_events | D37: t_account_number | E37: Số tài khoản | F37: string | G37: T24_AC_LOCKED_EVENTS.T_ACCOUNT_NUMBER
A38: T24 | B38: ACCOUNT | C38: sat_account_locked_events | D38: t_description | E38: Diễn giải | F38: string | G38: T24_AC_LOCKED_EVENTS.T_DESCRIPTION
A39: T24 | B39: ACCOUNT | C39: sat_account_locked_events | D39: t_from_date | E39: Từ ngày | F39: string | G39: T24_AC_LOCKED_EVENTS.T_FROM_DATE
A40: T24 | B40: ACCOUNT | C40: sat_account_locked_events | D40: t_to_date | E40: Đến ngày | F40: string | G40: T24_AC_LOCKED_EVENTS.T_TO_DATE
A41: T24 | B41: ACCOUNT | C41: sat_account_locked_events | D41: t_locked_amount | E41: Số tiền phong tỏa | F41: decimal(38, 10) | G41: T24_AC_LOCKED_EVENTS.T_LOCKED_AMOUNT
A42: T24 | B42: ACCOUNT | C42: sat_account_locked_events | D42: t_inputter | E42: Người nhập | F42: string | G42: T24_AC_LOCKED_EVENTS.T_INPUTTER
A43: T24 | B43: ACCOUNT | C43: sat_account_locked_events | D43: t_authoriser | E43: Người duyệt | F43: string | G43: T24_AC_LOCKED_EVENTS.T_AUTHORISER
A44: T24 | B44: ACCOUNT | C44: sat_account_locked_events | D44: t_date_time | E44: Ngày giờ thực hiện | F44: string | G44: T24_AC_LOCKED_EVENTS.T_DATE_TIME
A45: T24 | B45: ACCOUNT | C45: sat_account_locked_events | D45: t_block_reason | E45: Lý do phong tỏa | F45: string | G45: T24_AC_LOCKED_EVENTS.T_BLOCK_REASON
A46: T24 | B46: ACCOUNT | C46: sat_account_information | D46: account_hashkey | E46: Hub Hash Key tài khoản | F46: string | G46: T24_ACCOUNT.ID | H46: [PK]
A47: T24 | B47: ACCOUNT | C47: sat_account_information | D47: t_account_title_1 | E47: Tên tài khoản 1 | F47: string | G47: T24_ACCOUNT.T_ACCOUNT_TITLE_1
A48: T24 | B48: ACCOUNT | C48: sat_account_information | D48: t_account_title_2 | E48: Tên tài khoản 2 | F48: string | G48: T24_ACCOUNT.T_ACCOUNT_TITLE_2
A49: T24 | B49: ACCOUNT | C49: sat_account_information | D49: t_short_title | E49: Tên tài khoản rút ngắn | F49: string | G49: T24_ACCOUNT.T_SHORT_TITLE
A50: T24 | B50: ACCOUNT | C50: sat_account_information | D50: t_opening_date | E50: Ngày mở TK | F50: string | G50: T24_ACCOUNT.T_OPENING_DATE
A51: T24 | B51: ACCOUNT | C51: sat_account_information | D51: t_create_date | E51: Ngày tạo | F51: string | G51: T24_ACCOUNT.T_CREATE_DATE
A52: T24 | B52: ACCOUNT | C52: sat_account_information | D52: t_mature_date | E52: Ngày đáo hạn | F52: string | G52: T24_ACCOUNT.T_MATURE_DATE
A53: T24 | B53: ACCOUNT | C53: sat_account_information | D53: t_value_date | E53: Ngày giá trị | F53: string | G53: T24_ACCOUNT.T_VALUE_DATE
A54: T24 | B54: ACCOUNT | C54: sat_account_information | D54: t_acct_close_date | E54: Ngày đóng tài khoản | F54: string | G54: T24_ACCOUNT_CLOSED.T_ACCT_CLOSE_DATE
A55: T24 | B55: ACCOUNT | C55: sat_account_information | D55: t_term_xau | E55: Kỳ hạn | F55: string | G55: T24_ACCOUNT.T_TERM_XAU
A56: T24 | B56: ACCOUNT | C56: sat_account_information | D56: t_posting_restrict | E56: Thuộc tính hạn chế tài khoản | F56: string | G56: T24_ACCOUNT.T_POSTING_RESTRICT
A57: T24 | B57: ACCOUNT | C57: sat_account_information | D57: t_record_status | E57: Tình trạng bản ghi | F57: string | G57: T24_ACCOUNT.T_RECORD_STATUS
A58: T24 | B58: ACCOUNT | C58: sat_account_information | D58: t_alt_acct_id | E58: Số TK cũ | F58: string | G58: T24_ACCOUNT.T_ALT_ACCT_ID
... A63: T24 | B63: ACCOUNT | C63: sat_account_information | D63: t_ocb_beauty_sts | E63: Kênh mở TK ngắn | F63: string | G63: T24_ACCOUNT.T_OCB_BEAUTY_STS
A64: T24 | B64: ACCOUNT | C64: sat_account_debit_int | D64: account_hashkey | E64: Hub Hash Key tài khoản | F64: string | G64: T24_ACCOUNT_DEBIT_INT.ID -- cắt chuỗi trước dấu '-' (lấy phần đầu) | H64: [PK]
A65: T24 | B65: ACCOUNT | C65: sat_account_debit_int | D65: ma_key | E65: Ngày áp dụng lãi suất | F65: string | G65: T24_ACCOUNT_DEBIT_INT.ID -- cắt chuỗi sau dấu '-' (lấy phần sau) | H65: [PK]
A66: T24 | B66: ACCOUNT | C66: sat_account_debit_int | D66: t_charge_key | E66: Mã code phí | F66: string | G66: T24_ACCOUNT_DEBIT_INT.T_CHARGE_KEY
A67: T24 | B67: ACCOUNT | C67: sat_account_debit_int | D67: t_interest_day_basis | E67: Cơ sở tính lãi | F67: string | G67: T24_ACCOUNT_DEBIT_INT.T_INTEREST_DAY_BASIS
A68: T24 | B68: ACCOUNT | C68: sat_account_debit_int | D68: t_dr_balance_type | E68: Cách tính số dư ghi nợ | F68: string | G68: T24_ACCOUNT_DEBIT_INT.T_DR_BALANCE_TYPE
A69: T24 | B69: ACCOUNT | C69: sat_account_debit_int | D69: t_dr_calcul_type | E69: Phương pháp tính lãi ghi nợ | F69: string | G69: T24_ACCOUNT_DEBIT_INT.T_DR_CALCUL_TYPE
A70: T24 | B70: ACCOUNT | C70: sat_account_debit_int | D70: t_dr_int_rate | E70: Lãi suất ghi nợ | F70: decimal(38, 10) | G70: T24_ACCOUNT_DEBIT_INT.T_DR_INT_RATE
A71: T24 | B71: ACCOUNT | C71: sat_account_debit_int | D71: t_dr_margin_rate | E71: Giá trị biên độ để điều chỉnh lãi suất | F71: decimal(38, 10) | G71: T24_ACCOUNT_DEBIT_INT.T_DR_MARGIN_RATE
A72: T24 | B72: ACCOUNT | C72: sat_account_debit_int | D72: t_dr_basic_rate | E72: Mức Lãi suất cơ bản ghi nợ | F72: decimal(38, 10) | G72: T24_ACCOUNT_DEBIT_INT.T_DR_BASIC_RATE
A73: T24 | B73: ACCOUNT | C73: sat_account_debit_int | D73: t_dr_margin_oper | E73: Phương pháp điều chỉnh lãi suất bằng biên độ | F73: string | G73: T24_ACCOUNT_DEBIT_INT.T_DR_MARGIN_OPER
A74: T24 | B74: ACCOUNT | C74: sat_account_credit_int | D74: account_hashkey | E74: Hub Hash Key tài khoản | F74: string | G74: T24_ACCOUNT_CREDIT_INT.ID -- cắt chuỗi trước dấu '-' (lấy phần đầu) | H74: [PK]
A75: T24 | B75: ACCOUNT | C75: sat_account_credit_int | D75: ma_key | E75: Ngày áp dụng lãi suất | F75: string | G75: T24_ACCOUNT_CREDIT_INT.ID -- cắt chuỗi sau dấu '-' (lấy phần sau) | H75: [PK]
A76: T24 | B76: ACCOUNT | C76: sat_account_credit_int | D76: t_interest_day_basis | E76: Cơ sở tính lãi | F76: string | G76: T24_ACCOUNT_CREDIT_INT.T_INTEREST_DAY_BASIS
A77: T24 | B77: ACCOUNT | C77: sat_account_credit_int | D77: t_cr_balance_type | E77: Loại số dư tính lãi ghi có | F77: string | G77: T24_ACCOUNT_CREDIT_INT.T_CR_BALANCE_TYPE
A78: T24 | B78: ACCOUNT | C78: sat_account_credit_int | D78: t_cr_calcul_type | E78: Phương pháp tính lãi ghi có | F78: string | G78: T24_ACCOUNT_CREDIT_INT.T_CR_CALCUL_TYPE
A79: T24 | B79: ACCOUNT | C79: sat_account_credit_int | D79: t_cr_int_rate | E79: Lãi suất ghi có | F79: string | G79: T24_ACCOUNT_CREDIT_INT.T_CR_INT_RATE
A80: T24 | B80: ACCOUNT | C80: sat_account_credit_int | D80: t_cr_margin_rate | E80: Margin lãi suất | F80: string | G80: T24_ACCOUNT_CREDIT_INT.T_CR_MARGIN_RATE
A81: T24 | B81: ACCOUNT | C81: sat_account_credit_int | D81: t_cr_minimum_bal | E81: Số dư tối thiểu tính lãi ghi có | F81: decimal(38, 10) | G81: T24_ACCOUNT_CREDIT_INT.T_CR_MINIMUM_BAL
A82: T24 | B82: ACCOUNT | C82: sat_account_credit_int | D82: t_cr_limit_amt | E82: Số tiền tối đa tính lãi ghi có | F82: string | G82: T24_ACCOUNT_CREDIT_INT.T_CR_LIMIT_AMT
A83: T24 | B83: ACCOUNT | C83: sat_account_classification | D83: account_hashkey | E83: Hub Hash Key tài khoản | F83: string | G83: T24_ACCOUNT.ID | H83: [PK]
A84: T24 | B84: ACCOUNT | C84: sat_account_classification | D84: t_category | E84: Mã phân loại category | F84: int | G84: T24_ACCOUNT.T_CATEGORY
A85: T24 | B85: ACCOUNT | C85: sat_account_classification | D85: t_sub_product | E85: Mã sản phẩm thấu chi TK | F85: string | G85: T24_ACCOUNT.T_SUB_PRODUCT
A86: T24 | B86: ACCOUNT | C86: sat_account_classification | D86: t_pl_cate | E86: Mã PL category liên quan đến thu nhập chi phí | F86: string | G86: T24_ACCOUNT.T_PL_CATE
A87: T24 | B87: ACCOUNT | C87: sat_account_classification | D87: t_cust_group | E87: Mã khối | F87: string | G87: T24_ACCOUNT.T_CUST_GROUP
A88: T24 | B88: ACCOUNT | C88: sat_account_classification | D88: t_condition_group | E88: Mã nhóm điều kiện lãi suất | F88: int | G88: T24_ACCOUNT.T_CONDITION_GROUP
A89: T24 | B89: ACCOUNT | C89: sat_account_classification | D89: t_limit_ref | E89: Mã hạn mức | F89: string | G89: T24_ACCOUNT.T_LIMIT_REF
A90: T24 | B90: ACCOUNT | C90: sat_account_classification | D90: t_cb_package_id | E90: Mã gói ưu đãi KHDN (Smart) | F90: string | G90: T24_ACCOUNT.T_CB_PACKAGE_ID
A91: T24 | B91: ACCOUNT | C91: sat_account_balance | D91: account_hashkey | E91: Hub Hash Key tài khoản | F91: string | G91: T24_ACCOUNT.ID | H91: [PK]
A92: T24 | B92: ACCOUNT | C92: sat_account_balance | D92: t_interest_rate | E92: Lãi suất | F92: decimal(10,4) | G92: T24_ACCOUNT.T_INTEREST_RATE
A93: T24 | B93: ACCOUNT | C93: sat_account_balance | D93: t_currency | E93: Đơn vị tiền tệ | F93: string | G93: T24_ACCOUNT.T_CURRENCY
A94: T24 | B94: ACCOUNT | C94: sat_account_balance | D94: t_open_actual_bal | E94: Số dư đầu ngày | F94: decimal(23,4) | G94: T24_ACCOUNT.T_OPEN_ACTUAL_BAL
A95: T24 | B95: ACCOUNT | C95: sat_account_balance | D95: t_online_actual_bal | E95: Số dư hiện tại | F95: decimal(23,4) | G95: T24_ACCOUNT.T_ONLINE_ACTUAL_BAL
A96: T24 | B96: ACCOUNT | C96: sat_account_balance | D96: t_working_balance | E96: Số dư khả dụng | F96: decimal(23,4) | G96: T24_ACCOUNT.T_WORKING_BALANCE
A97: T24 | B97: ACCOUNT | C97: sat_account_balance | D97: t_locked_amount | E97: Số dư bị phong tỏa | F97: string | G97: T24_ACCOUNT.T_LOCKED_AMOUNT
A98: T24 | B98: ACCOUNT | C98: sat_account_balance | D98: t_date_last_cr_cust | E98: Ngày sau cùng KH thực hiện giao dịch ghi có | F98: string | G98: T24_ACCOUNT.T_DATE_LAST_CR_CUST
A99: T24 | B99: ACCOUNT | C99: sat_account_balance | D99: t_date_last_dr_cust | E99: Ngày sau cùng KH thực hiện giao dịch ghi nợ | F99: string | G99: T24_ACCOUNT.T_DATE_LAST_DR_CUST
A100: T24 | B100: ACCOUNT | C100: sat_account_balance | D100: t_amnt_last_cr_cust | E100: Số tiền sau cùng KH thực hiện giao dịch ghi có | F100: string | G100: T24_ACCOUNT.T_AMNT_LAST_CR_CUST
A101: T24 | B101: ACCOUNT | C101: sat_account_balance | D101: t_amnt_last_dr_cust | E101: Số tiền sau cùng KH thực hiện giao dịch ghi nợ | F101: string | G101: T24_ACCOUNT.T_AMNT_LAST_DR_CUST
A102: T24 | B102: ACCOUNT | C102: link_virtual_account_customer | D102: link_virtual_account_customer_hashkey | E102: Link HK | F102: string | G102: T24_OCBH_SUB_VIRTUAL_ACCOUNT.ID + T24_OCBH_SUB_VIRTUAL_ACCOUNT.T_CIF | H102: [PK]
A103: T24 | B103: ACCOUNT | C103: link_virtual_account_customer | D103: virtual_account_hashkey | E103: Tham chiếu Hub Virtual Account | F103: string | G103: T24_OCBH_SUB_VIRTUAL_ACCOUNT.ID
A104: T24 | B104: ACCOUNT | C104: link_virtual_account_customer | D104: customer_hashkey | E104: Tham chiếu Hub Customer | F104: string | G104: T24_OCBH_SUB_VIRTUAL_ACCOUNT.T_CIF
...

Sheet Summary Raw Vault
A1: Source | B1: Group | C1: Table Name | D1: Description | E1: Relationship of Links | F1: Satellite Content Classification | G1: Note
A2: All | B2: REFERENCE | C2: reference | D2: Bảng tổng hợp tất cả các bảng danh mục chứa thông tin mô tả và phân loại từ các nguồn T24, Way4, Omni, BPM
A3: T24 | B3: ACCOUNT | C3: hub_virtual_account | D3: Bảng định danh số tài khoản của KHDN (tài khoản ảo để thanh toán hóa đơn, thu hộ,...)
A4: T24 | B4: ACCOUNT | C4: sts_hub_virtual_account | D4: Bảng theo dõi trạng thái I (Insert - Thêm mới/Tái nhập) và D (Delete - Xóa) của các Key nằm trong bảng T24_ocbh_sub_virtual_account khi được load vào hub_virtual_account
A5: T24 | B5: ACCOUNT | C5: hub_account_locked_events | D5: Bảng định danh mã phong tỏa tài khoản
A6: T24 | B6: ACCOUNT | C6: sts_hub_account_locked_events | D6: Bảng theo dõi trạng thái I (Insert - Thêm mới/Tái nhập) và D (Delete - Xóa) của các Key nằm trong bảng T24_account_locked_events khi được load vào hub_account_locked_events
A7: T24 | B7: ACCOUNT | C7: hub_account | D7: Bảng định danh số tài khoản: toàn bộ tài khoản của KH và tài khoản nội bộ, tài khoản working account
A8: T24 | B8: ACCOUNT | C8: sts_hub_account | D8: Bảng theo dõi trạng thái I (Insert - Thêm mới/Tái nhập) và D (Delete - Xóa) của các Key nằm trong bảng T24_account khi được load vào hub_account | G8: Union thêm bảng T24_ACCOUNT_CLOSED để lấy ra những trường hợp mà tài khoản tạo rồi xóa luôn trong ngày Các bảng phụ của T24_ACCOUNT được load vào: t24_account_debit_int t24_account_credit_int t24_accr_acct_cr t24_accr_acct_dr t24_ocbh_ac_restrict t24_stmt_acct_cr t24_stmt_acct_dr t24_acct_activity
A9: T24 | B9: ACCOUNT | C9: sat_virtual_account | D9: Thông tin thanh toán hóa đơn, thu hộ,... của các tài khoản ảo của KHDN (tạo từ bảng T24_ocbh_sub_virtual_account) | F9: information
A10: T24 | B10: ACCOUNT | C10: sat_account_system | D10: Thông tin hệ thống (người nhập, người duyệt, số lần thay đổi,...) | F10: system
A11: T24 | B11: ACCOUNT | C11: sat_account_other | D11: Bảng bổ sung cho các trường không sử dụng | F11: other
A12: T24 | B12: ACCOUNT | C12: sat_account_locked_events | D12: Thông tin các tài khoản bị phong tỏa số dư | F12: information
A13: T24 | B13: ACCOUNT | C13: sat_account_information | D13: Thông tin chung tài khoản (Tên TK, ngày mở TK, ngày tạo,...) | F13: information
A14: T24 | B14: ACCOUNT | C14: sat_account_debit_int | D14: Thông tin về lãi suất cho số dư nợ trên từng tài khoản (mã code phí, cơ sở tính lãi, cách tính số dư ghi nợ,...) (tạo từ bảng t24_account_debit_int) | F14: information
A15: T24 | B15: ACCOUNT | C15: sts_hub_account_debit_int | D15: Bảng theo dõi trạng thái I (Insert - Thêm mới/Tái nhập) và D (Delete - Xóa) của các Key được bổ sung từ bảng phụ T24_account_debit_int vào hub_account (các ID tồn tại trong T24_account_debit_int nhưng không có trong bảng chính T24_account)
A16: T24 | B16: ACCOUNT | C16: sat_account_credit_int | D16: Thông tin lãi suất trên số dư có cho từng tài khoản (cơ sở tính lãi, loại số dư tính lãi ghi có, phương pháp tính lãi ghi có, lãi suất ghi có,..) (tạo từ bảng t24_account_credit_int) | F16: information
A17: T24 | B17: ACCOUNT | C17: sts_hub_account_credit_int | D17: Bảng theo dõi trạng thái I (Insert - Thêm mới/Tái nhập) và D (Delete - Xóa) của các Key được bổ sung từ bảng phụ T24_account_credit_int vào hub_account (các ID tồn tại trong T24_account_credit_int nhưng không có trong bảng chính T24_account)
A18: T24 | B18: ACCOUNT | C18: sat_account_classification | D18: Thông tin phân loại tài khoản (mã phân loại, mã nhóm, mã gói, mã hạn mức,...) | F18: classification
A19: T24 | B19: ACCOUNT | C19: sat_account_balance | D19: Thông tin số dư tài khoản (số dư đầu ngày, số dư hiện tại, số dư khả dụng, số dư bị phong tỏa...) | F19: balance
A20: T24 | B20: ACCOUNT | C20: link_virtual_account_customer | D20: Liên kết số tài khoản của KHDN (tài khoản ảo) với khách hàng là chủ tài khoản
A21: T24 | B21: ACCOUNT | C21: link_virtual_account_account_t24 | D21: Liên kết số tài khoản của KHDN (tài khoản ảo) với tài khoản ghi có ở hệ thống T24
A22: T24 | B22: ACCOUNT | C22: link_account_locked_events_branch | D22: Liên kết mã phong tỏa tài khoản với chi nhánh quản lý phong tỏa
A23: T24 | B23: ACCOUNT | C23: link_account_locked_events_account | D23: Liên kết mã phong tỏa tài khoản với số tài khoản ở T24_ACCOUNT
A24: T24 | B24: ACCOUNT | C24: link_account_limit | D24: Liên kết tài khoản với hạn mức gắn với tài khoản
A25: T24 | B25: ACCOUNT | C25: effsat_link_account_limit | D25: Bảng thông tin theo dõi hiệu lực của mối quan hệ liên kết giữa tài khoản và mã hạn mức
A26: T24 | B26: ACCOUNT | C26: link_account_dept_acct_officer | D26: Liên kết tài khoản với NV bán hàng
A27: T24 | B27: ACCOUNT | C27: effsat_link_account_dept_acct_officer | D27: Bảng thông tin theo dõi hiệu lực của mối quan hệ liên kết giữa tài khoản và nhân viên bán hàng
A28: T24 | B28: ACCOUNT | C28: link_account_customer | D28: Liên kết tài khoản với khách hàng là chủ tài khoản
A29: T24 | B29: ACCOUNT | C29: link_account_branch | D29: Liên kết tài khoản với chi nhánh quản lý tài khoản
A30: T24 | B30: ACCOUNT | C30: sat_accr_acct_cr_information | D30: Bảng thông tin khai báo lãi suất trên số dư Có cho từng tài khoản (tạo từ bảng T24_ACCR_ACCT_CR) | F30: information
A31: T24 | B31: ACCOUNT | C31: sat_accr_acct_cr_dynamic | D31: Bảng chứa những trường có tần suất thay đổi nhiều của bảng khai báo lãi suất trên số dư Có cho từng tài khoản (gồm Ngày cuối kì tính lãi, Ngày post tính lãi cuối, Số ngày tính lãi, Số tiền lãi, Tổng tiền lãi) | F31: dynamic
A32: T24 | B32: ACCOUNT | C32: sat_accr_acct_cr_other | D32: Bảng bổ sung cho các trường không sử dụng của bảng nguồn T24_ACCR_ACCT_CR | F32: other
A33: T24 | B33: ACCOUNT | C33: sts_hub_account_accr_acct_cr | D33: Bảng theo dõi trạng thái I (Insert - Thêm mới/Tái nhập) và D (Delete - Xóa) của các Key nằm trong bảng T24_accr_acct_cr khi được load vào hub_account (các ID tồn tại trong bảng T24_accr_acct_cr nhưng không có trong bảng chính T24_account)
A34: T24 | B34: ACCOUNT | C34: sat_accr_acct_dr_information | D34: Bảng thông tin khai báo lãi suất trên số dư Nợ cho từng tài khoản (tạo từ bảng T24_ACCR_ACCT_DR) | F34: information
A35: T24 | B35: ACCOUNT | C35: sat_accr_acct_dr_dynamic | D35: Bảng chứa những trường có tần suất thay đổi nhiều của bảng khai báo lãi suất trên số dư Nợ cho từng tài khoản (gồm Ngày cuối kì tính lãi, Số ngày) | F35: dynamic
A36: T24 | B36: ACCOUNT | C36: sts_hub_account_accr_acct_dr | D36: Bảng theo dõi trạng thái I (Insert - Thêm mới/Tái nhập) và D (Delete - Xóa) của các Key nằm trong bảng T24_accr_acct_dr khi được load vào hub_account (các ID tồn tại trong bảng T24_accr_acct_dr nhưng không có trong bảng chính T24_account)
A37: T24 | B37: ACCOUNT | C37: sat_acct_activity | D37: Bảng thông tin lưu biến động số dư tài khoản trong 1 tháng - ghi nhận các giao dịch phát sinh làm thay đổi số dư nợ, số dư có của tài khoản khách hàng. | F37: information
A38: T24 | B38: ACCOUNT | C38: sts_hub_account_acct_activity | D38: Bảng theo dõi trạng thái I (Insert - Thêm mới/Tái nhập) và D (Delete - Xóa) của các Key nằm trong bảng T24_acct_activity khi được load vào hub_account (các ID tồn tại trong bảng T24_acct_activity nhưng không có trong bảng chính T24_account)
A39: T24 | B39: ACCOUNT | C39: sat_ac_restrict | D39: Bảng thông tin đăng kí tài khoản hạn chế của tài khoản thấu chi và đăng kí thu hộ (tạo từ bảng T24_OCBH_AC_RESTRICT) | F39: information
A40: T24 | B40: ACCOUNT | C40: sts_hub_account_ac_restrict | D40: Bảng theo dõi trạng thái I (Insert - Thêm mới/Tái nhập) và D (Delete - Xóa) của các Key nằm trong bảng T24_ocbh_ac_restrict khi được load vào hub_account (các ID tồn tại trong bảng T24_ocbh_ac_restrict nhưng không có trong bảng chính T24_account)
A41: T24 | B41: ACCOUNT | C41: ref_t24_acct_group_condition | D41: Bảng khai báo nhóm số dư tối thiểu tài khoản
A42: T24 | B42: ACCOUNT | C42: ref_t24_group_capitalisation | D42: Bảng tham số ngày kép lãi của nhóm SP tài khoản
A43: T24 | B43: ACCOUNT | C43: sat_stmt_acct_cr | D43: Bảng thông tin chi tiết kép lãi ghi có của tài khoản (tạo từ bảng T24_STMT_ACCT_CR) | F43: information
A44: T24 | B44: ACCOUNT | C44: sat_stmt_acct_cr_other | D44: Bảng bổ sung cho các trường không sử dụng | F44: other
A45: T24 | B45: ACCOUNT | C45: sts_hub_account_stmt_acct_cr | D45: Bảng theo dõi trạng thái I (Insert - Thêm mới/Tái nhập) và D (Delete - Xóa) của các Key nằm trong bảng T24_stmt_acct_cr khi được load vào hub_account (các ID tồn tại trong bảng T24_stmt_acct_cr nhưng không có trong bảng chính T24_account)
A46: T24 | B46: ACCOUNT | C46: sat_stmt_acct_dr | D46: Bảng thông tin chi tiết kép lãi ghi nợ của tài khoản (tạo từ bảng T24_STMT_ACCT_DR) | F46: information
A47: T24 | B47: ACCOUNT | C47: sts_hub_account_stmt_acct_dr | D47: Bảng theo dõi trạng thái I (Insert - Thêm mới/Tái nhập) và D (Delete - Xóa) của các Key nằm trong bảng T24_stmt_acct_dr khi được load vào hub_account (các ID tồn tại trong bảng T24_stmt_acct_dr nhưng không có trong bảng chính T24_account)
A48: T24 | B48: ACCOUNTING | C48: hub_categ_entry | D48: Bảng định danh bút toán thu nhập/chi phí
A49: T24 | B49: ACCOUNTING | C49: hub_re_stat_line_bal | D49: Bảng định danh cân đối số dư toàn hàng
A50: T24 | B50: ACCOUNTING | C50: hub_pc_re_stat_line_bal | D50: Bảng định danh cân đối số dư toàn hàng có điều chỉnh
A51: T24 | B51: ACCOUNTING | C51: hub_consolidate_profit_n_loss | D51: Bảng định danh chi phí/lợi nhuận toàn hàng
A52: T24 | B52: ACCOUNTING | C52: sts_hub_consolidate_profit_n_loss | D52: Bảng theo dõi trạng thái I (Insert - Thêm mới/Tái nhập) và D (Delete - Xóa) của các Key nằm trong bảng T24_consolidate_profit_n_loss khi được load vào hub_consolidate_profit_n_loss
A53: T24 | B53: ACCOUNTING | C53: hub_line_movement_toanhang | D53: Bảng định chi tiết biến động tài khoản kế toán toàn hàng
A54: T24 | B54: ACCOUNTING | C54: hub_re_consol_spec_entry | D54: Bảng định danh bút toán liên quan đến hợp đồng (LD,AZ,..)
A55: T24 | B55: ACCOUNTING | C55: hub_stmt_entry | D55: Bảng định danh bút toán liên quan biến động giao dịch tác động đến các loại hợp đồng
A56: T24 | B56: ACCOUNTING | C56: sat_categ_entry_information | D56: Thông tin chung bút toán thu nhập/chi phí (Loại tiền, số tiền, số giao dịch, mã giao dịch,..) | F56: information
A57: T24 | B57: ACCOUNTING | C57: sat_categ_entry_classification | D57: Thông tin mang tính phân loại của bút toán thu nhập/chi phí (mã cate, loại nợ, loại giao dịch,...) | F57: classification
A58: T24 | B58: ACCOUNTING | C58: sat_categ_entry_audit | D58: Thông tin truy xuất các bút toán thu nhập/chi phí (user nhập, user duyệt, kỳ đóng sổ điều chỉnh,...) | F58: audit
A59: T24 | B59: ACCOUNTING | C59: sat_pc_re_stat_line_bal | D59: Thông tin cân đối số dư toàn hàng có điều chỉnh (tạo từ bảng t24_pc_re_stat_line_bal) | F59: information
A60: T24 | B60: ACCOUNTING | C60: sat_re_stat_line_bal | D60: Thông tin cân đối số dư toàn hàng | F60: information
A61: T24 | B61: ACCOUNTING | C61: sat_consolidate_profit_n_loss_information | D61: Thông tin chi phí/lợi nhuận toàn hàng | F61: information
A62: T24 | B62: ACCOUNTING | C62: sat_line_movement_toanhang | D62: Thông tin chi tiết biến động tài khoản kế toán toàn hàng | F62: information
A63: T24 | B63: ACCOUNTING | C63: sat_re_consol_spec_entry_information | D63: Thông tin bút toán liên quan đến hợp đồng (số tiền nội tệ, ngoại tệ, nội dung, ngày giá trị,...) | F63: information
A64: T24 | B64: ACCOUNTING | C64: sat_re_consol_spec_entry_classification | D64: Thông tin mang tính phân loại của các bút toán liên quan đến hợp đồng (loại consol key, mã cate pl, mã cate sản phẩm, system id,...) | F64: classification
A65: T24 | B65: ACCOUNTING | C65: sat_re_consol_spec_entry_audit | D65: Thông tin truy xuất của các bút toán liên quan hợp đồng (reversal_marker, trạng thái giao dịch, user nhập,...) | F65: audit
A66: T24 | B66: ACCOUNTING | C66: sat_stmt_entry_information | D66: Thông tin chung các bút toán liên quan biến động của các hợp đồng (tài khoản, số tiền nội tệ, số gd, ngày giá trị,...) | F66: information
A67: T24 | B67: ACCOUNTING | C67: sat_stmt_entry_classification | D67: Thông tin mang tính phân loại của các bút toán liên quan biến động hợp đồng (mã cate PL, mã cate sản phẩm,...) | F67: classification
A68: T24 | B68: ACCOUNTING | C68: sat_stmt_entry_audit | D68: Thông tin truy xuất các bút toán liên quan biến động của hợp đồng (ngày, trạng thái giao dịch, user nhập,...) | F68: audit
A69: T24 | B69: ACCOUNTING | C69: link_categ_entry_customer | D69: Liên kết mã bút toán thu nhập/chi phí với khách hàng
A70: T24 | B70: ACCOUNTING | C70: link_categ_entry_branch | D70: Liên kết mã bút toán thu nhập/chi phí với chi nhánh
A71: T24 | B71: ACCOUNTING | C71: link_line_movement_toanhang_stmt_entry | D71: Liên kết mã biến động tài khoản kế toán toàn hàng với bút toán liên quan biến động của các hợp đồng
A72: T24 | B72: ACCOUNTING | C72: link_line_movement_toanhang_categ_entry | D72: Liên kết mã biến động tài khoản kế toán toàn hàng với bút toán thu nhập/chi phí
A73: T24 | B73: ACCOUNTING | C73: link_line_movement_toanhang_re_consol_spec_entry | D73: Liên kết mã biến động tài khoản kế toán toàn hàng với bút toán liên quan hợp đồng
A74: T24 | B74: ACCOUNTING | C74: link_re_consol_spec_entry_branch | D74: Liên kết mã bút toán liên quan hợp đồng với chi nhánh
A75: T24 | B75: ACCOUNTING | C75: link_re_consol_spec_entry_customer | D75: Liên kết mã bút toán liên quan hợp đồng với khách hàng
A76: T24 | B76: ACCOUNTING | C76: link_re_consol_spec_entry_officer | D76: Liên kết mã bút toán liên quan hợp đồng với NVQL
A77: T24 | B77: ACCOUNTING | C77: link_stmt_entry_customer | D77: Liên kết mã bút toán liên quan biến động giao dịch tác động đến các loại hợp đồng với khách hàng
A78: T24 | B78: ACCOUNTING | C78: link_stmt_entry_branch | D78: Liên kết mã bút toán liên quan biến động giao dịch tác động đến các loại hợp đồng với chi nhánh
A79: T24 | B79: ACCOUNTING | C79: link_stmt_entry_officer | D79: Liên kết mã bút toán liên quan biến động giao dịch tác động đến các loại hợp đồng với NVQL
A80: T24 | B80: ACCOUNTING | C80: hub_crb | D80: Bảng thông tin các hợp đồng còn số dư trên CRB (LD, ACCOUNT, LETTER OF CREDIT, MD DEAL , DRAWINGS, SECURITY, FOREX, MONEY MARKET, TOTAL, ROUNDING.ADJUSTMENT, v.v)
A81: T24 | B81: ACCOUNTING | C81: sts_hub_crb | D81: Bảng theo dõi trạng thái I (Insert - Thêm mới/Tái nhập) và D (Delete - Xóa) của các Key nằm trong bảng T24_crb khi được load vào hub_crb
A82: T24 | B82: ACCOUNTING | C82: sat_crb_balance | D82: Thông tin balance của CRB (loại đồng tiền, số tiền nội tệ, số tiền ngoại tệ, phân loại sản phẩm) | F82: balance
A83: T24 | B83: ACCOUNTING | C83: sat_crb_information | D83: Thông tin chung của CRB (số tài khoản có, lãi suất, kỳ hạn hối phiếu,...) | F83: information
A84: T24 | B84: ACCOUNTING | C84: link_crb_branch | D84: Liên kết CRB với chi nhánh
A85: T24 | B85: ACCOUNTING | C85: effsat_link_crb_branch | D85: Bảng thông tin theo dõi hiệu lực của mối quan hệ liên kết giữa CRB và chi nhánh
A86: T24 | B86: ACCOUNTING | C86: link_crb_customer | D86: Liên kết CRB với khách hàng
A87: T24 | B87: ACCOUNTING | C87: effsat_link_crb_customer | D87: Bảng thông tin theo dõi hiệu lực của mối quan hệ liên kết giữa CRB và khách hàng
A88: T24 | B88: ACCOUNTING | C88: link_crb_loans | D88: Liên kết CRB với hợp đồng khoản vay/ tín dụng
A89: T24 | B89: ACCOUNTING | C89: link_crb_loans_payment_due | D89: Liên kết CRB với hợp đồng khoản vay/ tín dụng quá hạn (bao gồm thấu chi và vay LD)
A90: T24 | B90: ACCOUNTING | C90: link_crb_account | D90: Liên kết CRB với tài khoản
A91: T24 | B91: ACCOUNTING | C91: hub_apportion_acct_categ | D91: Bảng định danh mã dùng để xử lý VAT và thu nhập
A92: T24 | B92: ACCOUNTING | C92: sts_hub_apportion_acct_categ | D92: Bảng theo dõi trạng thái I (Insert - Thêm mới/Tái nhập) và D (Delete - Xóa) của các Key nằm trong bảng T24_apportion_acct_categ khi được load vào hub_apportion_acct_categ
A93: T24 | B93: ACCOUNTING | C93: sat_apportion_acct_categ | D93: Bảng thông tin dùng để xử lý VAT và thu nhập (bảng local riêng) | F93: information
A94: T24 | B94: ACCOUNTING | C94: hub_rpt_pl_vat | D94: Bảng định danh mã kết chuyển bút toán lợi nhuận, chi phí
A95: T24 | B95: ACCOUNTING | C95: sts_hub_rpt_pl_vat | D95: Bảng theo dõi trạng thái I (Insert - Thêm mới/Tái nhập) và D (Delete - Xóa) của các Key nằm trong bảng T24_VMBH_RPT_PL_VAT khi được load vào hub_rpt_pl_vat
A96: T24 | B96: ACCOUNTING | C96: sat_rpt_pl_vat | D96: Bảng thông tin hoạt động kết chuyển bút toán lợi nhuận, chi phí | F96: information
A97: T24 | B97: COLLATERAL | C97: hub_collateral | D97: Bảng định danh mã tài sản đảm bảo (TSĐB) | G97: UNION thêm bảng T24_OCBH_COLLATERAL_BASEL để đảm bảo đủ số lượng COLLATERAL ID trong trường hợp báo cáo muốn lấy dữ liệu từ bảng phụ lên
A98: T24 | B98: COLLATERAL | C98: sts_hub_collateral | D98: Bảng theo dõi trạng thái I (Insert - Thêm mới/Tái nhập) và D (Delete - Xóa) của các Key nằm trong bảng T24_collateral khi được load vào hub_collateral
A99: T24 | B99: COLLATERAL | C99: sts_hub_collateral_basel | D99: Bảng theo dõi trạng thái I (Insert - Thêm mới/Tái nhập) và D (Delete - Xóa) của các Key được bổ sung từ bảng phụ T24_ocbh_coll_basel vào hub_collateral (các ID tồn tại trong T24_ocbh_coll_basel nhưng không có trong bảng chính T24_collateral)
A100: T24 | B100: COLLATERAL | C100: hub_collateral_right | D100: Bảng định danh liên kết quyền TSBĐ
...

Sheet Summary Tracking Zone C
A1: Zone C Vault Mapping - Tracking by Source Table
A2: Source | B2: Mapping PIC | C2: Dev PIC | D2: Total Source Tables | E2: Source Mapping Completed | F2: % Mapping | G2: hub + sts | H2: link | I2: sat + effsat + non_his_sat | J2: ref_ | K2: Total Vault Tables | L2: Vault Mapping Completed | M2: % Mapping | N2: Dev Completed | O2: % Dev (vs Mapping) | P2: Note
A3: COMB | B3: {=IFERROR(INDEX(_xlfn._xlws.FILTER('Tracking Mapping&Dev Zone C'!$C:$C,('Tracking Mapping&Dev Zone C'!$A:$A=$A3)*('Tracking Mapping&Dev Zone C'!$C:$C<>"")),1),"")} -> TrangNT | C3: {=IFERROR(_xlfn.TEXTJOIN(", ",TRUE,_xlfn.UNIQUE(_xlfn._xlws.FILTER('Tracking Mapping&Dev Zone C'!$E:$E,('Tracking Mapping&Dev Zone C'!$A:$A=$A3)*('Tracking Mapping&Dev Zone C'!$E:$E<>"")))),"")} -> Huy | D3: =COUNTIF('Source Tables Zone C'!$A$2:$A$200,$A3) -> 5 | E3: =COUNTIFS('Source Tables Zone C'!$A$2:$A$200,$A3,'Source Tables Zone C'!$C$2:$C$200,"Done") -> 5 | F3: =IFERROR(E3/D3,"") -> 1 | G3: {=ROUND(SUMPRODUCT((('ZONE C Vault Mapping'!$A$2:$A$10174=$A3)*((LEFT('ZONE C Vault Mapping'!$B$2:$B$10174,4)="hub_")+(LEFT('ZONE C Vault Mapping'!$B$2:$B$10174,4)="sts_"))*('ZONE C Vault Mapping'!$H$2:$H$10174<>"Cancel"))/COUNTIFS('ZONE C Vault Mapping'!$B$2:$B$10174,'ZONE C Vault Mapping'!$B$2:$B$10174&"")),0)} -> 5 | H3: {=ROUND(SUMPRODUCT(('ZONE C Vault Mapping'!$A$2:$A$10174=$A3)*(LEFT('ZONE C Vault Mapping'!$B$2:$B$10174,5)="link_")*('ZONE C Vault Mapping'!$H$2:$H$10174<>"Cancel")/COUNTIFS('ZONE C Vault Mapping'!$B$2:$B$10174,'ZONE C Vault Mapping'!$B$2:$B$10174&"")),0)} -> 2 | I3: {=ROUND(SUMPRODUCT((('ZONE C Vault Mapping'!$A$2:$A$10174=$A3)*((LEFT('ZONE C Vault Mapping'!$B$2:$B$10174,4)="sat_")+(LEFT('ZONE C Vault Mapping'!$B$2:$B$10174,7)="effsat_")+(LEFT('ZONE C Vault Mapping'!$B$2:$B$10174,12)="non_his_sat_"))*('ZONE C Vault Mapping'!$H$2:$H$10174<>"Cancel"))/COUNTIFS('ZONE C Vault Mapping'!$B$2:$B$10174,'ZONE C Vault Mapping'!$B$2:$B$10174&"")),0)} -> 11 | J3: {=ROUND(SUMPRODUCT((('ZONE C Vault Mapping'!$A$2:$A$10174=$A3)*(LEFT('ZONE C Vault Mapping'!$B$2:$B$10174,4)="ref_")*(IFERROR(_xlfn.XLOOKUP('ZONE C Vault Mapping'!$B$2:$B$10174,'Tracking Mapping&Dev Zone C'!$B:$B,'Tracking Mapping&Dev Zone C'!$D:$D),"")<>"Cancel"))/COUNTIFS('ZONE C Vault Mapping'!$B$2:$B$10174,'ZONE C Vault Mapping'!$B$2:$B$10174&"")),0)} -> 1 | K3: =SUM(G3:J3) -> 19 | L3: {=ROUND(SUMPRODUCT((('ZONE C Vault Mapping'!$A$2:$A$10174=$A3)*((LEFT('ZONE C Vault Mapping'!$B$2:$B$10174,4)="hub_")+(LEFT('ZONE C Vault Mapping'!$B$2:$B$10174,4)="sts_")+(LEFT('ZONE C Vault Mapping'!$B$2:$B$10174,5)="link_")+(LEFT('ZONE C Vault Mapping'!$B$2:$B$10174,4)="sat_")+(LEFT('ZONE C Vault Mapping'!$B$2:$B$10174,7)="effsat_")+(LEFT('ZONE C Vault Mapping'!$B$2:$B$10174,4)="ref_")+(LEFT('ZONE C Vault Mapping'!$B$2:$B$10174,12)="non_his_sat_"))*('ZONE C Vault Mapping'!$H$2:$H$10174="Done"))/COUNTIFS('ZONE C Vault Mapping'!$B$2:$B$10174,'ZONE C Vault Mapping'!$B$2:$B$10174&"")),0)} -> 19 | M3: =IFERROR(L3/K3,"") -> 1 | N3: {=ROUND(SUMPRODUCT((('ZONE C Vault Mapping'!$A$2:$A$10174=$A3)*((LEFT('ZONE C Vault Mapping'!$B$2:$B$10174,4)="hub_")+(LEFT('ZONE C Vault Mapping'!$B$2:$B$10174,4)="sts_")+(LEFT('ZONE C Vault Mapping'!$B$2:$B$10174,5)="link_")+(LEFT('ZONE C Vault Mapping'!$B$2:$B$10174,4)="sat_")+(LEFT('ZONE C Vault Mapping'!$B$2:$B$10174,7)="effsat_")+(LEFT('ZONE C Vault Mapping'!$B$2:$B$10174,4)="ref_")+(LEFT('ZONE C Vault Mapping'!$B$2:$B$10174,12)="non_his_sat_"))*('ZONE C Vault Mapping'!$H$2:$H$10174<>"Cancel")*(IFERROR(_xlfn.XLOOKUP('ZONE C Vault Mapping'!$B$2:$B$10174,'Tracking Mapping&Dev Zone C'!$B:$B,'Tracking Mapping&Dev Zone C'!$F:$F),"")="Done"))/COUNTIFS('ZONE C Vault Mapping'!$B$2:$B$10174,'ZONE C Vault Mapping'!$B$2:$B$10174&"")),0)} -> 11 | O3: =IFERROR(N3/L3,"") -> 0.57894737
A4: OCBCHANNEL | B4: {=IFERROR(INDEX(_xlfn._xlws.FILTER('Tracking Mapping&Dev Zone C'!$C:$C,('Tracking Mapping&Dev Zone C'!$A:$A=$A4)*('Tracking Mapping&Dev Zone C'!$C:$C<>"")),1),"")} -> TrangNT | C4: {=IFERROR(_xlfn.TEXTJOIN(", ",TRUE,_xlfn.UNIQUE(_xlfn._xlws.FILTER('Tracking Mapping&Dev Zone C'!$E:$E,('Tracking Mapping&Dev Zone C'!$A:$A=$A4)*('Tracking Mapping&Dev Zone C'!$E:$E<>"")))),"")} -> Thụ | D4: =COUNTIF('Source Tables Zone C'!$A$2:$A$200,$A4) -> 27 | E4: =COUNTIFS('Source Tables Zone C'!$A$2:$A$200,$A4,'Source Tables Zone C'!$C$2:$C$200,"Done") -> 26 | F4: =IFERROR(E4/D4,"") -> 0.96296296 | G4: {=ROUND(SUMPRODUCT((('ZONE C Vault Mapping'!$A$2:$A$10174=$A4)*((LEFT('ZONE C Vault Mapping'!$B$2:$B$10174,4)="hub_")+(LEFT('ZONE C Vault Mapping'!$B$2:$B$10174,4)="sts_"))*('ZONE C Vault Mapping'!$H$2:$H$10174<>"Cancel"))/COUNTIFS('ZONE C Vault Mapping'!$B$2:$B$10174,'ZONE C Vault Mapping'!$B$2:$B$10174&"")),0)} -> 17 | H4: {=ROUND(SUMPRODUCT(('ZONE C Vault Mapping'!$A$2:$A$10174=$A4)*(LEFT('ZONE C Vault Mapping'!$B$2:$B$10174,5)="link_")*('ZONE C Vault Mapping'!$H$2:$H$10174<>"Cancel")/COUNTIFS('ZONE C Vault Mapping'!$B$2:$B$10174,'ZONE C Vault Mapping'!$B$2:$B$10174&"")),0)} -> 38 | I4: {=ROUND(SUMPRODUCT((('ZONE C Vault Mapping'!$A$2:$A$10174=$A4)*((LEFT('ZONE C Vault Mapping'!$B$2:$B$10174,4)="sat_")+(LEFT('ZONE C Vault Mapping'!$B$2:$B$10174,7)="effsat_")+(LEFT('ZONE C Vault Mapping'!$B$2:$B$10174,12)="non_his_sat_"))*('ZONE C Vault Mapping'!$H$2:$H$10174<>"Cancel"))/COUNTIFS('ZONE C Vault Mapping'!$B$2:$B$10174,'ZONE C Vault Mapping'!$B$2:$B$10174&"")),0)} -> 35 | J4: {=ROUND(SUMPRODUCT((('ZONE C Vault Mapping'!$A$2:$A$10174=$A4)*(LEFT('ZONE C Vault Mapping'!$B$2:$B$10174,4)="ref_")*(IFERROR(_xlfn.XLOOKUP('ZONE C Vault Mapping'!$B$2:$B$10174,'Tracking Mapping&Dev Zone C'!$B:$B,'Tracking Mapping&Dev Zone C'!$D:$D),"")<>"Cancel"))/COUNTIFS('ZONE C Vault Mapping'!$B$2:$B$10174,'ZONE C Vault Mapping'!$B$2:$B$10174&"")),0)} -> 4 | K4: =SUM(G4:J4) -> 94 | L4: {=ROUND(SUMPRODUCT((('ZONE C Vault Mapping'!$A$2:$A$10174=$A4)*((LEFT('ZONE C Vault Mapping'!$B$2:$B$10174,4)="hub_")+(LEFT('ZONE C Vault Mapping'!$B$2:$B$10174,4)="sts_")+(LEFT('ZONE C Vault Mapping'!$B$2:$B$10174,5)="link_")+(LEFT('ZONE C Vault Mapping'!$B$2:$B$10174,4)="sat_")+(LEFT('ZONE C Vault Mapping'!$B$2:$B$10174,7)="effsat_")+(LEFT('ZONE C Vault Mapping'!$B$2:$B$10174,4)="ref_")+(LEFT('ZONE C Vault Mapping'!$B$2:$B$10174,12)="non_his_sat_"))*('ZONE C Vault Mapping'!$H$2:$H$10174="Done"))/COUNTIFS('ZONE C Vault Mapping'!$B$2:$B$10174,'ZONE C Vault Mapping'!$B$2:$B$10174&"")),0)} -> 94 | M4: =IFERROR(L4/K4,"") -> 1 | N4: {=ROUND(SUMPRODUCT((('ZONE C Vault Mapping'!$A$2:$A$10174=$A4)*((LEFT('ZONE C Vault Mapping'!$B$2:$B$10174,4)="hub_")+(LEFT('ZONE C Vault Mapping'!$B$2:$B$10174,4)="sts_")+(LEFT('ZONE C Vault Mapping'!$B$2:$B$10174,5)="link_")+(LEFT('ZONE C Vault Mapping'!$B$2:$B$10174,4)="sat_")+(LEFT('ZONE C Vault Mapping'!$B$2:$B$10174,7)="effsat_")+(LEFT('ZONE C Vault Mapping'!$B$2:$B$10174,4)="ref_")+(LEFT('ZONE C Vault Mapping'!$B$2:$B$10174,12)="non_his_sat_"))*('ZONE C Vault Mapping'!$H$2:$H$10174<>"Cancel")*(IFERROR(_xlfn.XLOOKUP('ZONE C Vault Mapping'!$B$2:$B$10174,'Tracking Mapping&Dev Zone C'!$B:$B,'Tracking Mapping&Dev Zone C'!$F:$F),"")="Done"))/COUNTIFS('ZONE C Vault Mapping'!$B$2:$B$10174,'ZONE C Vault Mapping'!$B$2:$B$10174&"")),0)} -> 52 | O4: =IFERROR(N4/L4,"") -> 0.55319149
A5: T24 | B5: {=IFERROR(INDEX(_xlfn._xlws.FILTER('Tracking Mapping&Dev Zone C'!$C:$C,('Tracking Mapping&Dev Zone C'!$A:$A=$A5)*('Tracking Mapping&Dev Zone C'!$C:$C<>"")),1),"")} -> TrangNT | C5: {=IFERROR(_xlfn.TEXTJOIN(", ",TRUE,_xlfn.UNIQUE(_xlfn._xlws.FILTER('Tracking Mapping&Dev Zone C'!$E:$E,('Tracking Mapping&Dev Zone C'!$A:$A=$A5)*('Tracking Mapping&Dev Zone C'!$E:$E<>"")))),"")} -> Thụ, Huy | D5: =COUNTIF('Source Tables Zone C'!$A$2:$A$200,$A5) -> 8 | E5: =COUNTIFS('Source Tables Zone C'!$A$2:$A$200,$A5,'Source Tables Zone C'!$C$2:$C$200,"Done") -> 8 | F5: =IFERROR(E5/D5,"") -> 1 | G5: {=ROUND(SUMPRODUCT((('ZONE C Vault Mapping'!$A$2:$A$10174=$A5)*((LEFT('ZONE C Vault Mapping'!$B$2:$B$10174,4)="hub_")+(LEFT('ZONE C Vault Mapping'!$B$2:$B$10174,4)="sts_"))*('ZONE C Vault Mapping'!$H$2:$H$10174<>"Cancel"))/COUNTIFS('ZONE C Vault Mapping'!$B$2:$B$10174,'ZONE C Vault Mapping'!$B$2:$B$10174&"")),0)} -> 0 | H5: {=ROUND(SUMPRODUCT(('ZONE C Vault Mapping'!$A$2:$A$10174=$A5)*(LEFT('ZONE C Vault Mapping'!$B$2:$B$10174,5)="link_")*('ZONE C Vault Mapping'!$H$2:$H$10174<>"Cancel")/COUNTIFS('ZONE C Vault Mapping'!$B$2:$B$10174,'ZONE C Vault Mapping'!$B$2:$B$10174&"")),0)} -> 0 | I5: {=ROUND(SUMPRODUCT((('ZONE C Vault Mapping'!$A$2:$A$10174=$A5)*((LEFT('ZONE C Vault Mapping'!$B$2:$B$10174,4)="sat_")+(LEFT('ZONE C Vault Mapping'!$B$2:$B$10174,7)="effsat_")+(LEFT('ZONE C Vault Mapping'!$B$2:$B$10174,12)="non_his_sat_"))*('ZONE C Vault Mapping'!$H$2:$H$10174<>"Cancel"))/COUNTIFS('ZONE C Vault Mapping'!$B$2:$B$10174,'ZONE C Vault Mapping'!$B$2:$B$10174&"")),0)} -> 3 | J5: {=ROUND(SUMPRODUCT((('ZONE C Vault Mapping'!$A$2:$A$10174=$A5)*(LEFT('ZONE C Vault Mapping'!$B$2:$B$10174,4)="ref_")*(IFERROR(_xlfn.XLOOKUP('ZONE C Vault Mapping'!$B$2:$B$10174,'Tracking Mapping&Dev Zone C'!$B:$B,'Tracking Mapping&Dev Zone C'!$D:$D),"")<>"Cancel"))/COUNTIFS('ZONE C Vault Mapping'!$B$2:$B$10174,'ZONE C Vault Mapping'!$B$2:$B$10174&"")),0)} -> 2 | K5: =SUM(G5:J5) -> 5 | L5: {=ROUND(SUMPRODUCT((('ZONE C Vault Mapping'!$A$2:$A$10174=$A5)*((LEFT('ZONE C Vault Mapping'!$B$2:$B$10174,4)="hub_")+(LEFT('ZONE C Vault Mapping'!$B$2:$B$10174,4)="sts_")+(LEFT('ZONE C Vault Mapping'!$B$2:$B$10174,5)="link_")+(LEFT('ZONE C Vault Mapping'!$B$2:$B$10174,4)="sat_")+(LEFT('ZONE C Vault Mapping'!$B$2:$B$10174,7)="effsat_")+(LEFT('ZONE C Vault Mapping'!$B$2:$B$10174,4)="ref_")+(LEFT('ZONE C Vault Mapping'!$B$2:$B$10174,12)="non_his_sat_"))*('ZONE C Vault Mapping'!$H$2:$H$10174="Done"))/COUNTIFS('ZONE C Vault Mapping'!$B$2:$B$10174,'ZONE C Vault Mapping'!$B$2:$B$10174&"")),0)} -> 5 | M5: =IFERROR(L5/K5,"") -> 1 | N5: {=ROUND(SUMPRODUCT((('ZONE C Vault Mapping'!$A$2:$A$10174=$A5)*((LEFT('ZONE C Vault Mapping'!$B$2:$B$10174,4)="hub_")+(LEFT('ZONE C Vault Mapping'!$B$2:$B$10174,4)="sts_")+(LEFT('ZONE C Vault Mapping'!$B$2:$B$10174,5)="link_")+(LEFT('ZONE C Vault Mapping'!$B$2:$B$10174,4)="sat_")+(LEFT('ZONE C Vault Mapping'!$B$2:$B$10174,7)="effsat_")+(LEFT('ZONE C Vault Mapping'!$B$2:$B$10174,4)="ref_")+(LEFT('ZONE C Vault Mapping'!$B$2:$B$10174,12)="non_his_sat_"))*('ZONE C Vault Mapping'!$H$2:$H$10174<>"Cancel")*(IFERROR(_xlfn.XLOOKUP('ZONE C Vault Mapping'!$B$2:$B$10174,'Tracking Mapping&Dev Zone C'!$B:$B,'Tracking Mapping&Dev Zone C'!$F:$F),"")="Done"))/COUNTIFS('ZONE C Vault Mapping'!$B$2:$B$10174,'ZONE C Vault Mapping'!$B$2:$B$10174&"")),0)} -> 4 | O5: =IFERROR(N5/L5,"") -> 0.8
A6: ESB | B6: {=IFERROR(INDEX(_xlfn._xlws.FILTER('Tracking Mapping&Dev Zone C'!$C:$C,('Tracking Mapping&Dev Zone C'!$A:$A=$A6)*('Tracking Mapping&Dev Zone C'!$C:$C<>"")),1),"")} -> TrangNT | C6: {=IFERROR(_xlfn.TEXTJOIN(", ",TRUE,_xlfn.UNIQUE(_xlfn._xlws.FILTER('Tracking Mapping&Dev Zone C'!$E:$E,('Tracking Mapping&Dev Zone C'!$A:$A=$A6)*('Tracking Mapping&Dev Zone C'!$E:$E<>"")))),"")} -> Thụ | D6: =COUNTIF('Source Tables Zone C'!$A$2:$A$200,$A6) -> 4 | E6: =COUNTIFS('Source Tables Zone C'!$A$2:$A$200,$A6,'Source Tables Zone C'!$C$2:$C$200,"Done") -> 4 | F6: =IFERROR(E6/D6,"") -> 1 | G6: {=ROUND(SUMPRODUCT((('ZONE C Vault Mapping'!$A$2:$A$10174=$A6)*((LEFT('ZONE C Vault Mapping'!$B$2:$B$10174,4)="hub_")+(LEFT('ZONE C Vault Mapping'!$B$2:$B$10174,4)="sts_"))*('ZONE C Vault Mapping'!$H$2:$H$10174<>"Cancel"))/COUNTIFS('ZONE C Vault Mapping'!$B$2:$B$10174,'ZONE C Vault Mapping'!$B$2:$B$10174&"")),0)} -> 3 | H6: {=ROUND(SUMPRODUCT(('ZONE C Vault Mapping'!$A$2:$A$10174=$A6)*(LEFT('ZONE C Vault Mapping'!$B$2:$B$10174,5)="link_")*('ZONE C Vault Mapping'!$H$2:$H$10174<>"Cancel")/COUNTIFS('ZONE C Vault Mapping'!$B$2:$B$10174,'ZONE C Vault Mapping'!$B$2:$B$10174&"")),0)} -> 9 | I6: {=ROUND(SUMPRODUCT((('ZONE C Vault Mapping'!$A$2:$A$10174=$A6)*((LEFT('ZONE C Vault Mapping'!$B$2:$B$10174,4)="sat_")+(LEFT('ZONE C Vault Mapping'!$B$2:$B$10174,7)="effsat_")+(LEFT('ZONE C Vault Mapping'!$B$2:$B$10174,12)="non_his_sat_"))*('ZONE C Vault Mapping'!$H$2:$H$10174<>"Cancel"))/COUNTIFS('ZONE C Vault Mapping'!$B$2:$B$10174,'ZONE C Vault Mapping'!$B$2:$B$10174&"")),0)} -> 5 | J6: {=ROUND(SUMPRODUCT((('ZONE C Vault Mapping'!$A$2:$A$10174=$A6)*(LEFT('ZONE C Vault Mapping'!$B$2:$B$10174,4)="ref_")*(IFERROR(_xlfn.XLOOKUP('ZONE C Vault Mapping'!$B$2:$B$10174,'Tracking Mapping&Dev Zone C'!$B:$B,'Tracking Mapping&Dev Zone C'!$D:$D),"")<>"Cancel"))/COUNTIFS('ZONE C Vault Mapping'!$B$2:$B$10174,'ZONE C Vault Mapping'!$B$2:$B$10174&"")),0)} -> 0 | K6: =SUM(G6:J6) -> 17 | L6: {=ROUND(SUMPRODUCT((('ZONE C Vault Mapping'!$A$2:$A$10174=$A6)*((LEFT('ZONE C Vault Mapping'!$B$2:$B$10174,4)="hub_")+(LEFT('ZONE C Vault Mapping'!$B$2:$B$10174,4)="sts_")+(LEFT('ZONE C Vault Mapping'!$B$2:$B$10174,5)="link_")+(LEFT('ZONE C Vault Mapping'!$B$2:$B$10174,4)="sat_")+(LEFT('ZONE C Vault Mapping'!$B$2:$B$10174,7)="effsat_")+(LEFT('ZONE C Vault Mapping'!$B$2:$B$10174,4)="ref_")+(LEFT('ZONE C Vault Mapping'!$B$2:$B$10174,12)="non_his_sat_"))*('ZONE C Vault Mapping'!$H$2:$H$10174="Done"))/COUNTIFS('ZONE C Vault Mapping'!$B$2:$B$10174,'ZONE C Vault Mapping'!$B$2:$B$10174&"")),0)} -> 17 | M6: =IFERROR(L6/K6,"") -> 1 | N6: {=ROUND(SUMPRODUCT((('ZONE C Vault Mapping'!$A$2:$A$10174=$A6)*((LEFT('ZONE C Vault Mapping'!$B$2:$B$10174,4)="hub_")+(LEFT('ZONE C Vault Mapping'!$B$2:$B$10174,4)="sts_")+(LEFT('ZONE C Vault Mapping'!$B$2:$B$10174,5)="link_")+(LEFT('ZONE C Vault Mapping'!$B$2:$B$10174,4)="sat_")+(LEFT('ZONE C Vault Mapping'!$B$2:$B$10174,7)="effsat_")+(LEFT('ZONE C Vault Mapping'!$B$2:$B$10174,4)="ref_")+(LEFT('ZONE C Vault Mapping'!$B$2:$B$10174,12)="non_his_sat_"))*('ZONE C Vault Mapping'!$H$2:$H$10174<>"Cancel")*(IFERROR(_xlfn.XLOOKUP('ZONE C Vault Mapping'!$B$2:$B$10174,'Tracking Mapping&Dev Zone C'!$B:$B,'Tracking Mapping&Dev Zone C'!$F:$F),"")="Done"))/COUNTIFS('ZONE C Vault Mapping'!$B$2:$B$10174,'ZONE C Vault Mapping'!$B$2:$B$10174&"")),0)} -> 2 | O6: =IFERROR(N6/L6,"") -> 0.11764706
A7: BPM | B7: {=IFERROR(INDEX(_xlfn._xlws.FILTER('Tracking Mapping&Dev Zone C'!$C:$C,('Tracking Mapping&Dev Zone C'!$A:$A=$A7)*('Tracking Mapping&Dev Zone C'!$C:$C<>"")),1),"")} -> TrangNT | C7: {=IFERROR(_xlfn.TEXTJOIN(", ",TRUE,_xlfn.UNIQUE(_xlfn._xlws.FILTER('Tracking Mapping&Dev Zone C'!$E:$E,('Tracking Mapping&Dev Zone C'!$A:$A=$A7)*('Tracking Mapping&Dev Zone C'!$E:$E<>"")))),"")} -> Huy | D7: =COUNTIF('Source Tables Zone C'!$A$2:$A$200,$A7) -> 21 | E7: =COUNTIFS('Source Tables Zone C'!$A$2:$A$200,$A7,'Source Tables Zone C'!$C$2:$C$200,"Done") -> 20 | F7: =IFERROR(E7/D7,"") -> 0.95238095 | G7: {=ROUND(SUMPRODUCT((('ZONE C Vault Mapping'!$A$2:$A$10174=$A7)*((LEFT('ZONE C Vault Mapping'!$B$2:$B$10174,4)="hub_")+(LEFT('ZONE C Vault Mapping'!$B$2:$B$10174,4)="sts_"))*('ZONE C Vault Mapping'!$H$2:$H$10174<>"Cancel"))/COUNTIFS('ZONE C Vault Mapping'!$B$2:$B$10174,'ZONE C Vault Mapping'!$B$2:$B$10174&"")),0)} -> 2 | H7: {=ROUND(SUMPRODUCT(('ZONE C Vault Mapping'!$A$2:$A$10174=$A7)*(LEFT('ZONE C Vault Mapping'!$B$2:$B$10174,5)="link_")*('ZONE C Vault Mapping'!$H$2:$H$10174<>"Cancel")/COUNTIFS('ZONE C Vault Mapping'!$B$2:$B$10174,'ZONE C Vault Mapping'!$B$2:$B$10174&"")),0)} -> 2 | I7: {=ROUND(SUMPRODUCT((('ZONE C Vault Mapping'!$A$2:$A$10174=$A7)*((LEFT('ZONE C Vault Mapping'!$B$2:$B$10174,4)="sat_")+(LEFT('ZONE C Vault Mapping'!$B$2:$B$10174,7)="effsat_")+(LEFT('ZONE C Vault Mapping'!$B$2:$B$10174,12)="non_his_sat_"))*('ZONE C Vault Mapping'!$H$2:$H$10174<>"Cancel"))/COUNTIFS('ZONE C Vault Mapping'!$B$2:$B$10174,'ZONE C Vault Mapping'!$B$2:$B$10174&"")),0)} -> 34 | J7: {=ROUND(SUMPRODUCT((('ZONE C Vault Mapping'!$A$2:$A$10174=$A7)*(LEFT('ZONE C Vault Mapping'!$B$2:$B$10174,4)="ref_")*(IFERROR(_xlfn.XLOOKUP('ZONE C Vault Mapping'!$B$2:$B$10174,'Tracking Mapping&Dev Zone C'!$B:$B,'Tracking Mapping&Dev Zone C'!$D:$D),"")<>"Cancel"))/COUNTIFS('ZONE C Vault Mapping'!$B$2:$B$10174,'ZONE C Vault Mapping'!$B$2:$B$10174&"")),0)} -> 2 | K7: =SUM(G7:J7) -> 40 | L7: {=ROUND(SUMPRODUCT((('ZONE C Vault Mapping'!$A$2:$A$10174=$A7)*((LEFT('ZONE C Vault Mapping'!$B$2:$B$10174,4)="hub_")+(LEFT('ZONE C Vault Mapping'!$B$2:$B$10174,4)="sts_")+(LEFT('ZONE C Vault Mapping'!$B$2:$B$10174,5)="link_")+(LEFT('ZONE C Vault Mapping'!$B$2:$B$10174,4)="sat_")+(LEFT('ZONE C Vault Mapping'!$B$2:$B$10174,7)="effsat_")+(LEFT('ZONE C Vault Mapping'!$B$2:$B$10174,4)="ref_")+(LEFT('ZONE C Vault Mapping'!$B$2:$B$10174,12)="non_his_sat_"))*('ZONE C Vault Mapping'!$H$2:$H$10174="Done"))/COUNTIFS('ZONE C Vault Mapping'!$B$2:$B$10174,'ZONE C Vault Mapping'!$B$2:$B$10174&"")),0)} -> 40 | M7: =IFERROR(L7/K7,"") -> 1 | N7: {=ROUND(SUMPRODUCT((('ZONE C Vault Mapping'!$A$2:$A$10174=$A7)*((LEFT('ZONE C Vault Mapping'!$B$2:$B$10174,4)="hub_")+(LEFT('ZONE C Vault Mapping'!$B$2:$B$10174,4)="sts_")+(LEFT('ZONE C Vault Mapping'!$B$2:$B$10174,5)="link_")+(LEFT('ZONE C Vault Mapping'!$B$2:$B$10174,4)="sat_")+(LEFT('ZONE C Vault Mapping'!$B$2:$B$10174,7)="effsat_")+(LEFT('ZONE C Vault Mapping'!$B$2:$B$10174,4)="ref_")+(LEFT('ZONE C Vault Mapping'!$B$2:$B$10174,12)="non_his_sat_"))*('ZONE C Vault Mapping'!$H$2:$H$10174<>"Cancel")*(IFERROR(_xlfn.XLOOKUP('ZONE C Vault Mapping'!$B$2:$B$10174,'Tracking Mapping&Dev Zone C'!$B:$B,'Tracking Mapping&Dev Zone C'!$F:$F),"")="Done"))/COUNTIFS('ZONE C Vault Mapping'!$B$2:$B$10174,'ZONE C Vault Mapping'!$B$2:$B$10174&"")),0)} -> 5 | O7: =IFERROR(N7/L7,"") -> 0.125
A8: NEWFO | B8: {=IFERROR(INDEX(_xlfn._xlws.FILTER('Tracking Mapping&Dev Zone C'!$C:$C,('Tracking Mapping&Dev Zone C'!$A:$A=$A8)*('Tracking Mapping&Dev Zone C'!$C:$C<>"")),1),"")} -> TrangNT | C8: {=IFERROR(_xlfn.TEXTJOIN(", ",TRUE,_xlfn.UNIQUE(_xlfn._xlws.FILTER('Tracking Mapping&Dev Zone C'!$E:$E,('Tracking Mapping&Dev Zone C'!$A:$A=$A8)*('Tracking Mapping&Dev Zone C'!$E:$E<>"")))),"")} -> Huy | D8: =COUNTIF('Source Tables Zone C'!$A$2:$A$200,$A8) -> 2 | E8: =COUNTIFS('Source Tables Zone C'!$A$2:$A$200,$A8,'Source Tables Zone C'!$C$2:$C$200,"Done") -> 2 | F8: =IFERROR(E8/D8,"") -> 1 | G8: {=ROUND(SUMPRODUCT((('ZONE C Vault Mapping'!$A$2:$A$10174=$A8)*((LEFT('ZONE C Vault Mapping'!$B$2:$B$10174,4)="hub_")+(LEFT('ZONE C Vault Mapping'!$B$2:$B$10174,4)="sts_"))*('ZONE C Vault Mapping'!$H$2:$H$10174<>"Cancel"))/COUNTIFS('ZONE C Vault Mapping'!$B$2:$B$10174,'ZONE C Vault Mapping'!$B$2:$B$10174&"")),0)} -> 2 | H8: {=ROUND(SUMPRODUCT(('ZONE C Vault Mapping'!$A$2:$A$10174=$A8)*(LEFT('ZONE C Vault Mapping'!$B$2:$B$10174,5)="link_")*('ZONE C Vault Mapping'!$H$2:$H$10174<>"Cancel")/COUNTIFS('ZONE C Vault Mapping'!$B$2:$B$10174,'ZONE C Vault Mapping'!$B$2:$B$10174&"")),0)} -> 4 | I8: {=ROUND(SUMPRODUCT((('ZONE C Vault Mapping'!$A$2:$A$10174=$A8)*((LEFT('ZONE C Vault Mapping'!$B$2:$B$10174,4)="sat_")+(LEFT('ZONE C Vault Mapping'!$B$2:$B$10174,7)="effsat_")+(LEFT('ZONE C Vault Mapping'!$B$2:$B$10174,12)="non_his_sat_"))*('ZONE C Vault Mapping'!$H$2:$H$10174<>"Cancel"))/COUNTIFS('ZONE C Vault Mapping'!$B$2:$B$10174,'ZONE C Vault Mapping'!$B$2:$B$10174&"")),0)} -> 2 | J8: {=ROUND(SUMPRODUCT((('ZONE C Vault Mapping'!$A$2:$A$10174=$A8)*(LEFT('ZONE C Vault Mapping'!$B$2:$B$10174,4)="ref_")*(IFERROR(_xlfn.XLOOKUP('ZONE C Vault Mapping'!$B$2:$B$10174,'Tracking Mapping&Dev Zone C'!$B:$B,'Tracking Mapping&Dev Zone C'!$D:$D),"")<>"Cancel"))/COUNTIFS('ZONE C Vault Mapping'!$B$2:$B$10174,'ZONE C Vault Mapping'!$B$2:$B$10174&"")),0)} -> 0 | K8: =SUM(G8:J8) -> 8 | L8: {=ROUND(SUMPRODUCT((('ZONE C Vault Mapping'!$A$2:$A$10174=$A8)*((LEFT('ZONE C Vault Mapping'!$B$2:$B$10174,4)="hub_")+(LEFT('ZONE C Vault Mapping'!$B$2:$B$10174,4)="sts_")+(LEFT('ZONE C Vault Mapping'!$B$2:$B$10174,5)="link_")+(LEFT('ZONE C Vault Mapping'!$B$2:$B$10174,4)="sat_")+(LEFT('ZONE C Vault Mapping'!$B$2:$B$10174,7)="effsat_")+(LEFT('ZONE C Vault Mapping'!$B$2:$B$10174,4)="ref_")+(LEFT('ZONE C Vault Mapping'!$B$2:$B$10174,12)="non_his_sat_"))*('ZONE C Vault Mapping'!$H$2:$H$10174="Done"))/COUNTIFS('ZONE C Vault Mapping'!$B$2:$B$10174,'ZONE C Vault Mapping'!$B$2:$B$10174&"")),0)} -> 8 | M8: =IFERROR(L8/K8,"") -> 1 | N8: {=ROUND(SUMPRODUCT((('ZONE C Vault Mapping'!$A$2:$A$10174=$A8)*((LEFT('ZONE C Vault Mapping'!$B$2:$B$10174,4)="hub_")+(LEFT('ZONE C Vault Mapping'!$B$2:$B$10174,4)="sts_")+(LEFT('ZONE C Vault Mapping'!$B$2:$B$10174,5)="link_")+(LEFT('ZONE C Vault Mapping'!$B$2:$B$10174,4)="sat_")+(LEFT('ZONE C Vault Mapping'!$B$2:$B$10174,7)="effsat_")+(LEFT('ZONE C Vault Mapping'!$B$2:$B$10174,4)="ref_")+(LEFT('ZONE C Vault Mapping'!$B$2:$B$10174,12)="non_his_sat_"))*('ZONE C Vault Mapping'!$H$2:$H$10174<>"Cancel")*(IFERROR(_xlfn.XLOOKUP('ZONE C Vault Mapping'!$B$2:$B$10174,'Tracking Mapping&Dev Zone C'!$B:$B,'Tracking Mapping&Dev Zone C'!$F:$F),"")="Done"))/COUNTIFS('ZONE C Vault Mapping'!$B$2:$B$10174,'ZONE C Vault Mapping'!$B$2:$B$10174&"")),0)} -> 5 | O8: =IFERROR(N8/L8,"") -> 0.625
A9: QLDT | B9: {=IFERROR(INDEX(_xlfn._xlws.FILTER('Tracking Mapping&Dev Zone C'!$C:$C,('Tracking Mapping&Dev Zone C'!$A:$A=$A9)*('Tracking Mapping&Dev Zone C'!$C:$C<>"")),1),"")} -> TrangNT | C9: {=IFERROR(_xlfn.TEXTJOIN(", ",TRUE,_xlfn.UNIQUE(_xlfn._xlws.FILTER('Tracking Mapping&Dev Zone C'!$E:$E,('Tracking Mapping&Dev Zone C'!$A:$A=$A9)*('Tracking Mapping&Dev Zone C'!$E:$E<>"")))),"")} -> Huy | D9: =COUNTIF('Source Tables Zone C'!$A$2:$A$200,$A9) -> 2 | E9: =COUNTIFS('Source Tables Zone C'!$A$2:$A$200,$A9,'Source Tables Zone C'!$C$2:$C$200,"Done") -> 2 | F9: =IFERROR(E9/D9,"") -> 1 | G9: {=ROUND(SUMPRODUCT((('ZONE C Vault Mapping'!$A$2:$A$10174=$A9)*((LEFT('ZONE C Vault Mapping'!$B$2:$B$10174,4)="hub_")+(LEFT('ZONE C Vault Mapping'!$B$2:$B$10174,4)="sts_"))*('ZONE C Vault Mapping'!$H$2:$H$10174<>"Cancel"))/COUNTIFS('ZONE C Vault Mapping'!$B$2:$B$10174,'ZONE C Vault Mapping'!$B$2:$B$10174&"")),0)} -> 1 | H9: {=ROUND(SUMPRODUCT(('ZONE C Vault Mapping'!$A$2:$A$10174=$A9)*(LEFT('ZONE C Vault Mapping'!$B$2:$B$10174,5)="link_")*('ZONE C Vault Mapping'!$H$2:$H$10174<>"Cancel")/COUNTIFS('ZONE C Vault Mapping'!$B$2:$B$10174,'ZONE C Vault Mapping'!$B$2:$B$10174&"")),0)} -> 2 | I9: {=ROUND(SUMPRODUCT((('ZONE C Vault Mapping'!$A$2:$A$10174=$A9)*((LEFT('ZONE C Vault Mapping'!$B$2:$B$10174,4)="sat_")+(LEFT('ZONE C Vault Mapping'!$B$2:$B$10174,7)="effsat_")+(LEFT('ZONE C Vault Mapping'!$B$2:$B$10174,12)="non_his_sat_"))*('ZONE C Vault Mapping'!$H$2:$H$10174<>"Cancel"))/COUNTIFS('ZONE C Vault Mapping'!$B$2:$B$10174,'ZONE C Vault Mapping'!$B$2:$B$10174&"")),0)} -> 2 | J9: {=ROUND(SUMPRODUCT((('ZONE C Vault Mapping'!$A$2:$A$10174=$A9)*(LEFT('ZONE C Vault Mapping'!$B$2:$B$10174,4)="ref_")*(IFERROR(_xlfn.XLOOKUP('ZONE C Vault Mapping'!$B$2:$B$10174,'Tracking Mapping&Dev Zone C'!$B:$B,'Tracking Mapping&Dev Zone C'!$D:$D),"")<>"Cancel"))/COUNTIFS('ZONE C Vault Mapping'!$B$2:$B$10174,'ZONE C Vault Mapping'!$B$2:$B$10174&"")),0)} -> 1 | K9: =SUM(G9:J9) -> 6 | L9: {=ROUND(SUMPRODUCT((('ZONE C Vault Mapping'!$A$2:$A$10174=$A9)*((LEFT('ZONE C Vault Mapping'!$B$2:$B$10174,4)="hub_")+(LEFT('ZONE C Vault Mapping'!$B$2:$B$10174,4)="sts_")+(LEFT('ZONE C Vault Mapping'!$B$2:$B$10174,5)="link_")+(LEFT('ZONE C Vault Mapping'!$B$2:$B$10174,4)="sat_")+(LEFT('ZONE C Vault Mapping'!$B$2:$B$10174,7)="effsat_")+(LEFT('ZONE C Vault Mapping'!$B$2:$B$10174,4)="ref_")+(LEFT('ZONE C Vault Mapping'!$B$2:$B$10174,12)="non_his_sat_"))*('ZONE C Vault Mapping'!$H$2:$H$10174="Done"))/COUNTIFS('ZONE C Vault Mapping'!$B$2:$B$10174,'ZONE C Vault Mapping'!$B$2:$B$10174&"")),0)} -> 6 | M9: =IFERROR(L9/K9,"") -> 1 | N9: {=ROUND(SUMPRODUCT((('ZONE C Vault Mapping'!$A$2:$A$10174=$A9)*((LEFT('ZONE C Vault Mapping'!$B$2:$B$10174,4)="hub_")+(LEFT('ZONE C Vault Mapping'!$B$2:$B$10174,4)="sts_")+(LEFT('ZONE C Vault Mapping'!$B$2:$B$10174,5)="link_")+(LEFT('ZONE C Vault Mapping'!$B$2:$B$10174,4)="sat_")+(LEFT('ZONE C Vault Mapping'!$B$2:$B$10174,7)="effsat_")+(LEFT('ZONE C Vault Mapping'!$B$2:$B$10174,4)="ref_")+(LEFT('ZONE C Vault Mapping'!$B$2:$B$10174,12)="non_his_sat_"))*('ZONE C Vault Mapping'!$H$2:$H$10174<>"Cancel")*(IFERROR(_xlfn.XLOOKUP('ZONE C Vault Mapping'!$B$2:$B$10174,'Tracking Mapping&Dev Zone C'!$B:$B,'Tracking Mapping&Dev Zone C'!$F:$F),"")="Done"))/COUNTIFS('ZONE C Vault Mapping'!$B$2:$B$10174,'ZONE C Vault Mapping'!$B$2:$B$10174&"")),0)} -> 5 | O9: =IFERROR(N9/L9,"") -> 0.83333333
A10: OMNIMA | B10: {=IFERROR(INDEX(_xlfn._xlws.FILTER('Tracking Mapping&Dev Zone C'!$C:$C,('Tracking Mapping&Dev Zone C'!$A:$A=$A10)*('Tracking Mapping&Dev Zone C'!$C:$C<>"")),1),"")} -> TrangNT | C10: {=IFERROR(_xlfn.TEXTJOIN(", ",TRUE,_xlfn.UNIQUE(_xlfn._xlws.FILTER('Tracking Mapping&Dev Zone C'!$E:$E,('Tracking Mapping&Dev Zone C'!$A:$A=$A10)*('Tracking Mapping&Dev Zone C'!$E:$E<>"")))),"")} -> Thụ | D10: =COUNTIF('Source Tables Zone C'!$A$2:$A$200,$A10) -> 1 | E10: =COUNTIFS('Source Tables Zone C'!$A$2:$A$200,$A10,'Source Tables Zone C'!$C$2:$C$200,"Done") -> 1 | F10: =IFERROR(E10/D10,"") -> 1 | G10: {=ROUND(SUMPRODUCT((('ZONE C Vault Mapping'!$A$2:$A$10174=$A10)*((LEFT('ZONE C Vault Mapping'!$B$2:$B$10174,4)="hub_")+(LEFT('ZONE C Vault Mapping'!$B$2:$B$10174,4)="sts_"))*('ZONE C Vault Mapping'!$H$2:$H$10174<>"Cancel"))/COUNTIFS('ZONE C Vault Mapping'!$B$2:$B$10174,'ZONE C Vault Mapping'!$B$2:$B$10174&"")),0)} -> 1 | H10: {=ROUND(SUMPRODUCT(('ZONE C Vault Mapping'!$A$2:$A$10174=$A10)*(LEFT('ZONE C Vault Mapping'!$B$2:$B$10174,5)="link_")*('ZONE C Vault Mapping'!$H$2:$H$10174<>"Cancel")/COUNTIFS('ZONE C Vault Mapping'!$B$2:$B$10174,'ZONE C Vault Mapping'!$B$2:$B$10174&"")),0)} -> 2 | I10: {=ROUND(SUMPRODUCT((('ZONE C Vault Mapping'!$A$2:$A$10174=$A10)*((LEFT('ZONE C Vault Mapping'!$B$2:$B$10174,4)="sat_")+(LEFT('ZONE C Vault Mapping'!$B$2:$B$10174,7)="effsat_")+(LEFT('ZONE C Vault Mapping'!$B$2:$B$10174,12)="non_his_sat_"))*('ZONE C Vault Mapping'!$H$2:$H$10174<>"Cancel"))/COUNTIFS('ZONE C Vault Mapping'!$B$2:$B$10174,'ZONE C Vault Mapping'!$B$2:$B$10174&"")),0)} -> 3 | J10: {=ROUND(SUMPRODUCT((('ZONE C Vault Mapping'!$A$2:$A$10174=$A10)*(LEFT('ZONE C Vault Mapping'!$B$2:$B$10174,4)="ref_")*(IFERROR(_xlfn.XLOOKUP('ZONE C Vault Mapping'!$B$2:$B$10174,'Tracking Mapping&Dev Zone C'!$B:$B,'Tracking Mapping&Dev Zone C'!$D:$D),"")<>"Cancel"))/COUNTIFS('ZONE C Vault Mapping'!$B$2:$B$10174,'ZONE C Vault Mapping'!$B$2:$B$10174&"")),0)} -> 0 | K10: =SUM(G10:J10) -> 6 | L10: {=ROUND(SUMPRODUCT((('ZONE C Vault Mapping'!$A$2:$A$10174=$A10)*((LEFT('ZONE C Vault Mapping'!$B$2:$B$10174,4)="hub_")+(LEFT('ZONE C Vault Mapping'!$B$2:$B$10174,4)="sts_")+(LEFT('ZONE C Vault Mapping'!$B$2:$B$10174,5)="link_")+(LEFT('ZONE C Vault Mapping'!$B$2:$B$10174,4)="sat_")+(LEFT('ZONE C Vault Mapping'!$B$2:$B$10174,7)="effsat_")+(LEFT('ZONE C Vault Mapping'!$B$2:$B$10174,4)="ref_")+(LEFT('ZONE C Vault Mapping'!$B$2:$B$10174,12)="non_his_sat_"))*('ZONE C Vault Mapping'!$H$2:$H$10174="Done"))/COUNTIFS('ZONE C Vault Mapping'!$B$2:$B$10174,'ZONE C Vault Mapping'!$B$2:$B$10174&"")),0)} -> 6 | M10: =IFERROR(L10/K10,"") -> 1 | N10: {=ROUND(SUMPRODUCT((('ZONE C Vault Mapping'!$A$2:$A$10174=$A10)*((LEFT('ZONE C Vault Mapping'!$B$2:$B$10174,4)="hub_")+(LEFT('ZONE C Vault Mapping'!$B$2:$B$10174,4)="sts_")+(LEFT('ZONE C Vault Mapping'!$B$2:$B$10174,5)="link_")+(LEFT('ZONE C Vault Mapping'!$B$2:$B$10174,4)="sat_")+(LEFT('ZONE C Vault Mapping'!$B$2:$B$10174,7)="effsat_")+(LEFT('ZONE C Vault Mapping'!$B$2:$B$10174,4)="ref_")+(LEFT('ZONE C Vault Mapping'!$B$2:$B$10174,12)="non_his_sat_"))*('ZONE C Vault Mapping'!$H$2:$H$10174<>"Cancel")*(IFERROR(_xlfn.XLOOKUP('ZONE C Vault Mapping'!$B$2:$B$10174,'Tracking Mapping&Dev Zone C'!$B:$B,'Tracking Mapping&Dev Zone C'!$F:$F),"")="Done"))/COUNTIFS('ZONE C Vault Mapping'!$B$2:$B$10174,'ZONE C Vault Mapping'!$B$2:$B$10174&"")),0)} -> 3 | O10: =IFERROR(N10/L10,"") -> 0.5
A11: GAMS | B11: {=IFERROR(INDEX(_xlfn._xlws.FILTER('Tracking Mapping&Dev Zone C'!$C:$C,('Tracking Mapping&Dev Zone C'!$A:$A=$A11)*('Tracking Mapping&Dev Zone C'!$C:$C<>"")),1),"")} -> TrangNT | C11: {=IFERROR(_xlfn.TEXTJOIN(", ",TRUE,_xlfn.UNIQUE(_xlfn._xlws.FILTER('Tracking Mapping&Dev Zone C'!$E:$E,('Tracking Mapping&Dev Zone C'!$A:$A=$A11)*('Tracking Mapping&Dev Zone C'!$E:$E<>"")))),"")} -> Thụ | D11: =COUNTIF('Source Tables Zone C'!$A$2:$A$200,$A11) -> 1 | E11: =COUNTIFS('Source Tables Zone C'!$A$2:$A$200,$A11,'Source Tables Zone C'!$C$2:$C$200,"Done") -> 1 | F11: =IFERROR(E11/D11,"") -> 1 | G11: {=ROUND(SUMPRODUCT((('ZONE C Vault Mapping'!$A$2:$A$10174=$A11)*((LEFT('ZONE C Vault Mapping'!$B$2:$B$10174,4)="hub_")+(LEFT('ZONE C Vault Mapping'!$B$2:$B$10174,4)="sts_"))*('ZONE C Vault Mapping'!$H$2:$H$10174<>"Cancel"))/COUNTIFS('ZONE C Vault Mapping'!$B$2:$B$10174,'ZONE C Vault Mapping'!$B$2:$B$10174&"")),0)} -> 1 | H11: {=ROUND(SUMPRODUCT(('ZONE C Vault Mapping'!$A$2:$A$10174=$A11)*(LEFT('ZONE C Vault Mapping'!$B$2:$B$10174,5)="link_")*('ZONE C Vault Mapping'!$H$2:$H$10174<>"Cancel")/COUNTIFS('ZONE C Vault Mapping'!$B$2:$B$10174,'ZONE C Vault Mapping'!$B$2:$B$10174&"")),0)} -> 2 | I11: {=ROUND(SUMPRODUCT((('ZONE C Vault Mapping'!$A$2:$A$10174=$A11)*((LEFT('ZONE C Vault Mapping'!$B$2:$B$10174,4)="sat_")+(LEFT('ZONE C Vault Mapping'!$B$2:$B$10174,7)="effsat_")+(LEFT('ZONE C Vault Mapping'!$B$2:$B$10174,12)="non_his_sat_"))*('ZONE C Vault Mapping'!$H$2:$H$10174<>"Cancel"))/COUNTIFS('ZONE C Vault Mapping'!$B$2:$B$10174,'ZONE C Vault Mapping'!$B$2:$B$10174&"")),0)} -> 1 | J11: {=ROUND(SUMPRODUCT((('ZONE C Vault Mapping'!$A$2:$A$10174=$A11)*(LEFT('ZONE C Vault Mapping'!$B$2:$B$10174,4)="ref_")*(IFERROR(_xlfn.XLOOKUP('ZONE C Vault Mapping'!$B$2:$B$10174,'Tracking Mapping&Dev Zone C'!$B:$B,'Tracking Mapping&Dev Zone C'!$D:$D),"")<>"Cancel"))/COUNTIFS('ZONE C Vault Mapping'!$B$2:$B$10174,'ZONE C Vault Mapping'!$B$2:$B$10174&"")),0)} -> 0 | K11: =SUM(G11:J11) -> 4 | L11: {=ROUND(SUMPRODUCT((('ZONE C Vault Mapping'!$A$2:$A$10174=$A11)*((LEFT('ZONE C Vault Mapping'!$B$2:$B$10174,4)="hub_")+(LEFT('ZONE C Vault Mapping'!$B$2:$B$10174,4)="sts_")+(LEFT('ZONE C Vault Mapping'!$B$2:$B$10174,5)="link_")+(LEFT('ZONE C Vault Mapping'!$B$2:$B$10174,4)="sat_")+(LEFT('ZONE C Vault Mapping'!$B$2:$B$10174,7)="effsat_")+(LEFT('ZONE C Vault Mapping'!$B$2:$B$10174,4)="ref_")+(LEFT('ZONE C Vault Mapping'!$B$2:$B$10174,12)="non_his_sat_"))*('ZONE C Vault Mapping'!$H$2:$H$10174="Done"))/COUNTIFS('ZONE C Vault Mapping'!$B$2:$B$10174,'ZONE C Vault Mapping'!$B$2:$B$10174&"")),0)} -> 4 | M11: =IFERROR(L11/K11,"") -> 1 | N11: {=ROUND(SUMPRODUCT((('ZONE C Vault Mapping'!$A$2:$A$10174=$A11)*((LEFT('ZONE C Vault Mapping'!$B$2:$B$10174,4)="hub_")+(LEFT('ZONE C Vault Mapping'!$B$2:$B$10174,4)="sts_")+(LEFT('ZONE C Vault Mapping'!$B$2:$B$10174,5)="link_")+(LEFT('ZONE C Vault Mapping'!$B$2:$B$10174,4)="sat_")+(LEFT('ZONE C Vault Mapping'!$B$2:$B$10174,7)="effsat_")+(LEFT('ZONE C Vault Mapping'!$B$2:$B$10174,4)="ref_")+(LEFT('ZONE C Vault Mapping'!$B$2:$B$10174,12)="non_his_sat_"))*('ZONE C Vault Mapping'!$H$2:$H$10174<>"Cancel")*(IFERROR(_xlfn.XLOOKUP('ZONE C Vault Mapping'!$B$2:$B$10174,'Tracking Mapping&Dev Zone C'!$B:$B,'Tracking Mapping&Dev Zone C'!$F:$F),"")="Done"))/COUNTIFS('ZONE C Vault Mapping'!$B$2:$B$10174,'ZONE C Vault Mapping'!$B$2:$B$10174&"")),0)} -> 0 | O11: =IFERROR(N11/L11,"") -> 0
A12: TREASURY | B12: {=IFERROR(INDEX(_xlfn._xlws.FILTER('Tracking Mapping&Dev Zone C'!$C:$C,('Tracking Mapping&Dev Zone C'!$A:$A=$A12)*('Tracking Mapping&Dev Zone C'!$C:$C<>"")),1),"")} -> TrangNT | C12: {=IFERROR(_xlfn.TEXTJOIN(", ",TRUE,_xlfn.UNIQUE(_xlfn._xlws.FILTER('Tracking Mapping&Dev Zone C'!$E:$E,('Tracking Mapping&Dev Zone C'!$A:$A=$A12)*('Tracking Mapping&Dev Zone C'!$E:$E<>"")))),"")} -> Thụ | D12: =COUNTIF('Source Tables Zone C'!$A$2:$A$200,$A12) -> 1 | E12: =COUNTIFS('Source Tables Zone C'!$A$2:$A$200,$A12,'Source Tables Zone C'!$C$2:$C$200,"Done") -> 1 | F12: =IFERROR(E12/D12,"") -> 1 | G12: {=ROUND(SUMPRODUCT((('ZONE C Vault Mapping'!$A$2:$A$10174=$A12)*((LEFT('ZONE C Vault Mapping'!$B$2:$B$10174,4)="hub_")+(LEFT('ZONE C Vault Mapping'!$B$2:$B$10174,4)="sts_"))*('ZONE C Vault Mapping'!$H$2:$H$10174<>"Cancel"))/COUNTIFS('ZONE C Vault Mapping'!$B$2:$B$10174,'ZONE C Vault Mapping'!$B$2:$B$10174&"")),0)} -> 1 | H12: {=ROUND(SUMPRODUCT(('ZONE C Vault Mapping'!$A$2:$A$10174=$A12)*(LEFT('ZONE C Vault Mapping'!$B$2:$B$10174,5)="link_")*('ZONE C Vault Mapping'!$H$2:$H$10174<>"Cancel")/COUNTIFS('ZONE C Vault Mapping'!$B$2:$B$10174,'ZONE C Vault Mapping'!$B$2:$B$10174&"")),0)} -> 1 | I12: {=ROUND(SUMPRODUCT((('ZONE C Vault Mapping'!$A$2:$A$10174=$A12)*((LEFT('ZONE C Vault Mapping'!$B$2:$B$10174,4)="sat_")+(LEFT('ZONE C Vault Mapping'!$B$2:$B$10174,7)="effsat_")+(LEFT('ZONE C Vault Mapping'!$B$2:$B$10174,12)="non_his_sat_"))*('ZONE C Vault Mapping'!$H$2:$H$10174<>"Cancel"))/COUNTIFS('ZONE C Vault Mapping'!$B$2:$B$10174,'ZONE C Vault Mapping'!$B$2:$B$10174&"")),0)} -> 1 | J12: {=ROUND(SUMPRODUCT((('ZONE C Vault Mapping'!$A$2:$A$10174=$A12)*(LEFT('ZONE C Vault Mapping'!$B$2:$B$10174,4)="ref_")*(IFERROR(_xlfn.XLOOKUP('ZONE C Vault Mapping'!$B$2:$B$10174,'Tracking Mapping&Dev Zone C'!$B:$B,'Tracking Mapping&Dev Zone C'!$D:$D),"")<>"Cancel"))/COUNTIFS('ZONE C Vault Mapping'!$B$2:$B$10174,'ZONE C Vault Mapping'!$B$2:$B$10174&"")),0)} -> 0 | K12: =SUM(G12:J12) -> 3 | L12: {=ROUND(SUMPRODUCT((('ZONE C Vault Mapping'!$A$2:$A$10174=$A12)*((LEFT('ZONE C Vault Mapping'!$B$2:$B$10174,4)="hub_")+(LEFT('ZONE C Vault Mapping'!$B$2:$B$10174,4)="sts_")+(LEFT('ZONE C Vault Mapping'!$B$2:$B$10174,5)="link_")+(LEFT('ZONE C Vault Mapping'!$B$2:$B$10174,4)="sat_")+(LEFT('ZONE C Vault Mapping'!$B$2:$B$10174,7)="effsat_")+(LEFT('ZONE C Vault Mapping'!$B$2:$B$10174,4)="ref_")+(LEFT('ZONE C Vault Mapping'!$B$2:$B$10174,12)="non_his_sat_"))*('ZONE C Vault Mapping'!$H$2:$H$10174="Done"))/COUNTIFS('ZONE C Vault Mapping'!$B$2:$B$10174,'ZONE C Vault Mapping'!$B$2:$B$10174&"")),0)} -> 3 | M12: =IFERROR(L12/K12,"") -> 1 | N12: {=ROUND(SUMPRODUCT((('ZONE C Vault Mapping'!$A$2:$A$10174=$A12)*((LEFT('ZONE C Vault Mapping'!$B$2:$B$10174,4)="hub_")+(LEFT('ZONE C Vault Mapping'!$B$2:$B$10174,4)="sts_")+(LEFT('ZONE C Vault Mapping'!$B$2:$B$10174,5)="link_")+(LEFT('ZONE C Vault Mapping'!$B$2:$B$10174,4)="sat_")+(LEFT('ZONE C Vault Mapping'!$B$2:$B$10174,7)="effsat_")+(LEFT('ZONE C Vault Mapping'!$B$2:$B$10174,4)="ref_")+(LEFT('ZONE C Vault Mapping'!$B$2:$B$10174,12)="non_his_sat_"))*('ZONE C Vault Mapping'!$H$2:$H$10174<>"Cancel")*(IFERROR(_xlfn.XLOOKUP('ZONE C Vault Mapping'!$B$2:$B$10174,'Tracking Mapping&Dev Zone C'!$B:$B,'Tracking Mapping&Dev Zone C'!$F:$F),"")="Done"))/COUNTIFS('ZONE C Vault Mapping'!$B$2:$B$10174,'ZONE C Vault Mapping'!$B$2:$B$10174&"")),0)} -> 0 | O12: =IFERROR(N12/L12,"") -> 0
A13: SBV | B13: {=IFERROR(INDEX(_xlfn._xlws.FILTER('Tracking Mapping&Dev Zone C'!$C:$C,('Tracking Mapping&Dev Zone C'!$A:$A=$A13)*('Tracking Mapping&Dev Zone C'!$C:$C<>"")),1),"")} -> TrangNT | C13: {=IFERROR(_xlfn.TEXTJOIN(", ",TRUE,_xlfn.UNIQUE(_xlfn._xlws.FILTER('Tracking Mapping&Dev Zone C'!$E:$E,('Tracking Mapping&Dev Zone C'!$A:$A=$A13)*('Tracking Mapping&Dev Zone C'!$E:$E<>"")))),"")} -> Thụ | D13: =COUNTIF('Source Tables Zone C'!$A$2:$A$200,$A13) -> 1 | E13: =COUNTIFS('Source Tables Zone C'!$A$2:$A$200,$A13,'Source Tables Zone C'!$C$2:$C$200,"Done") -> 1 | F13: =IFERROR(E13/D13,"") -> 1 | G13: {=ROUND(SUMPRODUCT((('ZONE C Vault Mapping'!$A$2:$A$10174=$A13)*((LEFT('ZONE C Vault Mapping'!$B$2:$B$10174,4)="hub_")+(LEFT('ZONE C Vault Mapping'!$B$2:$B$10174,4)="sts_"))*('ZONE C Vault Mapping'!$H$2:$H$10174<>"Cancel"))/COUNTIFS('ZONE C Vault Mapping'!$B$2:$B$10174,'ZONE C Vault Mapping'!$B$2:$B$10174&"")),0)} -> 1 | H13: {=ROUND(SUMPRODUCT(('ZONE C Vault Mapping'!$A$2:$A$10174=$A13)*(LEFT('ZONE C Vault Mapping'!$B$2:$B$10174,5)="link_")*('ZONE C Vault Mapping'!$H$2:$H$10174<>"Cancel")/COUNTIFS('ZONE C Vault Mapping'!$B$2:$B$10174,'ZONE C Vault Mapping'!$B$2:$B$10174&"")),0)} -> 2 | I13: {=ROUND(SUMPRODUCT((('ZONE C Vault Mapping'!$A$2:$A$10174=$A13)*((LEFT('ZONE C Vault Mapping'!$B$2:$B$10174,4)="sat_")+(LEFT('ZONE C Vault Mapping'!$B$2:$B$10174,7)="effsat_")+(LEFT('ZONE C Vault Mapping'!$B$2:$B$10174,12)="non_his_sat_"))*('ZONE C Vault Mapping'!$H$2:$H$10174<>"Cancel"))/COUNTIFS('ZONE C Vault Mapping'!$B$2:$B$10174,'ZONE C Vault Mapping'!$B$2:$B$10174&"")),0)} -> 1 | J13: {=ROUND(SUMPRODUCT((('ZONE C Vault Mapping'!$A$2:$A$10174=$A13)*(LEFT('ZONE C Vault Mapping'!$B$2:$B$10174,4)="ref_")*(IFERROR(_xlfn.XLOOKUP('ZONE C Vault Mapping'!$B$2:$B$10174,'Tracking Mapping&Dev Zone C'!$B:$B,'Tracking Mapping&Dev Zone C'!$D:$D),"")<>"Cancel"))/COUNTIFS('ZONE C Vault Mapping'!$B$2:$B$10174,'ZONE C Vault Mapping'!$B$2:$B$10174&"")),0)} -> 0 | K13: =SUM(G13:J13) -> 4 | L13: {=ROUND(SUMPRODUCT((('ZONE C Vault Mapping'!$A$2:$A$10174=$A13)*((LEFT('ZONE C Vault Mapping'!$B$2:$B$10174,4)="hub_")+(LEFT('ZONE C Vault Mapping'!$B$2:$B$10174,4)="sts_")+(LEFT('ZONE C Vault Mapping'!$B$2:$B$10174,5)="link_")+(LEFT('ZONE C Vault Mapping'!$B$2:$B$10174,4)="sat_")+(LEFT('ZONE C Vault Mapping'!$B$2:$B$10174,7)="effsat_")+(LEFT('ZONE C Vault Mapping'!$B$2:$B$10174,4)="ref_")+(LEFT('ZONE C Vault Mapping'!$B$2:$B$10174,12)="non_his_sat_"))*('ZONE C Vault Mapping'!$H$2:$H$10174="Done"))/COUNTIFS('ZONE C Vault Mapping'!$B$2:$B$10174,'ZONE C Vault Mapping'!$B$2:$B$10174&"")),0)} -> 4 | M13: =IFERROR(L13/K13,"") -> 1 | N13: {=ROUND(SUMPRODUCT((('ZONE C Vault Mapping'!$A$2:$A$10174=$A13)*((LEFT('ZONE C Vault Mapping'!$B$2:$B$10174,4)="hub_")+(LEFT('ZONE C Vault Mapping'!$B$2:$B$10174,4)="sts_")+(LEFT('ZONE C Vault Mapping'!$B$2:$B$10174,5)="link_")+(LEFT('ZONE C Vault Mapping'!$B$2:$B$10174,4)="sat_")+(LEFT('ZONE C Vault Mapping'!$B$2:$B$10174,7)="effsat_")+(LEFT('ZONE C Vault Mapping'!$B$2:$B$10174,4)="ref_")+(LEFT('ZONE C Vault Mapping'!$B$2:$B$10174,12)="non_his_sat_"))*('ZONE C Vault Mapping'!$H$2:$H$10174<>"Cancel")*(IFERROR(_xlfn.XLOOKUP('ZONE C Vault Mapping'!$B$2:$B$10174,'Tracking Mapping&Dev Zone C'!$B:$B,'Tracking Mapping&Dev Zone C'!$F:$F),"")="Done"))/COUNTIFS('ZONE C Vault Mapping'!$B$2:$B$10174,'ZONE C Vault Mapping'!$B$2:$B$10174&"")),0)} -> 0 | O13: =IFERROR(N13/L13,"") -> 0
A14: TOTAL | B14: {=IFERROR(INDEX(_xlfn._xlws.FILTER('Tracking Mapping&Dev Zone C'!$C:$C,('Tracking Mapping&Dev Zone C'!$A:$A=$A14)*('Tracking Mapping&Dev Zone C'!$C:$C<>"")),1),"")} | C14: {=IFERROR(_xlfn.TEXTJOIN(", ",TRUE,_xlfn.UNIQUE(_xlfn._xlws.FILTER('Tracking Mapping&Dev Zone C'!$E:$E,('Tracking Mapping&Dev Zone C'!$A:$A=$A14)*('Tracking Mapping&Dev Zone C'!$E:$E<>"")))),"")} | D14: =SUM(D3:D13) -> 73 | E14: =SUM(E3:E13) -> 71 | F14: =E14/D14 -> 0.97260274 | G14: =SUM(G3:G13) -> 34 | H14: =SUM(H3:H13) -> 64 | I14: =SUM(I3:I13) -> 98 | J14: =SUM(J3:J13) -> 10 | K14: =SUM(K3:K13) -> 206 | L14: =SUM(L3:L13) -> 206 | M14: =L14/K14 -> 1 | N14: =SUM(N3:N13) -> 87 | O14: =N14/K14 -> 0.4223301
A20: Bổ sung Zone C - Tracking by Source Table
A21: Source System | B21: Source Tables | C21: Mapping PIC | D21: Dev PIC | E21: Total Source Tables | F21: Source Mapping Completed | G21: % Mapping | H21: Total Vault Tables | I21: Dev Completed | J21: % Dev (vs Mapping) | K21: Note
A22: T24 | B22: t24_aa_arrangement, t24_aa_arr_account | C22: LinhNT | D22: Huy | E22: 2 | F22: 2 | G22: =IFERROR(F22/E22,"") -> 1 | H22: {=COUNTA(_xlfn.UNIQUE(_xlfn._xlws.FILTER('Các bảng bổ sung sang Zone C'!$C$2:$C$100000,('Các bảng bổ sung sang Zone C'!$A$2:$A$100000=$A22)*('Các bảng bổ sung sang Zone C'!$K$2:$K$100000<>"Cancel")*('Các bảng bổ sung sang Zone C'!$C$2:$C$100000<>""))))} -> 10 | I22: {=SUMPRODUCT((_xlfn.XLOOKUP(_xlfn.UNIQUE(_xlfn._xlws.FILTER('Các bảng bổ sung sang Zone C'!$C$2:$C$100000,('Các bảng bổ sung sang Zone C'!$A$2:$A$100000=$A22)*('Các bảng bổ sung sang Zone C'!$C$2:$C$100000<>""))),'Tracking Mapping&Dev Zone C'!$B:$B,'Tracking Mapping&Dev Zone C'!$F:$F,"")="Done")*1)} -> 10 | J22: {=IFERROR(I22/SUMPRODUCT((_xlfn.XLOOKUP(_xlfn.UNIQUE(_xlfn._xlws.FILTER('Các bảng bổ sung sang Zone C'!$C$2:$C$100000,('Các bảng bổ sung sang Zone C'!$A$2:$A$100000=$A22)*('Các bảng bổ sung sang Zone C'!$C$2:$C$100000<>""))),'Tracking Mapping&Dev Zone C'!$B:$B,'Tracking Mapping&Dev Zone C'!$D:$D,"")="Done")*1),"")} -> 1
A23: WAY4 | B23: branch, country, currency | C23: TrangNT | D23: Huy | E23: 3 | F23: 3 | G23: =IFERROR(F23/E23,"") -> 1 | H23: {=COUNTA(_xlfn.UNIQUE(_xlfn._xlws.FILTER('Các bảng bổ sung sang Zone C'!$C$2:$C$100000,('Các bảng bổ sung sang Zone C'!$A$2:$A$100000=$A23)*('Các bảng bổ sung sang Zone C'!$K$2:$K$100000<>"Cancel")*('Các bảng bổ sung sang Zone C'!$C$2:$C$100000<>""))))} -> 3 | I23: {=SUMPRODUCT((_xlfn.XLOOKUP(_xlfn.UNIQUE(_xlfn._xlws.FILTER('Các bảng bổ sung sang Zone C'!$C$2:$C$100000,('Các bảng bổ sung sang Zone C'!$A$2:$A$100000=$A23)*('Các bảng bổ sung sang Zone C'!$C$2:$C$100000<>""))),'Tracking Mapping&Dev Zone C'!$B:$B,'Tracking Mapping&Dev Zone C'!$F:$F,"")="Done")*1)} -> 3 | J23: {=IFERROR(I23/SUMPRODUCT((_xlfn.XLOOKUP(_xlfn.UNIQUE(_xlfn._xlws.FILTER('Các bảng bổ sung sang Zone C'!$C$2:$C$100000,('Các bảng bổ sung sang Zone C'!$A$2:$A$100000=$A23)*('Các bảng bổ sung sang Zone C'!$C$2:$C$100000<>""))),'Tracking Mapping&Dev Zone C'!$B:$B,'Tracking Mapping&Dev Zone C'!$D:$D,"")="Done")*1),"")} -> 1
A24: CRM | B24: crm_user_structure | C24: TrangNT | D24: Thụ | E24: 1 | F24: 1 | G24: =IFERROR(F24/E24,"") -> 1 | H24: {=COUNTA(_xlfn.UNIQUE(_xlfn._xlws.FILTER('Các bảng bổ sung sang Zone C'!$C$2:$C$100000,('Các bảng bổ sung sang Zone C'!$A$2:$A$100000=$A24)*('Các bảng bổ sung sang Zone C'!$K$2:$K$100000<>"Cancel")*('Các bảng bổ sung sang Zone C'!$C$2:$C$100000<>""))))} -> 3 | I24: {=SUMPRODUCT((_xlfn.XLOOKUP(_xlfn.UNIQUE(_xlfn._xlws.FILTER('Các bảng bổ sung sang Zone C'!$C$2:$C$100000,('Các bảng bổ sung sang Zone C'!$A$2:$A$100000=$A24)*('Các bảng bổ sung sang Zone C'!$C$2:$C$100000<>""))),'Tracking Mapping&Dev Zone C'!$B:$B,'Tracking Mapping&Dev Zone C'!$F:$F,"")="Done")*1)} -> 3 | J24: {=IFERROR(I24/SUMPRODUCT((_xlfn.XLOOKUP(_xlfn.UNIQUE(_xlfn._xlws.FILTER('Các bảng bổ sung sang Zone C'!$C$2:$C$100000,('Các bảng bổ sung sang Zone C'!$A$2:$A$100000=$A24)*('Các bảng bổ sung sang Zone C'!$C$2:$C$100000<>""))),'Tracking Mapping&Dev Zone C'!$B:$B,'Tracking Mapping&Dev Zone C'!$D:$D,"")="Done")*1),"")} -> 1
A25: CleverTap | B25: profiles | C25: TrangPM | D25: Thụ | E25: 1 | F25: 1 | G25: =IFERROR(F25/E25,"") -> 1 | H25: {=COUNTA(_xlfn.UNIQUE(_xlfn._xlws.FILTER('Các bảng bổ sung sang Zone C'!$C$2:$C$100000,('Các bảng bổ sung sang Zone C'!$A$2:$A$100000=$A25)*('Các bảng bổ sung sang Zone C'!$K$2:$K$100000<>"Cancel")*('Các bảng bổ sung sang Zone C'!$C$2:$C$100000<>""))))} -> 4 | I25: {=SUMPRODUCT((_xlfn.XLOOKUP(_xlfn.UNIQUE(_xlfn._xlws.FILTER('Các bảng bổ sung sang Zone C'!$C$2:$C$100000,('Các bảng bổ sung sang Zone C'!$A$2:$A$100000=$A25)*('Các bảng bổ sung sang Zone C'!$C$2:$C$100000<>""))),'Tracking Mapping&Dev Zone C'!$B:$B,'Tracking Mapping&Dev Zone C'!$F:$F,"")="Done")*1)} -> 4 | J25: {=IFERROR(I25/SUMPRODUCT((_xlfn.XLOOKUP(_xlfn.UNIQUE(_xlfn._xlws.FILTER('Các bảng bổ sung sang Zone C'!$C$2:$C$100000,('Các bảng bổ sung sang Zone C'!$A$2:$A$100000=$A25)*('Các bảng bổ sung sang Zone C'!$C$2:$C$100000<>""))),'Tracking Mapping&Dev Zone C'!$B:$B,'Tracking Mapping&Dev Zone C'!$D:$D,"")="Done")*1),"")} -> 1
A26: TOTAL | E26: =SUM(E22:E25) -> 7 | F26: =SUM(F22:F25) -> 7 | G26: =F26/E26 -> 1 | H26: =SUM(H22:H25) -> 20 | I26: =SUM(I22:I25) -> 20 | J26: =I26/H26 -> 1

Sheet Source Tables Zone C
A1: SOURCE | B1: TABNAME | C1: MAPPING_STATUS | D1: MAPPING_CHECKING | E1: SAMPLE_DATA_DBX (DEV) | F1: SAMPLE_DATA_DBX (PILOT) | G1: DESCRIPTION | H1: NOTE
A2: BPM | B2: KT_HACH_TOAN | C2: Done | D2: Done | E2: Y | F2: Y
A3: BPM | B3: XL_CT_TSBD | C3: Done | D3: Done | E3: Y | F3: Y
A4: BPM | B4: BC_AUTH_TO_CHUC_DON_VI_KHU_VUC | C4: Done | D4: Done | E4: Y | F4: Y | H4: id 2891 bị dup => dedup
A5: BPM | B5: Y_KIEN_YCBS | C5: Done | D5: Done | E5: Y | F5: Y
A6: BPM | B6: DANH_MUC_CHI_TIET | C6: Done | D6: Done | E6: Y | F6: Y
A7: BPM | B7: GIAO_DICH_CHI_TIET | C7: Done | D7: Done | E7: Y | F7: Y
A8: BPM | B8: GIAO_DICH_THOI_GIAN_XU_LY_BY_NHOM | C8: Done | D8: Done | E8: Y | F8: Y
A9: BPM | B9: AUTH_TO_CHUC_DVI_LINK | C9: Done | D9: Done | E9: Y | F9: Y
A10: BPM | B10: MD_3544_SAN_PHAM_T24 | C10: Done | D10: Done | E10: Y | F10: Y | H10: id 10638 bị dup => dedup
A11: BPM | B11: TSBD_BAO_CAO_THOIGIAN_XULY | C11: Done | D11: Done | F11: Y
A12: BPM | B12: TDCN_ST_VAN_KIEN | C12: Done | D12: Done | E12: Y | F12: Y
A13: BPM | B13: TSBD_BC_THOI_GIAN_XU_LY_BY_NHOM | C13: Done | D13: Done | E13: Y | F13: Y
A14: BPM | B14: EXTERNAL_TRANSACTION | C14: Done | D14: Done | E14: Y | F14: Y
A15: BPM | B15: PDTD_COMMENT | C15: Done | D15: Done | E15: Y | F15: Y
A16: BPM | B16: TSBD_BAO_CAO_THONGTIN | C16: Done | D16: Done | E16: Y | F16: Y
A17: BPM | B17: MUC_CAP_TIN_DUNG | C17: Done | D17: Done | E17: Y | F17: Y
A18: BPM | B18: XL_HSTD_HT_CAP | C18: Done | D18: Done | E18: Y | F18: Y
A19: BPM | B19: XL_BAO_CAO_TONG_HOP | C19: Done | D19: Done | E19: Y | F19: Y
A20: BPM | B20: XL_BC_THOI_GIAN_XU_LY_BY_NHOM | C20: Done | D20: Done | E20: Y | F20: Y
A21: BPM | B21: PDTD_BC_THOI_GIAN_XU_LY_BY_NHOM | C21: Done | D21: Done | E21: Y | F21: Y
A22: COMB | B22: APP_PRODUCT | C22: Done | D22: Done | E22: Y | F22: Y | H22: 20260721
A23: COMB | B23: CONSUMER_LOAN | C23: Done | D23: Done | E23: Y | F23: Y
A24: COMB | B24: CONSUMER_LOAN_WO | C24: Done | D24: Done | E24: Y | G24: không có bảng trên pilot
A25: COMB | B25: FACT_COLLECTION_COMB | C25: Done | D25: Done | E25: Y | F25: Y
A26: COMB | B26: NEXT_PAYMENT_AMOUNT | C26: Done | D26: Done | E26: Y | F26: Y
A27: ESB | B27: BATCH_TRANS_DETAILS | C27: Done | D27: Done | E27: Y | F27: Y
A28: ESB | B28: MERCHANT_VIETQR | C28: Done | D28: Done | E28: Y | F28: Y
A29: ESB | B29: OMNI_TRANSACTION_HIST | C29: Done | D29: Done | E29: Y | F29: Y
A30: ESB | B30: TRANSACTIONS | C30: Done | D30: Done | E30: Y | F30: Y
A31: GAMS | B31: ASS_ENTRIES_POST_SYNC | C31: Done | D31: Done | E31: Y | F31: Y
A32: NEWFO | B32: PASSBOOK | C32: Done | D32: Done | E32: Y | F32: Y | H32: 20260716
A33: NEWFO | B33: USERS_LOGON | C33: Done | D33: Done | E33: Y | F33: Y
A34: OCBCHANNEL | B34: BRANCH_MAPPING | C34: Done | D34: Done | E34: Y | F34: Y
A35: OCBCHANNEL | B35: ADMIN_COMMAND_QUEUE | C35: Done | D35: Done | E35: Y | F35: Y
A36: OCBCHANNEL | B36: APPORTION_TRANS_BATCH_DETAILS | C36: Done | D36: Done | E36: Y | F36: Y
A37: OCBCHANNEL | B37: AUTHEN_TYPE | C37: Done | D37: Done | E37: Y | F37: Y
A38: OCBCHANNEL | B38: CUSTOMER_FILE | C38: Done | D38: Done | E38: Y | F38: Y
A39: OCBCHANNEL | B39: EB_PACKAGE_TYPE | C39: Done | D39: Done | E39: Y | F39: Y
A40: OCBCHANNEL | B40: EB_USER_SESSION | C40: Done | D40: Done | E40: Y | F40: Y
A41: OCBCHANNEL | B41: EB_USERS | C41: Done | D41: Done | E41: Y | F41: Y
A42: OCBCHANNEL | B42: OCB_BILL_PROVIDERS | C42: Done | D42: Done | E42: Y | F42: Y
A43: OCBCHANNEL | B43: OCB_BILL_SERVICE_PROVIDER | C43: Done | D43: Done | E43: Y | F43: Y
A44: OCBCHANNEL | B44: OCB_BILL_SERVICES | C44: Done | D44: Done | E44: Y | F44: Y
... A62: QLDT | B62: LDM_PARTNER_TYPE | C62: Done | D62: Done | E62: Y | F62: Y
A63: T24 | B63: T24_APPORTION_ACCT_CATEG | C63: Done | D63: Done | E63: Y | F63: Y | H63: đã có ở T24 Vault Mapping
A64: T24 | B64: T24_OCBH_CAT_PROD | C64: Done | D64: Done | E64: Y | G64: không có bảng trên pilot
A65: T24 | B65: T24_OCBH_CO_GROUP | C65: Done | D65: Done | E65: Y | G65: không có bảng trên pilot
A66: T24 | B66: T24_LD_ECONOMIC_SECTOR | C66: Done | D66: Done | E66: Y | F66: Y | H66: đã có ở T24 Vault Mapping
A67: T24 | B67: T24_FUNDS_TRANSFER | C67: Done | D67: Done | E67: Y | F67: Y | H67: đã có ở T24 Vault Mapping là bảng tách giá trị từ bảng t24_funds_transfer_b1
A68: T24 | B68: T24_JOB_TITLE | C68: Done | D68: Done | E68: Y | F68: Y | H68: đã có ở T24 Vault Mapping
A69: T24 | B69: T24_PAYMENT_DUE | C69: Done | D69: Done | E69: Y | F69: Y | H69: đã có ở T24 Vault Mapping bảng này tách subvalue ra bảng t24_payment_due_sv
A70: T24 | B70: T24_COMP_LEVEL_GROUP | C70: Done | D70: Done | E70: Y | F70: Y | H70: đã có ở T24 Vault Mapping
A71: TREASURY | B71: SC_INTEREST_RATE_HIS | C71: Done | D71: Done | E71: Y | F71: Y
A72: OCBCHANNEL | B72: FO_TRANS_NO | H72: bảng thuộc 2 bảng mới bổ sung
A73: BPM | B73: XL_CT_SAN_PHAM | H73: bảng thuộc 2 bảng mới bổ sung
A74: SBV | B74: ACCOUNTBC_SAVE | C74: Done | D74: Done | F74: Y | H74: bảng nguồn này ban đầu vào luồng checklist thủ công => bổ sung mapping lên silver

Sheet Tracking Mapping&Dev Zone C
A1: Source System | B1: Table Name | C1: Mapping PIC | D1: Mapping Status | E1: Dev PIC | F1: Dev Status | G1: Change Request | H1: Note
A2: =IF($B2="","",IFERROR(_xlfn.XLOOKUP($B2,'ZONE C Vault Mapping'!$B:$B,'ZONE C Vault Mapping'!$A:$A),IFERROR(_xlfn.XLOOKUP($B2,'Các bảng bổ sung sang Zone C'!$C:$C,'Các bảng bổ sung sang Zone C'!$A:$A),""))) -> COMB | B2: {=_xlfn.UNIQUE(_xlfn.VSTACK(_xlfn._xlws.FILTER('ZONE C Vault Mapping'!B2:B1048576,'ZONE C Vault Mapping'!B2:B1048576<>""),_xlfn._xlws.FILTER('Các bảng bổ sung sang Zone C'!C2:C1048576,'Các bảng bổ sung sang Zone C'!C2:C1048576<>"")))} -> hub_app_product | C2: TrangNT | D2: =IF($B2="","",IFERROR(T(_xlfn.XLOOKUP($B2,'ZONE C Vault Mapping'!$B:$B,'ZONE C Vault Mapping'!$H:$H)),IFERROR(T(_xlfn.XLOOKUP($B2,'Các bảng bổ sung sang Zone C'!$C:$C,'Các bảng bổ sung sang Zone C'!$K:$K)),""))) -> Cancel | E2: Huy | F2: Checking | G2: 20260807: cancel
A3: =IF($B3="","",IFERROR(_xlfn.XLOOKUP($B3,'ZONE C Vault Mapping'!$B:$B,'ZONE C Vault Mapping'!$A:$A),IFERROR(_xlfn.XLOOKUP($B3,'Các bảng bổ sung sang Zone C'!$C:$C,'Các bảng bổ sung sang Zone C'!$A:$A),""))) -> COMB | B3: sts_hub_app_product | C3: TrangNT | D3: =IF($B3="","",IFERROR(T(_xlfn.XLOOKUP($B3,'ZONE C Vault Mapping'!$B:$B,'ZONE C Vault Mapping'!$H:$H)),IFERROR(T(_xlfn.XLOOKUP($B3,'Các bảng bổ sung sang Zone C'!$C:$C,'Các bảng bổ sung sang Zone C'!$K:$K)),""))) -> Cancel | E3: Huy | F3: Checking | G3: 20260807: cancel
A4: =IF($B4="","",IFERROR(_xlfn.XLOOKUP($B4,'ZONE C Vault Mapping'!$B:$B,'ZONE C Vault Mapping'!$A:$A),IFERROR(_xlfn.XLOOKUP($B4,'Các bảng bổ sung sang Zone C'!$C:$C,'Các bảng bổ sung sang Zone C'!$A:$A),""))) -> COMB | B4: sat_app_product | C4: TrangNT | D4: =IF($B4="","",IFERROR(T(_xlfn.XLOOKUP($B4,'ZONE C Vault Mapping'!$B:$B,'ZONE C Vault Mapping'!$H:$H)),IFERROR(T(_xlfn.XLOOKUP($B4,'Các bảng bổ sung sang Zone C'!$C:$C,'Các bảng bổ sung sang Zone C'!$K:$K)),""))) -> Cancel | E4: Huy | F4: Checking | G4: 20260807: cancel
A5: =IF($B5="","",IFERROR(_xlfn.XLOOKUP($B5,'ZONE C Vault Mapping'!$B:$B,'ZONE C Vault Mapping'!$A:$A),IFERROR(_xlfn.XLOOKUP($B5,'Các bảng bổ sung sang Zone C'!$C:$C,'Các bảng bổ sung sang Zone C'!$A:$A),""))) -> COMB | B5: ref_comb_app_product | C5: TrangNT | D5: =IF($B5="","",IFERROR(T(_xlfn.XLOOKUP($B5,'ZONE C Vault Mapping'!$B:$B,'ZONE C Vault Mapping'!$H:$H)),IFERROR(T(_xlfn.XLOOKUP($B5,'Các bảng bổ sung sang Zone C'!$C:$C,'Các bảng bổ sung sang Zone C'!$K:$K)),""))) -> Done | E5: Huy | F5: Checking | G5: 20260807: chuyển app_product thành bảng ref
A6: =IF($B6="","",IFERROR(_xlfn.XLOOKUP($B6,'ZONE C Vault Mapping'!$B:$B,'ZONE C Vault Mapping'!$A:$A),IFERROR(_xlfn.XLOOKUP($B6,'Các bảng bổ sung sang Zone C'!$C:$C,'Các bảng bổ sung sang Zone C'!$A:$A),""))) -> COMB | B6: sat_app_product_dynamic | C6: TrangNT | D6: =IF($B6="","",IFERROR(T(_xlfn.XLOOKUP($B6,'ZONE C Vault Mapping'!$B:$B,'ZONE C Vault Mapping'!$H:$H)),IFERROR(T(_xlfn.XLOOKUP($B6,'Các bảng bổ sung sang Zone C'!$C:$C,'Các bảng bổ sung sang Zone C'!$K:$K)),""))) -> Cancel | E6: Huy | F6: Checking | G6: 20260807: cancel
A7: =IF($B7="","",IFERROR(_xlfn.XLOOKUP($B7,'ZONE C Vault Mapping'!$B:$B,'ZONE C Vault Mapping'!$A:$A),IFERROR(_xlfn.XLOOKUP($B7,'Các bảng bổ sung sang Zone C'!$C:$C,'Các bảng bổ sung sang Zone C'!$A:$A),""))) -> COMB | B7: hub_consumer_loan | C7: TrangNT | D7: =IF($B7="","",IFERROR(T(_xlfn.XLOOKUP($B7,'ZONE C Vault Mapping'!$B:$B,'ZONE C Vault Mapping'!$H:$H)),IFERROR(T(_xlfn.XLOOKUP($B7,'Các bảng bổ sung sang Zone C'!$C:$C,'Các bảng bổ sung sang Zone C'!$K:$K)),""))) -> Done | E7: Huy | F7: Done
A8: =IF($B8="","",IFERROR(_xlfn.XLOOKUP($B8,'ZONE C Vault Mapping'!$B:$B,'ZONE C Vault Mapping'!$A:$A),IFERROR(_xlfn.XLOOKUP($B8,'Các bảng bổ sung sang Zone C'!$C:$C,'Các bảng bổ sung sang Zone C'!$A:$A),""))) -> COMB | B8: sts_hub_consumer_loan | C8: TrangNT | D8: =IF($B8="","",IFERROR(T(_xlfn.XLOOKUP($B8,'ZONE C Vault Mapping'!$B:$B,'ZONE C Vault Mapping'!$H:$H)),IFERROR(T(_xlfn.XLOOKUP($B8,'Các bảng bổ sung sang Zone C'!$C:$C,'Các bảng bổ sung sang Zone C'!$K:$K)),""))) -> Done | E8: Huy | F8: Done | G8: 20260721: sửa mapping
A9: =IF($B9="","",IFERROR(_xlfn.XLOOKUP($B9,'ZONE C Vault Mapping'!$B:$B,'ZONE C Vault Mapping'!$A:$A),IFERROR(_xlfn.XLOOKUP($B9,'Các bảng bổ sung sang Zone C'!$C:$C,'Các bảng bổ sung sang Zone C'!$A:$A),""))) -> COMB | B9: sts_hub_consumer_loan_wo | C9: TrangNT | D9: =IF($B9="","",IFERROR(T(_xlfn.XLOOKUP($B9,'ZONE C Vault Mapping'!$B:$B,'ZONE C Vault Mapping'!$H:$H)),IFERROR(T(_xlfn.XLOOKUP($B9,'Các bảng bổ sung sang Zone C'!$C:$C,'Các bảng bổ sung sang Zone C'!$K:$K)),""))) -> Done | E9: Huy | F9: Done
A10: =IF($B10="","",IFERROR(_xlfn.XLOOKUP($B10,'ZONE C Vault Mapping'!$B:$B,'ZONE C Vault Mapping'!$A:$A),IFERROR(_xlfn.XLOOKUP($B10,'Các bảng bổ sung sang Zone C'!$C:$C,'Các bảng bổ sung sang Zone C'!$A:$A),""))) -> COMB | B10: sts_hub_consumer_loan_fact_collection | C10: TrangNT | D10: =IF($B10="","",IFERROR(T(_xlfn.XLOOKUP($B10,'ZONE C Vault Mapping'!$B:$B,'ZONE C Vault Mapping'!$H:$H)),IFERROR(T(_xlfn.XLOOKUP($B10,'Các bảng bổ sung sang Zone C'!$C:$C,'Các bảng bổ sung sang Zone C'!$K:$K)),""))) -> Done | E10: Huy | F10: Done
A11: =IF($B11="","",IFERROR(_xlfn.XLOOKUP($B11,'ZONE C Vault Mapping'!$B:$B,'ZONE C Vault Mapping'!$A:$A),IFERROR(_xlfn.XLOOKUP($B11,'Các bảng bổ sung sang Zone C'!$C:$C,'Các bảng bổ sung sang Zone C'!$A:$A),""))) -> COMB | B11: sts_hub_consumer_loan_next_payment_amount | C11: TrangNT | D11: =IF($B11="","",IFERROR(T(_xlfn.XLOOKUP($B11,'ZONE C Vault Mapping'!$B:$B,'ZONE C Vault Mapping'!$H:$H)),IFERROR(T(_xlfn.XLOOKUP($B11,'Các bảng bổ sung sang Zone C'!$C:$C,'Các bảng bổ sung sang Zone C'!$K:$K)),""))) -> Done | E11: Huy | F11: Done
A12: =IF($B12="","",IFERROR(_xlfn.XLOOKUP($B12,'ZONE C Vault Mapping'!$B:$B,'ZONE C Vault Mapping'!$A:$A),IFERROR(_xlfn.XLOOKUP($B12,'Các bảng bổ sung sang Zone C'!$C:$C,'Các bảng bổ sung sang Zone C'!$A:$A),""))) -> COMB | B12: link_consumer_loan_customer | C12: TrangNT | D12: =IF($B12="","",IFERROR(T(_xlfn.XLOOKUP($B12,'ZONE C Vault Mapping'!$B:$B,'ZONE C Vault Mapping'!$H:$H)),IFERROR(T(_xlfn.XLOOKUP($B12,'Các bảng bổ sung sang Zone C'!$C:$C,'Các bảng bổ sung sang Zone C'!$K:$K)),""))) -> Done | E12: Huy | F12: Done
A13: =IF($B13="","",IFERROR(_xlfn.XLOOKUP($B13,'ZONE C Vault Mapping'!$B:$B,'ZONE C Vault Mapping'!$A:$A),IFERROR(_xlfn.XLOOKUP($B13,'Các bảng bổ sung sang Zone C'!$C:$C,'Các bảng bổ sung sang Zone C'!$A:$A),""))) -> COMB | B13: link_consumer_loan_branch | C13: TrangNT | D13: =IF($B13="","",IFERROR(T(_xlfn.XLOOKUP($B13,'ZONE C Vault Mapping'!$B:$B,'ZONE C Vault Mapping'!$H:$H)),IFERROR(T(_xlfn.XLOOKUP($B13,'Các bảng bổ sung sang Zone C'!$C:$C,'Các bảng bổ sung sang Zone C'!$K:$K)),""))) -> Done | E13: Huy | F13: Done
A14: =IF($B14="","",IFERROR(_xlfn.XLOOKUP($B14,'ZONE C Vault Mapping'!$B:$B,'ZONE C Vault Mapping'!$A:$A),IFERROR(_xlfn.XLOOKUP($B14,'Các bảng bổ sung sang Zone C'!$C:$C,'Các bảng bổ sung sang Zone C'!$A:$A),""))) -> COMB | B14: sat_consumer_loan_information | C14: TrangNT | D14: =IF($B14="","",IFERROR(T(_xlfn.XLOOKUP($B14,'ZONE C Vault Mapping'!$B:$B,'ZONE C Vault Mapping'!$H:$H)),IFERROR(T(_xlfn.XLOOKUP($B14,'Các bảng bổ sung sang Zone C'!$C:$C,'Các bảng bổ sung sang Zone C'!$K:$K)),""))) -> Done | E14: Huy | F14: Checking | G14: 20260807: thêm mới, bỏ bảng sat_consumer_loan cũ, chia ra làm 3 bảng
A15: =IF($B15="","",IFERROR(_xlfn.XLOOKUP($B15,'ZONE C Vault Mapping'!$B:$B,'ZONE C Vault Mapping'!$A:$A),IFERROR(_xlfn.XLOOKUP($B15,'Các bảng bổ sung sang Zone C'!$C:$C,'Các bảng bổ sung sang Zone C'!$A:$A),""))) -> COMB | B15: sat_consumer_loan_classification | C15: TrangNT | D15: =IF($B15="","",IFERROR(T(_xlfn.XLOOKUP($B15,'ZONE C Vault Mapping'!$B:$B,'ZONE C Vault Mapping'!$H:$H)),IFERROR(T(_xlfn.XLOOKUP($B15,'Các bảng bổ sung sang Zone C'!$C:$C,'Các bảng bổ sung sang Zone C'!$K:$K)),""))) -> Done | E15: Huy | F15: Checking | G15: 20260807: thêm mới, bỏ bảng sat_consumer_loan cũ, chia ra làm 3 bảng
A16: =IF($B16="","",IFERROR(_xlfn.XLOOKUP($B16,'ZONE C Vault Mapping'!$B:$B,'ZONE C Vault Mapping'!$A:$A),IFERROR(_xlfn.XLOOKUP($B16,'Các bảng bổ sung sang Zone C'!$C:$C,'Các bảng bổ sung sang Zone C'!$A:$A),""))) -> COMB | B16: sat_consumer_loan_balance | C16: TrangNT | D16: =IF($B16="","",IFERROR(T(_xlfn.XLOOKUP($B16,'ZONE C Vault Mapping'!$B:$B,'ZONE C Vault Mapping'!$H:$H)),IFERROR(T(_xlfn.XLOOKUP($B16,'Các bảng bổ sung sang Zone C'!$C:$C,'Các bảng bổ sung sang Zone C'!$K:$K)),""))) -> Done | E16: Huy | F16: Checking | G16: 20260807: thêm mới, bỏ bảng sat_consumer_loan cũ, chia ra làm 3 bảng
A17: =IF($B17="","",IFERROR(_xlfn.XLOOKUP($B17,'ZONE C Vault Mapping'!$B:$B,'ZONE C Vault Mapping'!$A:$A),IFERROR(_xlfn.XLOOKUP($B17,'Các bảng bổ sung sang Zone C'!$C:$C,'Các bảng bổ sung sang Zone C'!$A:$A),""))) -> COMB | B17: sat_consumer_loan_dynamic | C17: TrangNT | D17: =IF($B17="","",IFERROR(T(_xlfn.XLOOKUP($B17,'ZONE C Vault Mapping'!$B:$B,'ZONE C Vault Mapping'!$H:$H)),IFERROR(T(_xlfn.XLOOKUP($B17,'Các bảng bổ sung sang Zone C'!$C:$C,'Các bảng bổ sung sang Zone C'!$K:$K)),""))) -> Done | E17: Huy | F17: Done
A18: =IF($B18="","",IFERROR(_xlfn.XLOOKUP($B18,'ZONE C Vault Mapping'!$B:$B,'ZONE C Vault Mapping'!$A:$A),IFERROR(_xlfn.XLOOKUP($B18,'Các bảng bổ sung sang Zone C'!$C:$C,'Các bảng bổ sung sang Zone C'!$A:$A),""))) -> COMB | B18: sat_consumer_loan_wo_information | C18: TrangNT | D18: =IF($B18="","",IFERROR(T(_xlfn.XLOOKUP($B18,'ZONE C Vault Mapping'!$B:$B,'ZONE C Vault Mapping'!$H:$H)),IFERROR(T(_xlfn.XLOOKUP($B18,'Các bảng bổ sung sang Zone C'!$C:$C,'Các bảng bổ sung sang Zone C'!$K:$K)),""))) -> Done | E18: Huy | F18: Checking | G18: 20260807: thêm tiền tố _information vào tên, điều chỉnh số lượng cột
A19: =IF($B19="","",IFERROR(_xlfn.XLOOKUP($B19,'ZONE C Vault Mapping'!$B:$B,'ZONE C Vault Mapping'!$A:$A),IFERROR(_xlfn.XLOOKUP($B19,'Các bảng bổ sung sang Zone C'!$C:$C,'Các bảng bổ sung sang Zone C'!$A:$A),""))) -> COMB | B19: sat_consumer_loan_wo_classification | C19: TrangNT | D19: =IF($B19="","",IFERROR(T(_xlfn.XLOOKUP($B19,'ZONE C Vault Mapping'!$B:$B,'ZONE C Vault Mapping'!$H:$H)),IFERROR(T(_xlfn.XLOOKUP($B19,'Các bảng bổ sung sang Zone C'!$C:$C,'Các bảng bổ sung sang Zone C'!$K:$K)),""))) -> Done | E19: Huy | F19: Checking | G19: 20260810: thêm mới
A20: =IF($B20="","",IFERROR(_xlfn.XLOOKUP($B20,'ZONE C Vault Mapping'!$B:$B,'ZONE C Vault Mapping'!$A:$A),IFERROR(_xlfn.XLOOKUP($B20,'Các bảng bổ sung sang Zone C'!$C:$C,'Các bảng bổ sung sang Zone C'!$A:$A),""))) -> COMB | B20: sat_consumer_loan_wo_balance | C20: TrangNT | D20: =IF($B20="","",IFERROR(T(_xlfn.XLOOKUP($B20,'ZONE C Vault Mapping'!$B:$B,'ZONE C Vault Mapping'!$H:$H)),IFERROR(T(_xlfn.XLOOKUP($B20,'Các bảng bổ sung sang Zone C'!$C:$C,'Các bảng bổ sung sang Zone C'!$K:$K)),""))) -> Done | E20: Huy | F20: Checking | G20: 20260810: thêm mới
A21: =IF($B21="","",IFERROR(_xlfn.XLOOKUP($B21,'ZONE C Vault Mapping'!$B:$B,'ZONE C Vault Mapping'!$A:$A),IFERROR(_xlfn.XLOOKUP($B21,'Các bảng bổ sung sang Zone C'!$C:$C,'Các bảng bổ sung sang Zone C'!$A:$A),""))) -> COMB | B21: sat_consumer_loan_wo_dynamic | C21: TrangNT | D21: =IF($B21="","",IFERROR(T(_xlfn.XLOOKUP($B21,'ZONE C Vault Mapping'!$B:$B,'ZONE C Vault Mapping'!$H:$H)),IFERROR(T(_xlfn.XLOOKUP($B21,'Các bảng bổ sung sang Zone C'!$C:$C,'Các bảng bổ sung sang Zone C'!$K:$K)),""))) -> Done | E21: Huy | F21: Done
A22: =IF($B22="","",IFERROR(_xlfn.XLOOKUP($B22,'ZONE C Vault Mapping'!$B:$B,'ZONE C Vault Mapping'!$A:$A),IFERROR(_xlfn.XLOOKUP($B22,'Các bảng bổ sung sang Zone C'!$C:$C,'Các bảng bổ sung sang Zone C'!$A:$A),""))) -> COMB | B22: hub_fact_collection | C22: TrangNT | D22: =IF($B22="","",IFERROR(T(_xlfn.XLOOKUP($B22,'ZONE C Vault Mapping'!$B:$B,'ZONE C Vault Mapping'!$H:$H)),IFERROR(T(_xlfn.XLOOKUP($B22,'Các bảng bổ sung sang Zone C'!$C:$C,'Các bảng bổ sung sang Zone C'!$K:$K)),""))) -> Cancel | E22: Huy | F22: Cancel
A23: =IF($B23="","",IFERROR(_xlfn.XLOOKUP($B23,'ZONE C Vault Mapping'!$B:$B,'ZONE C Vault Mapping'!$A:$A),IFERROR(_xlfn.XLOOKUP($B23,'Các bảng bổ sung sang Zone C'!$C:$C,'Các bảng bổ sung sang Zone C'!$A:$A),""))) -> COMB | B23: link_fact_collection_branch | C23: TrangNT | D23: =IF($B23="","",IFERROR(T(_xlfn.XLOOKUP($B23,'ZONE C Vault Mapping'!$B:$B,'ZONE C Vault Mapping'!$H:$H)),IFERROR(T(_xlfn.XLOOKUP($B23,'Các bảng bổ sung sang Zone C'!$C:$C,'Các bảng bổ sung sang Zone C'!$K:$K)),""))) -> Cancel | E23: Huy | F23: Cancel
A24: =IF($B24="","",IFERROR(_xlfn.XLOOKUP($B24,'ZONE C Vault Mapping'!$B:$B,'ZONE C Vault Mapping'!$A:$A),IFERROR(_xlfn.XLOOKUP($B24,'Các bảng bổ sung sang Zone C'!$C:$C,'Các bảng bổ sung sang Zone C'!$A:$A),""))) -> COMB | B24: sat_fact_collection_information | C24: TrangNT | D24: =IF($B24="","",IFERROR(T(_xlfn.XLOOKUP($B24,'ZONE C Vault Mapping'!$B:$B,'ZONE C Vault Mapping'!$H:$H)),IFERROR(T(_xlfn.XLOOKUP($B24,'Các bảng bổ sung sang Zone C'!$C:$C,'Các bảng bổ sung sang Zone C'!$K:$K)),""))) -> Done | E24: Huy | F24: Checking | G24: 20260810: thêm tiền tố information vào tên 20260709: thêm 2 trường date_cob, created_date
A25: =IF($B25="","",IFERROR(_xlfn.XLOOKUP($B25,'ZONE C Vault Mapping'!$B:$B,'ZONE C Vault Mapping'!$A:$A),IFERROR(_xlfn.XLOOKUP($B25,'Các bảng bổ sung sang Zone C'!$C:$C,'Các bảng bổ sung sang Zone C'!$A:$A),""))) -> COMB | B25: sat_fact_collection_dynamic | C25: TrangNT | D25: =IF($B25="","",IFERROR(T(_xlfn.XLOOKUP($B25,'ZONE C Vault Mapping'!$B:$B,'ZONE C Vault Mapping'!$H:$H)),IFERROR(T(_xlfn.XLOOKUP($B25,'Các bảng bổ sung sang Zone C'!$C:$C,'Các bảng bổ sung sang Zone C'!$K:$K)),""))) -> Done | E25: Huy | F25: Done
A26: =IF($B26="","",IFERROR(_xlfn.XLOOKUP($B26,'ZONE C Vault Mapping'!$B:$B,'ZONE C Vault Mapping'!$A:$A),IFERROR(_xlfn.XLOOKUP($B26,'Các bảng bổ sung sang Zone C'!$C:$C,'Các bảng bổ sung sang Zone C'!$A:$A),""))) -> OCBCHANNEL | B26: hub_admin_command_queue | C26: TrangNT | D26: =IF($B26="","",IFERROR(T(_xlfn.XLOOKUP($B26,'ZONE C Vault Mapping'!$B:$B,'ZONE C Vault Mapping'!$H:$H)),IFERROR(T(_xlfn.XLOOKUP($B26,'Các bảng bổ sung sang Zone C'!$C:$C,'Các bảng bổ sung sang Zone C'!$K:$K)),""))) -> Done | E26: Thụ | F26: Done
A27: =IF($B27="","",IFERROR(_xlfn.XLOOKUP($B27,'ZONE C Vault Mapping'!$B:$B,'ZONE C Vault Mapping'!$A:$A),IFERROR(_xlfn.XLOOKUP($B27,'Các bảng bổ sung sang Zone C'!$C:$C,'Các bảng bổ sung sang Zone C'!$A:$A),""))) -> OCBCHANNEL | B27: link_admin_command_queue_branch | C27: TrangNT | D27: =IF($B27="","",IFERROR(T(_xlfn.XLOOKUP($B27,'ZONE C Vault Mapping'!$B:$B,'ZONE C Vault Mapping'!$H:$H)),IFERROR(T(_xlfn.XLOOKUP($B27,'Các bảng bổ sung sang Zone C'!$C:$C,'Các bảng bổ sung sang Zone C'!$K:$K)),""))) -> Done | E27: Thụ | F27: Done
A28: =IF($B28="","",IFERROR(_xlfn.XLOOKUP($B28,'ZONE C Vault Mapping'!$B:$B,'ZONE C Vault Mapping'!$A:$A),IFERROR(_xlfn.XLOOKUP($B28,'Các bảng bổ sung sang Zone C'!$C:$C,'Các bảng bổ sung sang Zone C'!$A:$A),""))) -> OCBCHANNEL | B28: link_admin_command_queue_eb_users | C28: TrangNT | D28: =IF($B28="","",IFERROR(T(_xlfn.XLOOKUP($B28,'ZONE C Vault Mapping'!$B:$B,'ZONE C Vault Mapping'!$H:$H)),IFERROR(T(_xlfn.XLOOKUP($B28,'Các bảng bổ sung sang Zone C'!$C:$C,'Các bảng bổ sung sang Zone C'!$K:$K)),""))) -> Done | E28: Thụ | G28: 20260807: thêm mới
A29: =IF($B29="","",IFERROR(_xlfn.XLOOKUP($B29,'ZONE C Vault Mapping'!$B:$B,'ZONE C Vault Mapping'!$A:$A),IFERROR(_xlfn.XLOOKUP($B29,'Các bảng bổ sung sang Zone C'!$C:$C,'Các bảng bổ sung sang Zone C'!$A:$A),""))) -> OCBCHANNEL | B29: link_admin_command_queue_customer | C29: TrangNT | D29: =IF($B29="","",IFERROR(T(_xlfn.XLOOKUP($B29,'ZONE C Vault Mapping'!$B:$B,'ZONE C Vault Mapping'!$H:$H)),IFERROR(T(_xlfn.XLOOKUP($B29,'Các bảng bổ sung sang Zone C'!$C:$C,'Các bảng bổ sung sang Zone C'!$K:$K)),""))) -> Done | E29: Thụ | G29: 20260810: thêm mới
A30: =IF($B30="","",IFERROR(_xlfn.XLOOKUP($B30,'ZONE C Vault Mapping'!$B:$B,'ZONE C Vault Mapping'!$A:$A),IFERROR(_xlfn.XLOOKUP($B30,'Các bảng bổ sung sang Zone C'!$C:$C,'Các bảng bổ sung sang Zone C'!$A:$A),""))) -> OCBCHANNEL | B30: sat_admin_command_queue | C30: TrangNT | D30: =IF($B30="","",IFERROR(T(_xlfn.XLOOKUP($B30,'ZONE C Vault Mapping'!$B:$B,'ZONE C Vault Mapping'!$H:$H)),IFERROR(T(_xlfn.XLOOKUP($B30,'Các bảng bổ sung sang Zone C'!$C:$C,'Các bảng bổ sung sang Zone C'!$K:$K)),""))) -> Done | E30: Thụ | F30: Checking | G30: 20260807: điều chỉnh số lượng cột
A31: =IF($B31="","",IFERROR(_xlfn.XLOOKUP($B31,'ZONE C Vault Mapping'!$B:$B,'ZONE C Vault Mapping'!$A:$A),IFERROR(_xlfn.XLOOKUP($B31,'Các bảng bổ sung sang Zone C'!$C:$C,'Các bảng bổ sung sang Zone C'!$A:$A),""))) -> OCBCHANNEL | B31: hub_apportion_trans_batch_details | C31: TrangNT | D31: =IF($B31="","",IFERROR(T(_xlfn.XLOOKUP($B31,'ZONE C Vault Mapping'!$B:$B,'ZONE C Vault Mapping'!$H:$H)),IFERROR(T(_xlfn.XLOOKUP($B31,'Các bảng bổ sung sang Zone C'!$C:$C,'Các bảng bổ sung sang Zone C'!$K:$K)),""))) -> Done | E31: Thụ | F31: Done | G31: 20260805: lấy ITEM_ID làm BK thay vì BATCH_ID
A32: =IF($B32="","",IFERROR(_xlfn.XLOOKUP($B32,'ZONE C Vault Mapping'!$B:$B,'ZONE C Vault Mapping'!$A:$A),IFERROR(_xlfn.XLOOKUP($B32,'Các bảng bổ sung sang Zone C'!$C:$C,'Các bảng bổ sung sang Zone C'!$A:$A),""))) -> OCBCHANNEL | B32: link_apportion_trans_batch_details_branch | C32: TrangNT | D32: =IF($B32="","",IFERROR(T(_xlfn.XLOOKUP($B32,'ZONE C Vault Mapping'!$B:$B,'ZONE C Vault Mapping'!$H:$H)),IFERROR(T(_xlfn.XLOOKUP($B32,'Các bảng bổ sung sang Zone C'!$C:$C,'Các bảng bổ sung sang Zone C'!$K:$K)),""))) -> Done | E32: Thụ | F32: Done | G32: 20260805: lấy ITEM_ID làm BK thay vì BATCH_ID
A33: =IF($B33="","",IFERROR(_xlfn.XLOOKUP($B33,'ZONE C Vault Mapping'!$B:$B,'ZONE C Vault Mapping'!$A:$A),IFERROR(_xlfn.XLOOKUP($B33,'Các bảng bổ sung sang Zone C'!$C:$C,'Các bảng bổ sung sang Zone C'!$A:$A),""))) -> OCBCHANNEL | B33: link_apportion_trans_batch_details_debit_account | C33: TrangNT | D33: =IF($B33="","",IFERROR(T(_xlfn.XLOOKUP($B33,'ZONE C Vault Mapping'!$B:$B,'ZONE C Vault Mapping'!$H:$H)),IFERROR(T(_xlfn.XLOOKUP($B33,'Các bảng bổ sung sang Zone C'!$C:$C,'Các bảng bổ sung sang Zone C'!$K:$K)),""))) -> Done | E33: Thụ | G33: 20260805: mới thêm
A34: =IF($B34="","",IFERROR(_xlfn.XLOOKUP($B34,'ZONE C Vault Mapping'!$B:$B,'ZONE C Vault Mapping'!$A:$A),IFERROR(_xlfn.XLOOKUP($B34,'Các bảng bổ sung sang Zone C'!$C:$C,'Các bảng bổ sung sang Zone C'!$A:$A),""))) -> OCBCHANNEL | B34: link_apportion_trans_batch_details_credit_account | C34: TrangNT | D34: =IF($B34="","",IFERROR(T(_xlfn.XLOOKUP($B34,'ZONE C Vault Mapping'!$B:$B,'ZONE C Vault Mapping'!$H:$H)),IFERROR(T(_xlfn.XLOOKUP($B34,'Các bảng bổ sung sang Zone C'!$C:$C,'Các bảng bổ sung sang Zone C'!$K:$K)),""))) -> Done | E34: Thụ | G34: 20260805: mới thêm
A35: =IF($B35="","",IFERROR(_xlfn.XLOOKUP($B35,'ZONE C Vault Mapping'!$B:$B,'ZONE C Vault Mapping'!$A:$A),IFERROR(_xlfn.XLOOKUP($B35,'Các bảng bổ sung sang Zone C'!$C:$C,'Các bảng bổ sung sang Zone C'!$A:$A),""))) -> OCBCHANNEL | B35: link_apportion_trans_batch_details_funds_transfer | C35: TrangNT | D35: =IF($B35="","",IFERROR(T(_xlfn.XLOOKUP($B35,'ZONE C Vault Mapping'!$B:$B,'ZONE C Vault Mapping'!$H:$H)),IFERROR(T(_xlfn.XLOOKUP($B35,'Các bảng bổ sung sang Zone C'!$C:$C,'Các bảng bổ sung sang Zone C'!$K:$K)),""))) -> Done | E35: Thụ | G35: 20260810: sửa mapping funds_transfer_hashkey 20260807: mới thêm
A36: =IF($B36="","",IFERROR(_xlfn.XLOOKUP($B36,'ZONE C Vault Mapping'!$B:$B,'ZONE C Vault Mapping'!$A:$A),IFERROR(_xlfn.XLOOKUP($B36,'Các bảng bổ sung sang Zone C'!$C:$C,'Các bảng bổ sung sang Zone C'!$A:$A),""))) -> OCBCHANNEL | B36: sat_apportion_trans_batch_details | C36: TrangNT | D36: =IF($B36="","",IFERROR(T(_xlfn.XLOOKUP($B36,'ZONE C Vault Mapping'!$B:$B,'ZONE C Vault Mapping'!$H:$H)),IFERROR(T(_xlfn.XLOOKUP($B36,'Các bảng bổ sung sang Zone C'!$C:$C,'Các bảng bổ sung sang Zone C'!$K:$K)),""))) -> Done | E36: Thụ | F36: Checking | G36: 20260807: điều chỉnh số lượng cột 20260805: lấy ITEM_ID làm BK thay vì BATCH_ID, điều chỉnh lại số lượng cột, không làm multiactive sat nữa
A37: =IF($B37="","",IFERROR(_xlfn.XLOOKUP($B37,'ZONE C Vault Mapping'!$B:$B,'ZONE C Vault Mapping'!$A:$A),IFERROR(_xlfn.XLOOKUP($B37,'Các bảng bổ sung sang Zone C'!$C:$C,'Các bảng bổ sung sang Zone C'!$A:$A),""))) -> OCBCHANNEL | B37: ref_ocbchannel_authen_type | C37: TrangNT | D37: =IF($B37="","",IFERROR(T(_xlfn.XLOOKUP($B37,'ZONE C Vault Mapping'!$B:$B,'ZONE C Vault Mapping'!$H:$H)),IFERROR(T(_xlfn.XLOOKUP($B37,'Các bảng bổ sung sang Zone C'!$C:$C,'Các bảng bổ sung sang Zone C'!$K:$K)),""))) -> Done | E37: Thụ | F37: Checking | G37: 20260806: thêm 1 cột
A38: =IF($B38="","",IFERROR(_xlfn.XLOOKUP($B38,'ZONE C Vault Mapping'!$B:$B,'ZONE C Vault Mapping'!$A:$A),IFERROR(_xlfn.XLOOKUP($B38,'Các bảng bổ sung sang Zone C'!$C:$C,'Các bảng bổ sung sang Zone C'!$A:$A),""))) -> OCBCHANNEL | B38: hub_customer_file | C38: TrangNT | D38: =IF($B38="","",IFERROR(T(_xlfn.XLOOKUP($B38,'ZONE C Vault Mapping'!$B:$B,'ZONE C Vault Mapping'!$H:$H)),IFERROR(T(_xlfn.XLOOKUP($B38,'Các bảng bổ sung sang Zone C'!$C:$C,'Các bảng bổ sung sang Zone C'!$K:$K)),""))) -> Done | E38: Thụ | F38: Done
A39: =IF($B39="","",IFERROR(_xlfn.XLOOKUP($B39,'ZONE C Vault Mapping'!$B:$B,'ZONE C Vault Mapping'!$A:$A),IFERROR(_xlfn.XLOOKUP($B39,'Các bảng bổ sung sang Zone C'!$C:$C,'Các bảng bổ sung sang Zone C'!$A:$A),""))) -> OCBCHANNEL | B39: link_customer_file_customer | C39: TrangNT | D39: =IF($B39="","",IFERROR(T(_xlfn.XLOOKUP($B39,'ZONE C Vault Mapping'!$B:$B,'ZONE C Vault Mapping'!$H:$H)),IFERROR(T(_xlfn.XLOOKUP($B39,'Các bảng bổ sung sang Zone C'!$C:$C,'Các bảng bổ sung sang Zone C'!$K:$K)),""))) -> Done | E39: Thụ | F39: Done
A40: =IF($B40="","",IFERROR(_xlfn.XLOOKUP($B40,'ZONE C Vault Mapping'!$B:$B,'ZONE C Vault Mapping'!$A:$A),IFERROR(_xlfn.XLOOKUP($B40,'Các bảng bổ sung sang Zone C'!$C:$C,'Các bảng bổ sung sang Zone C'!$A:$A),""))) -> OCBCHANNEL | B40: link_customer_file_branch | C40: TrangNT | D40: =IF($B40="","",IFERROR(T(_xlfn.XLOOKUP($B40,'ZONE C Vault Mapping'!$B:$B,'ZONE C Vault Mapping'!$H:$H)),IFERROR(T(_xlfn.XLOOKUP($B40,'Các bảng bổ sung sang Zone C'!$C:$C,'Các bảng bổ sung sang Zone C'!$K:$K)),""))) -> Done | E40: Thụ | F40: Done
A41: =IF($B41="","",IFERROR(_xlfn.XLOOKUP($B41,'ZONE C Vault Mapping'!$B:$B,'ZONE C Vault Mapping'!$A:$A),IFERROR(_xlfn.XLOOKUP($B41,'Các bảng bổ sung sang Zone C'!$C:$C,'Các bảng bổ sung sang Zone C'!$A:$A),""))) -> OCBCHANNEL | B41: sat_customer_file_information | C41: TrangNT | D41: =IF($B41="","",IFERROR(T(_xlfn.XLOOKUP($B41,'ZONE C Vault Mapping'!$B:$B,'ZONE C Vault Mapping'!$H:$H)),IFERROR(T(_xlfn.XLOOKUP($B41,'Các bảng bổ sung sang Zone C'!$C:$C,'Các bảng bổ sung sang Zone C'!$K:$K)),""))) -> Done | E41: Thụ | F41: Checking | G41: 20260807:Điều chỉnh số lượng trường
A42: =IF($B42="","",IFERROR(_xlfn.XLOOKUP($B42,'ZONE C Vault Mapping'!$B:$B,'ZONE C Vault Mapping'!$A:$A),IFERROR(_xlfn.XLOOKUP($B42,'Các bảng bổ sung sang Zone C'!$C:$C,'Các bảng bổ sung sang Zone C'!$A:$A),""))) -> OCBCHANNEL | B42: sat_customer_file_detail | C42: TrangNT | D42: =IF($B42="","",IFERROR(T(_xlfn.XLOOKUP($B42,'ZONE C Vault Mapping'!$B:$B,'ZONE C Vault Mapping'!$H:$H)),IFERROR(T(_xlfn.XLOOKUP($B42,'Các bảng bổ sung sang Zone C'!$C:$C,'Các bảng bổ sung sang Zone C'!$K:$K)),""))) -> Done | E42: Thụ | F42: Checking | G42: 20260807: Điều chỉnh số lượng trường
A43: =IF($B43="","",IFERROR(_xlfn.XLOOKUP($B43,'ZONE C Vault Mapping'!$B:$B,'ZONE C Vault Mapping'!$A:$A),IFERROR(_xlfn.XLOOKUP($B43,'Các bảng bổ sung sang Zone C'!$C:$C,'Các bảng bổ sung sang Zone C'!$A:$A),""))) -> OCBCHANNEL | B43: hub_ocbchannel_eb_package_type | C43: TrangNT | D43: =IF($B43="","",IFERROR(T(_xlfn.XLOOKUP($B43,'ZONE C Vault Mapping'!$B:$B,'ZONE C Vault Mapping'!$H:$H)),IFERROR(T(_xlfn.XLOOKUP($B43,'Các bảng bổ sung sang Zone C'!$C:$C,'Các bảng bổ sung sang Zone C'!$K:$K)),""))) -> Cancel
A44: =IF($B44="","",IFERROR(_xlfn.XLOOKUP($B44,'ZONE C Vault Mapping'!$B:$B,'ZONE C Vault Mapping'!$A:$A),IFERROR(_xlfn.XLOOKUP($B44,'Các bảng bổ sung sang Zone C'!$C:$C,'Các bảng bổ sung sang Zone C'!$A:$A),""))) -> OCBCHANNEL | B44: ref_ocbchannel_eb_package_type | C44: TrangNT | D44: =IF($B44="","",IFERROR(T(_xlfn.XLOOKUP($B44,'ZONE C Vault Mapping'!$B:$B,'ZONE C Vault Mapping'!$H:$H)),IFERROR(T(_xlfn.XLOOKUP($B44,'Các bảng bổ sung sang Zone C'!$C:$C,'Các bảng bổ sung sang Zone C'!$K:$K)),""))) -> Done | E44: Thụ | F44: Checking | G44: 20260805: sửa mapping ref_code 20260713: thêm 3 cột package_type_id, channel, package_name
A45: =IF($B45="","",IFERROR(_xlfn.XLOOKUP($B45,'ZONE C Vault Mapping'!$B:$B,'ZONE C Vault Mapping'!$A:$A),IFERROR(_xlfn.XLOOKUP($B45,'Các bảng bổ sung sang Zone C'!$C:$C,'Các bảng bổ sung sang Zone C'!$A:$A),""))) -> OCBCHANNEL | B45: hub_eb_user_channel | C45: TrangNT | D45: =IF($B45="","",IFERROR(T(_xlfn.XLOOKUP($B45,'ZONE C Vault Mapping'!$B:$B,'ZONE C Vault Mapping'!$H:$H)),IFERROR(T(_xlfn.XLOOKUP($B45,'Các bảng bổ sung sang Zone C'!$C:$C,'Các bảng bổ sung sang Zone C'!$K:$K)),""))) -> Cancel | E45: Thụ | F45: Checking | G45: 20260805: cancel
A46: =IF($B46="","",IFERROR(_xlfn.XLOOKUP($B46,'ZONE C Vault Mapping'!$B:$B,'ZONE C Vault Mapping'!$A:$A),IFERROR(_xlfn.XLOOKUP($B46,'Các bảng bổ sung sang Zone C'!$C:$C,'Các bảng bổ sung sang Zone C'!$A:$A),""))) -> OCBCHANNEL | B46: link_eb_user_channel_package_type | C46: TrangNT | D46: =IF($B46="","",IFERROR(T(_xlfn.XLOOKUP($B46,'ZONE C Vault Mapping'!$B:$B,'ZONE C Vault Mapping'!$H:$H)),IFERROR(T(_xlfn.XLOOKUP($B46,'Các bảng bổ sung sang Zone C'!$C:$C,'Các bảng bổ sung sang Zone C'!$K:$K)),""))) -> Cancel | E46: Thụ | F46: Checking | G46: 20260805: cancel
A47: =IF($B47="","",IFERROR(_xlfn.XLOOKUP($B47,'ZONE C Vault Mapping'!$B:$B,'ZONE C Vault Mapping'!$A:$A),IFERROR(_xlfn.XLOOKUP($B47,'Các bảng bổ sung sang Zone C'!$C:$C,'Các bảng bổ sung sang Zone C'!$A:$A),""))) -> OCBCHANNEL | B47: link_eb_user_channel_branch | C47: TrangNT | D47: =IF($B47="","",IFERROR(T(_xlfn.XLOOKUP($B47,'ZONE C Vault Mapping'!$B:$B,'ZONE C Vault Mapping'!$H:$H)),IFERROR(T(_xlfn.XLOOKUP($B47,'Các bảng bổ sung sang Zone C'!$C:$C,'Các bảng bổ sung sang Zone C'!$K:$K)),""))) -> Cancel | E47: Thụ | F47: Checking | G47: 20260805: cancel
A48: =IF($B48="","",IFERROR(_xlfn.XLOOKUP($B48,'ZONE C Vault Mapping'!$B:$B,'ZONE C Vault Mapping'!$A:$A),IFERROR(_xlfn.XLOOKUP($B48,'Các bảng bổ sung sang Zone C'!$C:$C,'Các bảng bổ sung sang Zone C'!$A:$A),""))) -> OCBCHANNEL | B48: sat_eb_user_channel_information | C48: TrangNT | D48: =IF($B48="","",IFERROR(T(_xlfn.XLOOKUP($B48,'ZONE C Vault Mapping'!$B:$B,'ZONE C Vault Mapping'!$H:$H)),IFERROR(T(_xlfn.XLOOKUP($B48,'Các bảng bổ sung sang Zone C'!$C:$C,'Các bảng bổ sung sang Zone C'!$K:$K)),""))) -> Done | E48: Thụ | F48: Checking | G48: 20260810: điều chỉnh số lượng cột 20260805: đổi tên cột hashkey
A49: =IF($B49="","",IFERROR(_xlfn.XLOOKUP($B49,'ZONE C Vault Mapping'!$B:$B,'ZONE C Vault Mapping'!$A:$A),IFERROR(_xlfn.XLOOKUP($B49,'Các bảng bổ sung sang Zone C'!$C:$C,'Các bảng bổ sung sang Zone C'!$A:$A),""))) -> OCBCHANNEL | B49: sat_eb_user_channel_detail | C49: TrangNT | D49: =IF($B49="","",IFERROR(T(_xlfn.XLOOKUP($B49,'ZONE C Vault Mapping'!$B:$B,'ZONE C Vault Mapping'!$H:$H)),IFERROR(T(_xlfn.XLOOKUP($B49,'Các bảng bổ sung sang Zone C'!$C:$C,'Các bảng bổ sung sang Zone C'!$K:$K)),""))) -> Done | E49: Thụ | F49: Checking | G49: 20260810: điều chỉnh số lượng cột 20260805: đổi tên cột hashkey
A50: =IF($B50="","",IFERROR(_xlfn.XLOOKUP($B50,'ZONE C Vault Mapping'!$B:$B,'ZONE C Vault Mapping'!$A:$A),IFERROR(_xlfn.XLOOKUP($B50,'Các bảng bổ sung sang Zone C'!$C:$C,'Các bảng bổ sung sang Zone C'!$A:$A),""))) -> OCBCHANNEL | B50: hub_eb_user_session | C50: TrangNT | D50: =IF($B50="","",IFERROR(T(_xlfn.XLOOKUP($B50,'ZONE C Vault Mapping'!$B:$B,'ZONE C Vault Mapping'!$H:$H)),IFERROR(T(_xlfn.XLOOKUP($B50,'Các bảng bổ sung sang Zone C'!$C:$C,'Các bảng bổ sung sang Zone C'!$K:$K)),""))) -> Done | E50: Thụ | F50: Done
A51: =IF($B51="","",IFERROR(_xlfn.XLOOKUP($B51,'ZONE C Vault Mapping'!$B:$B,'ZONE C Vault Mapping'!$A:$A),IFERROR(_xlfn.XLOOKUP($B51,'Các bảng bổ sung sang Zone C'!$C:$C,'Các bảng bổ sung sang Zone C'!$A:$A),""))) -> OCBCHANNEL | B51: sat_eb_user_session | C51: TrangNT | D51: =IF($B51="","",IFERROR(T(_xlfn.XLOOKUP($B51,'ZONE C Vault Mapping'!$B:$B,'ZONE C Vault Mapping'!$H:$H)),IFERROR(T(_xlfn.XLOOKUP($B51,'Các bảng bổ sung sang Zone C'!$C:$C,'Các bảng bổ sung sang Zone C'!$K:$K)),""))) -> Done | E51: Thụ | F51: Checking | G51: 20260805: đổi mapping cho ma_key
A52: =IF($B52="","",IFERROR(_xlfn.XLOOKUP($B52,'ZONE C Vault Mapping'!$B:$B,'ZONE C Vault Mapping'!$A:$A),IFERROR(_xlfn.XLOOKUP($B52,'Các bảng bổ sung sang Zone C'!$C:$C,'Các bảng bổ sung sang Zone C'!$A:$A),""))) -> OCBCHANNEL | B52: hub_eb_users | C52: TrangNT | D52: =IF($B52="","",IFERROR(T(_xlfn.XLOOKUP($B52,'ZONE C Vault Mapping'!$B:$B,'ZONE C Vault Mapping'!$H:$H)),IFERROR(T(_xlfn.XLOOKUP($B52,'Các bảng bổ sung sang Zone C'!$C:$C,'Các bảng bổ sung sang Zone C'!$K:$K)),""))) -> Done | E52: Thụ | F52: Checking | G52: 20260810: thêm UNION DISTINCT
A53: =IF($B53="","",IFERROR(_xlfn.XLOOKUP($B53,'ZONE C Vault Mapping'!$B:$B,'ZONE C Vault Mapping'!$A:$A),IFERROR(_xlfn.XLOOKUP($B53,'Các bảng bổ sung sang Zone C'!$C:$C,'Các bảng bổ sung sang Zone C'!$A:$A),""))) -> OCBCHANNEL | B53: link_eb_users_customer | C53: TrangNT | D53: =IF($B53="","",IFERROR(T(_xlfn.XLOOKUP($B53,'ZONE C Vault Mapping'!$B:$B,'ZONE C Vault Mapping'!$H:$H)),IFERROR(T(_xlfn.XLOOKUP($B53,'Các bảng bổ sung sang Zone C'!$C:$C,'Các bảng bổ sung sang Zone C'!$K:$K)),""))) -> Done | E53: Thụ | F53: Done
A54: =IF($B54="","",IFERROR(_xlfn.XLOOKUP($B54,'ZONE C Vault Mapping'!$B:$B,'ZONE C Vault Mapping'!$A:$A),IFERROR(_xlfn.XLOOKUP($B54,'Các bảng bổ sung sang Zone C'!$C:$C,'Các bảng bổ sung sang Zone C'!$A:$A),""))) -> OCBCHANNEL | B54: link_eb_users_branch | C54: TrangNT | D54: =IF($B54="","",IFERROR(T(_xlfn.XLOOKUP($B54,'ZONE C Vault Mapping'!$B:$B,'ZONE C Vault Mapping'!$H:$H)),IFERROR(T(_xlfn.XLOOKUP($B54,'Các bảng bổ sung sang Zone C'!$C:$C,'Các bảng bổ sung sang Zone C'!$K:$K)),""))) -> Done | E54: Thụ | F54: Checking | G54: 20260810: đổi tên cột hashkey
A55: =IF($B55="","",IFERROR(_xlfn.XLOOKUP($B55,'ZONE C Vault Mapping'!$B:$B,'ZONE C Vault Mapping'!$A:$A),IFERROR(_xlfn.XLOOKUP($B55,'Các bảng bổ sung sang Zone C'!$C:$C,'Các bảng bổ sung sang Zone C'!$A:$A),""))) -> OCBCHANNEL | B55: sat_eb_users | C55: TrangNT | D55: =IF($B55="","",IFERROR(T(_xlfn.XLOOKUP($B55,'ZONE C Vault Mapping'!$B:$B,'ZONE C Vault Mapping'!$H:$H)),IFERROR(T(_xlfn.XLOOKUP($B55,'Các bảng bổ sung sang Zone C'!$C:$C,'Các bảng bổ sung sang Zone C'!$K:$K)),""))) -> Done | E55: Thụ | F55: Checking | G55: 20260810: không sử dụng cif và branch_code trong sat nữa
A56: =IF($B56="","",IFERROR(_xlfn.XLOOKUP($B56,'ZONE C Vault Mapping'!$B:$B,'ZONE C Vault Mapping'!$A:$A),IFERROR(_xlfn.XLOOKUP($B56,'Các bảng bổ sung sang Zone C'!$C:$C,'Các bảng bổ sung sang Zone C'!$A:$A),""))) -> OCBCHANNEL | B56: hub_ocb_bill_providers | C56: TrangNT | D56: =IF($B56="","",IFERROR(T(_xlfn.XLOOKUP($B56,'ZONE C Vault Mapping'!$B:$B,'ZONE C Vault Mapping'!$H:$H)),IFERROR(T(_xlfn.XLOOKUP($B56,'Các bảng bổ sung sang Zone C'!$C:$C,'Các bảng bổ sung sang Zone C'!$K:$K)),""))) -> Done | E56: Thụ | F56: Done
A57: =IF($B57="","",IFERROR(_xlfn.XLOOKUP($B57,'ZONE C Vault Mapping'!$B:$B,'ZONE C Vault Mapping'!$A:$A),IFERROR(_xlfn.XLOOKUP($B57,'Các bảng bổ sung sang Zone C'!$C:$C,'Các bảng bổ sung sang Zone C'!$A:$A),""))) -> OCBCHANNEL | B57: sat_ocb_bill_providers | C57: TrangNT | D57: =IF($B57="","",IFERROR(T(_xlfn.XLOOKUP($B57,'ZONE C Vault Mapping'!$B:$B,'ZONE C Vault Mapping'!$H:$H)),IFERROR(T(_xlfn.XLOOKUP($B57,'Các bảng bổ sung sang Zone C'!$C:$C,'Các bảng bổ sung sang Zone C'!$K:$K)),""))) -> Done | E57: Thụ | F57: Done
A58: =IF($B58="","",IFERROR(_xlfn.XLOOKUP($B58,'ZONE C Vault Mapping'!$B:$B,'ZONE C Vault Mapping'!$A:$A),IFERROR(_xlfn.XLOOKUP($B58,'Các bảng bổ sung sang Zone C'!$C:$C,'Các bảng bổ sung sang Zone C'!$A:$A),""))) -> OCBCHANNEL | B58: hub_ocb_bill_services | C58: TrangNT | D58: =IF($B58="","",IFERROR(T(_xlfn.XLOOKUP($B58,'ZONE C Vault Mapping'!$B:$B,'ZONE C Vault Mapping'!$H:$H)),IFERROR(T(_xlfn.XLOOKUP($B58,'Các bảng bổ sung sang Zone C'!$C:$C,'Các bảng bổ sung sang Zone C'!$K:$K)),""))) -> Done | E58: Thụ | F58: Done
A59: =IF($B59="","",IFERROR(_xlfn.XLOOKUP($B59,'ZONE C Vault Mapping'!$B:$B,'ZONE C Vault Mapping'!$A:$A),IFERROR(_xlfn.XLOOKUP($B59,'Các bảng bổ sung sang Zone C'!$C:$C,'Các bảng bổ sung sang Zone C'!$A:$A),""))) -> OCBCHANNEL | B59: link_ocb_bill_service_provider | C59: TrangNT | D59: =IF($B59="","",IFERROR(T(_xlfn.XLOOKUP($B59,'ZONE C Vault Mapping'!$B:$B,'ZONE C Vault Mapping'!$H:$H)),IFERROR(T(_xlfn.XLOOKUP($B59,'Các bảng bổ sung sang Zone C'!$C:$C,'Các bảng bổ sung sang Zone C'!$K:$K)),""))) -> Done | E59: Thụ | F59: Done
A60: =IF($B60="","",IFERROR(_xlfn.XLOOKUP($B60,'ZONE C Vault Mapping'!$B:$B,'ZONE C Vault Mapping'!$A:$A),IFERROR(_xlfn.XLOOKUP($B60,'Các bảng bổ sung sang Zone C'!$C:$C,'Các bảng bổ sung sang Zone C'!$A:$A),""))) -> OCBCHANNEL | B60: sat_ocb_bill_service_provider | C60: TrangNT | D60: =IF($B60="","",IFERROR(T(_xlfn.XLOOKUP($B60,'ZONE C Vault Mapping'!$B:$B,'ZONE C Vault Mapping'!$H:$H)),IFERROR(T(_xlfn.XLOOKUP($B60,'Các bảng bổ sung sang Zone C'!$C:$C,'Các bảng bổ sung sang Zone C'!$K:$K)),""))) -> Done | E60: Thụ | F60: Checking | G60: 20260810: bỏ 2 trường thuộc tính service_id, provider_id
A61: =IF($B61="","",IFERROR(_xlfn.XLOOKUP($B61,'ZONE C Vault Mapping'!$B:$B,'ZONE C Vault Mapping'!$A:$A),IFERROR(_xlfn.XLOOKUP($B61,'Các bảng bổ sung sang Zone C'!$C:$C,'Các bảng bổ sung sang Zone C'!$A:$A),""))) -> OCBCHANNEL | B61: sat_ocb_bill_services | C61: TrangNT | D61: =IF($B61="","",IFERROR(T(_xlfn.XLOOKUP($B61,'ZONE C Vault Mapping'!$B:$B,'ZONE C Vault Mapping'!$H:$H)),IFERROR(T(_xlfn.XLOOKUP($B61,'Các bảng bổ sung sang Zone C'!$C:$C,'Các bảng bổ sung sang Zone C'!$K:$K)),""))) -> Done | E61: Thụ | F61: Done
A62: =IF($B62="","",IFERROR(_xlfn.XLOOKUP($B62,'ZONE C Vault Mapping'!$B:$B,'ZONE C Vault Mapping'!$A:$A),IFERROR(_xlfn.XLOOKUP($B62,'Các bảng bổ sung sang Zone C'!$C:$C,'Các bảng bổ sung sang Zone C'!$A:$A),""))) -> OCBCHANNEL | B62: hub_soa_cust_account | C62: TrangNT | D62: =IF($B62="","",IFERROR(T(_xlfn.XLOOKUP($B62,'ZONE C Vault Mapping'!$B:$B,'ZONE C Vault Mapping'!$H:$H)),IFERROR(T(_xlfn.XLOOKUP($B62,'Các bảng bổ sung sang Zone C'!$C:$C,'Các bảng bổ sung sang Zone C'!$K:$K)),""))) -> Done | E62: Thụ | F62: Done
A63: =IF($B63="","",IFERROR(_xlfn.XLOOKUP($B63,'ZONE C Vault Mapping'!$B:$B,'ZONE C Vault Mapping'!$A:$A),IFERROR(_xlfn.XLOOKUP($B63,'Các bảng bổ sung sang Zone C'!$C:$C,'Các bảng bổ sung sang Zone C'!$A:$A),""))) -> OCBCHANNEL | B63: link_soa_cust_account_customer | C63: TrangNT | D63: =IF($B63="","",IFERROR(T(_xlfn.XLOOKUP($B63,'ZONE C Vault Mapping'!$B:$B,'ZONE C Vault Mapping'!$H:$H)),IFERROR(T(_xlfn.XLOOKUP($B63,'Các bảng bổ sung sang Zone C'!$C:$C,'Các bảng bổ sung sang Zone C'!$K:$K)),""))) -> Done | E63: Thụ | F63: Done
A64: =IF($B64="","",IFERROR(_xlfn.XLOOKUP($B64,'ZONE C Vault Mapping'!$B:$B,'ZONE C Vault Mapping'!$A:$A),IFERROR(_xlfn.XLOOKUP($B64,'Các bảng bổ sung sang Zone C'!$C:$C,'Các bảng bổ sung sang Zone C'!$A:$A),""))) -> OCBCHANNEL | B64: link_soa_cust_account_branch | C64: TrangNT | D64: =IF($B64="","",IFERROR(T(_xlfn.XLOOKUP($B64,'ZONE C Vault Mapping'!$B:$B,'ZONE C Vault Mapping'!$H:$H)),IFERROR(T(_xlfn.XLOOKUP($B64,'Các bảng bổ sung sang Zone C'!$C:$C,'Các bảng bổ sung sang Zone C'!$K:$K)),""))) -> Done | E64: Thụ | F64: Done
A65: =IF($B65="","",IFERROR(_xlfn.XLOOKUP($B65,'ZONE C Vault Mapping'!$B:$B,'ZONE C Vault Mapping'!$A:$A),IFERROR(_xlfn.XLOOKUP($B65,'Các bảng bổ sung sang Zone C'!$C:$C,'Các bảng bổ sung sang Zone C'!$A:$A),""))) -> OCBCHANNEL | B65: sat_soa_cust_account_information | C65: TrangNT | D65: =IF($B65="","",IFERROR(T(_xlfn.XLOOKUP($B65,'ZONE C Vault Mapping'!$B:$B,'ZONE C Vault Mapping'!$H:$H)),IFERROR(T(_xlfn.XLOOKUP($B65,'Các bảng bổ sung sang Zone C'!$C:$C,'Các bảng bổ sung sang Zone C'!$K:$K)),""))) -> Done | E65: Thụ | F65: Checking | G65: 20260810: không sử dụng cif và branch_code trong sat nữa
A66: =IF($B66="","",IFERROR(_xlfn.XLOOKUP($B66,'ZONE C Vault Mapping'!$B:$B,'ZONE C Vault Mapping'!$A:$A),IFERROR(_xlfn.XLOOKUP($B66,'Các bảng bổ sung sang Zone C'!$C:$C,'Các bảng bổ sung sang Zone C'!$A:$A),""))) -> OCBCHANNEL | B66: sat_soa_cust_account_detail | C66: TrangNT | D66: =IF($B66="","",IFERROR(T(_xlfn.XLOOKUP($B66,'ZONE C Vault Mapping'!$B:$B,'ZONE C Vault Mapping'!$H:$H)),IFERROR(T(_xlfn.XLOOKUP($B66,'Các bảng bổ sung sang Zone C'!$C:$C,'Các bảng bổ sung sang Zone C'!$K:$K)),""))) -> Done | E66: Thụ | F66: Done
A67: =IF($B67="","",IFERROR(_xlfn.XLOOKUP($B67,'ZONE C Vault Mapping'!$B:$B,'ZONE C Vault Mapping'!$A:$A),IFERROR(_xlfn.XLOOKUP($B67,'Các bảng bổ sung sang Zone C'!$C:$C,'Các bảng bổ sung sang Zone C'!$A:$A),""))) -> OCBCHANNEL | B67: hub_soa_cust_package | C67: TrangNT | D67: =IF($B67="","",IFERROR(T(_xlfn.XLOOKUP($B67,'ZONE C Vault Mapping'!$B:$B,'ZONE C Vault Mapping'!$H:$H)),IFERROR(T(_xlfn.XLOOKUP($B67,'Các bảng bổ sung sang Zone C'!$C:$C,'Các bảng bổ sung sang Zone C'!$K:$K)),""))) -> Done | E67: Thụ | F67: Done
A68: =IF($B68="","",IFERROR(_xlfn.XLOOKUP($B68,'ZONE C Vault Mapping'!$B:$B,'ZONE C Vault Mapping'!$A:$A),IFERROR(_xlfn.XLOOKUP($B68,'Các bảng bổ sung sang Zone C'!$C:$C,'Các bảng bổ sung sang Zone C'!$A:$A),""))) -> OCBCHANNEL | B68: link_soa_cust_package_customer | C68: TrangNT | D68: =IF($B68="","",IFERROR(T(_xlfn.XLOOKUP($B68,'ZONE C Vault Mapping'!$B:$B,'ZONE C Vault Mapping'!$H:$H)),IFERROR(T(_xlfn.XLOOKUP($B68,'Các bảng bổ sung sang Zone C'!$C:$C,'Các bảng bổ sung sang Zone C'!$K:$K)),""))) -> Done | E68: Thụ | F68: Done
A69: =IF($B69="","",IFERROR(_xlfn.XLOOKUP($B69,'ZONE C Vault Mapping'!$B:$B,'ZONE C Vault Mapping'!$A:$A),IFERROR(_xlfn.XLOOKUP($B69,'Các bảng bổ sung sang Zone C'!$C:$C,'Các bảng bổ sung sang Zone C'!$A:$A),""))) -> OCBCHANNEL | B69: link_soa_cust_package_branch | C69: TrangNT | D69: =IF($B69="","",IFERROR(T(_xlfn.XLOOKUP($B69,'ZONE C Vault Mapping'!$B:$B,'ZONE C Vault Mapping'!$H:$H)),IFERROR(T(_xlfn.XLOOKUP($B69,'Các bảng bổ sung sang Zone C'!$C:$C,'Các bảng bổ sung sang Zone C'!$K:$K)),""))) -> Done | E69: Thụ | F69: Done
A70: =IF($B70="","",IFERROR(_xlfn.XLOOKUP($B70,'ZONE C Vault Mapping'!$B:$B,'ZONE C Vault Mapping'!$A:$A),IFERROR(_xlfn.XLOOKUP($B70,'Các bảng bổ sung sang Zone C'!$C:$C,'Các bảng bổ sung sang Zone C'!$A:$A),""))) -> OCBCHANNEL | B70: link_soa_cust_package_acct_officer | C70: TrangNT | D70: =IF($B70="","",IFERROR(T(_xlfn.XLOOKUP($B70,'ZONE C Vault Mapping'!$B:$B,'ZONE C Vault Mapping'!$H:$H)),IFERROR(T(_xlfn.XLOOKUP($B70,'Các bảng bổ sung sang Zone C'!$C:$C,'Các bảng bổ sung sang Zone C'!$K:$K)),""))) -> Done | E70: Thụ | G70: 20260810: thêm mới
A71: =IF($B71="","",IFERROR(_xlfn.XLOOKUP($B71,'ZONE C Vault Mapping'!$B:$B,'ZONE C Vault Mapping'!$A:$A),IFERROR(_xlfn.XLOOKUP($B71,'Các bảng bổ sung sang Zone C'!$C:$C,'Các bảng bổ sung sang Zone C'!$A:$A),""))) -> OCBCHANNEL | B71: sat_soa_cust_package_information | C71: TrangNT | D71: =IF($B71="","",IFERROR(T(_xlfn.XLOOKUP($B71,'ZONE C Vault Mapping'!$B:$B,'ZONE C Vault Mapping'!$H:$H)),IFERROR(T(_xlfn.XLOOKUP($B71,'Các bảng bổ sung sang Zone C'!$C:$C,'Các bảng bổ sung sang Zone C'!$K:$K)),""))) -> Done | E71: Thụ | F71: Checking | G71: 20260810: điều chỉnh số lượng cột
A72: =IF($B72="","",IFERROR(_xlfn.XLOOKUP($B72,'ZONE C Vault Mapping'!$B:$B,'ZONE C Vault Mapping'!$A:$A),IFERROR(_xlfn.XLOOKUP($B72,'Các bảng bổ sung sang Zone C'!$C:$C,'Các bảng bổ sung sang Zone C'!$A:$A),""))) -> OCBCHANNEL | B72: sat_soa_cust_package_detail | C72: TrangNT | D72: =IF($B72="","",IFERROR(T(_xlfn.XLOOKUP($B72,'ZONE C Vault Mapping'!$B:$B,'ZONE C Vault Mapping'!$H:$H)),IFERROR(T(_xlfn.XLOOKUP($B72,'Các bảng bổ sung sang Zone C'!$C:$C,'Các bảng bổ sung sang Zone C'!$K:$K)),""))) -> Done | E72: Thụ | F72: Done
A73: =IF($B73="","",IFERROR(_xlfn.XLOOKUP($B73,'ZONE C Vault Mapping'!$B:$B,'ZONE C Vault Mapping'!$A:$A),IFERROR(_xlfn.XLOOKUP($B73,'Các bảng bổ sung sang Zone C'!$C:$C,'Các bảng bổ sung sang Zone C'!$A:$A),""))) -> OCBCHANNEL | B73: hub_soa_ntdt_register | C73: TrangNT | D73: =IF($B73="","",IFERROR(T(_xlfn.XLOOKUP($B73,'ZONE C Vault Mapping'!$B:$B,'ZONE C Vault Mapping'!$H:$H)),IFERROR(T(_xlfn.XLOOKUP($B73,'Các bảng bổ sung sang Zone C'!$C:$C,'Các bảng bổ sung sang Zone C'!$K:$K)),""))) -> Done | E73: Thụ | F73: Done | G73: 20260713: sửa điều kiện mapping
A74: =IF($B74="","",IFERROR(_xlfn.XLOOKUP($B74,'ZONE C Vault Mapping'!$B:$B,'ZONE C Vault Mapping'!$A:$A),IFERROR(_xlfn.XLOOKUP($B74,'Các bảng bổ sung sang Zone C'!$C:$C,'Các bảng bổ sung sang Zone C'!$A:$A),""))) -> OCBCHANNEL | B74: link_soa_ntdt_register_branch | C74: TrangNT | D74: =IF($B74="","",IFERROR(T(_xlfn.XLOOKUP($B74,'ZONE C Vault Mapping'!$B:$B,'ZONE C Vault Mapping'!$H:$H)),IFERROR(T(_xlfn.XLOOKUP($B74,'Các bảng bổ sung sang Zone C'!$C:$C,'Các bảng bổ sung sang Zone C'!$K:$K)),""))) -> Done | E74: Thụ | F74: Done
A75: =IF($B75="","",IFERROR(_xlfn.XLOOKUP($B75,'ZONE C Vault Mapping'!$B:$B,'ZONE C Vault Mapping'!$A:$A),IFERROR(_xlfn.XLOOKUP($B75,'Các bảng bổ sung sang Zone C'!$C:$C,'Các bảng bổ sung sang Zone C'!$A:$A),""))) -> OCBCHANNEL | B75: link_soa_ntdt_register_account | C75: TrangNT | D75: =IF($B75="","",IFERROR(T(_xlfn.XLOOKUP($B75,'ZONE C Vault Mapping'!$B:$B,'ZONE C Vault Mapping'!$H:$H)),IFERROR(T(_xlfn.XLOOKUP($B75,'Các bảng bổ sung sang Zone C'!$C:$C,'Các bảng bổ sung sang Zone C'!$K:$K)),""))) -> Done | E75: Thụ | F75: Done
A76: =IF($B76="","",IFERROR(_xlfn.XLOOKUP($B76,'ZONE C Vault Mapping'!$B:$B,'ZONE C Vault Mapping'!$A:$A),IFERROR(_xlfn.XLOOKUP($B76,'Các bảng bổ sung sang Zone C'!$C:$C,'Các bảng bổ sung sang Zone C'!$A:$A),""))) -> OCBCHANNEL | B76: effsat_link_soa_ntdt_register_account | C76: TrangNT | D76: =IF($B76="","",IFERROR(T(_xlfn.XLOOKUP($B76,'ZONE C Vault Mapping'!$B:$B,'ZONE C Vault Mapping'!$H:$H)),IFERROR(T(_xlfn.XLOOKUP($B76,'Các bảng bổ sung sang Zone C'!$C:$C,'Các bảng bổ sung sang Zone C'!$K:$K)),""))) -> Done | E76: Thụ | F76: Done
A77: =IF($B77="","",IFERROR(_xlfn.XLOOKUP($B77,'ZONE C Vault Mapping'!$B:$B,'ZONE C Vault Mapping'!$A:$A),IFERROR(_xlfn.XLOOKUP($B77,'Các bảng bổ sung sang Zone C'!$C:$C,'Các bảng bổ sung sang Zone C'!$A:$A),""))) -> OCBCHANNEL | B77: sat_soa_ntdt_register_information | C77: TrangNT | D77: =IF($B77="","",IFERROR(T(_xlfn.XLOOKUP($B77,'ZONE C Vault Mapping'!$B:$B,'ZONE C Vault Mapping'!$H:$H)),IFERROR(T(_xlfn.XLOOKUP($B77,'Các bảng bổ sung sang Zone C'!$C:$C,'Các bảng bổ sung sang Zone C'!$K:$K)),""))) -> Done | E77: Thụ | F77: Checking | G77: 20260810: không dùng trường branch_code trong sat, thêm tiền tố _information vào tên
A78: =IF($B78="","",IFERROR(_xlfn.XLOOKUP($B78,'ZONE C Vault Mapping'!$B:$B,'ZONE C Vault Mapping'!$A:$A),IFERROR(_xlfn.XLOOKUP($B78,'Các bảng bổ sung sang Zone C'!$C:$C,'Các bảng bổ sung sang Zone C'!$A:$A),""))) -> OCBCHANNEL | B78: sat_soa_ntdt_register_bank_account | C78: TrangNT | D78: =IF($B78="","",IFERROR(T(_xlfn.XLOOKUP($B78,'ZONE C Vault Mapping'!$B:$B,'ZONE C Vault Mapping'!$H:$H)),IFERROR(T(_xlfn.XLOOKUP($B78,'Các bảng bổ sung sang Zone C'!$C:$C,'Các bảng bổ sung sang Zone C'!$K:$K)),""))) -> Done | E78: Thụ | F78: Done
A79: =IF($B79="","",IFERROR(_xlfn.XLOOKUP($B79,'ZONE C Vault Mapping'!$B:$B,'ZONE C Vault Mapping'!$A:$A),IFERROR(_xlfn.XLOOKUP($B79,'Các bảng bổ sung sang Zone C'!$C:$C,'Các bảng bổ sung sang Zone C'!$A:$A),""))) -> OCBCHANNEL | B79: hub_trans_type_mapping | C79: TrangNT | D79: =IF($B79="","",IFERROR(T(_xlfn.XLOOKUP($B79,'ZONE C Vault Mapping'!$B:$B,'ZONE C Vault Mapping'!$H:$H)),IFERROR(T(_xlfn.XLOOKUP($B79,'Các bảng bổ sung sang Zone C'!$C:$C,'Các bảng bổ sung sang Zone C'!$K:$K)),""))) -> Cancel | E79: Thụ | F79: Checking | G79: 20260806: cancel
A80: =IF($B80="","",IFERROR(_xlfn.XLOOKUP($B80,'ZONE C Vault Mapping'!$B:$B,'ZONE C Vault Mapping'!$A:$A),IFERROR(_xlfn.XLOOKUP($B80,'Các bảng bổ sung sang Zone C'!$C:$C,'Các bảng bổ sung sang Zone C'!$A:$A),""))) -> OCBCHANNEL | B80: sat_trans_type_mapping | C80: TrangNT | D80: =IF($B80="","",IFERROR(T(_xlfn.XLOOKUP($B80,'ZONE C Vault Mapping'!$B:$B,'ZONE C Vault Mapping'!$H:$H)),IFERROR(T(_xlfn.XLOOKUP($B80,'Các bảng bổ sung sang Zone C'!$C:$C,'Các bảng bổ sung sang Zone C'!$K:$K)),""))) -> Cancel | E80: Thụ | F80: Checking | G80: 20260806: cancel
A81: =IF($B81="","",IFERROR(_xlfn.XLOOKUP($B81,'ZONE C Vault Mapping'!$B:$B,'ZONE C Vault Mapping'!$A:$A),IFERROR(_xlfn.XLOOKUP($B81,'Các bảng bổ sung sang Zone C'!$C:$C,'Các bảng bổ sung sang Zone C'!$A:$A),""))) -> OCBCHANNEL | B81: ref_ocbchannel_trans_type_mapping | C81: TrangNT | D81: =IF($B81="","",IFERROR(T(_xlfn.XLOOKUP($B81,'ZONE C Vault Mapping'!$B:$B,'ZONE C Vault Mapping'!$H:$H)),IFERROR(T(_xlfn.XLOOKUP($B81,'Các bảng bổ sung sang Zone C'!$C:$C,'Các bảng bổ sung sang Zone C'!$K:$K)),""))) -> Done | E81: Thụ | G81: 20260806: mới thêm
A82: =IF($B82="","",IFERROR(_xlfn.XLOOKUP($B82,'ZONE C Vault Mapping'!$B:$B,'ZONE C Vault Mapping'!$A:$A),IFERROR(_xlfn.XLOOKUP($B82,'Các bảng bổ sung sang Zone C'!$C:$C,'Các bảng bổ sung sang Zone C'!$A:$A),""))) -> OCBCHANNEL | B82: hub_user_login_log | C82: TrangNT | D82: =IF($B82="","",IFERROR(T(_xlfn.XLOOKUP($B82,'ZONE C Vault Mapping'!$B:$B,'ZONE C Vault Mapping'!$H:$H)),IFERROR(T(_xlfn.XLOOKUP($B82,'Các bảng bổ sung sang Zone C'!$C:$C,'Các bảng bổ sung sang Zone C'!$K:$K)),""))) -> Cancel | E82: Thụ | F82: Checking | G82: 20260810: cancel 20260806: đổi tên cột hashkey
A83: =IF($B83="","",IFERROR(_xlfn.XLOOKUP($B83,'ZONE C Vault Mapping'!$B:$B,'ZONE C Vault Mapping'!$A:$A),IFERROR(_xlfn.XLOOKUP($B83,'Các bảng bổ sung sang Zone C'!$C:$C,'Các bảng bổ sung sang Zone C'!$A:$A),""))) -> OCBCHANNEL | B83: non_his_sat_user_login_log | C83: TrangNT | D83: =IF($B83="","",IFERROR(T(_xlfn.XLOOKUP($B83,'ZONE C Vault Mapping'!$B:$B,'ZONE C Vault Mapping'!$H:$H)),IFERROR(T(_xlfn.XLOOKUP($B83,'Các bảng bổ sung sang Zone C'!$C:$C,'Các bảng bổ sung sang Zone C'!$K:$K)),""))) -> Done | E83: Thụ | F83: Checking | G83: 20260810: chuyển từ multiactive sat thành non-his sat (và thêm tiền tố non_his_ phía trước tên cũ). Điều chỉnh số lượng cột. đổi tên cột hashkey
A84: =IF($B84="","",IFERROR(_xlfn.XLOOKUP($B84,'ZONE C Vault Mapping'!$B:$B,'ZONE C Vault Mapping'!$A:$A),IFERROR(_xlfn.XLOOKUP($B84,'Các bảng bổ sung sang Zone C'!$C:$C,'Các bảng bổ sung sang Zone C'!$A:$A),""))) -> OCBCHANNEL | B84: hub_soa_cust_termdeposit | C84: TrangNT | D84: =IF($B84="","",IFERROR(T(_xlfn.XLOOKUP($B84,'ZONE C Vault Mapping'!$B:$B,'ZONE C Vault Mapping'!$H:$H)),IFERROR(T(_xlfn.XLOOKUP($B84,'Các bảng bổ sung sang Zone C'!$C:$C,'Các bảng bổ sung sang Zone C'!$K:$K)),""))) -> Done | E84: Thụ | F84: Done
A85: =IF($B85="","",IFERROR(_xlfn.XLOOKUP($B85,'ZONE C Vault Mapping'!$B:$B,'ZONE C Vault Mapping'!$A:$A),IFERROR(_xlfn.XLOOKUP($B85,'Các bảng bổ sung sang Zone C'!$C:$C,'Các bảng bổ sung sang Zone C'!$A:$A),""))) -> OCBCHANNEL | B85: link_soa_cust_termdeposit_customer | C85: TrangNT | D85: =IF($B85="","",IFERROR(T(_xlfn.XLOOKUP($B85,'ZONE C Vault Mapping'!$B:$B,'ZONE C Vault Mapping'!$H:$H)),IFERROR(T(_xlfn.XLOOKUP($B85,'Các bảng bổ sung sang Zone C'!$C:$C,'Các bảng bổ sung sang Zone C'!$K:$K)),""))) -> Done | E85: Thụ | F85: Done
A86: =IF($B86="","",IFERROR(_xlfn.XLOOKUP($B86,'ZONE C Vault Mapping'!$B:$B,'ZONE C Vault Mapping'!$A:$A),IFERROR(_xlfn.XLOOKUP($B86,'Các bảng bổ sung sang Zone C'!$C:$C,'Các bảng bổ sung sang Zone C'!$A:$A),""))) -> OCBCHANNEL | B86: link_soa_cust_termdeposit_branch | C86: TrangNT | D86: =IF($B86="","",IFERROR(T(_xlfn.XLOOKUP($B86,'ZONE C Vault Mapping'!$B:$B,'ZONE C Vault Mapping'!$H:$H)),IFERROR(T(_xlfn.XLOOKUP($B86,'Các bảng bổ sung sang Zone C'!$C:$C,'Các bảng bổ sung sang Zone C'!$K:$K)),""))) -> Done | E86: Thụ | F86: Done
A87: =IF($B87="","",IFERROR(_xlfn.XLOOKUP($B87,'ZONE C Vault Mapping'!$B:$B,'ZONE C Vault Mapping'!$A:$A),IFERROR(_xlfn.XLOOKUP($B87,'Các bảng bổ sung sang Zone C'!$C:$C,'Các bảng bổ sung sang Zone C'!$A:$A),""))) -> OCBCHANNEL | B87: sat_soa_cust_termdeposit_information | C87: TrangNT | D87: =IF($B87="","",IFERROR(T(_xlfn.XLOOKUP($B87,'ZONE C Vault Mapping'!$B:$B,'ZONE C Vault Mapping'!$H:$H)),IFERROR(T(_xlfn.XLOOKUP($B87,'Các bảng bổ sung sang Zone C'!$C:$C,'Các bảng bổ sung sang Zone C'!$K:$K)),""))) -> Done | E87: Thụ | F87: Checking | G87: 20260810: điều chỉnh số lượng trường trong sat
A88: =IF($B88="","",IFERROR(_xlfn.XLOOKUP($B88,'ZONE C Vault Mapping'!$B:$B,'ZONE C Vault Mapping'!$A:$A),IFERROR(_xlfn.XLOOKUP($B88,'Các bảng bổ sung sang Zone C'!$C:$C,'Các bảng bổ sung sang Zone C'!$A:$A),""))) -> OCBCHANNEL | B88: sat_soa_cust_termdeposit_detail | C88: TrangNT | D88: =IF($B88="","",IFERROR(T(_xlfn.XLOOKUP($B88,'ZONE C Vault Mapping'!$B:$B,'ZONE C Vault Mapping'!$H:$H)),IFERROR(T(_xlfn.XLOOKUP($B88,'Các bảng bổ sung sang Zone C'!$C:$C,'Các bảng bổ sung sang Zone C'!$K:$K)),""))) -> Done | E88: Thụ | F88: Done
A89: =IF($B89="","",IFERROR(_xlfn.XLOOKUP($B89,'ZONE C Vault Mapping'!$B:$B,'ZONE C Vault Mapping'!$A:$A),IFERROR(_xlfn.XLOOKUP($B89,'Các bảng bổ sung sang Zone C'!$C:$C,'Các bảng bổ sung sang Zone C'!$A:$A),""))) -> OCBCHANNEL | B89: hub_soa_hdtg_da_nang | C89: TrangNT | D89: =IF($B89="","",IFERROR(T(_xlfn.XLOOKUP($B89,'ZONE C Vault Mapping'!$B:$B,'ZONE C Vault Mapping'!$H:$H)),IFERROR(T(_xlfn.XLOOKUP($B89,'Các bảng bổ sung sang Zone C'!$C:$C,'Các bảng bổ sung sang Zone C'!$K:$K)),""))) -> Done | E89: Thụ | F89: Done
A90: =IF($B90="","",IFERROR(_xlfn.XLOOKUP($B90,'ZONE C Vault Mapping'!$B:$B,'ZONE C Vault Mapping'!$A:$A),IFERROR(_xlfn.XLOOKUP($B90,'Các bảng bổ sung sang Zone C'!$C:$C,'Các bảng bổ sung sang Zone C'!$A:$A),""))) -> OCBCHANNEL | B90: link_soa_hdtg_da_nang_customer | C90: TrangNT | D90: =IF($B90="","",IFERROR(T(_xlfn.XLOOKUP($B90,'ZONE C Vault Mapping'!$B:$B,'ZONE C Vault Mapping'!$H:$H)),IFERROR(T(_xlfn.XLOOKUP($B90,'Các bảng bổ sung sang Zone C'!$C:$C,'Các bảng bổ sung sang Zone C'!$K:$K)),""))) -> Done | E90: Thụ | F90: Done
A91: =IF($B91="","",IFERROR(_xlfn.XLOOKUP($B91,'ZONE C Vault Mapping'!$B:$B,'ZONE C Vault Mapping'!$A:$A),IFERROR(_xlfn.XLOOKUP($B91,'Các bảng bổ sung sang Zone C'!$C:$C,'Các bảng bổ sung sang Zone C'!$A:$A),""))) -> OCBCHANNEL | B91: link_soa_hdtg_da_nang_branch | C91: TrangNT | D91: =IF($B91="","",IFERROR(T(_xlfn.XLOOKUP($B91,'ZONE C Vault Mapping'!$B:$B,'ZONE C Vault Mapping'!$H:$H)),IFERROR(T(_xlfn.XLOOKUP($B91,'Các bảng bổ sung sang Zone C'!$C:$C,'Các bảng bổ sung sang Zone C'!$K:$K)),""))) -> Done | E91: Thụ | F91: Done
A92: =IF($B92="","",IFERROR(_xlfn.XLOOKUP($B92,'ZONE C Vault Mapping'!$B:$B,'ZONE C Vault Mapping'!$A:$A),IFERROR(_xlfn.XLOOKUP($B92,'Các bảng bổ sung sang Zone C'!$C:$C,'Các bảng bổ sung sang Zone C'!$A:$A),""))) -> OCBCHANNEL | B92: sat_soa_hdtg_da_nang_information | C92: TrangNT | D92: =IF($B92="","",IFERROR(T(_xlfn.XLOOKUP($B92,'ZONE C Vault Mapping'!$B:$B,'ZONE C Vault Mapping'!$H:$H)),IFERROR(T(_xlfn.XLOOKUP($B92,'Các bảng bổ sung sang Zone C'!$C:$C,'Các bảng bổ sung sang Zone C'!$K:$K)),""))) -> Done | E92: Thụ | F92: Checking | G92: 20260810: điều chỉnh số lượng trường trong sat
A93: =IF($B93="","",IFERROR(_xlfn.XLOOKUP($B93,'ZONE C Vault Mapping'!$B:$B,'ZONE C Vault Mapping'!$A:$A),IFERROR(_xlfn.XLOOKUP($B93,'Các bảng bổ sung sang Zone C'!$C:$C,'Các bảng bổ sung sang Zone C'!$A:$A),""))) -> OCBCHANNEL | B93: sat_soa_hdtg_da_nang_detail | C93: TrangNT | D93: =IF($B93="","",IFERROR(T(_xlfn.XLOOKUP($B93,'ZONE C Vault Mapping'!$B:$B,'ZONE C Vault Mapping'!$H:$H)),IFERROR(T(_xlfn.XLOOKUP($B93,'Các bảng bổ sung sang Zone C'!$C:$C,'Các bảng bổ sung sang Zone C'!$K:$K)),""))) -> Done | E93: Thụ | F93: Done
A94: =IF($B94="","",IFERROR(_xlfn.XLOOKUP($B94,'ZONE C Vault Mapping'!$B:$B,'ZONE C Vault Mapping'!$A:$A),IFERROR(_xlfn.XLOOKUP($B94,'Các bảng bổ sung sang Zone C'!$C:$C,'Các bảng bổ sung sang Zone C'!$A:$A),""))) -> FTP | B94: sat_branch_list | C94: TrangNT | D94: =IF($B94="","",IFERROR(T(_xlfn.XLOOKUP($B94,'ZONE C Vault Mapping'!$B:$B,'ZONE C Vault Mapping'!$H:$H)),IFERROR(T(_xlfn.XLOOKUP($B94,'Các bảng bổ sung sang Zone C'!$C:$C,'Các bảng bổ sung sang Zone C'!$K:$K)),""))) -> Cancel
A95: =IF($B95="","",IFERROR(_xlfn.XLOOKUP($B95,'ZONE C Vault Mapping'!$B:$B,'ZONE C Vault Mapping'!$A:$A),IFERROR(_xlfn.XLOOKUP($B95,'Các bảng bổ sung sang Zone C'!$C:$C,'Các bảng bổ sung sang Zone C'!$A:$A),""))) -> OCBCHANNEL | B95: link_branch_parent_branch | C95: TrangNT | D95: =IF($B95="","",IFERROR(T(_xlfn.XLOOKUP($B95,'ZONE C Vault Mapping'!$B:$B,'ZONE C Vault Mapping'!$H:$H)),IFERROR(T(_xlfn.XLOOKUP($B95,'Các bảng bổ sung sang Zone C'!$C:$C,'Các bảng bổ sung sang Zone C'!$K:$K)),""))) -> Done | E95: Thụ | G95: 20260806: mới thêm
A96: =IF($B96="","",IFERROR(_xlfn.XLOOKUP($B96,'ZONE C Vault Mapping'!$B:$B,'ZONE C Vault Mapping'!$A:$A),IFERROR(_xlfn.XLOOKUP($B96,'Các bảng bổ sung sang Zone C'!$C:$C,'Các bảng bổ sung sang Zone C'!$A:$A),""))) -> OCBCHANNEL | B96: sat_branch_mapping | C96: TrangNT | D96: =IF($B96="","",IFERROR(T(_xlfn.XLOOKUP($B96,'ZONE C Vault Mapping'!$B:$B,'ZONE C Vault Mapping'!$H:$H)),IFERROR(T(_xlfn.XLOOKUP($B96,'Các bảng bổ sung sang Zone C'!$C:$C,'Các bảng bổ sung sang Zone C'!$K:$K)),""))) -> Done | E96: Thụ | F96: Checking | G96: 20260810: bỏ trường parent_branch_code
A97: =IF($B97="","",IFERROR(_xlfn.XLOOKUP($B97,'ZONE C Vault Mapping'!$B:$B,'ZONE C Vault Mapping'!$A:$A),IFERROR(_xlfn.XLOOKUP($B97,'Các bảng bổ sung sang Zone C'!$C:$C,'Các bảng bổ sung sang Zone C'!$A:$A),""))) -> T24 | B97: ref_t24_ocbh_co_group | C97: TrangNT | D97: =IF($B97="","",IFERROR(T(_xlfn.XLOOKUP($B97,'ZONE C Vault Mapping'!$B:$B,'ZONE C Vault Mapping'!$H:$H)),IFERROR(T(_xlfn.XLOOKUP($B97,'Các bảng bổ sung sang Zone C'!$C:$C,'Các bảng bổ sung sang Zone C'!$K:$K)),""))) -> Done | E97: Thụ | F97: Done
A98: =IF($B98="","",IFERROR(_xlfn.XLOOKUP($B98,'ZONE C Vault Mapping'!$B:$B,'ZONE C Vault Mapping'!$A:$A),IFERROR(_xlfn.XLOOKUP($B98,'Các bảng bổ sung sang Zone C'!$C:$C,'Các bảng bổ sung sang Zone C'!$A:$A),""))) -> ESB | B98: hub_omni_transaction_hist | C98: TrangNT | D98: =IF($B98="","",IFERROR(T(_xlfn.XLOOKUP($B98,'ZONE C Vault Mapping'!$B:$B,'ZONE C Vault Mapping'!$H:$H)),IFERROR(T(_xlfn.XLOOKUP($B98,'Các bảng bổ sung sang Zone C'!$C:$C,'Các bảng bổ sung sang Zone C'!$K:$K)),""))) -> Cancel | E98: Thụ | F98: Checking | G98: 20260806: cancel
A99: =IF($B99="","",IFERROR(_xlfn.XLOOKUP($B99,'ZONE C Vault Mapping'!$B:$B,'ZONE C Vault Mapping'!$A:$A),IFERROR(_xlfn.XLOOKUP($B99,'Các bảng bổ sung sang Zone C'!$C:$C,'Các bảng bổ sung sang Zone C'!$A:$A),""))) -> ESB | B99: link_omni_transaction_hist_customer | C99: TrangNT | D99: =IF($B99="","",IFERROR(T(_xlfn.XLOOKUP($B99,'ZONE C Vault Mapping'!$B:$B,'ZONE C Vault Mapping'!$H:$H)),IFERROR(T(_xlfn.XLOOKUP($B99,'Các bảng bổ sung sang Zone C'!$C:$C,'Các bảng bổ sung sang Zone C'!$K:$K)),""))) -> Done | E99: Thụ | F99: Done
