Workbook

Sheet Hướng dẫn
B2: CHECKLIST REVIEW CODE MAPPING SILVER (DATA VAULT 2.0) SANG GOLD (DATA MART) – ZONE C OCB
B4: Mục đích
B5: Đội Data Engineer của Raffles dùng checklist này để tự rà soát code và mapping của từng bảng/khung nhìn Zone C trước khi gửi OCB review. Nội dung checklist lấy từ hai nguồn: các tiêu chí đã thống nhất với OCB (sheet "Checklist - Raffles" và "Quality check") và các lỗi thực tế ghi nhận trong quá trình review Batch 1 (Issue log). Cách kiểm tra của từng tiêu chí tham chiếu trực tiếp đến tài liệu OCB_DBX_ZONEC – Technical Document v1.1, mục III.4.2 "Quy tắc khi xử lí các bảng từ Silver".
B6: Cách sử dụng
B7: 1. Sheet "Checklist tiêu chí": mô tả điều kiện đạt và cách kiểm tra của từng tiêu chí, kèm mục tài liệu tham chiếu.
B8: 2. Sheet "Review theo bảng": mỗi dòng là một bảng/khung nhìn Gold. Với từng tiêu chí, DE chọn Pass / Fail / N/A từ danh sách chọn. Tiêu chí Fail phải ghi bằng chứng tại cột "Ghi chú / Bằng chứng lỗi" theo dạng: mã tiêu chí, tên file script, dòng code hoặc tên CTE liên quan.
B9: 3. Tỷ lệ lỗi tính tự động theo trọng số đã thống nhất với OCB: Nhóm 1 – Summary/Mapping 10%, Nhóm 2 – Logic 80%, Nhóm 3 – Optimization 10%. Một tiêu chí Fail thì cả nhóm đó tính là lỗi cho bảng đang xét.
B10: 4. Sheet "Tổng hợp Dashboard": tổng hợp số bảng Đạt / Không đạt theo batch và so với ngưỡng lỗi cho phép (Batch 1: 30%; Batch 2 và Batch 3: 20%).
B11: 5. Chỉ gửi code và mapping sang OCB khi bảng có kết luận "Đạt". Bảng "Không đạt" phải sửa theo pattern chuẩn nêu tại cột "Điều kiện đạt / Cách kiểm tra" rồi review lại.
B12: Bốn lỗi phải kiểm tra kỹ (rút từ Issue log Batch 1)
B13: - Điều kiện source_event_date <= :DATADT bị bỏ sót ở một vài bảng trong cùng script, hoặc đặt thêm cận dưới (>= start_date) làm bỏ sót bản ghi trạng thái mới nhất – Issue log #1.
B14: - Cùng một mục đích lấy bản ghi hiệu lực nhưng mỗi script lọc cdc_status một kiểu khác nhau – Issue log #2. Toàn bộ Zone C dùng một pattern duy nhất tại mục III.4.2.1.
... B16: - Bảng DIM sinh surrogate key bằng MAX(<DIM_ID>) + ROW_NUMBER(), trùng khóa khi chạy song song hoặc nạp lại lịch sử – Issue log #4. Dùng APPLY CHANGES … STORED AS SCD TYPE 2.

Sheet Checklist tiêu chí
A1: Nhóm | B1: Trọng số nhóm | C1: Mã | D1: Tiêu chí kiểm tra | E1: Điều kiện đạt / Cách kiểm tra | F1: Tham chiếu (Technical Document / Issue log / Checklist RVN-OCB)
A2: Nhóm 1 - Summary / Mapping | B2: 0.1 | C2: 1.1 | D2: Mapping đầy đủ từ Silver và nguồn upload sang Gold | E2: Đối chiếu tài liệu mapping source-to-target với script: đủ cột đầu ra, đủ bảng nguồn cần dùng, không thêm cột ngoài đặc tả. Ghi dữ liệu vào đúng catalog/schema đích ocb_datavault_${env}_curated.<schema>, không hard-code tên catalog. | F2: TDD mục III.4.1 Quy ước chung; Quality check tiêu chí 1
A3: Nhóm 1 - Summary / Mapping | B3: 0.1 | C3: 1.2 | D3: Danh sách bảng và khung nhìn khớp tài liệu thiết kế | E3: Danh sách đối tượng triển khai trong batch khớp danh sách đã thống nhất với OCB. Thay đổi phạm vi hoặc mô hình dữ liệu phải được thống nhất và cập nhật vào tài liệu trước khi triển khai. | F3: TDD v1.1 mục I.3 Phạm vi tài liệu; Plan điều chỉnh 5.3.3
A4: Nhóm 2 - Logic | B4: 0.8 | C4: 2.1 | D4: Chỉ lấy bản ghi Hub đang có hiệu lực | E4: Join hub_* với sts_hub_* theo pattern tại mục III.4.2.1: GROUP BY hashkey, HAVING max_by(cdc_status, source_event_date) = 'D' để lấy tập khóa đã xóa, sau đó LEFT JOIN và loại các khóa này khỏi kết quả. Chỉ giữ bản ghi đã xóa khi có yêu cầu nghiệp vụ và phải ghi rõ trong mapping. | F4: TDD v1.1 mục III.4.2.1; Checklist RVN-OCB #1; Issue log #3
A5: Nhóm 2 - Logic | B5: 0.8 | C5: 2.2 | D5: Dùng một pattern thống nhất để lấy bản ghi hiệu lực | E5: Toàn bộ script Zone C dùng chung một pattern max_by(cdc_status, source_event_date) trên sts_hub. Không để hai script cùng xử lý một loại logic theo hai cách khác nhau, ví dụ một script lọc cdc_status <> 'D' trực tiếp trên satellite, script khác lọc = 'D' trên sts_hub. | F5: TDD v1.1 mục III.4.2.1; Issue log #2
A6: Nhóm 2 - Logic | B6: 0.8 | C6: 2.3 | D6: Điều kiện trạng thái đặt ở lớp ngoài, không đặt trong ON của LEFT JOIN | E6: Điều kiện lọc trạng thái và điều kiện lấy bản ghi mới nhất đặt tại WHERE hoặc QUALIFY của lớp ngoài. Đặt trong ON của LEFT JOIN sẽ sai kết quả khi không match. Ngoại lệ được phép: join PIT với satellite theo source_event_date = <sat>_src_ev_dt là equi-join nên đặt trong ON. | F6: TDD v1.1 mục III.4.2.3 và III.4.2.4; Issue log #3
A7: Nhóm 2 - Logic | B7: 0.8 | C7: 2.4 | D7: Điều kiện source_event_date áp dụng nhất quán trong cùng script | E7: Mọi hub, satellite, link, effsat trong cùng một script đều chặn source_event_date <= TO_DATE(:DATADT,'yyyyMMdd'), không đặt cận dưới. Riêng nhóm bảng transaction tại mục "Các trường hợp đặc biệt" lọc source_event_date = :DATADT. Bảng PIT lọc theo snapshot_date. | F7: TDD v1.1 mục III.4.2 và mục "Các trường hợp đặc biệt"; Issue log #1
A8: Nhóm 2 - Logic | B8: 0.8 | C8: 2.5 | D8: Không lặp lại lỗi logic đã được xử lý trước đó | E8: Đối chiếu với các lỗi mà DA Data Vault đã xác nhận sửa ở các lần review trước; script viết lại trên nền tảng mới không quay lại logic cũ. Ghi rõ trong ghi chú các điểm đã từng bị sửa để reviewer đối chiếu nhanh. | F8: Issue log #1
A9: Nhóm 2 - Logic | B9: 0.8 | C9: 2.6 | D9: Bảng DIM áp dụng SCD Type 2 theo cơ chế APPLY CHANGES | E9: Bảng DIM dùng APPLY CHANGES INTO … KEYS (…) SEQUENCE BY … STORED AS SCD TYPE 2 trên streaming table. Không tự sinh surrogate key bằng MAX(<DIM_ID>) + ROW_NUMBER() vì trùng khóa khi chạy song song hoặc nạp lại dữ liệu lịch sử. | F9: TDD v1.1 mục III.2.3 và III.2.4; Issue log #4
A10: Nhóm 2 - Logic | B10: 0.8 | C10: 2.7 | D10: CASE WHEN đủ nhánh so với job hiện hữu | E10: So từng nhánh CASE WHEN với job on-prem tương ứng, gồm cả nhánh ELSE và giá trị mặc định. Giữ nguyên logic cũ nếu chưa có thay đổi được thống nhất; thay đổi phải ghi vào tài liệu mapping. | F10: Checklist RVN-OCB #10
A11: Nhóm 2 - Logic | B11: 0.8 | C11: 2.8 | D11: Cột SUM và COUNT xử lý giá trị NULL đúng | E11: Cột tổng hợp coalesce về 0 khi nghiệp vụ yêu cầu. Nếu code hiện hữu không dùng NVL thì giữ nguyên hành vi của code cũ và bổ sung NVL ở script đối soát để không lệch khi lấy hiệu số. | F11: Checklist RVN-OCB #11
A12: Nhóm 2 - Logic | B12: 0.8 | C12: 2.9 | D12: Subquery, custom function và điều kiện LIKE đúng ý nghĩa nghiệp vụ | E12: Đọc lại logic bên trong subquery, custom function và các điều kiện LIKE, xác nhận đúng ý nghĩa nghiệp vụ so với job hiện hữu, không chỉ đúng cú pháp. Ghi lại cách hiểu nghiệp vụ trong mapping để OCB xác nhận. | F12: Checklist RVN-OCB #6
A13: Nhóm 2 - Logic | B13: 0.8 | C13: 2.10 | D13: Aggregation lọc đúng kỳ dữ liệu | E13: Điều kiện lọc kỳ báo cáo đi kèm SUM/COUNT/AVG đúng phạm vi ngày hoặc tháng cần xử lý. Bảng nạp theo tháng lọc theo kỳ đang chạy, không quét toàn bộ lịch sử. | F13: Checklist RVN-OCB #7
... A21: Nhóm 3 - Optimization | B21: 0.1 | C21: 3.6 | D21: Window function dùng có chủ đích và có comment | E21: Chỉ dùng window function khi max_by hoặc QUALIFY không đáp ứng được yêu cầu nghiệp vụ. Khi dùng phải ghi comment nêu lý do ngay tại chỗ dùng. | F21: Checklist RVN-OCB #8

Sheet Review theo bảng
A1: STT | B1: Tên bảng / khung nhìn (Gold) | C1: Batch | D1: PIC review | E1: Ngày review | F1: NHÓM 1 - SUMMARY / MAPPING (trọng số 10%) | H1: NHÓM 2 - LOGIC (trọng số 80%) | T1: NHÓM 3 - OPTIMIZATION (trọng số 10%) | Z1: KẾT QUẢ TỔNG HỢP (tự động tính)
F2: Đủ mapping Silver → Gold (1.1) | G2: Danh sách bảng khớp thiết kế (1.2) | H2: Hub hiệu lực qua sts_hub (2.1) | I2: Một pattern lấy bản ghi hiệu lực (2.2) | J2: Điều kiện trạng thái ở lớp ngoài (2.3) | K2: source_event_date nhất quán (2.4) | L2: Không lặp lỗi đã xử lý (2.5) | M2: DIM SCD2 bằng APPLY CHANGES (2.6) | N2: CASE WHEN đủ nhánh (2.7) | O2: SUM/COUNT xử lý NULL (2.8) | P2: Subquery/function/ LIKE đúng nghiệp vụ (2.9) | Q2: Aggregation đúng kỳ dữ liệu (2.10) | R2: Join đúng key, link về hiện hành (2.11) | S2: Build từ CTE snapshot Silver (2.12) | T2: Không SELECT * (3.1) | U2: CTE không tính lại nhiều lần (3.2) | V2: Lọc trước join, partition pruning (3.3) | W2: Cache truy vấn dùng lại (3.4) | X2: MAX_BY thay ROW_NUMBER (3.5) | Y2: Window function có comment (3.6) | Z2: N1 Fail? | AA2: N2 Fail? | AB2: N3 Fail? | AC2: Tỷ lệ lỗi bảng | AD2: Ngưỡng cho phép | AE2: Kết luận | AF2: Ghi rõ: mã tiêu chí – file script – dòng/CTE
A3: 1 | B3: TCKH.V_BCN_THUNO | C3: Batch 2 | D3: QUANG | E3: 2026-08-11 | F3: Pass | G3: Pass | H3: Pass | I3: Pass | J3: Pass | K3: Pass | L3: Pass | M3: Pass | N3: Pass | O3: Pass | P3: Pass | Q3: Pass | R3: Pass | S3: Pass | T3: Pass | U3: Pass | V3: WARN | W3: Pass | X3: Pass | Y3: Pass | Z3: =IF(B3="","",IF(COUNTIF(F3:G3,"Fail")>0,1,0)) | AA3: =IF(B3="","",IF(COUNTIF(H3:S3,"Fail")>0,1,0)) | AB3: =IF(B3="","",IF(COUNTIF(T3:Y3,"Fail")>0,1,0)) | AC3: =IF(B3="","",0.1*Z3+0.8*AA3+0.1*AB3) | AD3: =IF(B3="","",IF(C3="Batch 1",0.3,0.2)) | AE3: =IF(B3="","",IF(AC3<=AD3,"Đạt","Không đạt")) | AF3: ╔══ WARN: 1 tiêu chí — 3.3 ▼ 3.3 — Filter trước khi join, tận dụng partition pruning • 1 bảng join trực tiếp mà không có filter riêng: tb_ar_bcn_dtl (bundle)
A4: 2 | B4: TCKH.V_BRANCH_LIST | C4: Batch 2 | D4: HOP | E4: 2026-08-11 | F4: Pass | G4: Pass | H4: Pass | I4: Pass | J4: Pass | K4: Pass | L4: Pass | M4: Pass | N4: Pass | O4: Pass | P4: Pass | Q4: Pass | R4: Pass | S4: Pass | T4: Pass | U4: Pass | V4: Pass | W4: Pass | X4: Pass | Y4: Pass | Z4: =IF(B4="","",IF(COUNTIF(F4:G4,"Fail")>0,1,0)) | AA4: =IF(B4="","",IF(COUNTIF(H4:S4,"Fail")>0,1,0)) | AB4: =IF(B4="","",IF(COUNTIF(T4:Y4,"Fail")>0,1,0)) | AC4: =IF(B4="","",0.1*Z4+0.8*AA4+0.1*AB4) | AD4: =IF(B4="","",IF(C4="Batch 1",0.3,0.2)) | AE4: =IF(B4="","",IF(AC4<=AD4,"Đạt","Không đạt")) | AF4: Đạt toàn bộ tiêu chí.
A5: 3 | B5: TCKH.V_CDR_AMT | C5: Batch 2 | D5: QUANG | E5: 2026-08-11 | F5: Pass | G5: Pass | H5: Pass | I5: Pass | J5: Pass | K5: Pass | L5: Pass | M5: Pass | N5: Pass | O5: Pass | P5: Pass | Q5: WARN | R5: Pass | S5: Pass | T5: Pass | U5: Pass | V5: Pass | W5: Pass | X5: Pass | Y5: Pass | Z5: =IF(B5="","",IF(COUNTIF(F5:G5,"Fail")>0,1,0)) | AA5: =IF(B5="","",IF(COUNTIF(H5:S5,"Fail")>0,1,0)) | AB5: =IF(B5="","",IF(COUNTIF(T5:Y5,"Fail")>0,1,0)) | AC5: =IF(B5="","",0.1*Z5+0.8*AA5+0.1*AB5) | AD5: =IF(B5="","",IF(C5="Batch 1",0.3,0.2)) | AE5: =IF(B5="","",IF(AC5<=AD5,"Đạt","Không đạt")) | AF5: ╔══ WARN: 1 tiêu chí — 2.10 ▼ 2.10 — Aggregation kèm filter date range chính xác • 1 khối tổng hợp không thấy filter theo ngày/tham số: SELECT tu V_ENTRY_STMT_QUYMO
A6: 4 | B6: TCKH.V_CDTK_DAILY | C6: Batch 2 | D6: QUANG | E6: 2026-08-11 | F6: Pass | G6: Pass | H6: Pass | I6: Pass | J6: Pass | K6: Pass | L6: Pass | M6: Pass | N6: Pass | O6: Pass | P6: Pass | Q6: Pass | R6: Pass | S6: Pass | T6: Pass | U6: Pass | V6: Pass | W6: Pass | X6: Pass | Y6: Pass | Z6: =IF(B6="","",IF(COUNTIF(F6:G6,"Fail")>0,1,0)) | AA6: =IF(B6="","",IF(COUNTIF(H6:S6,"Fail")>0,1,0)) | AB6: =IF(B6="","",IF(COUNTIF(T6:Y6,"Fail")>0,1,0)) | AC6: =IF(B6="","",0.1*Z6+0.8*AA6+0.1*AB6) | AD6: =IF(B6="","",IF(C6="Batch 1",0.3,0.2)) | AE6: =IF(B6="","",IF(AC6<=AD6,"Đạt","Không đạt")) | AF6: Đạt toàn bộ tiêu chí.
A7: 5 | B7: TCKH.V_CREDIT_LIMIT | C7: Batch 2 | D7: BAOANH | E7: 2026-08-11 | F7: Pass | G7: Pass | H7: Pass | I7: Pass | J7: Pass | K7: Pass | L7: Pass | M7: Pass | N7: Pass | O7: Pass | P7: Pass | Q7: Pass | R7: WARN | S7: Pass | T7: Pass | U7: WARN | V7: Pass | W7: WARN | X7: Pass | Y7: Pass | Z7: =IF(B7="","",IF(COUNTIF(F7:G7,"Fail")>0,1,0)) | AA7: =IF(B7="","",IF(COUNTIF(H7:S7,"Fail")>0,1,0)) | AB7: =IF(B7="","",IF(COUNTIF(T7:Y7,"Fail")>0,1,0)) | AC7: =IF(B7="","",0.1*Z7+0.8*AA7+0.1*AB7) | AD7: =IF(B7="","",IF(C7="Batch 1",0.3,0.2)) | AE7: =IF(B7="","",IF(AC7<=AD7,"Đạt","Không đạt")) | AF7: ╔══ WARN: 3 tiêu chí — 2.11, 3.2, 3.4 ▼ 2.11 — Join dùng key hợp lý, không lạm dụng UNION ALL + EXISTS/NOT EXISTS • join không có điều kiện bằng (=): ['h'] ▼ 3.2 — CTE không bị scan lại nhiều lần • CTE bị tham chiếu lại nhiều lần: hub_by_date x2 ▼ 3.4 — Sử dụng CACHE cho query lặp lại trong cùng luồng • 1 CTE nặng dùng lại >= 2 lần mà không có CACHE: hub_by_date
A8: 6 | B8: TCKH.V_CUSTOMER_SEGMENT_CMB | C8: Batch 2 | D8: PHAT | E8: 2026-08-11 | F8: Pass | G8: Pass | H8: Pass | I8: Pass | J8: Pass | K8: Pass | L8: Pass | M8: Pass | N8: Pass | O8: Pass | P8: Pass | Q8: Pass | R8: Pass | S8: WARN | T8: Pass | U8: Pass | V8: Pass | W8: Pass | X8: Pass | Y8: Pass | Z8: =IF(B8="","",IF(COUNTIF(F8:G8,"Fail")>0,1,0)) | AA8: =IF(B8="","",IF(COUNTIF(H8:S8,"Fail")>0,1,0)) | AB8: =IF(B8="","",IF(COUNTIF(T8:Y8,"Fail")>0,1,0)) | AC8: =IF(B8="","",0.1*Z8+0.8*AA8+0.1*AB8) | AD8: =IF(B8="","",IF(C8="Batch 1",0.3,0.2)) | AE8: =IF(B8="","",IF(AC8<=AD8,"Đạt","Không đạt")) | AF8: ╔══ WARN: 1 tiêu chí — 2.12 ▼ 2.12 — Build Gold từ CTE snapshot Silver, không build nhiều tầng chồng chéo • bảng bị đọc lại ở nhiều khối SELECT, xét gom thành 1 CTE: CUSTOMER_SEGMENT_CMB ở 2 khối
A9: 7 | B9: TCKH.V_CUSTOMER_SEGMENT_RB | C9: Batch 2 | D9: PHAT | E9: 2026-08-11 | F9: Pass | G9: Pass | H9: Pass | I9: Pass | J9: Pass | K9: Pass | L9: Pass | M9: Pass | N9: Pass | O9: Pass | P9: Pass | Q9: Pass | R9: Pass | S9: WARN | T9: Pass | U9: Pass | V9: Pass | W9: Pass | X9: Pass | Y9: Pass | Z9: =IF(B9="","",IF(COUNTIF(F9:G9,"Fail")>0,1,0)) | AA9: =IF(B9="","",IF(COUNTIF(H9:S9,"Fail")>0,1,0)) | AB9: =IF(B9="","",IF(COUNTIF(T9:Y9,"Fail")>0,1,0)) | AC9: =IF(B9="","",0.1*Z9+0.8*AA9+0.1*AB9) | AD9: =IF(B9="","",IF(C9="Batch 1",0.3,0.2)) | AE9: =IF(B9="","",IF(AC9<=AD9,"Đạt","Không đạt")) | AF9: ╔══ WARN: 1 tiêu chí — 2.12 ▼ 2.12 — Build Gold từ CTE snapshot Silver, không build nhiều tầng chồng chéo • bảng bị đọc lại ở nhiều khối SELECT, xét gom thành 1 CTE: CUSTOMER_SEGMENT_RAW ở 2 khối
A10: 8 | B10: TCKH.V_CUST_STATUS | C10: Batch 2 | D10: BAOANH | E10: 2026-08-11 | F10: Pass | G10: Pass | H10: Pass | I10: Pass | J10: Pass | K10: Pass | L10: Pass | M10: Pass | N10: Pass | O10: Pass | P10: Pass | Q10: Pass | R10: Pass | S10: Pass | T10: Pass | U10: Pass | V10: Pass | W10: Pass | X10: Pass | Y10: Pass | Z10: =IF(B10="","",IF(COUNTIF(F10:G10,"Fail")>0,1,0)) | AA10: =IF(B10="","",IF(COUNTIF(H10:S10,"Fail")>0,1,0)) | AB10: =IF(B10="","",IF(COUNTIF(T10:Y10,"Fail")>0,1,0)) | AC10: =IF(B10="","",0.1*Z10+0.8*AA10+0.1*AB10) | AD10: =IF(B10="","",IF(C10="Batch 1",0.3,0.2)) | AE10: =IF(B10="","",IF(AC10<=AD10,"Đạt","Không đạt")) | AF10: Đạt toàn bộ tiêu chí.
A11: 9 | B11: TCKH.V_CUST_STATUS_NEW | C11: Batch 2 | D11: BAOANH | E11: 2026-08-11 | F11: Pass | G11: Pass | H11: Pass | I11: Pass | J11: Pass | K11: Pass | L11: Pass | M11: Pass | N11: Pass | O11: Pass | P11: Pass | Q11: Pass | R11: Pass | S11: Pass | T11: Pass | U11: Pass | V11: Pass | W11: Pass | X11: Pass | Y11: Pass | Z11: =IF(B11="","",IF(COUNTIF(F11:G11,"Fail")>0,1,0)) | AA11: =IF(B11="","",IF(COUNTIF(H11:S11,"Fail")>0,1,0)) | AB11: =IF(B11="","",IF(COUNTIF(T11:Y11,"Fail")>0,1,0)) | AC11: =IF(B11="","",0.1*Z11+0.8*AA11+0.1*AB11) | AD11: =IF(B11="","",IF(C11="Batch 1",0.3,0.2)) | AE11: =IF(B11="","",IF(AC11<=AD11,"Đạt","Không đạt")) | AF11: Đạt toàn bộ tiêu chí.
A12: 10 | B12: TCKH.V_FTP_003 | C12: Batch 2 | D12: PHAT | E12: 2026-08-11 | F12: Pass | G12: Pass | H12: Pass | I12: Pass | J12: Pass | K12: Pass | L12: Pass | M12: Pass | N12: Pass | O12: Pass | P12: Pass | Q12: Pass | R12: Pass | S12: WARN | T12: Pass | U12: Pass | V12: Pass | W12: Pass | X12: Pass | Y12: Pass | Z12: =IF(B12="","",IF(COUNTIF(F12:G12,"Fail")>0,1,0)) | AA12: =IF(B12="","",IF(COUNTIF(H12:S12,"Fail")>0,1,0)) | AB12: =IF(B12="","",IF(COUNTIF(T12:Y12,"Fail")>0,1,0)) | AC12: =IF(B12="","",0.1*Z12+0.8*AA12+0.1*AB12) | AD12: =IF(B12="","",IF(C12="Batch 1",0.3,0.2)) | AE12: =IF(B12="","",IF(AC12<=AD12,"Đạt","Không đạt")) | AF12: ╔══ WARN: 1 tiêu chí — 2.12 ▼ 2.12 — Build Gold từ CTE snapshot Silver, không build nhiều tầng chồng chéo • bảng bị đọc lại ở nhiều khối SELECT, xét gom thành 1 CTE: calendar ở 2 khối
A13: 11 | B13: TCKH.V_HT_CP_UPL | C13: Batch 2 | D13: PHAT | E13: 2026-08-11 | F13: Pass | G13: Pass | H13: Pass | I13: Pass | J13: Pass | K13: Pass | L13: Pass | M13: Pass | N13: Pass | O13: Pass | P13: Pass | Q13: Pass | R13: Pass | S13: Pass | T13: Pass | U13: Pass | V13: Pass | W13: Pass | X13: Pass | Y13: Pass | Z13: =IF(B13="","",IF(COUNTIF(F13:G13,"Fail")>0,1,0)) | AA13: =IF(B13="","",IF(COUNTIF(H13:S13,"Fail")>0,1,0)) | AB13: =IF(B13="","",IF(COUNTIF(T13:Y13,"Fail")>0,1,0)) | AC13: =IF(B13="","",0.1*Z13+0.8*AA13+0.1*AB13) | AD13: =IF(B13="","",IF(C13="Batch 1",0.3,0.2)) | AE13: =IF(B13="","",IF(AC13<=AD13,"Đạt","Không đạt")) | AF13: Đạt toàn bộ tiêu chí.
A14: 12 | B14: TCKH.V_LNSCHD_AVY | C14: Batch 2 | D14: BAOANH | E14: 2026-08-11 | F14: Pass | G14: Pass | H14: Pass | I14: Pass | J14: Pass | K14: Pass | L14: Pass | M14: Pass | N14: Pass | O14: WARN | P14: Pass | Q14: Pass | R14: WARN | S14: Pass | T14: Pass | U14: WARN | V14: WARN | W14: WARN | X14: Pass | Y14: Pass | Z14: =IF(B14="","",IF(COUNTIF(F14:G14,"Fail")>0,1,0)) | AA14: =IF(B14="","",IF(COUNTIF(H14:S14,"Fail")>0,1,0)) | AB14: =IF(B14="","",IF(COUNTIF(T14:Y14,"Fail")>0,1,0)) | AC14: =IF(B14="","",0.1*Z14+0.8*AA14+0.1*AB14) | AD14: =IF(B14="","",IF(C14="Batch 1",0.3,0.2)) | AE14: =IF(B14="","",IF(AC14<=AD14,"Đạt","Không đạt")) | AF14: ╔══ FAIL: 1 tiêu chí — X.1 ▼ X.1 — [Bổ sung] Link phải rút về current trước khi join (chống fan-out) [bổ sung, không tính điểm — Technical Document ZoneC v1.1, mục III.4.2.3] • Lý do: 2 bảng link_* join trực tiếp mà chưa rút về current, sẽ nhân đôi số dòng: link_loans_limit (dong 470), link_loans_payment_due (dong 306) → Cách sửa: Theo Technical Document III.4.2.3: rút link về một dòng cho mỗi driving key trước khi join vào fact/dim — SELECT <driving_hk>, max_by(<target_hk>, source_event_date) FROM link_<x> WHERE source_event_date <= :DATADT GROUP BY <driving_hk>. Quan hệ M:N thì khử trùng ở mức link_hashkey, không partition theo một phía. Join link thô rồi SUM sẽ nhân đôi số tiền. ╔══ WARN: 5 tiêu chí — 2.8, 2.11, 3.2, 3.3, 3.4 ▼ 2.8 — Cột SUM/COUNT được COALESCE/NVL hợp lý • 1 biểu thức tổng hợp chưa coalesce: shd_amount = SUM(shd_amount) • khi đối soát với hệ thống cũ phải bọc NVL/ISNULL CẢ HAI phía để không lệch khi trừ (Checklist RVN-OCB #11) ▼ 2.11 — Join dùng key hợp lý, không lạm dụng UNION ALL + EXISTS/NOT EXISTS • join không có điều kiện bằng (=): ['h', 's'] ▼ 3.2 — CTE không bị scan lại nhiều lần • CTE bị tham chiếu lại nhiều lần: calendar_dates x3, hub_loans_by_date x2, hub_md_deal_by_date x2, cte_snap_sts_hub_loans_payment_due x2, cte_snap_sat_loans_payment_due_information x2, cte_snap_sat_loans_payment_due_overdue x2, payment_due_link_by_date x2, pdpd_hub_by_date x2 ▼ 3.3 — Filter trước khi join, tận dụng partition pruning • 12 bảng join trực tiếp mà không có filter riêng: hub_limit (lim), hub_loans (h), hub_md_deal (md), link_loans_limit (ll), link_loans_payment_due (l), sat_limit_information (info), sat_loans_schedule (s), sat_md_deal_information (di) ▼ 3.4 — Sử dụng CACHE cho query lặp lại trong cùng luồng • 8 CTE nặng dùng lại >= 2 lần mà không có CACHE: calendar_dates, cte_snap_sat_loans_payment_due_information, cte_snap_sat_loans_payment_due_overdue, cte_snap_sts_hub_loans_payment_due, hub_loans_by_date, hub_md_deal_by_date, payment_due_link_by_date, pdpd_hub_by_date
... A93: 91 | B93: TCIMPORT.FACT_BPM_AP_TAT | C93: Batch 2 | D93: LINH | E93: 2026-08-11 | F93: Pass | G93: Pass | H93: Pass | I93: Pass | J93: Pass | K93: Pass | L93: Pass | M93: Pass | N93: Pass | O93: Pass | P93: Pass | Q93: Pass | R93: Pass | S93: Pass | T93: Pass | U93: Pass | V93: WARN | W93: Pass | X93: Pass | Y93: Pass | Z93: =IF(B93="","",IF(COUNTIF(F93:G93,"Fail")>0,1,0)) | AA93: =IF(B93="","",IF(COUNTIF(H93:S93,"Fail")>0,1,0)) | AB93: =IF(B93="","",IF(COUNTIF(T93:Y93,"Fail")>0,1,0)) | AC93: =IF(B93="","",0.1*Z93+0.8*AA93+0.1*AB93) | AD93: =IF(B93="","",IF(C93="Batch 1",0.3,0.2)) | AE93: =IF(B93="","",IF(AC93<=AD93,"Đạt","Không đạt")) | AF93: ╔══ WARN: 1 tiêu chí — 3.3 ▼ 3.3 — Filter trước khi join, tận dụng partition pruning • 1 bảng join trực tiếp mà không có filter riêng: bpm_v_application (app)
A94: 92 | Z94: =IF(B94="","",IF(COUNTIF(F94:G94,"Fail")>0,1,0)) | AA94: =IF(B94="","",IF(COUNTIF(H94:S94,"Fail")>0,1,0)) | AB94: =IF(B94="","",IF(COUNTIF(T94:Y94,"Fail")>0,1,0)) | AC94: =IF(B94="","",0.1*Z94+0.8*AA94+0.1*AB94) | AD94: =IF(B94="","",IF(C94="Batch 1",0.3,0.2)) | AE94: =IF(B94="","",IF(AC94<=AD94,"Đạt","Không đạt"))
A95: 93 | Z95: =IF(B95="","",IF(COUNTIF(F95:G95,"Fail")>0,1,0)) | AA95: =IF(B95="","",IF(COUNTIF(H95:S95,"Fail")>0,1,0)) | AB95: =IF(B95="","",IF(COUNTIF(T95:Y95,"Fail")>0,1,0)) | AC95: =IF(B95="","",0.1*Z95+0.8*AA95+0.1*AB95) | AD95: =IF(B95="","",IF(C95="Batch 1",0.3,0.2)) | AE95: =IF(B95="","",IF(AC95<=AD95,"Đạt","Không đạt"))
A96: 94 | Z96: =IF(B96="","",IF(COUNTIF(F96:G96,"Fail")>0,1,0)) | AA96: =IF(B96="","",IF(COUNTIF(H96:S96,"Fail")>0,1,0)) | AB96: =IF(B96="","",IF(COUNTIF(T96:Y96,"Fail")>0,1,0)) | AC96: =IF(B96="","",0.1*Z96+0.8*AA96+0.1*AB96) | AD96: =IF(B96="","",IF(C96="Batch 1",0.3,0.2)) | AE96: =IF(B96="","",IF(AC96<=AD96,"Đạt","Không đạt"))
A97: 95 | Z97: =IF(B97="","",IF(COUNTIF(F97:G97,"Fail")>0,1,0)) | AA97: =IF(B97="","",IF(COUNTIF(H97:S97,"Fail")>0,1,0)) | AB97: =IF(B97="","",IF(COUNTIF(T97:Y97,"Fail")>0,1,0)) | AC97: =IF(B97="","",0.1*Z97+0.8*AA97+0.1*AB97) | AD97: =IF(B97="","",IF(C97="Batch 1",0.3,0.2)) | AE97: =IF(B97="","",IF(AC97<=AD97,"Đạt","Không đạt"))
A98: 96 | Z98: =IF(B98="","",IF(COUNTIF(F98:G98,"Fail")>0,1,0)) | AA98: =IF(B98="","",IF(COUNTIF(H98:S98,"Fail")>0,1,0)) | AB98: =IF(B98="","",IF(COUNTIF(T98:Y98,"Fail")>0,1,0)) | AC98: =IF(B98="","",0.1*Z98+0.8*AA98+0.1*AB98) | AD98: =IF(B98="","",IF(C98="Batch 1",0.3,0.2)) | AE98: =IF(B98="","",IF(AC98<=AD98,"Đạt","Không đạt"))
A99: 97 | Z99: =IF(B99="","",IF(COUNTIF(F99:G99,"Fail")>0,1,0)) | AA99: =IF(B99="","",IF(COUNTIF(H99:S99,"Fail")>0,1,0)) | AB99: =IF(B99="","",IF(COUNTIF(T99:Y99,"Fail")>0,1,0)) | AC99: =IF(B99="","",0.1*Z99+0.8*AA99+0.1*AB99) | AD99: =IF(B99="","",IF(C99="Batch 1",0.3,0.2)) | AE99: =IF(B99="","",IF(AC99<=AD99,"Đạt","Không đạt"))
A100: 98 | Z100: =IF(B100="","",IF(COUNTIF(F100:G100,"Fail")>0,1,0)) | AA100: =IF(B100="","",IF(COUNTIF(H100:S100,"Fail")>0,1,0)) | AB100: =IF(B100="","",IF(COUNTIF(T100:Y100,"Fail")>0,1,0)) | AC100: =IF(B100="","",0.1*Z100+0.8*AA100+0.1*AB100) | AD100: =IF(B100="","",IF(C100="Batch 1",0.3,0.2)) | AE100: =IF(B100="","",IF(AC100<=AD100,"Đạt","Không đạt"))
A101: 99 | Z101: =IF(B101="","",IF(COUNTIF(F101:G101,"Fail")>0,1,0)) | AA101: =IF(B101="","",IF(COUNTIF(H101:S101,"Fail")>0,1,0)) | AB101: =IF(B101="","",IF(COUNTIF(T101:Y101,"Fail")>0,1,0)) | AC101: =IF(B101="","",0.1*Z101+0.8*AA101+0.1*AB101) | AD101: =IF(B101="","",IF(C101="Batch 1",0.3,0.2)) | AE101: =IF(B101="","",IF(AC101<=AD101,"Đạt","Không đạt"))
A102: 100 | Z102: =IF(B102="","",IF(COUNTIF(F102:G102,"Fail")>0,1,0)) | AA102: =IF(B102="","",IF(COUNTIF(H102:S102,"Fail")>0,1,0)) | AB102: =IF(B102="","",IF(COUNTIF(T102:Y102,"Fail")>0,1,0)) | AC102: =IF(B102="","",0.1*Z102+0.8*AA102+0.1*AB102) | AD102: =IF(B102="","",IF(C102="Batch 1",0.3,0.2)) | AE102: =IF(B102="","",IF(AC102<=AD102,"Đạt","Không đạt"))
A103: 101 | Z103: =IF(B103="","",IF(COUNTIF(F103:G103,"Fail")>0,1,0)) | AA103: =IF(B103="","",IF(COUNTIF(H103:S103,"Fail")>0,1,0)) | AB103: =IF(B103="","",IF(COUNTIF(T103:Y103,"Fail")>0,1,0)) | AC103: =IF(B103="","",0.1*Z103+0.8*AA103+0.1*AB103) | AD103: =IF(B103="","",IF(C103="Batch 1",0.3,0.2)) | AE103: =IF(B103="","",IF(AC103<=AD103,"Đạt","Không đạt"))
A104: 102 | Z104: =IF(B104="","",IF(COUNTIF(F104:G104,"Fail")>0,1,0)) | AA104: =IF(B104="","",IF(COUNTIF(H104:S104,"Fail")>0,1,0)) | AB104: =IF(B104="","",IF(COUNTIF(T104:Y104,"Fail")>0,1,0)) | AC104: =IF(B104="","",0.1*Z104+0.8*AA104+0.1*AB104) | AD104: =IF(B104="","",IF(C104="Batch 1",0.3,0.2)) | AE104: =IF(B104="","",IF(AC104<=AD104,"Đạt","Không đạt"))
A105: 103 | Z105: =IF(B105="","",IF(COUNTIF(F105:G105,"Fail")>0,1,0)) | AA105: =IF(B105="","",IF(COUNTIF(H105:S105,"Fail")>0,1,0)) | AB105: =IF(B105="","",IF(COUNTIF(T105:Y105,"Fail")>0,1,0)) | AC105: =IF(B105="","",0.1*Z105+0.8*AA105+0.1*AB105) | AD105: =IF(B105="","",IF(C105="Batch 1",0.3,0.2)) | AE105: =IF(B105="","",IF(AC105<=AD105,"Đạt","Không đạt"))
... A200: 198 | Z200: =IF(B200="","",IF(COUNTIF(F200:G200,"Fail")>0,1,0)) | AA200: =IF(B200="","",IF(COUNTIF(H200:S200,"Fail")>0,1,0)) | AB200: =IF(B200="","",IF(COUNTIF(T200:Y200,"Fail")>0,1,0)) | AC200: =IF(B200="","",0.1*Z200+0.8*AA200+0.1*AB200) | AD200: =IF(B200="","",IF(C200="Batch 1",0.3,0.2)) | AE200: =IF(B200="","",IF(AC200<=AD200,"Đạt","Không đạt"))

Sheet Tổng hợp Dashboard
B2: TỔNG HỢP KẾT QUẢ REVIEW CODE THEO BATCH – ZONE C OCB
B4: Batch | C4: Ngưỡng lỗi cho phép | D4: Số bảng đã review | E4: Số bảng Đạt | F4: Số bảng Không đạt | G4: Tỷ lệ lỗi bình quân | H4: Tỷ lệ bảng Không đạt | I4: Kết luận Batch
B5: Batch 1 | C5: 0.3 | D5: =COUNTIF('Review theo bảng'!$C$3:$C$200,B5) | E5: =COUNTIFS('Review theo bảng'!$C$3:$C$200,B5,'Review theo bảng'!$AE$3:$AE$200,"Đạt") | F5: =COUNTIFS('Review theo bảng'!$C$3:$C$200,B5,'Review theo bảng'!$AE$3:$AE$200,"Không đạt") | G5: =IFERROR(AVERAGEIF('Review theo bảng'!$C$3:$C$200,B5,'Review theo bảng'!$AC$3:$AC$200),0) | H5: =IFERROR(F5/D5,0) | I5: =IF(D5=0,"Chưa có dữ liệu",IF(H5<=C5,"Đạt yêu cầu","Không đạt yêu cầu"))
B6: Batch 2 | C6: 0.2 | D6: =COUNTIF('Review theo bảng'!$C$3:$C$200,B6) | E6: =COUNTIFS('Review theo bảng'!$C$3:$C$200,B6,'Review theo bảng'!$AE$3:$AE$200,"Đạt") | F6: =COUNTIFS('Review theo bảng'!$C$3:$C$200,B6,'Review theo bảng'!$AE$3:$AE$200,"Không đạt") | G6: =IFERROR(AVERAGEIF('Review theo bảng'!$C$3:$C$200,B6,'Review theo bảng'!$AC$3:$AC$200),0) | H6: =IFERROR(F6/D6,0) | I6: =IF(D6=0,"Chưa có dữ liệu",IF(H6<=C6,"Đạt yêu cầu","Không đạt yêu cầu"))
B7: Batch 3 | C7: 0.2 | D7: =COUNTIF('Review theo bảng'!$C$3:$C$200,B7) | E7: =COUNTIFS('Review theo bảng'!$C$3:$C$200,B7,'Review theo bảng'!$AE$3:$AE$200,"Đạt") | F7: =COUNTIFS('Review theo bảng'!$C$3:$C$200,B7,'Review theo bảng'!$AE$3:$AE$200,"Không đạt") | G7: =IFERROR(AVERAGEIF('Review theo bảng'!$C$3:$C$200,B7,'Review theo bảng'!$AC$3:$AC$200),0) | H7: =IFERROR(F7/D7,0) | I7: =IF(D7=0,"Chưa có dữ liệu",IF(H7<=C7,"Đạt yêu cầu","Không đạt yêu cầu"))
B9: Ghi chú: Tỷ lệ lỗi bình quân và kết luận lấy tự động từ sheet "Review theo bảng" (cột AE và AG). Ngưỡng lỗi theo thống nhất với OCB: Batch 1 tối đa 30%, Batch 2 và Batch 3 tối đa 20% (sheet "Quality check").

Sheet Auto-check chi tiết
A1: Object Gold | B1: Profile | C1: Mã | D1: Nhóm | E1: Tiêu chí | F1: Kết quả máy | G1: Ghi vào Excel | H1: Bằng chứng / số dòng | I1: Cách sửa | J1: File
A2: TCKH.V_BCN_THUNO | B2: GOLD_DERIVED | C2: 1.1 | D2: Nhom 1 - Mapping | E2: Đầy đủ mapping từ Silver/manual sang Gold | F2: PASS | G2: Pass | H2: workbook 001. OCB_GOLD_TCKH_V_BCN_THUNO_QUANG.xlsx: thiết kế 40 field, SQL có 40 cột | I2: Mở workbook thiết kế, đối chiếu block FIELD MAPPING với danh sách cột trong câu SELECT/INSERT của file SQL. Cột nào thiếu thì bổ sung vào SQL; cột nào SQL có mà thiết kế không có thì bổ sung vào workbook hoặc bỏ khỏi SQL. | J2: 001. OCB_GOLD_TCKH_V_BCN_THUNO_QUANG.xlsx [Script SQL: V_BCN_THUNO]
A3: TCKH.V_BCN_THUNO | B3: GOLD_DERIVED | C3: 1.2 | D3: Nhom 1 - Mapping | E3: Danh sách bảng/view Gold khớp tài liệu thiết kế đã duyệt | F3: PASS | G3: Pass | H3: V_BCN_THUNO có workbook thiết kế: 001. OCB_GOLD_TCKH_V_BCN_THUNO_QUANG.xlsx | I3: Đảm bảo object có workbook thiết kế tương ứng trong thư mục --mapping-dir. Muốn đối chiếu với danh sách đã duyệt thì chạy thêm tham số --gold-list "<file danh sách Gold>.xlsx". | J3: 001. OCB_GOLD_TCKH_V_BCN_THUNO_QUANG.xlsx [Script SQL: V_BCN_THUNO]
A4: TCKH.V_BCN_THUNO | B4: GOLD_DERIVED | C4: 2.1 | D4: Nhom 2 - Logic | E4: Chỉ lấy bản ghi active, loại bản ghi đã xóa (qua sts_hub) | F4: N-A | G4: Pass | H4: khong ap dung cho profile GOLD_DERIVED | I4: Theo Technical Document mục III.4.2.1: với mỗi hub_<ent> phải thêm 2 CTE — (1) <ent>_sts_del đọc sts_hub_<ent>, GROUP BY hashkey, HAVING max_by(cdc_status, source_event_date) = 'D'; (2) <ent>_active đọc hub_<ent> LEFT JOIN <ent>_sts_del rồi lọc d.<hashkey> IS NULL. Tuyệt đối KHÔNG lọc cdc_status trong satellite — trạng thái xóa chỉ lọc ở sts_hub. | J4: 001. OCB_GOLD_TCKH_V_BCN_THUNO_QUANG.xlsx [Script SQL: V_BCN_THUNO]
A5: TCKH.V_BCN_THUNO | B5: GOLD_DERIVED | C5: 2.2 | D5: Nhom 2 - Logic | E5: Thống nhất MỘT pattern duy nhất xác định bản ghi active mới nhất | F5: N-A | G5: Pass | H5: khong ap dung cho profile GOLD_DERIVED | I5: Toàn bộ script trong batch phải dùng cùng một cách lấy bản ghi mới nhất: max_by(<cột>, source_event_date) + GROUP BY hashkey. Không để file này dùng ROW_NUMBER, file kia dùng max_by. Hướng lọc cdc_status cũng phải nhất quán (luôn là loại 'D', không có chỗ nào giữ 'D'). | J5: 001. OCB_GOLD_TCKH_V_BCN_THUNO_QUANG.xlsx [Script SQL: V_BCN_THUNO]
A6: TCKH.V_BCN_THUNO | B6: GOLD_DERIVED | C6: 2.3 | D6: Nhom 2 - Logic | E6: Điều kiện lọc trạng thái đặt SAU khi xác định bản ghi mới nhất | F6: PASS | G6: Pass | H6: không có điều kiện trạng thái nào lồng trong JOIN ON | I6: Chuyển các điều kiện cdc_status / rn = 1 ra khỏi phần ON của LEFT JOIN, đưa vào WHERE hoặc QUALIFY của chính subquery/CTE lấy dữ liệu. Đặt trong ON của LEFT JOIN thì khi không match sẽ ra NULL âm thầm, sai kết quả (Issue log #3). Riêng pattern PIT (sat.source_event_date = p.<sat>_src_ev_dt) và 49 bảng transaction được phép đặt trong ON. | J6: 001. OCB_GOLD_TCKH_V_BCN_THUNO_QUANG.xlsx [Script SQL: V_BCN_THUNO]
A7: TCKH.V_BCN_THUNO | B7: GOLD_DERIVED | C7: 2.4 | D7: Nhom 2 - Logic | E7: source_event_date áp dụng đúng dạng theo loại bảng | F7: N-A | G7: Pass | H7: khong ap dung cho profile GOLD_DERIVED | I7: Bảng thường: WHERE source_event_date <= TO_DATE(:DATADT,'yyyyMMdd') và KHÔNG đặt cận dưới (>= start_date) vì sẽ bỏ sót bản ghi mới nhất nằm trước khoảng thời gian. Riêng 49 bảng transaction ở mục 'Các trường hợp đặc biệt' của Technical Document (sat_stmt_entry_*, sat_categ_entry_*, sat_account_balance, sat_funds_transfer_*, sat_gl_trace_*, …) phải dùng source_event_date = :DATADT. Danh sách đầy đủ ở tools/gold_review/doc_standard.py. | J7: 001. OCB_GOLD_TCKH_V_BCN_THUNO_QUANG.xlsx [Script SQL: V_BCN_THUNO]
A8: TCKH.V_BCN_THUNO | B8: GOLD_DERIVED | C8: 2.5 | D8: Nhom 2 - Logic | E8: Không lặp lại lỗi logic cũ đã được DA Data Vault fix | F8: PASS | G8: Pass | H8: không trùng lỗi nào trong Issue log của DA Data Vault | I8: Sửa đúng các dòng được chỉ ra ở trên theo pattern chuẩn: lấy bản ghi mới nhất bằng max_by(<cột>, source_event_date) + GROUP BY hashkey; trạng thái xoá lọc ở sts_hub_* bằng HAVING max_by(cdc_status, source_event_date) = 'D' rồi anti-join IS NULL; không đặt cdc_status / rn = 1 trong ON hay trong subquery của JOIN; surrogate key DIM không sinh bằng MAX(<DIM_ID>) + ROW_NUMBER(). Danh sách lỗi lấy từ 'ZoneC Mapping - Iss log.xlsx' sheet Issue; OCB trả lỗi mới thì thêm 1 regex vào tools/gold_review/engine/known_issues.json để lần sau tự bắt được. | J8: 001. OCB_GOLD_TCKH_V_BCN_THUNO_QUANG.xlsx [Script SQL: V_BCN_THUNO]
A9: TCKH.V_BCN_THUNO | B9: GOLD_DERIVED | C9: 2.6 | D9: Nhom 2 - Logic | E9: SCD Type 2 cho bảng DIM áp dụng đúng kỹ thuật đã thống nhất | F9: N-A | G9: Pass | H9: object không phải bảng DIM nên không áp dụng SCD Type 2 | I9: Dùng APPLY CHANGES INTO <bảng>_scd FROM STREAM(stg_<ent>_changes) KEYS (<hashkey>) SEQUENCE BY source_event_date STORED AS SCD TYPE 2 TRACK HISTORY ON (...) — Databricks tự quản __START_AT/__END_AT. Nếu tự quản thì phải có cột effective_date/end_date/current_flag. TUYỆT ĐỐI không sinh surrogate key bằng MAX(<DIM_ID>) + ROW_NUMBER() vì trùng khi chạy song song hoặc load lại lịch sử (Issue log #4). | J9: 001. OCB_GOLD_TCKH_V_BCN_THUNO_QUANG.xlsx [Script SQL: V_BCN_THUNO]
A10: TCKH.V_BCN_THUNO | B10: GOLD_DERIVED | C10: 2.7 | D10: Nhom 2 - Logic | E10: CASE WHEN cover đủ nhánh như job on-prem | F10: PASS | G10: Pass | H10: cả 1 CASE đều có nhánh ELSE | I10: Mở job on-prem tương ứng (DataStage DSX hoặc SQL cũ), đối chiếu từng nhánh WHEN và cả nhánh ELSE. CASE không có ELSE sẽ trả NULL âm thầm — xác nhận đó là ý muốn hay thiếu nhánh. | J10: 001. OCB_GOLD_TCKH_V_BCN_THUNO_QUANG.xlsx [Script SQL: V_BCN_THUNO]
A11: TCKH.V_BCN_THUNO | B11: GOLD_DERIVED | C11: 2.8 | D11: Nhom 2 - Logic | E11: Cột SUM/COUNT được COALESCE/NVL hợp lý | F11: PASS | G11: Pass | H11: mọi SUM/COUNT đều đã coalesce (trực tiếp hoặc ở lớp ngoài) | I11: Bọc COALESCE(SUM(...), 0) cho các cột tổng hợp cần trả 0 khi không có dòng. Nếu code cũ không bọc thì giữ nguyên logic nhưng khi đối soát số liệu với hệ thống cũ phải bọc NVL/ISNULL ở CẢ HAI phía để không lệch khi trừ. | J11: 001. OCB_GOLD_TCKH_V_BCN_THUNO_QUANG.xlsx [Script SQL: V_BCN_THUNO]
A12: TCKH.V_BCN_THUNO | B12: GOLD_DERIVED | C12: 2.9 | D12: Nhom 2 - Logic | E12: Subquery / custom function / điều kiện LIKE đúng ý nghĩa nghiệp vụ | F12: N-A | G12: Pass | H12: script không có điều kiện LIKE hay scalar subquery nào | I12: Đọc lại từng điều kiện LIKE và từng subquery, đối chiếu ý nghĩa nghiệp vụ với on-prem — đúng cú pháp không đủ. Chú ý pattern LIKE có ký tự % ở đầu/cuối và phân biệt chữ hoa/thường. | J12: 001. OCB_GOLD_TCKH_V_BCN_THUNO_QUANG.xlsx [Script SQL: V_BCN_THUNO]
... A24: TCKH.V_BCN_THUNO | B24: GOLD_DERIVED | C24: X.7 | D24: Nhom X - Bo sung Raffles | E24: [Bổ sung] Không hard-code catalog, dùng biến môi trường | F24: PASS | G24: Pass | H24: dùng biến môi trường cho catalog | I24: Thay tên catalog cứng bằng IDENTIFIER(:cleaned || '.raw_vault.<bảng>') / IDENTIFIER(:curated || '.tckh.<bảng>'), hoặc ${cleaned_catalog} / ${curated_catalog} trong Lakeflow Declarative Pipeline. Hard-code thì deploy sang môi trường khác phải sửa tay từng file. | J24: 001. OCB_GOLD_TCKH_V_BCN_THUNO_QUANG.xlsx [Script SQL: V_BCN_THUNO]
A25: TCKH.V_BCN_THUNO | B25: GOLD_DERIVED | C25: X.10 | D25: Nhom X - Bo sung Raffles | E25: Bang raw_vault/business_vault duoc doc phai TON TAI THAT trong Data Vault model | F25: N-A | G25: Pass | H25: script không đọc bảng raw_vault/business_vault nào | J25: 001. OCB_GOLD_TCKH_V_BCN_THUNO_QUANG.xlsx [Script SQL: V_BCN_THUNO]
A26: TCKH.V_BCN_THUNO | B26: GOLD_DERIVED | C26: X.11 | D26: Nhom X - Bo sung Raffles | E26: Cot doc tu satellite (sat_*) phai TON TAI THAT trong model | F26: N-A | G26: Pass | H26: không có bảng sat_* nào đủ điều kiện đối chiếu (Select chỉ đọc 1 bảng) | J26: 001. OCB_GOLD_TCKH_V_BCN_THUNO_QUANG.xlsx [Script SQL: V_BCN_THUNO]
A27: TCKH.V_BRANCH_LIST | B27: GOLD_DERIVED | C27: 1.1 | D27: Nhom 1 - Mapping | E27: Đầy đủ mapping từ Silver/manual sang Gold | F27: PASS | G27: Pass | H27: workbook 002. OCB_GOLD_TCKH_V_BRANCH_LIST_HOP.xlsx: thiết kế 5 field, SQL có 5 cột | I27: Mở workbook thiết kế, đối chiếu block FIELD MAPPING với danh sách cột trong câu SELECT/INSERT của file SQL. Cột nào thiếu thì bổ sung vào SQL; cột nào SQL có mà thiết kế không có thì bổ sung vào workbook hoặc bỏ khỏi SQL. | J27: 002. OCB_GOLD_TCKH_V_BRANCH_LIST_HOP.xlsx [SCRIPT: V_BRANCH_LIST]
A28: TCKH.V_BRANCH_LIST | B28: GOLD_DERIVED | C28: 1.2 | D28: Nhom 1 - Mapping | E28: Danh sách bảng/view Gold khớp tài liệu thiết kế đã duyệt | F28: PASS | G28: Pass | H28: V_BRANCH_LIST có workbook thiết kế: 002. OCB_GOLD_TCKH_V_BRANCH_LIST_HOP.xlsx | I28: Đảm bảo object có workbook thiết kế tương ứng trong thư mục --mapping-dir. Muốn đối chiếu với danh sách đã duyệt thì chạy thêm tham số --gold-list "<file danh sách Gold>.xlsx". | J28: 002. OCB_GOLD_TCKH_V_BRANCH_LIST_HOP.xlsx [SCRIPT: V_BRANCH_LIST]
A29: TCKH.V_BRANCH_LIST | B29: GOLD_DERIVED | C29: 2.1 | D29: Nhom 2 - Logic | E29: Chỉ lấy bản ghi active, loại bản ghi đã xóa (qua sts_hub) | F29: N-A | G29: Pass | H29: khong ap dung cho profile GOLD_DERIVED | I29: Theo Technical Document mục III.4.2.1: với mỗi hub_<ent> phải thêm 2 CTE — (1) <ent>_sts_del đọc sts_hub_<ent>, GROUP BY hashkey, HAVING max_by(cdc_status, source_event_date) = 'D'; (2) <ent>_active đọc hub_<ent> LEFT JOIN <ent>_sts_del rồi lọc d.<hashkey> IS NULL. Tuyệt đối KHÔNG lọc cdc_status trong satellite — trạng thái xóa chỉ lọc ở sts_hub. | J29: 002. OCB_GOLD_TCKH_V_BRANCH_LIST_HOP.xlsx [SCRIPT: V_BRANCH_LIST]
A30: TCKH.V_BRANCH_LIST | B30: GOLD_DERIVED | C30: 2.2 | D30: Nhom 2 - Logic | E30: Thống nhất MỘT pattern duy nhất xác định bản ghi active mới nhất | F30: N-A | G30: Pass | H30: khong ap dung cho profile GOLD_DERIVED | I30: Toàn bộ script trong batch phải dùng cùng một cách lấy bản ghi mới nhất: max_by(<cột>, source_event_date) + GROUP BY hashkey. Không để file này dùng ROW_NUMBER, file kia dùng max_by. Hướng lọc cdc_status cũng phải nhất quán (luôn là loại 'D', không có chỗ nào giữ 'D'). | J30: 002. OCB_GOLD_TCKH_V_BRANCH_LIST_HOP.xlsx [SCRIPT: V_BRANCH_LIST]
A31: TCKH.V_BRANCH_LIST | B31: GOLD_DERIVED | C31: 2.3 | D31: Nhom 2 - Logic | E31: Điều kiện lọc trạng thái đặt SAU khi xác định bản ghi mới nhất | F31: PASS | G31: Pass | H31: không có điều kiện trạng thái nào lồng trong JOIN ON | I31: Chuyển các điều kiện cdc_status / rn = 1 ra khỏi phần ON của LEFT JOIN, đưa vào WHERE hoặc QUALIFY của chính subquery/CTE lấy dữ liệu. Đặt trong ON của LEFT JOIN thì khi không match sẽ ra NULL âm thầm, sai kết quả (Issue log #3). Riêng pattern PIT (sat.source_event_date = p.<sat>_src_ev_dt) và 49 bảng transaction được phép đặt trong ON. | J31: 002. OCB_GOLD_TCKH_V_BRANCH_LIST_HOP.xlsx [SCRIPT: V_BRANCH_LIST]
A32: TCKH.V_BRANCH_LIST | B32: GOLD_DERIVED | C32: 2.4 | D32: Nhom 2 - Logic | E32: source_event_date áp dụng đúng dạng theo loại bảng | F32: N-A | G32: Pass | H32: khong ap dung cho profile GOLD_DERIVED | I32: Bảng thường: WHERE source_event_date <= TO_DATE(:DATADT,'yyyyMMdd') và KHÔNG đặt cận dưới (>= start_date) vì sẽ bỏ sót bản ghi mới nhất nằm trước khoảng thời gian. Riêng 49 bảng transaction ở mục 'Các trường hợp đặc biệt' của Technical Document (sat_stmt_entry_*, sat_categ_entry_*, sat_account_balance, sat_funds_transfer_*, sat_gl_trace_*, …) phải dùng source_event_date = :DATADT. Danh sách đầy đủ ở tools/gold_review/doc_standard.py. | J32: 002. OCB_GOLD_TCKH_V_BRANCH_LIST_HOP.xlsx [SCRIPT: V_BRANCH_LIST]
A33: TCKH.V_BRANCH_LIST | B33: GOLD_DERIVED | C33: 2.5 | D33: Nhom 2 - Logic | E33: Không lặp lại lỗi logic cũ đã được DA Data Vault fix | F33: PASS | G33: Pass | H33: không trùng lỗi nào trong Issue log của DA Data Vault | I33: Sửa đúng các dòng được chỉ ra ở trên theo pattern chuẩn: lấy bản ghi mới nhất bằng max_by(<cột>, source_event_date) + GROUP BY hashkey; trạng thái xoá lọc ở sts_hub_* bằng HAVING max_by(cdc_status, source_event_date) = 'D' rồi anti-join IS NULL; không đặt cdc_status / rn = 1 trong ON hay trong subquery của JOIN; surrogate key DIM không sinh bằng MAX(<DIM_ID>) + ROW_NUMBER(). Danh sách lỗi lấy từ 'ZoneC Mapping - Iss log.xlsx' sheet Issue; OCB trả lỗi mới thì thêm 1 regex vào tools/gold_review/engine/known_issues.json để lần sau tự bắt được. | J33: 002. OCB_GOLD_TCKH_V_BRANCH_LIST_HOP.xlsx [SCRIPT: V_BRANCH_LIST]
A34: TCKH.V_BRANCH_LIST | B34: GOLD_DERIVED | C34: 2.6 | D34: Nhom 2 - Logic | E34: SCD Type 2 cho bảng DIM áp dụng đúng kỹ thuật đã thống nhất | F34: N-A | G34: Pass | H34: object không phải bảng DIM nên không áp dụng SCD Type 2 | I34: Dùng APPLY CHANGES INTO <bảng>_scd FROM STREAM(stg_<ent>_changes) KEYS (<hashkey>) SEQUENCE BY source_event_date STORED AS SCD TYPE 2 TRACK HISTORY ON (...) — Databricks tự quản __START_AT/__END_AT. Nếu tự quản thì phải có cột effective_date/end_date/current_flag. TUYỆT ĐỐI không sinh surrogate key bằng MAX(<DIM_ID>) + ROW_NUMBER() vì trùng khi chạy song song hoặc load lại lịch sử (Issue log #4). | J34: 002. OCB_GOLD_TCKH_V_BRANCH_LIST_HOP.xlsx [SCRIPT: V_BRANCH_LIST]
A35: TCKH.V_BRANCH_LIST | B35: GOLD_DERIVED | C35: 2.7 | D35: Nhom 2 - Logic | E35: CASE WHEN cover đủ nhánh như job on-prem | F35: N-A | G35: Pass | H35: script không có CASE WHEN nào | I35: Mở job on-prem tương ứng (DataStage DSX hoặc SQL cũ), đối chiếu từng nhánh WHEN và cả nhánh ELSE. CASE không có ELSE sẽ trả NULL âm thầm — xác nhận đó là ý muốn hay thiếu nhánh. | J35: 002. OCB_GOLD_TCKH_V_BRANCH_LIST_HOP.xlsx [SCRIPT: V_BRANCH_LIST]
A36: TCKH.V_BRANCH_LIST | B36: GOLD_DERIVED | C36: 2.8 | D36: Nhom 2 - Logic | E36: Cột SUM/COUNT được COALESCE/NVL hợp lý | F36: PASS | G36: Pass | H36: mọi SUM/COUNT đều đã coalesce (trực tiếp hoặc ở lớp ngoài) | I36: Bọc COALESCE(SUM(...), 0) cho các cột tổng hợp cần trả 0 khi không có dòng. Nếu code cũ không bọc thì giữ nguyên logic nhưng khi đối soát số liệu với hệ thống cũ phải bọc NVL/ISNULL ở CẢ HAI phía để không lệch khi trừ. | J36: 002. OCB_GOLD_TCKH_V_BRANCH_LIST_HOP.xlsx [SCRIPT: V_BRANCH_LIST]
A37: TCKH.V_BRANCH_LIST | B37: GOLD_DERIVED | C37: 2.9 | D37: Nhom 2 - Logic | E37: Subquery / custom function / điều kiện LIKE đúng ý nghĩa nghiệp vụ | F37: N-A | G37: Pass | H37: script không có điều kiện LIKE hay scalar subquery nào | I37: Đọc lại từng điều kiện LIKE và từng subquery, đối chiếu ý nghĩa nghiệp vụ với on-prem — đúng cú pháp không đủ. Chú ý pattern LIKE có ký tự % ở đầu/cuối và phân biệt chữ hoa/thường. | J37: 002. OCB_GOLD_TCKH_V_BRANCH_LIST_HOP.xlsx [SCRIPT: V_BRANCH_LIST]
A38: TCKH.V_BRANCH_LIST | B38: GOLD_DERIVED | C38: 2.10 | D38: Nhom 2 - Logic | E38: Aggregation kèm filter date range chính xác | F38: PASS | G38: Pass | H38: mọi khối tổng hợp đều có điều kiện theo kỳ dữ liệu | I38: Mỗi khối SUM/COUNT/AVG phải có điều kiện lọc theo kỳ dữ liệu (CDR_DT_ID, DATA_DATE, :DATADT…). Nếu điều kiện nằm ở CTE nguồn thì ghi rõ trong comment để người review không phải truy ngược. | J38: 002. OCB_GOLD_TCKH_V_BRANCH_LIST_HOP.xlsx [SCRIPT: V_BRANCH_LIST]
... A49: TCKH.V_BRANCH_LIST | B49: GOLD_DERIVED | C49: X.7 | D49: Nhom X - Bo sung Raffles | E49: [Bổ sung] Không hard-code catalog, dùng biến môi trường | F49: PASS | G49: Pass | H49: dùng biến môi trường cho catalog | I49: Thay tên catalog cứng bằng IDENTIFIER(:cleaned || '.raw_vault.<bảng>') / IDENTIFIER(:curated || '.tckh.<bảng>'), hoặc ${cleaned_catalog} / ${curated_catalog} trong Lakeflow Declarative Pipeline. Hard-code thì deploy sang môi trường khác phải sửa tay từng file. | J49: 002. OCB_GOLD_TCKH_V_BRANCH_LIST_HOP.xlsx [SCRIPT: V_BRANCH_LIST]
A50: TCKH.V_BRANCH_LIST | B50: GOLD_DERIVED | C50: X.10 | D50: Nhom X - Bo sung Raffles | E50: Bang raw_vault/business_vault duoc doc phai TON TAI THAT trong Data Vault model | F50: N-A | G50: Pass | H50: script không đọc bảng raw_vault/business_vault nào | J50: 002. OCB_GOLD_TCKH_V_BRANCH_LIST_HOP.xlsx [SCRIPT: V_BRANCH_LIST]
A51: TCKH.V_BRANCH_LIST | B51: GOLD_DERIVED | C51: X.11 | D51: Nhom X - Bo sung Raffles | E51: Cot doc tu satellite (sat_*) phai TON TAI THAT trong model | F51: N-A | G51: Pass | H51: không có bảng sat_* nào đủ điều kiện đối chiếu (Select chỉ đọc 1 bảng) | J51: 002. OCB_GOLD_TCKH_V_BRANCH_LIST_HOP.xlsx [SCRIPT: V_BRANCH_LIST]
A52: TCKH.V_CDR_AMT | B52: GOLD_DERIVED | C52: 1.1 | D52: Nhom 1 - Mapping | E52: Đầy đủ mapping từ Silver/manual sang Gold | F52: PASS | G52: Pass | H52: workbook 003. OCB_GOLD_TCKH_V_CDR_AMT_QUANG.xlsx: thiết kế 6 field, SQL có 6 cột | I52: Mở workbook thiết kế, đối chiếu block FIELD MAPPING với danh sách cột trong câu SELECT/INSERT của file SQL. Cột nào thiếu thì bổ sung vào SQL; cột nào SQL có mà thiết kế không có thì bổ sung vào workbook hoặc bỏ khỏi SQL. | J52: 003. OCB_GOLD_TCKH_V_CDR_AMT_QUANG.xlsx [Script SQL: V_CDR_AMT]
A53: TCKH.V_CDR_AMT | B53: GOLD_DERIVED | C53: 1.2 | D53: Nhom 1 - Mapping | E53: Danh sách bảng/view Gold khớp tài liệu thiết kế đã duyệt | F53: PASS | G53: Pass | H53: V_CDR_AMT có workbook thiết kế: 003. OCB_GOLD_TCKH_V_CDR_AMT_QUANG.xlsx | I53: Đảm bảo object có workbook thiết kế tương ứng trong thư mục --mapping-dir. Muốn đối chiếu với danh sách đã duyệt thì chạy thêm tham số --gold-list "<file danh sách Gold>.xlsx". | J53: 003. OCB_GOLD_TCKH_V_CDR_AMT_QUANG.xlsx [Script SQL: V_CDR_AMT]
A54: TCKH.V_CDR_AMT | B54: GOLD_DERIVED | C54: 2.1 | D54: Nhom 2 - Logic | E54: Chỉ lấy bản ghi active, loại bản ghi đã xóa (qua sts_hub) | F54: N-A | G54: Pass | H54: khong ap dung cho profile GOLD_DERIVED | I54: Theo Technical Document mục III.4.2.1: với mỗi hub_<ent> phải thêm 2 CTE — (1) <ent>_sts_del đọc sts_hub_<ent>, GROUP BY hashkey, HAVING max_by(cdc_status, source_event_date) = 'D'; (2) <ent>_active đọc hub_<ent> LEFT JOIN <ent>_sts_del rồi lọc d.<hashkey> IS NULL. Tuyệt đối KHÔNG lọc cdc_status trong satellite — trạng thái xóa chỉ lọc ở sts_hub. | J54: 003. OCB_GOLD_TCKH_V_CDR_AMT_QUANG.xlsx [Script SQL: V_CDR_AMT]
A55: TCKH.V_CDR_AMT | B55: GOLD_DERIVED | C55: 2.2 | D55: Nhom 2 - Logic | E55: Thống nhất MỘT pattern duy nhất xác định bản ghi active mới nhất | F55: N-A | G55: Pass | H55: khong ap dung cho profile GOLD_DERIVED | I55: Toàn bộ script trong batch phải dùng cùng một cách lấy bản ghi mới nhất: max_by(<cột>, source_event_date) + GROUP BY hashkey. Không để file này dùng ROW_NUMBER, file kia dùng max_by. Hướng lọc cdc_status cũng phải nhất quán (luôn là loại 'D', không có chỗ nào giữ 'D'). | J55: 003. OCB_GOLD_TCKH_V_CDR_AMT_QUANG.xlsx [Script SQL: V_CDR_AMT]
A56: TCKH.V_CDR_AMT | B56: GOLD_DERIVED | C56: 2.3 | D56: Nhom 2 - Logic | E56: Điều kiện lọc trạng thái đặt SAU khi xác định bản ghi mới nhất | F56: PASS | G56: Pass | H56: không có điều kiện trạng thái nào lồng trong JOIN ON | I56: Chuyển các điều kiện cdc_status / rn = 1 ra khỏi phần ON của LEFT JOIN, đưa vào WHERE hoặc QUALIFY của chính subquery/CTE lấy dữ liệu. Đặt trong ON của LEFT JOIN thì khi không match sẽ ra NULL âm thầm, sai kết quả (Issue log #3). Riêng pattern PIT (sat.source_event_date = p.<sat>_src_ev_dt) và 49 bảng transaction được phép đặt trong ON. | J56: 003. OCB_GOLD_TCKH_V_CDR_AMT_QUANG.xlsx [Script SQL: V_CDR_AMT]
A57: TCKH.V_CDR_AMT | B57: GOLD_DERIVED | C57: 2.4 | D57: Nhom 2 - Logic | E57: source_event_date áp dụng đúng dạng theo loại bảng | F57: N-A | G57: Pass | H57: khong ap dung cho profile GOLD_DERIVED | I57: Bảng thường: WHERE source_event_date <= TO_DATE(:DATADT,'yyyyMMdd') và KHÔNG đặt cận dưới (>= start_date) vì sẽ bỏ sót bản ghi mới nhất nằm trước khoảng thời gian. Riêng 49 bảng transaction ở mục 'Các trường hợp đặc biệt' của Technical Document (sat_stmt_entry_*, sat_categ_entry_*, sat_account_balance, sat_funds_transfer_*, sat_gl_trace_*, …) phải dùng source_event_date = :DATADT. Danh sách đầy đủ ở tools/gold_review/doc_standard.py. | J57: 003. OCB_GOLD_TCKH_V_CDR_AMT_QUANG.xlsx [Script SQL: V_CDR_AMT]
A58: TCKH.V_CDR_AMT | B58: GOLD_DERIVED | C58: 2.5 | D58: Nhom 2 - Logic | E58: Không lặp lại lỗi logic cũ đã được DA Data Vault fix | F58: PASS | G58: Pass | H58: không trùng lỗi nào trong Issue log của DA Data Vault | I58: Sửa đúng các dòng được chỉ ra ở trên theo pattern chuẩn: lấy bản ghi mới nhất bằng max_by(<cột>, source_event_date) + GROUP BY hashkey; trạng thái xoá lọc ở sts_hub_* bằng HAVING max_by(cdc_status, source_event_date) = 'D' rồi anti-join IS NULL; không đặt cdc_status / rn = 1 trong ON hay trong subquery của JOIN; surrogate key DIM không sinh bằng MAX(<DIM_ID>) + ROW_NUMBER(). Danh sách lỗi lấy từ 'ZoneC Mapping - Iss log.xlsx' sheet Issue; OCB trả lỗi mới thì thêm 1 regex vào tools/gold_review/engine/known_issues.json để lần sau tự bắt được. | J58: 003. OCB_GOLD_TCKH_V_CDR_AMT_QUANG.xlsx [Script SQL: V_CDR_AMT]
A59: TCKH.V_CDR_AMT | B59: GOLD_DERIVED | C59: 2.6 | D59: Nhom 2 - Logic | E59: SCD Type 2 cho bảng DIM áp dụng đúng kỹ thuật đã thống nhất | F59: N-A | G59: Pass | H59: object không phải bảng DIM nên không áp dụng SCD Type 2 | I59: Dùng APPLY CHANGES INTO <bảng>_scd FROM STREAM(stg_<ent>_changes) KEYS (<hashkey>) SEQUENCE BY source_event_date STORED AS SCD TYPE 2 TRACK HISTORY ON (...) — Databricks tự quản __START_AT/__END_AT. Nếu tự quản thì phải có cột effective_date/end_date/current_flag. TUYỆT ĐỐI không sinh surrogate key bằng MAX(<DIM_ID>) + ROW_NUMBER() vì trùng khi chạy song song hoặc load lại lịch sử (Issue log #4). | J59: 003. OCB_GOLD_TCKH_V_CDR_AMT_QUANG.xlsx [Script SQL: V_CDR_AMT]
A60: TCKH.V_CDR_AMT | B60: GOLD_DERIVED | C60: 2.7 | D60: Nhom 2 - Logic | E60: CASE WHEN cover đủ nhánh như job on-prem | F60: PASS | G60: Pass | H60: cả 4 CASE đều có nhánh ELSE | I60: Mở job on-prem tương ứng (DataStage DSX hoặc SQL cũ), đối chiếu từng nhánh WHEN và cả nhánh ELSE. CASE không có ELSE sẽ trả NULL âm thầm — xác nhận đó là ý muốn hay thiếu nhánh. | J60: 003. OCB_GOLD_TCKH_V_CDR_AMT_QUANG.xlsx [Script SQL: V_CDR_AMT]
A61: TCKH.V_CDR_AMT | B61: GOLD_DERIVED | C61: 2.8 | D61: Nhom 2 - Logic | E61: Cột SUM/COUNT được COALESCE/NVL hợp lý | F61: PASS | G61: Pass | H61: mọi SUM/COUNT đều đã coalesce (trực tiếp hoặc ở lớp ngoài) | I61: Bọc COALESCE(SUM(...), 0) cho các cột tổng hợp cần trả 0 khi không có dòng. Nếu code cũ không bọc thì giữ nguyên logic nhưng khi đối soát số liệu với hệ thống cũ phải bọc NVL/ISNULL ở CẢ HAI phía để không lệch khi trừ. | J61: 003. OCB_GOLD_TCKH_V_CDR_AMT_QUANG.xlsx [Script SQL: V_CDR_AMT]
A62: TCKH.V_CDR_AMT | B62: GOLD_DERIVED | C62: 2.9 | D62: Nhom 2 - Logic | E62: Subquery / custom function / điều kiện LIKE đúng ý nghĩa nghiệp vụ | F62: N-A | G62: Pass | H62: script không có điều kiện LIKE hay scalar subquery nào | I62: Đọc lại từng điều kiện LIKE và từng subquery, đối chiếu ý nghĩa nghiệp vụ với on-prem — đúng cú pháp không đủ. Chú ý pattern LIKE có ký tự % ở đầu/cuối và phân biệt chữ hoa/thường. | J62: 003. OCB_GOLD_TCKH_V_CDR_AMT_QUANG.xlsx [Script SQL: V_CDR_AMT]
A63: TCKH.V_CDR_AMT | B63: GOLD_DERIVED | C63: 2.10 | D63: Nhom 2 - Logic | E63: Aggregation kèm filter date range chính xác | F63: WARN | G63: WARN | H63: 1 khối tổng hợp không thấy filter theo ngày/tham số: SELECT tu V_ENTRY_STMT_QUYMO | I63: Mỗi khối SUM/COUNT/AVG phải có điều kiện lọc theo kỳ dữ liệu (CDR_DT_ID, DATA_DATE, :DATADT…). Nếu điều kiện nằm ở CTE nguồn thì ghi rõ trong comment để người review không phải truy ngược. | J63: 003. OCB_GOLD_TCKH_V_CDR_AMT_QUANG.xlsx [Script SQL: V_CDR_AMT]
... A74: TCKH.V_CDR_AMT | B74: GOLD_DERIVED | C74: X.7 | D74: Nhom X - Bo sung Raffles | E74: [Bổ sung] Không hard-code catalog, dùng biến môi trường | F74: PASS | G74: Pass | H74: dùng biến môi trường cho catalog | I74: Thay tên catalog cứng bằng IDENTIFIER(:cleaned || '.raw_vault.<bảng>') / IDENTIFIER(:curated || '.tckh.<bảng>'), hoặc ${cleaned_catalog} / ${curated_catalog} trong Lakeflow Declarative Pipeline. Hard-code thì deploy sang môi trường khác phải sửa tay từng file. | J74: 003. OCB_GOLD_TCKH_V_CDR_AMT_QUANG.xlsx [Script SQL: V_CDR_AMT]
A75: TCKH.V_CDR_AMT | B75: GOLD_DERIVED | C75: X.10 | D75: Nhom X - Bo sung Raffles | E75: Bang raw_vault/business_vault duoc doc phai TON TAI THAT trong Data Vault model | F75: N-A | G75: Pass | H75: script không đọc bảng raw_vault/business_vault nào | J75: 003. OCB_GOLD_TCKH_V_CDR_AMT_QUANG.xlsx [Script SQL: V_CDR_AMT]
A76: TCKH.V_CDR_AMT | B76: GOLD_DERIVED | C76: X.11 | D76: Nhom X - Bo sung Raffles | E76: Cot doc tu satellite (sat_*) phai TON TAI THAT trong model | F76: N-A | G76: Pass | H76: không có bảng sat_* nào đủ điều kiện đối chiếu (Select chỉ đọc 1 bảng) | J76: 003. OCB_GOLD_TCKH_V_CDR_AMT_QUANG.xlsx [Script SQL: V_CDR_AMT]
A77: TCKH.V_CDTK_DAILY | B77: GOLD_DERIVED | C77: 1.1 | D77: Nhom 1 - Mapping | E77: Đầy đủ mapping từ Silver/manual sang Gold | F77: PASS | G77: Pass | H77: workbook 004. OCB_GOLD_TCKH_V_CDTK_DAILY_QUANG.xlsx: thiết kế 17 field, SQL có 17 cột | I77: Mở workbook thiết kế, đối chiếu block FIELD MAPPING với danh sách cột trong câu SELECT/INSERT của file SQL. Cột nào thiếu thì bổ sung vào SQL; cột nào SQL có mà thiết kế không có thì bổ sung vào workbook hoặc bỏ khỏi SQL. | J77: 004. OCB_GOLD_TCKH_V_CDTK_DAILY_QUANG.xlsx [Script SQL: V_CDTK_DAILY]
A78: TCKH.V_CDTK_DAILY | B78: GOLD_DERIVED | C78: 1.2 | D78: Nhom 1 - Mapping | E78: Danh sách bảng/view Gold khớp tài liệu thiết kế đã duyệt | F78: PASS | G78: Pass | H78: V_CDTK_DAILY có workbook thiết kế: 004. OCB_GOLD_TCKH_V_CDTK_DAILY_QUANG.xlsx | I78: Đảm bảo object có workbook thiết kế tương ứng trong thư mục --mapping-dir. Muốn đối chiếu với danh sách đã duyệt thì chạy thêm tham số --gold-list "<file danh sách Gold>.xlsx". | J78: 004. OCB_GOLD_TCKH_V_CDTK_DAILY_QUANG.xlsx [Script SQL: V_CDTK_DAILY]
A79: TCKH.V_CDTK_DAILY | B79: GOLD_DERIVED | C79: 2.1 | D79: Nhom 2 - Logic | E79: Chỉ lấy bản ghi active, loại bản ghi đã xóa (qua sts_hub) | F79: N-A | G79: Pass | H79: khong ap dung cho profile GOLD_DERIVED | I79: Theo Technical Document mục III.4.2.1: với mỗi hub_<ent> phải thêm 2 CTE — (1) <ent>_sts_del đọc sts_hub_<ent>, GROUP BY hashkey, HAVING max_by(cdc_status, source_event_date) = 'D'; (2) <ent>_active đọc hub_<ent> LEFT JOIN <ent>_sts_del rồi lọc d.<hashkey> IS NULL. Tuyệt đối KHÔNG lọc cdc_status trong satellite — trạng thái xóa chỉ lọc ở sts_hub. | J79: 004. OCB_GOLD_TCKH_V_CDTK_DAILY_QUANG.xlsx [Script SQL: V_CDTK_DAILY]
A80: TCKH.V_CDTK_DAILY | B80: GOLD_DERIVED | C80: 2.2 | D80: Nhom 2 - Logic | E80: Thống nhất MỘT pattern duy nhất xác định bản ghi active mới nhất | F80: N-A | G80: Pass | H80: khong ap dung cho profile GOLD_DERIVED | I80: Toàn bộ script trong batch phải dùng cùng một cách lấy bản ghi mới nhất: max_by(<cột>, source_event_date) + GROUP BY hashkey. Không để file này dùng ROW_NUMBER, file kia dùng max_by. Hướng lọc cdc_status cũng phải nhất quán (luôn là loại 'D', không có chỗ nào giữ 'D'). | J80: 004. OCB_GOLD_TCKH_V_CDTK_DAILY_QUANG.xlsx [Script SQL: V_CDTK_DAILY]
A81: TCKH.V_CDTK_DAILY | B81: GOLD_DERIVED | C81: 2.3 | D81: Nhom 2 - Logic | E81: Điều kiện lọc trạng thái đặt SAU khi xác định bản ghi mới nhất | F81: PASS | G81: Pass | H81: không có điều kiện trạng thái nào lồng trong JOIN ON | I81: Chuyển các điều kiện cdc_status / rn = 1 ra khỏi phần ON của LEFT JOIN, đưa vào WHERE hoặc QUALIFY của chính subquery/CTE lấy dữ liệu. Đặt trong ON của LEFT JOIN thì khi không match sẽ ra NULL âm thầm, sai kết quả (Issue log #3). Riêng pattern PIT (sat.source_event_date = p.<sat>_src_ev_dt) và 49 bảng transaction được phép đặt trong ON. | J81: 004. OCB_GOLD_TCKH_V_CDTK_DAILY_QUANG.xlsx [Script SQL: V_CDTK_DAILY]
A82: TCKH.V_CDTK_DAILY | B82: GOLD_DERIVED | C82: 2.4 | D82: Nhom 2 - Logic | E82: source_event_date áp dụng đúng dạng theo loại bảng | F82: N-A | G82: Pass | H82: khong ap dung cho profile GOLD_DERIVED | I82: Bảng thường: WHERE source_event_date <= TO_DATE(:DATADT,'yyyyMMdd') và KHÔNG đặt cận dưới (>= start_date) vì sẽ bỏ sót bản ghi mới nhất nằm trước khoảng thời gian. Riêng 49 bảng transaction ở mục 'Các trường hợp đặc biệt' của Technical Document (sat_stmt_entry_*, sat_categ_entry_*, sat_account_balance, sat_funds_transfer_*, sat_gl_trace_*, …) phải dùng source_event_date = :DATADT. Danh sách đầy đủ ở tools/gold_review/doc_standard.py. | J82: 004. OCB_GOLD_TCKH_V_CDTK_DAILY_QUANG.xlsx [Script SQL: V_CDTK_DAILY]
A83: TCKH.V_CDTK_DAILY | B83: GOLD_DERIVED | C83: 2.5 | D83: Nhom 2 - Logic | E83: Không lặp lại lỗi logic cũ đã được DA Data Vault fix | F83: PASS | G83: Pass | H83: không trùng lỗi nào trong Issue log của DA Data Vault | I83: Sửa đúng các dòng được chỉ ra ở trên theo pattern chuẩn: lấy bản ghi mới nhất bằng max_by(<cột>, source_event_date) + GROUP BY hashkey; trạng thái xoá lọc ở sts_hub_* bằng HAVING max_by(cdc_status, source_event_date) = 'D' rồi anti-join IS NULL; không đặt cdc_status / rn = 1 trong ON hay trong subquery của JOIN; surrogate key DIM không sinh bằng MAX(<DIM_ID>) + ROW_NUMBER(). Danh sách lỗi lấy từ 'ZoneC Mapping - Iss log.xlsx' sheet Issue; OCB trả lỗi mới thì thêm 1 regex vào tools/gold_review/engine/known_issues.json để lần sau tự bắt được. | J83: 004. OCB_GOLD_TCKH_V_CDTK_DAILY_QUANG.xlsx [Script SQL: V_CDTK_DAILY]
A84: TCKH.V_CDTK_DAILY | B84: GOLD_DERIVED | C84: 2.6 | D84: Nhom 2 - Logic | E84: SCD Type 2 cho bảng DIM áp dụng đúng kỹ thuật đã thống nhất | F84: N-A | G84: Pass | H84: object không phải bảng DIM nên không áp dụng SCD Type 2 | I84: Dùng APPLY CHANGES INTO <bảng>_scd FROM STREAM(stg_<ent>_changes) KEYS (<hashkey>) SEQUENCE BY source_event_date STORED AS SCD TYPE 2 TRACK HISTORY ON (...) — Databricks tự quản __START_AT/__END_AT. Nếu tự quản thì phải có cột effective_date/end_date/current_flag. TUYỆT ĐỐI không sinh surrogate key bằng MAX(<DIM_ID>) + ROW_NUMBER() vì trùng khi chạy song song hoặc load lại lịch sử (Issue log #4). | J84: 004. OCB_GOLD_TCKH_V_CDTK_DAILY_QUANG.xlsx [Script SQL: V_CDTK_DAILY]
A85: TCKH.V_CDTK_DAILY | B85: GOLD_DERIVED | C85: 2.7 | D85: Nhom 2 - Logic | E85: CASE WHEN cover đủ nhánh như job on-prem | F85: N-A | G85: Pass | H85: script không có CASE WHEN nào | I85: Mở job on-prem tương ứng (DataStage DSX hoặc SQL cũ), đối chiếu từng nhánh WHEN và cả nhánh ELSE. CASE không có ELSE sẽ trả NULL âm thầm — xác nhận đó là ý muốn hay thiếu nhánh. | J85: 004. OCB_GOLD_TCKH_V_CDTK_DAILY_QUANG.xlsx [Script SQL: V_CDTK_DAILY]
A86: TCKH.V_CDTK_DAILY | B86: GOLD_DERIVED | C86: 2.8 | D86: Nhom 2 - Logic | E86: Cột SUM/COUNT được COALESCE/NVL hợp lý | F86: PASS | G86: Pass | H86: mọi SUM/COUNT đều đã coalesce (trực tiếp hoặc ở lớp ngoài) | I86: Bọc COALESCE(SUM(...), 0) cho các cột tổng hợp cần trả 0 khi không có dòng. Nếu code cũ không bọc thì giữ nguyên logic nhưng khi đối soát số liệu với hệ thống cũ phải bọc NVL/ISNULL ở CẢ HAI phía để không lệch khi trừ. | J86: 004. OCB_GOLD_TCKH_V_CDTK_DAILY_QUANG.xlsx [Script SQL: V_CDTK_DAILY]
A87: TCKH.V_CDTK_DAILY | B87: GOLD_DERIVED | C87: 2.9 | D87: Nhom 2 - Logic | E87: Subquery / custom function / điều kiện LIKE đúng ý nghĩa nghiệp vụ | F87: N-A | G87: Pass | H87: script không có điều kiện LIKE hay scalar subquery nào | I87: Đọc lại từng điều kiện LIKE và từng subquery, đối chiếu ý nghĩa nghiệp vụ với on-prem — đúng cú pháp không đủ. Chú ý pattern LIKE có ký tự % ở đầu/cuối và phân biệt chữ hoa/thường. | J87: 004. OCB_GOLD_TCKH_V_CDTK_DAILY_QUANG.xlsx [Script SQL: V_CDTK_DAILY]
A88: TCKH.V_CDTK_DAILY | B88: GOLD_DERIVED | C88: 2.10 | D88: Nhom 2 - Logic | E88: Aggregation kèm filter date range chính xác | F88: PASS | G88: Pass | H88: mọi khối tổng hợp đều có điều kiện theo kỳ dữ liệu | I88: Mỗi khối SUM/COUNT/AVG phải có điều kiện lọc theo kỳ dữ liệu (CDR_DT_ID, DATA_DATE, :DATADT…). Nếu điều kiện nằm ở CTE nguồn thì ghi rõ trong comment để người review không phải truy ngược. | J88: 004. OCB_GOLD_TCKH_V_CDTK_DAILY_QUANG.xlsx [Script SQL: V_CDTK_DAILY]
... A99: TCKH.V_CDTK_DAILY | B99: GOLD_DERIVED | C99: X.7 | D99: Nhom X - Bo sung Raffles | E99: [Bổ sung] Không hard-code catalog, dùng biến môi trường | F99: PASS | G99: Pass | H99: dùng biến môi trường cho catalog | I99: Thay tên catalog cứng bằng IDENTIFIER(:cleaned || '.raw_vault.<bảng>') / IDENTIFIER(:curated || '.tckh.<bảng>'), hoặc ${cleaned_catalog} / ${curated_catalog} trong Lakeflow Declarative Pipeline. Hard-code thì deploy sang môi trường khác phải sửa tay từng file. | J99: 004. OCB_GOLD_TCKH_V_CDTK_DAILY_QUANG.xlsx [Script SQL: V_CDTK_DAILY]
A100: TCKH.V_CDTK_DAILY | B100: GOLD_DERIVED | C100: X.10 | D100: Nhom X - Bo sung Raffles | E100: Bang raw_vault/business_vault duoc doc phai TON TAI THAT trong Data Vault model | F100: N-A | G100: Pass | H100: script không đọc bảng raw_vault/business_vault nào | J100: 004. OCB_GOLD_TCKH_V_CDTK_DAILY_QUANG.xlsx [Script SQL: V_CDTK_DAILY]
A101: TCKH.V_CDTK_DAILY | B101: GOLD_DERIVED | C101: X.11 | D101: Nhom X - Bo sung Raffles | E101: Cot doc tu satellite (sat_*) phai TON TAI THAT trong model | F101: N-A | G101: Pass | H101: không có bảng sat_* nào đủ điều kiện đối chiếu (Select chỉ đọc 1 bảng) | J101: 004. OCB_GOLD_TCKH_V_CDTK_DAILY_QUANG.xlsx [Script SQL: V_CDTK_DAILY]
A102: TCKH.V_CREDIT_LIMIT | B102: SILVER_CONSUMER | C102: 1.1 | D102: Nhom 1 - Mapping | E102: Đầy đủ mapping từ Silver/manual sang Gold | F102: PASS | G102: Pass | H102: workbook 005. OCB_GOLD_TCKH_V_CREDIT_LIMIT_BAOANH.xlsx: thiết kế 3 field, SQL có 3 cột | I102: Mở workbook thiết kế, đối chiếu block FIELD MAPPING với danh sách cột trong câu SELECT/INSERT của file SQL. Cột nào thiếu thì bổ sung vào SQL; cột nào SQL có mà thiết kế không có thì bổ sung vào workbook hoặc bỏ khỏi SQL. | J102: 005. OCB_GOLD_TCKH_V_CREDIT_LIMIT_BAOANH.xlsx [Script: V_CREDIT_LIMIT]
A103: TCKH.V_CREDIT_LIMIT | B103: SILVER_CONSUMER | C103: 1.2 | D103: Nhom 1 - Mapping | E103: Danh sách bảng/view Gold khớp tài liệu thiết kế đã duyệt | F103: PASS | G103: Pass | H103: V_CREDIT_LIMIT có workbook thiết kế: 005. OCB_GOLD_TCKH_V_CREDIT_LIMIT_BAOANH.xlsx | I103: Đảm bảo object có workbook thiết kế tương ứng trong thư mục --mapping-dir. Muốn đối chiếu với danh sách đã duyệt thì chạy thêm tham số --gold-list "<file danh sách Gold>.xlsx". | J103: 005. OCB_GOLD_TCKH_V_CREDIT_LIMIT_BAOANH.xlsx [Script: V_CREDIT_LIMIT]
A104: TCKH.V_CREDIT_LIMIT | B104: SILVER_CONSUMER | C104: 2.1 | D104: Nhom 2 - Logic | E104: Chỉ lấy bản ghi active, loại bản ghi đã xóa (qua sts_hub) | F104: PASS | G104: Pass | H104: 1 sts_hub_* đọc đúng format | I104: Theo Technical Document mục III.4.2.1: với mỗi hub_<ent> phải thêm 2 CTE — (1) <ent>_sts_del đọc sts_hub_<ent>, GROUP BY hashkey, HAVING max_by(cdc_status, source_event_date) = 'D'; (2) <ent>_active đọc hub_<ent> LEFT JOIN <ent>_sts_del rồi lọc d.<hashkey> IS NULL. Tuyệt đối KHÔNG lọc cdc_status trong satellite — trạng thái xóa chỉ lọc ở sts_hub. | J104: 005. OCB_GOLD_TCKH_V_CREDIT_LIMIT_BAOANH.xlsx [Script: V_CREDIT_LIMIT]
A105: TCKH.V_CREDIT_LIMIT | B105: SILVER_CONSUMER | C105: 2.2 | D105: Nhom 2 - Logic | E105: Thống nhất MỘT pattern duy nhất xác định bản ghi active mới nhất | F105: PASS | G105: Pass | H105: file này dùng: ['MAX_BY']; toàn batch dùng: ['MAX_BY'] | I105: Toàn bộ script trong batch phải dùng cùng một cách lấy bản ghi mới nhất: max_by(<cột>, source_event_date) + GROUP BY hashkey. Không để file này dùng ROW_NUMBER, file kia dùng max_by. Hướng lọc cdc_status cũng phải nhất quán (luôn là loại 'D', không có chỗ nào giữ 'D'). | J105: 005. OCB_GOLD_TCKH_V_CREDIT_LIMIT_BAOANH.xlsx [Script: V_CREDIT_LIMIT]
A106: TCKH.V_CREDIT_LIMIT | B106: SILVER_CONSUMER | C106: 2.3 | D106: Nhom 2 - Logic | E106: Điều kiện lọc trạng thái đặt SAU khi xác định bản ghi mới nhất | F106: PASS | G106: Pass | H106: không có điều kiện trạng thái nào lồng trong JOIN ON | I106: Chuyển các điều kiện cdc_status / rn = 1 ra khỏi phần ON của LEFT JOIN, đưa vào WHERE hoặc QUALIFY của chính subquery/CTE lấy dữ liệu. Đặt trong ON của LEFT JOIN thì khi không match sẽ ra NULL âm thầm, sai kết quả (Issue log #3). Riêng pattern PIT (sat.source_event_date = p.<sat>_src_ev_dt) và 49 bảng transaction được phép đặt trong ON. | J106: 005. OCB_GOLD_TCKH_V_CREDIT_LIMIT_BAOANH.xlsx [Script: V_CREDIT_LIMIT]
A107: TCKH.V_CREDIT_LIMIT | B107: SILVER_CONSUMER | C107: 2.4 | D107: Nhom 2 - Logic | E107: source_event_date áp dụng đúng dạng theo loại bảng | F107: PASS | G107: Pass | H107: 1 satellite đều đúng dạng điều kiện source_event_date | I107: Bảng thường: WHERE source_event_date <= TO_DATE(:DATADT,'yyyyMMdd') và KHÔNG đặt cận dưới (>= start_date) vì sẽ bỏ sót bản ghi mới nhất nằm trước khoảng thời gian. Riêng 49 bảng transaction ở mục 'Các trường hợp đặc biệt' của Technical Document (sat_stmt_entry_*, sat_categ_entry_*, sat_account_balance, sat_funds_transfer_*, sat_gl_trace_*, …) phải dùng source_event_date = :DATADT. Danh sách đầy đủ ở tools/gold_review/doc_standard.py. | J107: 005. OCB_GOLD_TCKH_V_CREDIT_LIMIT_BAOANH.xlsx [Script: V_CREDIT_LIMIT]
A108: TCKH.V_CREDIT_LIMIT | B108: SILVER_CONSUMER | C108: 2.5 | D108: Nhom 2 - Logic | E108: Không lặp lại lỗi logic cũ đã được DA Data Vault fix | F108: PASS | G108: Pass | H108: không trùng lỗi nào trong Issue log của DA Data Vault | I108: Sửa đúng các dòng được chỉ ra ở trên theo pattern chuẩn: lấy bản ghi mới nhất bằng max_by(<cột>, source_event_date) + GROUP BY hashkey; trạng thái xoá lọc ở sts_hub_* bằng HAVING max_by(cdc_status, source_event_date) = 'D' rồi anti-join IS NULL; không đặt cdc_status / rn = 1 trong ON hay trong subquery của JOIN; surrogate key DIM không sinh bằng MAX(<DIM_ID>) + ROW_NUMBER(). Danh sách lỗi lấy từ 'ZoneC Mapping - Iss log.xlsx' sheet Issue; OCB trả lỗi mới thì thêm 1 regex vào tools/gold_review/engine/known_issues.json để lần sau tự bắt được. | J108: 005. OCB_GOLD_TCKH_V_CREDIT_LIMIT_BAOANH.xlsx [Script: V_CREDIT_LIMIT]
A109: TCKH.V_CREDIT_LIMIT | B109: SILVER_CONSUMER | C109: 2.6 | D109: Nhom 2 - Logic | E109: SCD Type 2 cho bảng DIM áp dụng đúng kỹ thuật đã thống nhất | F109: N-A | G109: Pass | H109: object không phải bảng DIM nên không áp dụng SCD Type 2 | I109: Dùng APPLY CHANGES INTO <bảng>_scd FROM STREAM(stg_<ent>_changes) KEYS (<hashkey>) SEQUENCE BY source_event_date STORED AS SCD TYPE 2 TRACK HISTORY ON (...) — Databricks tự quản __START_AT/__END_AT. Nếu tự quản thì phải có cột effective_date/end_date/current_flag. TUYỆT ĐỐI không sinh surrogate key bằng MAX(<DIM_ID>) + ROW_NUMBER() vì trùng khi chạy song song hoặc load lại lịch sử (Issue log #4). | J109: 005. OCB_GOLD_TCKH_V_CREDIT_LIMIT_BAOANH.xlsx [Script: V_CREDIT_LIMIT]
A110: TCKH.V_CREDIT_LIMIT | B110: SILVER_CONSUMER | C110: 2.7 | D110: Nhom 2 - Logic | E110: CASE WHEN cover đủ nhánh như job on-prem | F110: N-A | G110: Pass | H110: script không có CASE WHEN nào | I110: Mở job on-prem tương ứng (DataStage DSX hoặc SQL cũ), đối chiếu từng nhánh WHEN và cả nhánh ELSE. CASE không có ELSE sẽ trả NULL âm thầm — xác nhận đó là ý muốn hay thiếu nhánh. | J110: 005. OCB_GOLD_TCKH_V_CREDIT_LIMIT_BAOANH.xlsx [Script: V_CREDIT_LIMIT]
A111: TCKH.V_CREDIT_LIMIT | B111: SILVER_CONSUMER | C111: 2.8 | D111: Nhom 2 - Logic | E111: Cột SUM/COUNT được COALESCE/NVL hợp lý | F111: PASS | G111: Pass | H111: mọi SUM/COUNT đều đã coalesce (trực tiếp hoặc ở lớp ngoài) | I111: Bọc COALESCE(SUM(...), 0) cho các cột tổng hợp cần trả 0 khi không có dòng. Nếu code cũ không bọc thì giữ nguyên logic nhưng khi đối soát số liệu với hệ thống cũ phải bọc NVL/ISNULL ở CẢ HAI phía để không lệch khi trừ. | J111: 005. OCB_GOLD_TCKH_V_CREDIT_LIMIT_BAOANH.xlsx [Script: V_CREDIT_LIMIT]
A112: TCKH.V_CREDIT_LIMIT | B112: SILVER_CONSUMER | C112: 2.9 | D112: Nhom 2 - Logic | E112: Subquery / custom function / điều kiện LIKE đúng ý nghĩa nghiệp vụ | F112: N-A | G112: Pass | H112: script không có điều kiện LIKE hay scalar subquery nào | I112: Đọc lại từng điều kiện LIKE và từng subquery, đối chiếu ý nghĩa nghiệp vụ với on-prem — đúng cú pháp không đủ. Chú ý pattern LIKE có ký tự % ở đầu/cuối và phân biệt chữ hoa/thường. | J112: 005. OCB_GOLD_TCKH_V_CREDIT_LIMIT_BAOANH.xlsx [Script: V_CREDIT_LIMIT]
A113: TCKH.V_CREDIT_LIMIT | B113: SILVER_CONSUMER | C113: 2.10 | D113: Nhom 2 - Logic | E113: Aggregation kèm filter date range chính xác | F113: PASS | G113: Pass | H113: mọi khối tổng hợp đều có điều kiện theo kỳ dữ liệu | I113: Mỗi khối SUM/COUNT/AVG phải có điều kiện lọc theo kỳ dữ liệu (CDR_DT_ID, DATA_DATE, :DATADT…). Nếu điều kiện nằm ở CTE nguồn thì ghi rõ trong comment để người review không phải truy ngược. | J113: 005. OCB_GOLD_TCKH_V_CREDIT_LIMIT_BAOANH.xlsx [Script: V_CREDIT_LIMIT]
... A124: TCKH.V_CREDIT_LIMIT | B124: SILVER_CONSUMER | C124: X.7 | D124: Nhom X - Bo sung Raffles | E124: [Bổ sung] Không hard-code catalog, dùng biến môi trường | F124: PASS | G124: Pass | H124: dùng biến môi trường cho catalog | I124: Thay tên catalog cứng bằng IDENTIFIER(:cleaned || '.raw_vault.<bảng>') / IDENTIFIER(:curated || '.tckh.<bảng>'), hoặc ${cleaned_catalog} / ${curated_catalog} trong Lakeflow Declarative Pipeline. Hard-code thì deploy sang môi trường khác phải sửa tay từng file. | J124: 005. OCB_GOLD_TCKH_V_CREDIT_LIMIT_BAOANH.xlsx [Script: V_CREDIT_LIMIT]
A125: TCKH.V_CREDIT_LIMIT | B125: SILVER_CONSUMER | C125: X.10 | D125: Nhom X - Bo sung Raffles | E125: Bang raw_vault/business_vault duoc doc phai TON TAI THAT trong Data Vault model | F125: PASS | G125: Pass | H125: 4 bảng Silver đều có thật trong Data Vault model | J125: 005. OCB_GOLD_TCKH_V_CREDIT_LIMIT_BAOANH.xlsx [Script: V_CREDIT_LIMIT]
A126: TCKH.V_CREDIT_LIMIT | B126: SILVER_CONSUMER | C126: X.11 | D126: Nhom X - Bo sung Raffles | E126: Cot doc tu satellite (sat_*) phai TON TAI THAT trong model | F126: N-A | G126: Pass | H126: không có bảng sat_* nào đủ điều kiện đối chiếu (Select chỉ đọc 1 bảng) | J126: 005. OCB_GOLD_TCKH_V_CREDIT_LIMIT_BAOANH.xlsx [Script: V_CREDIT_LIMIT]
A127: TCKH.V_CUSTOMER_SEGMENT_CMB | B127: GOLD_DERIVED | C127: 1.1 | D127: Nhom 1 - Mapping | E127: Đầy đủ mapping từ Silver/manual sang Gold | F127: PASS | G127: Pass | H127: workbook 006. OCB_GOLD_TCKH_V_CUSTOMER_SEGMENT_CMB_PHAT.xlsx: thiết kế 3 field, SQL có 3 cột | I127: Mở workbook thiết kế, đối chiếu block FIELD MAPPING với danh sách cột trong câu SELECT/INSERT của file SQL. Cột nào thiếu thì bổ sung vào SQL; cột nào SQL có mà thiết kế không có thì bổ sung vào workbook hoặc bỏ khỏi SQL. | J127: 006. OCB_GOLD_TCKH_V_CUSTOMER_SEGMENT_CMB_PHAT.xlsx [Script: V_CUSTOMER_SEGMENT_CMB]
A128: TCKH.V_CUSTOMER_SEGMENT_CMB | B128: GOLD_DERIVED | C128: 1.2 | D128: Nhom 1 - Mapping | E128: Danh sách bảng/view Gold khớp tài liệu thiết kế đã duyệt | F128: PASS | G128: Pass | H128: V_CUSTOMER_SEGMENT_CMB có workbook thiết kế: 006. OCB_GOLD_TCKH_V_CUSTOMER_SEGMENT_CMB_PHAT.xlsx | I128: Đảm bảo object có workbook thiết kế tương ứng trong thư mục --mapping-dir. Muốn đối chiếu với danh sách đã duyệt thì chạy thêm tham số --gold-list "<file danh sách Gold>.xlsx". | J128: 006. OCB_GOLD_TCKH_V_CUSTOMER_SEGMENT_CMB_PHAT.xlsx [Script: V_CUSTOMER_SEGMENT_CMB]
A129: TCKH.V_CUSTOMER_SEGMENT_CMB | B129: GOLD_DERIVED | C129: 2.1 | D129: Nhom 2 - Logic | E129: Chỉ lấy bản ghi active, loại bản ghi đã xóa (qua sts_hub) | F129: N-A | G129: Pass | H129: khong ap dung cho profile GOLD_DERIVED | I129: Theo Technical Document mục III.4.2.1: với mỗi hub_<ent> phải thêm 2 CTE — (1) <ent>_sts_del đọc sts_hub_<ent>, GROUP BY hashkey, HAVING max_by(cdc_status, source_event_date) = 'D'; (2) <ent>_active đọc hub_<ent> LEFT JOIN <ent>_sts_del rồi lọc d.<hashkey> IS NULL. Tuyệt đối KHÔNG lọc cdc_status trong satellite — trạng thái xóa chỉ lọc ở sts_hub. | J129: 006. OCB_GOLD_TCKH_V_CUSTOMER_SEGMENT_CMB_PHAT.xlsx [Script: V_CUSTOMER_SEGMENT_CMB]
A130: TCKH.V_CUSTOMER_SEGMENT_CMB | B130: GOLD_DERIVED | C130: 2.2 | D130: Nhom 2 - Logic | E130: Thống nhất MỘT pattern duy nhất xác định bản ghi active mới nhất | F130: N-A | G130: Pass | H130: khong ap dung cho profile GOLD_DERIVED | I130: Toàn bộ script trong batch phải dùng cùng một cách lấy bản ghi mới nhất: max_by(<cột>, source_event_date) + GROUP BY hashkey. Không để file này dùng ROW_NUMBER, file kia dùng max_by. Hướng lọc cdc_status cũng phải nhất quán (luôn là loại 'D', không có chỗ nào giữ 'D'). | J130: 006. OCB_GOLD_TCKH_V_CUSTOMER_SEGMENT_CMB_PHAT.xlsx [Script: V_CUSTOMER_SEGMENT_CMB]
A131: TCKH.V_CUSTOMER_SEGMENT_CMB | B131: GOLD_DERIVED | C131: 2.3 | D131: Nhom 2 - Logic | E131: Điều kiện lọc trạng thái đặt SAU khi xác định bản ghi mới nhất | F131: PASS | G131: Pass | H131: không có điều kiện trạng thái nào lồng trong JOIN ON | I131: Chuyển các điều kiện cdc_status / rn = 1 ra khỏi phần ON của LEFT JOIN, đưa vào WHERE hoặc QUALIFY của chính subquery/CTE lấy dữ liệu. Đặt trong ON của LEFT JOIN thì khi không match sẽ ra NULL âm thầm, sai kết quả (Issue log #3). Riêng pattern PIT (sat.source_event_date = p.<sat>_src_ev_dt) và 49 bảng transaction được phép đặt trong ON. | J131: 006. OCB_GOLD_TCKH_V_CUSTOMER_SEGMENT_CMB_PHAT.xlsx [Script: V_CUSTOMER_SEGMENT_CMB]
A132: TCKH.V_CUSTOMER_SEGMENT_CMB | B132: GOLD_DERIVED | C132: 2.4 | D132: Nhom 2 - Logic | E132: source_event_date áp dụng đúng dạng theo loại bảng | F132: N-A | G132: Pass | H132: khong ap dung cho profile GOLD_DERIVED | I132: Bảng thường: WHERE source_event_date <= TO_DATE(:DATADT,'yyyyMMdd') và KHÔNG đặt cận dưới (>= start_date) vì sẽ bỏ sót bản ghi mới nhất nằm trước khoảng thời gian. Riêng 49 bảng transaction ở mục 'Các trường hợp đặc biệt' của Technical Document (sat_stmt_entry_*, sat_categ_entry_*, sat_account_balance, sat_funds_transfer_*, sat_gl_trace_*, …) phải dùng source_event_date = :DATADT. Danh sách đầy đủ ở tools/gold_review/doc_standard.py. | J132: 006. OCB_GOLD_TCKH_V_CUSTOMER_SEGMENT_CMB_PHAT.xlsx [Script: V_CUSTOMER_SEGMENT_CMB]
A133: TCKH.V_CUSTOMER_SEGMENT_CMB | B133: GOLD_DERIVED | C133: 2.5 | D133: Nhom 2 - Logic | E133: Không lặp lại lỗi logic cũ đã được DA Data Vault fix | F133: PASS | G133: Pass | H133: không trùng lỗi nào trong Issue log của DA Data Vault | I133: Sửa đúng các dòng được chỉ ra ở trên theo pattern chuẩn: lấy bản ghi mới nhất bằng max_by(<cột>, source_event_date) + GROUP BY hashkey; trạng thái xoá lọc ở sts_hub_* bằng HAVING max_by(cdc_status, source_event_date) = 'D' rồi anti-join IS NULL; không đặt cdc_status / rn = 1 trong ON hay trong subquery của JOIN; surrogate key DIM không sinh bằng MAX(<DIM_ID>) + ROW_NUMBER(). Danh sách lỗi lấy từ 'ZoneC Mapping - Iss log.xlsx' sheet Issue; OCB trả lỗi mới thì thêm 1 regex vào tools/gold_review/engine/known_issues.json để lần sau tự bắt được. | J133: 006. OCB_GOLD_TCKH_V_CUSTOMER_SEGMENT_CMB_PHAT.xlsx [Script: V_CUSTOMER_SEGMENT_CMB]
A134: TCKH.V_CUSTOMER_SEGMENT_CMB | B134: GOLD_DERIVED | C134: 2.6 | D134: Nhom 2 - Logic | E134: SCD Type 2 cho bảng DIM áp dụng đúng kỹ thuật đã thống nhất | F134: N-A | G134: Pass | H134: object không phải bảng DIM nên không áp dụng SCD Type 2 | I134: Dùng APPLY CHANGES INTO <bảng>_scd FROM STREAM(stg_<ent>_changes) KEYS (<hashkey>) SEQUENCE BY source_event_date STORED AS SCD TYPE 2 TRACK HISTORY ON (...) — Databricks tự quản __START_AT/__END_AT. Nếu tự quản thì phải có cột effective_date/end_date/current_flag. TUYỆT ĐỐI không sinh surrogate key bằng MAX(<DIM_ID>) + ROW_NUMBER() vì trùng khi chạy song song hoặc load lại lịch sử (Issue log #4). | J134: 006. OCB_GOLD_TCKH_V_CUSTOMER_SEGMENT_CMB_PHAT.xlsx [Script: V_CUSTOMER_SEGMENT_CMB]
A135: TCKH.V_CUSTOMER_SEGMENT_CMB | B135: GOLD_DERIVED | C135: 2.7 | D135: Nhom 2 - Logic | E135: CASE WHEN cover đủ nhánh như job on-prem | F135: PASS | G135: Pass | H135: cả 1 CASE đều có nhánh ELSE | I135: Mở job on-prem tương ứng (DataStage DSX hoặc SQL cũ), đối chiếu từng nhánh WHEN và cả nhánh ELSE. CASE không có ELSE sẽ trả NULL âm thầm — xác nhận đó là ý muốn hay thiếu nhánh. | J135: 006. OCB_GOLD_TCKH_V_CUSTOMER_SEGMENT_CMB_PHAT.xlsx [Script: V_CUSTOMER_SEGMENT_CMB]
A136: TCKH.V_CUSTOMER_SEGMENT_CMB | B136: GOLD_DERIVED | C136: 2.8 | D136: Nhom 2 - Logic | E136: Cột SUM/COUNT được COALESCE/NVL hợp lý | F136: PASS | G136: Pass | H136: mọi SUM/COUNT đều đã coalesce (trực tiếp hoặc ở lớp ngoài) | I136: Bọc COALESCE(SUM(...), 0) cho các cột tổng hợp cần trả 0 khi không có dòng. Nếu code cũ không bọc thì giữ nguyên logic nhưng khi đối soát số liệu với hệ thống cũ phải bọc NVL/ISNULL ở CẢ HAI phía để không lệch khi trừ. | J136: 006. OCB_GOLD_TCKH_V_CUSTOMER_SEGMENT_CMB_PHAT.xlsx [Script: V_CUSTOMER_SEGMENT_CMB]
A137: TCKH.V_CUSTOMER_SEGMENT_CMB | B137: GOLD_DERIVED | C137: 2.9 | D137: Nhom 2 - Logic | E137: Subquery / custom function / điều kiện LIKE đúng ý nghĩa nghiệp vụ | F137: N-A | G137: Pass | H137: script không có điều kiện LIKE hay scalar subquery nào | I137: Đọc lại từng điều kiện LIKE và từng subquery, đối chiếu ý nghĩa nghiệp vụ với on-prem — đúng cú pháp không đủ. Chú ý pattern LIKE có ký tự % ở đầu/cuối và phân biệt chữ hoa/thường. | J137: 006. OCB_GOLD_TCKH_V_CUSTOMER_SEGMENT_CMB_PHAT.xlsx [Script: V_CUSTOMER_SEGMENT_CMB]
A138: TCKH.V_CUSTOMER_SEGMENT_CMB | B138: GOLD_DERIVED | C138: 2.10 | D138: Nhom 2 - Logic | E138: Aggregation kèm filter date range chính xác | F138: PASS | G138: Pass | H138: mọi khối tổng hợp đều có điều kiện theo kỳ dữ liệu | I138: Mỗi khối SUM/COUNT/AVG phải có điều kiện lọc theo kỳ dữ liệu (CDR_DT_ID, DATA_DATE, :DATADT…). Nếu điều kiện nằm ở CTE nguồn thì ghi rõ trong comment để người review không phải truy ngược. | J138: 006. OCB_GOLD_TCKH_V_CUSTOMER_SEGMENT_CMB_PHAT.xlsx [Script: V_CUSTOMER_SEGMENT_CMB]
... A149: TCKH.V_CUSTOMER_SEGMENT_CMB | B149: GOLD_DERIVED | C149: X.7 | D149: Nhom X - Bo sung Raffles | E149: [Bổ sung] Không hard-code catalog, dùng biến môi trường | F149: PASS | G149: Pass | H149: dùng biến môi trường cho catalog | I149: Thay tên catalog cứng bằng IDENTIFIER(:cleaned || '.raw_vault.<bảng>') / IDENTIFIER(:curated || '.tckh.<bảng>'), hoặc ${cleaned_catalog} / ${curated_catalog} trong Lakeflow Declarative Pipeline. Hard-code thì deploy sang môi trường khác phải sửa tay từng file. | J149: 006. OCB_GOLD_TCKH_V_CUSTOMER_SEGMENT_CMB_PHAT.xlsx [Script: V_CUSTOMER_SEGMENT_CMB]
A150: TCKH.V_CUSTOMER_SEGMENT_CMB | B150: GOLD_DERIVED | C150: X.10 | D150: Nhom X - Bo sung Raffles | E150: Bang raw_vault/business_vault duoc doc phai TON TAI THAT trong Data Vault model | F150: N-A | G150: Pass | H150: script không đọc bảng raw_vault/business_vault nào | J150: 006. OCB_GOLD_TCKH_V_CUSTOMER_SEGMENT_CMB_PHAT.xlsx [Script: V_CUSTOMER_SEGMENT_CMB]
A151: TCKH.V_CUSTOMER_SEGMENT_CMB | B151: GOLD_DERIVED | C151: X.11 | D151: Nhom X - Bo sung Raffles | E151: Cot doc tu satellite (sat_*) phai TON TAI THAT trong model | F151: N-A | G151: Pass | H151: không có bảng sat_* nào đủ điều kiện đối chiếu (Select chỉ đọc 1 bảng) | J151: 006. OCB_GOLD_TCKH_V_CUSTOMER_SEGMENT_CMB_PHAT.xlsx [Script: V_CUSTOMER_SEGMENT_CMB]
A152: TCKH.V_CUSTOMER_SEGMENT_RB | B152: GOLD_DERIVED | C152: 1.1 | D152: Nhom 1 - Mapping | E152: Đầy đủ mapping từ Silver/manual sang Gold | F152: PASS | G152: Pass | H152: workbook 007. OCB_GOLD_TCKH_V_CUSTOMER_SEGMENT_RB_PHAT.xlsx: thiết kế 4 field, SQL có 4 cột | I152: Mở workbook thiết kế, đối chiếu block FIELD MAPPING với danh sách cột trong câu SELECT/INSERT của file SQL. Cột nào thiếu thì bổ sung vào SQL; cột nào SQL có mà thiết kế không có thì bổ sung vào workbook hoặc bỏ khỏi SQL. | J152: 007. OCB_GOLD_TCKH_V_CUSTOMER_SEGMENT_RB_PHAT.xlsx [Script: V_CUSTOMER_SEGMENT_RB]
A153: TCKH.V_CUSTOMER_SEGMENT_RB | B153: GOLD_DERIVED | C153: 1.2 | D153: Nhom 1 - Mapping | E153: Danh sách bảng/view Gold khớp tài liệu thiết kế đã duyệt | F153: PASS | G153: Pass | H153: V_CUSTOMER_SEGMENT_RB có workbook thiết kế: 007. OCB_GOLD_TCKH_V_CUSTOMER_SEGMENT_RB_PHAT.xlsx | I153: Đảm bảo object có workbook thiết kế tương ứng trong thư mục --mapping-dir. Muốn đối chiếu với danh sách đã duyệt thì chạy thêm tham số --gold-list "<file danh sách Gold>.xlsx". | J153: 007. OCB_GOLD_TCKH_V_CUSTOMER_SEGMENT_RB_PHAT.xlsx [Script: V_CUSTOMER_SEGMENT_RB]
A154: TCKH.V_CUSTOMER_SEGMENT_RB | B154: GOLD_DERIVED | C154: 2.1 | D154: Nhom 2 - Logic | E154: Chỉ lấy bản ghi active, loại bản ghi đã xóa (qua sts_hub) | F154: N-A | G154: Pass | H154: khong ap dung cho profile GOLD_DERIVED | I154: Theo Technical Document mục III.4.2.1: với mỗi hub_<ent> phải thêm 2 CTE — (1) <ent>_sts_del đọc sts_hub_<ent>, GROUP BY hashkey, HAVING max_by(cdc_status, source_event_date) = 'D'; (2) <ent>_active đọc hub_<ent> LEFT JOIN <ent>_sts_del rồi lọc d.<hashkey> IS NULL. Tuyệt đối KHÔNG lọc cdc_status trong satellite — trạng thái xóa chỉ lọc ở sts_hub. | J154: 007. OCB_GOLD_TCKH_V_CUSTOMER_SEGMENT_RB_PHAT.xlsx [Script: V_CUSTOMER_SEGMENT_RB]
A155: TCKH.V_CUSTOMER_SEGMENT_RB | B155: GOLD_DERIVED | C155: 2.2 | D155: Nhom 2 - Logic | E155: Thống nhất MỘT pattern duy nhất xác định bản ghi active mới nhất | F155: N-A | G155: Pass | H155: khong ap dung cho profile GOLD_DERIVED | I155: Toàn bộ script trong batch phải dùng cùng một cách lấy bản ghi mới nhất: max_by(<cột>, source_event_date) + GROUP BY hashkey. Không để file này dùng ROW_NUMBER, file kia dùng max_by. Hướng lọc cdc_status cũng phải nhất quán (luôn là loại 'D', không có chỗ nào giữ 'D'). | J155: 007. OCB_GOLD_TCKH_V_CUSTOMER_SEGMENT_RB_PHAT.xlsx [Script: V_CUSTOMER_SEGMENT_RB]
A156: TCKH.V_CUSTOMER_SEGMENT_RB | B156: GOLD_DERIVED | C156: 2.3 | D156: Nhom 2 - Logic | E156: Điều kiện lọc trạng thái đặt SAU khi xác định bản ghi mới nhất | F156: PASS | G156: Pass | H156: không có điều kiện trạng thái nào lồng trong JOIN ON | I156: Chuyển các điều kiện cdc_status / rn = 1 ra khỏi phần ON của LEFT JOIN, đưa vào WHERE hoặc QUALIFY của chính subquery/CTE lấy dữ liệu. Đặt trong ON của LEFT JOIN thì khi không match sẽ ra NULL âm thầm, sai kết quả (Issue log #3). Riêng pattern PIT (sat.source_event_date = p.<sat>_src_ev_dt) và 49 bảng transaction được phép đặt trong ON. | J156: 007. OCB_GOLD_TCKH_V_CUSTOMER_SEGMENT_RB_PHAT.xlsx [Script: V_CUSTOMER_SEGMENT_RB]
A157: TCKH.V_CUSTOMER_SEGMENT_RB | B157: GOLD_DERIVED | C157: 2.4 | D157: Nhom 2 - Logic | E157: source_event_date áp dụng đúng dạng theo loại bảng | F157: N-A | G157: Pass | H157: khong ap dung cho profile GOLD_DERIVED | I157: Bảng thường: WHERE source_event_date <= TO_DATE(:DATADT,'yyyyMMdd') và KHÔNG đặt cận dưới (>= start_date) vì sẽ bỏ sót bản ghi mới nhất nằm trước khoảng thời gian. Riêng 49 bảng transaction ở mục 'Các trường hợp đặc biệt' của Technical Document (sat_stmt_entry_*, sat_categ_entry_*, sat_account_balance, sat_funds_transfer_*, sat_gl_trace_*, …) phải dùng source_event_date = :DATADT. Danh sách đầy đủ ở tools/gold_review/doc_standard.py. | J157: 007. OCB_GOLD_TCKH_V_CUSTOMER_SEGMENT_RB_PHAT.xlsx [Script: V_CUSTOMER_SEGMENT_RB]
A158: TCKH.V_CUSTOMER_SEGMENT_RB | B158: GOLD_DERIVED | C158: 2.5 | D158: Nhom 2 - Logic | E158: Không lặp lại lỗi logic cũ đã được DA Data Vault fix | F158: PASS | G158: Pass | H158: không trùng lỗi nào trong Issue log của DA Data Vault | I158: Sửa đúng các dòng được chỉ ra ở trên theo pattern chuẩn: lấy bản ghi mới nhất bằng max_by(<cột>, source_event_date) + GROUP BY hashkey; trạng thái xoá lọc ở sts_hub_* bằng HAVING max_by(cdc_status, source_event_date) = 'D' rồi anti-join IS NULL; không đặt cdc_status / rn = 1 trong ON hay trong subquery của JOIN; surrogate key DIM không sinh bằng MAX(<DIM_ID>) + ROW_NUMBER(). Danh sách lỗi lấy từ 'ZoneC Mapping - Iss log.xlsx' sheet Issue; OCB trả lỗi mới thì thêm 1 regex vào tools/gold_review/engine/known_issues.json để lần sau tự bắt được. | J158: 007. OCB_GOLD_TCKH_V_CUSTOMER_SEGMENT_RB_PHAT.xlsx [Script: V_CUSTOMER_SEGMENT_RB]
A159: TCKH.V_CUSTOMER_SEGMENT_RB | B159: GOLD_DERIVED | C159: 2.6 | D159: Nhom 2 - Logic | E159: SCD Type 2 cho bảng DIM áp dụng đúng kỹ thuật đã thống nhất | F159: N-A | G159: Pass | H159: object không phải bảng DIM nên không áp dụng SCD Type 2 | I159: Dùng APPLY CHANGES INTO <bảng>_scd FROM STREAM(stg_<ent>_changes) KEYS (<hashkey>) SEQUENCE BY source_event_date STORED AS SCD TYPE 2 TRACK HISTORY ON (...) — Databricks tự quản __START_AT/__END_AT. Nếu tự quản thì phải có cột effective_date/end_date/current_flag. TUYỆT ĐỐI không sinh surrogate key bằng MAX(<DIM_ID>) + ROW_NUMBER() vì trùng khi chạy song song hoặc load lại lịch sử (Issue log #4). | J159: 007. OCB_GOLD_TCKH_V_CUSTOMER_SEGMENT_RB_PHAT.xlsx [Script: V_CUSTOMER_SEGMENT_RB]
A160: TCKH.V_CUSTOMER_SEGMENT_RB | B160: GOLD_DERIVED | C160: 2.7 | D160: Nhom 2 - Logic | E160: CASE WHEN cover đủ nhánh như job on-prem | F160: PASS | G160: Pass | H160: cả 2 CASE đều có nhánh ELSE | I160: Mở job on-prem tương ứng (DataStage DSX hoặc SQL cũ), đối chiếu từng nhánh WHEN và cả nhánh ELSE. CASE không có ELSE sẽ trả NULL âm thầm — xác nhận đó là ý muốn hay thiếu nhánh. | J160: 007. OCB_GOLD_TCKH_V_CUSTOMER_SEGMENT_RB_PHAT.xlsx [Script: V_CUSTOMER_SEGMENT_RB]
A161: TCKH.V_CUSTOMER_SEGMENT_RB | B161: GOLD_DERIVED | C161: 2.8 | D161: Nhom 2 - Logic | E161: Cột SUM/COUNT được COALESCE/NVL hợp lý | F161: PASS | G161: Pass | H161: mọi SUM/COUNT đều đã coalesce (trực tiếp hoặc ở lớp ngoài) | I161: Bọc COALESCE(SUM(...), 0) cho các cột tổng hợp cần trả 0 khi không có dòng. Nếu code cũ không bọc thì giữ nguyên logic nhưng khi đối soát số liệu với hệ thống cũ phải bọc NVL/ISNULL ở CẢ HAI phía để không lệch khi trừ. | J161: 007. OCB_GOLD_TCKH_V_CUSTOMER_SEGMENT_RB_PHAT.xlsx [Script: V_CUSTOMER_SEGMENT_RB]
...
